Workbook

Sheet ZJS_TEST_INTERFACE_DATA
A2: d | B2: d | C2: Object | D2: Type | E2: Category | F2: Github Object | G2: Github Type | H2: Version
A4: D | B4: OK | C4: =LEFT(F4,FIND(".",F4)-1) -> 53cdfaffcabea4b42116c2d6119be2ht | D4: {=INDEX('Not Req'!$E$4:$E$71,MATCH(MID(F4,FIND(".",F4)+1,LEN(F4)-FIND(".",F4)+1),'Not Req'!$D$4:$D$71,0))} -> Authorization Defaults (TADIR) | E4: =INDEX('Not Req'!$F$4:$F$71,MATCH(MID(F4,FIND(".",F4)+1,LEN(F4)-FIND(".",F4)+1),'Not Req'!$D$4:$D$71,0)) -> 1. Authorizations | F4: 53cdfaffcabea4b42116c2d6119be2ht.sush.xml | G4: UPDATED ON 02-FEB-26 | H4: 3 months ago
A5: D | B5: OK | C5: =LEFT(F5,FIND(".",F5)-1) -> f648cfa16bf0425c8346aa270e7d64ht | D5: {=INDEX('Not Req'!$E$4:$E$71,MATCH(MID(F5,FIND(".",F5)+1,LEN(F5)-FIND(".",F5)+1),'Not Req'!$D$4:$D$71,0))} -> Authorization Defaults (TADIR) | E5: =INDEX('Not Req'!$F$4:$F$71,MATCH(MID(F5,FIND(".",F5)+1,LEN(F5)-FIND(".",F5)+1),'Not Req'!$D$4:$D$71,0)) -> 1. Authorizations | F5: f648cfa16bf0425c8346aa270e7d64ht.sush.xml | G5: UPDATED ON 02-FEB-26 | H5: 3 months ago
A6: D | B6: OK | C6: =LEFT(F6,FIND(".",F6)-1) -> zjs_api_company_names_o2 | D6: {=INDEX('Not Req'!$E$4:$E$71,MATCH(MID(F6,FIND(".",F6)+1,LEN(F6)-FIND(".",F6)+1),'Not Req'!$D$4:$D$71,0))} -> Service Binding | E6: =INDEX('Not Req'!$F$4:$F$71,MATCH(MID(F6,FIND(".",F6)+1,LEN(F6)-FIND(".",F6)+1),'Not Req'!$D$4:$D$71,0)) -> 2. Business Services | F6: zjs_api_company_names_o2.srvb.xml | G6: UPDATED ON 02-FEB-26 | H6: 3 months ago
A7: D | B7: OK | C7: =LEFT(F7,FIND(".",F7)-1) -> zjs_api_company_names_o2_iwsg | D7: {=INDEX('Not Req'!$E$4:$E$71,MATCH(MID(F7,FIND(".",F7)+1,LEN(F7)-FIND(".",F7)+1),'Not Req'!$D$4:$D$71,0))} -> Inbound Service | E7: =INDEX('Not Req'!$F$4:$F$71,MATCH(MID(F7,FIND(".",F7)+1,LEN(F7)-FIND(".",F7)+1),'Not Req'!$D$4:$D$71,0)) -> 3. Cloud Communication Management | F7: zjs_api_company_names_o2_iwsg.sco2.xml | G7: UPDATED ON 02-FEB-26 | H7: 3 months ago
A8: D | B8: OK | C8: =LEFT(F8,FIND(".",F8)-1) -> zjs_c_dmocname | D8: {=INDEX('Not Req'!$E$4:$E$71,MATCH(MID(F8,FIND(".",F8)+1,LEN(F8)-FIND(".",F8)+1),'Not Req'!$D$4:$D$71,0))} -> BDEF | E8: =INDEX('Not Req'!$F$4:$F$71,MATCH(MID(F8,FIND(".",F8)+1,LEN(F8)-FIND(".",F8)+1),'Not Req'!$D$4:$D$71,0)) -> 4. CDS | F8: zjs_c_dmocname.bdef.asbdef | G8: UPDATED ON 02-FEB-26 | H8: 3 months ago
A9: D | B9: OK | C9: =LEFT(F9,FIND(".",F9)-1) -> zjs_i_dmocname | D9: {=INDEX('Not Req'!$E$4:$E$71,MATCH(MID(F9,FIND(".",F9)+1,LEN(F9)-FIND(".",F9)+1),'Not Req'!$D$4:$D$71,0))} -> BDEF | E9: =INDEX('Not Req'!$F$4:$F$71,MATCH(MID(F9,FIND(".",F9)+1,LEN(F9)-FIND(".",F9)+1),'Not Req'!$D$4:$D$71,0)) -> 4. CDS | F9: zjs_i_dmocname.bdef.asbdef | G9: UPDATED ON 02-FEB-26 | H9: 3 months ago
A10: D | B10: OK | C10: =LEFT(F10,FIND(".",F10)-1) -> zjs_c_dmocname | D10: {=INDEX('Not Req'!$E$4:$E$71,MATCH(MID(F10,FIND(".",F10)+1,LEN(F10)-FIND(".",F10)+1),'Not Req'!$D$4:$D$71,0))} -> Data Definition | E10: =INDEX('Not Req'!$F$4:$F$71,MATCH(MID(F10,FIND(".",F10)+1,LEN(F10)-FIND(".",F10)+1),'Not Req'!$D$4:$D$71,0)) -> 4. CDS | F10: zjs_c_dmocname.ddls.asddls | G10: UPDATED ON 02-FEB-26 | H10: 3 months ago
A11: D | B11: OK | C11: =LEFT(F11,FIND(".",F11)-1) -> zjs_i_dmocname | D11: {=INDEX('Not Req'!$E$4:$E$71,MATCH(MID(F11,FIND(".",F11)+1,LEN(F11)-FIND(".",F11)+1),'Not Req'!$D$4:$D$71,0))} -> Data Definition | E11: =INDEX('Not Req'!$F$4:$F$71,MATCH(MID(F11,FIND(".",F11)+1,LEN(F11)-FIND(".",F11)+1),'Not Req'!$D$4:$D$71,0)) -> 4. CDS | F11: zjs_i_dmocname.ddls.asddls | G11: UPDATED ON 02-FEB-26 | H11: 3 months ago
A12: D | B12: OK | C12: =LEFT(F12,FIND(".",F12)-1) -> zjs_dmo_cname | D12: {=INDEX('Not Req'!$E$4:$E$71,MATCH(MID(F12,FIND(".",F12)+1,LEN(F12)-FIND(".",F12)+1),'Not Req'!$D$4:$D$71,0))} -> Table | E12: =INDEX('Not Req'!$F$4:$F$71,MATCH(MID(F12,FIND(".",F12)+1,LEN(F12)-FIND(".",F12)+1),'Not Req'!$D$4:$D$71,0)) -> 5. Dictionary | F12: zjs_dmo_cname.tabl.xml | G12: UPDATED ON 02-FEB-26 | H12: 3 months ago
A13: D | B13: OK | C13: =LEFT(F13,FIND(".",F13)-1) -> zbp_js_demo_company_name | D13: {=INDEX('Not Req'!$E$4:$E$71,MATCH(MID(F13,FIND(".",F13)+1,LEN(F13)-FIND(".",F13)+1),'Not Req'!$D$4:$D$71,0))} -> Classes | E13: =INDEX('Not Req'!$F$4:$F$71,MATCH(MID(F13,FIND(".",F13)+1,LEN(F13)-FIND(".",F13)+1),'Not Req'!$D$4:$D$71,0)) -> 7. Source Code Library | F13: zbp_js_demo_company_name.clas.abap | G13: Updated 16-Mar-26 | H13: 2 months ago
A14: D | B14: OK | C14: =LEFT(F14,FIND(".",F14)-1) -> zcl_js_demo_rebuild_intf_data | D14: {=INDEX('Not Req'!$E$4:$E$71,MATCH(MID(F14,FIND(".",F14)+1,LEN(F14)-FIND(".",F14)+1),'Not Req'!$D$4:$D$71,0))} -> Classes | E14: =INDEX('Not Req'!$F$4:$F$71,MATCH(MID(F14,FIND(".",F14)+1,LEN(F14)-FIND(".",F14)+1),'Not Req'!$D$4:$D$71,0)) -> 7. Source Code Library | F14: zcl_js_demo_rebuild_intf_data.clas.abap | G14: Updated 16-Mar-26 | H14: 2 months ago
A15: D | B15: OK | C15: =LEFT(F15,FIND(".",F15)-1) -> zbp_js_demo_company_name | D15: {=INDEX('Not Req'!$E$4:$E$71,MATCH(MID(F15,FIND(".",F15)+1,LEN(F15)-FIND(".",F15)+1),'Not Req'!$D$4:$D$71,0))} -> Classes Local | E15: =INDEX('Not Req'!$F$4:$F$71,MATCH(MID(F15,FIND(".",F15)+1,LEN(F15)-FIND(".",F15)+1),'Not Req'!$D$4:$D$71,0)) -> 7. Source Code Library | F15: zbp_js_demo_company_name.clas.locals_imp.abap | G15: UPDATED ON 02-FEB-26 | H15: 3 months ago
... A24: D | B24: OK | C24: =LEFT(F24,FIND(".",F24)-1) -> package | D24: {=INDEX('Not Req'!$E$4:$E$71,MATCH(MID(F24,FIND(".",F24)+1,LEN(F24)-FIND(".",F24)+1),'Not Req'!$D$4:$D$71,0))} -> Description : Package | E24: =INDEX('Not Req'!$F$4:$F$71,MATCH(MID(F24,FIND(".",F24)+1,LEN(F24)-FIND(".",F24)+1),'Not Req'!$D$4:$D$71,0)) -> 99. Descriptions | F24: package.devc.xml | G24: UPDATED ON 02-FEB-26 | H24: 3 months ago

Sheet ZJS_DEMO_CDS_TYPE
A2: d | B2: d | C2: Object | D2: Type | E2: Category | F2: Github Object | G2: Github Type | H2: Version
A4: D | B4: OK | C4: =LEFT(F4,FIND(".",F4)-1) -> zjs_c_etypeprojection | D4: {=INDEX('Not Req'!$E$4:$E$71,MATCH(MID(F4,FIND(".",F4)+1,LEN(F4)-FIND(".",F4)+1),'Not Req'!$D$4:$D$71,0))} -> Data Definition | E4: =INDEX('Not Req'!$F$4:$F$71,MATCH(MID(F4,FIND(".",F4)+1,LEN(F4)-FIND(".",F4)+1),'Not Req'!$D$4:$D$71,0)) -> 4. CDS | F4: zjs_c_etypeprojection.ddls.asddls | G4: UPDATED ON 02-FEB-26 | H4: 3 months ago
A5: D | B5: OK | C5: =LEFT(F5,FIND(".",F5)-1) -> zjs_e_etypeexternalentity | D5: {=INDEX('Not Req'!$E$4:$E$71,MATCH(MID(F5,FIND(".",F5)+1,LEN(F5)-FIND(".",F5)+1),'Not Req'!$D$4:$D$71,0))} -> Data Definition | E5: =INDEX('Not Req'!$F$4:$F$71,MATCH(MID(F5,FIND(".",F5)+1,LEN(F5)-FIND(".",F5)+1),'Not Req'!$D$4:$D$71,0)) -> 4. CDS | F5: zjs_e_etypeexternalentity.ddls.asddls | G5: UPDATED ON 02-FEB-26 | H5: 3 months ago
A6: D | B6: OK | C6: =LEFT(F6,FIND(".",F6)-1) -> zjs_f_etypetablefunction | D6: {=INDEX('Not Req'!$E$4:$E$71,MATCH(MID(F6,FIND(".",F6)+1,LEN(F6)-FIND(".",F6)+1),'Not Req'!$D$4:$D$71,0))} -> Data Definition | E6: =INDEX('Not Req'!$F$4:$F$71,MATCH(MID(F6,FIND(".",F6)+1,LEN(F6)-FIND(".",F6)+1),'Not Req'!$D$4:$D$71,0)) -> 4. CDS | F6: zjs_f_etypetablefunction.ddls.asddls | G6: UPDATED ON 02-FEB-26 | H6: 3 months ago
A7: D | B7: OK | C7: =LEFT(F7,FIND(".",F7)-1) -> zjs_i_etypeclassicview | D7: {=INDEX('Not Req'!$E$4:$E$71,MATCH(MID(F7,FIND(".",F7)+1,LEN(F7)-FIND(".",F7)+1),'Not Req'!$D$4:$D$71,0))} -> Data Definition | E7: =INDEX('Not Req'!$F$4:$F$71,MATCH(MID(F7,FIND(".",F7)+1,LEN(F7)-FIND(".",F7)+1),'Not Req'!$D$4:$D$71,0)) -> 4. CDS | F7: zjs_i_etypeclassicview.ddls.asddls | G7: UPDATED ON 02-FEB-26 | H7: 3 months ago
A8: D | B8: OK | C8: =LEFT(F8,FIND(".",F8)-1) -> zjs_i_etypecustomentity | D8: {=INDEX('Not Req'!$E$4:$E$71,MATCH(MID(F8,FIND(".",F8)+1,LEN(F8)-FIND(".",F8)+1),'Not Req'!$D$4:$D$71,0))} -> Data Definition | E8: =INDEX('Not Req'!$F$4:$F$71,MATCH(MID(F8,FIND(".",F8)+1,LEN(F8)-FIND(".",F8)+1),'Not Req'!$D$4:$D$71,0)) -> 4. CDS | F8: zjs_i_etypecustomentity.ddls.asddls | G8: UPDATED ON 02-FEB-26 | H8: 3 months ago
A9: D | B9: OK | C9: =LEFT(F9,FIND(".",F9)-1) -> zjs_i_etypehierarchy | D9: {=INDEX('Not Req'!$E$4:$E$71,MATCH(MID(F9,FIND(".",F9)+1,LEN(F9)-FIND(".",F9)+1),'Not Req'!$D$4:$D$71,0))} -> Data Definition | E9: =INDEX('Not Req'!$F$4:$F$71,MATCH(MID(F9,FIND(".",F9)+1,LEN(F9)-FIND(".",F9)+1),'Not Req'!$D$4:$D$71,0)) -> 4. CDS | F9: zjs_i_etypehierarchy.ddls.asddls | G9: UPDATED ON 02-FEB-26 | H9: 3 months ago
A10: D | B10: OK | C10: =LEFT(F10,FIND(".",F10)-1) -> zjs_i_etypeviewentity | D10: {=INDEX('Not Req'!$E$4:$E$71,MATCH(MID(F10,FIND(".",F10)+1,LEN(F10)-FIND(".",F10)+1),'Not Req'!$D$4:$D$71,0))} -> Data Definition | E10: =INDEX('Not Req'!$F$4:$F$71,MATCH(MID(F10,FIND(".",F10)+1,LEN(F10)-FIND(".",F10)+1),'Not Req'!$D$4:$D$71,0)) -> 4. CDS | F10: zjs_i_etypeviewentity.ddls.asddls | G10: UPDATED ON 02-FEB-26 | H10: 3 months ago
A11: D | B11: OK | C11: =LEFT(F11,FIND(".",F11)-1) -> zjs_s_etypeabstractentity | D11: {=INDEX('Not Req'!$E$4:$E$71,MATCH(MID(F11,FIND(".",F11)+1,LEN(F11)-FIND(".",F11)+1),'Not Req'!$D$4:$D$71,0))} -> Data Definition | E11: =INDEX('Not Req'!$F$4:$F$71,MATCH(MID(F11,FIND(".",F11)+1,LEN(F11)-FIND(".",F11)+1),'Not Req'!$D$4:$D$71,0)) -> 4. CDS | F11: zjs_s_etypeabstractentity.ddls.asddls | G11: UPDATED ON 02-FEB-26 | H11: 3 months ago
A12: D | B12: OK | C12: =LEFT(F12,FIND(".",F12)-1) -> zjs_t_etypeassociation | D12: {=INDEX('Not Req'!$E$4:$E$71,MATCH(MID(F12,FIND(".",F12)+1,LEN(F12)-FIND(".",F12)+1),'Not Req'!$D$4:$D$71,0))} -> Data Definition | E12: =INDEX('Not Req'!$F$4:$F$71,MATCH(MID(F12,FIND(".",F12)+1,LEN(F12)-FIND(".",F12)+1),'Not Req'!$D$4:$D$71,0)) -> 4. CDS | F12: zjs_t_etypeassociation.ddls.asddls | G12: UPDATED ON 02-FEB-26 | H12: 3 months ago
A13: D | B13: OK | C13: =LEFT(F13,FIND(".",F13)-1) -> zjs_t_etypetableentity | D13: {=INDEX('Not Req'!$E$4:$E$71,MATCH(MID(F13,FIND(".",F13)+1,LEN(F13)-FIND(".",F13)+1),'Not Req'!$D$4:$D$71,0))} -> Data Definition | E13: =INDEX('Not Req'!$F$4:$F$71,MATCH(MID(F13,FIND(".",F13)+1,LEN(F13)-FIND(".",F13)+1),'Not Req'!$D$4:$D$71,0)) -> 4. CDS | F13: zjs_t_etypetableentity.ddls.asddls | G13: UPDATED ON 02-FEB-26 | H13: 3 months ago
A14: D | B14: OK | C14: =LEFT(F14,FIND(".",F14)-1) -> zcl_js_demo_etpye_tfunc | D14: {=INDEX('Not Req'!$E$4:$E$71,MATCH(MID(F14,FIND(".",F14)+1,LEN(F14)-FIND(".",F14)+1),'Not Req'!$D$4:$D$71,0))} -> Classes | E14: =INDEX('Not Req'!$F$4:$F$71,MATCH(MID(F14,FIND(".",F14)+1,LEN(F14)-FIND(".",F14)+1),'Not Req'!$D$4:$D$71,0)) -> 7. Source Code Library | F14: zcl_js_demo_etpye_tfunc.clas.abap | G14: Updated 16-Mar-26 | H14: 2 months ago
A15: D | B15: OK | C15: =LEFT(F15,FIND(".",F15)-1) -> zcl_js_demo_etype_query | D15: {=INDEX('Not Req'!$E$4:$E$71,MATCH(MID(F15,FIND(".",F15)+1,LEN(F15)-FIND(".",F15)+1),'Not Req'!$D$4:$D$71,0))} -> Classes | E15: =INDEX('Not Req'!$F$4:$F$71,MATCH(MID(F15,FIND(".",F15)+1,LEN(F15)-FIND(".",F15)+1),'Not Req'!$D$4:$D$71,0)) -> 7. Source Code Library | F15: zcl_js_demo_etype_query.clas.abap | G15: Updated 16-Mar-26 | H15: 2 months ago
... A38: D | B38: OK | C38: =LEFT(F38,FIND(".",F38)-1) -> package | D38: {=INDEX('Not Req'!$E$4:$E$71,MATCH(MID(F38,FIND(".",F38)+1,LEN(F38)-FIND(".",F38)+1),'Not Req'!$D$4:$D$71,0))} -> Description : Package | E38: =INDEX('Not Req'!$F$4:$F$71,MATCH(MID(F38,FIND(".",F38)+1,LEN(F38)-FIND(".",F38)+1),'Not Req'!$D$4:$D$71,0)) -> 99. Descriptions | F38: package.devc.xml | G38: UPDATED ON 02-FEB-26 | H38: 3 months ago

Sheet ZJS_CORE_DATA_SERVICE
A2: d | B2: d | C2: Object | D2: Type | E2: Category | F2: Github Object | G2: Github Type | H2: Version
A4: D | B4: OK | C4: =LEFT(F4,FIND(".",F4)-1) -> zjs_b_dmoauthbase | D4: {=INDEX('Not Req'!$E$4:$E$71,MATCH(MID(F4,FIND(".",F4)+1,LEN(F4)-FIND(".",F4)+1),'Not Req'!$D$4:$D$71,0))} -> Access Control | E4: =INDEX('Not Req'!$F$4:$F$71,MATCH(MID(F4,FIND(".",F4)+1,LEN(F4)-FIND(".",F4)+1),'Not Req'!$D$4:$D$71,0)) -> 4. CDS | F4: zjs_b_dmoauthbase.dcls.asdcls | G4: UPDATED ON 02-FEB-26 | H4: 3 months ago
A5: D | B5: OK | C5: =LEFT(F5,FIND(".",F5)-1) -> zjs_i_dmoauthbase | D5: {=INDEX('Not Req'!$E$4:$E$71,MATCH(MID(F5,FIND(".",F5)+1,LEN(F5)-FIND(".",F5)+1),'Not Req'!$D$4:$D$71,0))} -> Access Control | E5: =INDEX('Not Req'!$F$4:$F$71,MATCH(MID(F5,FIND(".",F5)+1,LEN(F5)-FIND(".",F5)+1),'Not Req'!$D$4:$D$71,0)) -> 4. CDS | F5: zjs_i_dmoauthbase.dcls.asdcls | G5: UPDATED ON 02-FEB-26 | H5: 3 months ago
A6: D | B6: OK | C6: =LEFT(F6,FIND(".",F6)-1) -> zjs_i_dmomaterial | D6: {=INDEX('Not Req'!$E$4:$E$71,MATCH(MID(F6,FIND(".",F6)+1,LEN(F6)-FIND(".",F6)+1),'Not Req'!$D$4:$D$71,0))} -> Access Control | E6: =INDEX('Not Req'!$F$4:$F$71,MATCH(MID(F6,FIND(".",F6)+1,LEN(F6)-FIND(".",F6)+1),'Not Req'!$D$4:$D$71,0)) -> 4. CDS | F6: zjs_i_dmomaterial.dcls.asdcls | G6: UPDATED ON 02-FEB-26 | H6: 3 months ago
A7: D | B7: OK | C7: =LEFT(F7,FIND(".",F7)-1) -> zjs_democdsinvoicestatus | D7: {=INDEX('Not Req'!$E$4:$E$71,MATCH(MID(F7,FIND(".",F7)+1,LEN(F7)-FIND(".",F7)+1),'Not Req'!$D$4:$D$71,0))} -> CDS Types | E7: =INDEX('Not Req'!$F$4:$F$71,MATCH(MID(F7,FIND(".",F7)+1,LEN(F7)-FIND(".",F7)+1),'Not Req'!$D$4:$D$71,0)) -> 4. CDS | F7: zjs_democdsinvoicestatus.drty.acds | G7: UPDATED ON 02-FEB-26 | H7: 3 months ago
A8: D | B8: OK | C8: =LEFT(F8,FIND(".",F8)-1) -> zjs_democdsinvoicestatusenum | D8: {=INDEX('Not Req'!$E$4:$E$71,MATCH(MID(F8,FIND(".",F8)+1,LEN(F8)-FIND(".",F8)+1),'Not Req'!$D$4:$D$71,0))} -> CDS Types | E8: =INDEX('Not Req'!$F$4:$F$71,MATCH(MID(F8,FIND(".",F8)+1,LEN(F8)-FIND(".",F8)+1),'Not Req'!$D$4:$D$71,0)) -> 4. CDS | F8: zjs_democdsinvoicestatusenum.drty.acds | G8: UPDATED ON 02-FEB-26 | H8: 3 months ago
A9: D | B9: OK | C9: =LEFT(F9,FIND(".",F9)-1) -> zjs_b_dmoauthbase | D9: {=INDEX('Not Req'!$E$4:$E$71,MATCH(MID(F9,FIND(".",F9)+1,LEN(F9)-FIND(".",F9)+1),'Not Req'!$D$4:$D$71,0))} -> Data Definition | E9: =INDEX('Not Req'!$F$4:$F$71,MATCH(MID(F9,FIND(".",F9)+1,LEN(F9)-FIND(".",F9)+1),'Not Req'!$D$4:$D$71,0)) -> 4. CDS | F9: zjs_b_dmoauthbase.ddls.asddls | G9: UPDATED ON 02-FEB-26 | H9: 3 months ago
A10: D | B10: OK | C10: =LEFT(F10,FIND(".",F10)-1) -> zjs_b_dmoteamview | D10: {=INDEX('Not Req'!$E$4:$E$71,MATCH(MID(F10,FIND(".",F10)+1,LEN(F10)-FIND(".",F10)+1),'Not Req'!$D$4:$D$71,0))} -> Data Definition | E10: =INDEX('Not Req'!$F$4:$F$71,MATCH(MID(F10,FIND(".",F10)+1,LEN(F10)-FIND(".",F10)+1),'Not Req'!$D$4:$D$71,0)) -> 4. CDS | F10: zjs_b_dmoteamview.ddls.asddls | G10: UPDATED ON 02-FEB-26 | H10: 3 months ago
A11: D | B11: OK | C11: =LEFT(F11,FIND(".",F11)-1) -> zjs_c_dmodicountcast | D11: {=INDEX('Not Req'!$E$4:$E$71,MATCH(MID(F11,FIND(".",F11)+1,LEN(F11)-FIND(".",F11)+1),'Not Req'!$D$4:$D$71,0))} -> Data Definition | E11: =INDEX('Not Req'!$F$4:$F$71,MATCH(MID(F11,FIND(".",F11)+1,LEN(F11)-FIND(".",F11)+1),'Not Req'!$D$4:$D$71,0)) -> 4. CDS | F11: zjs_c_dmodicountcast.ddls.asddls | G11: UPDATED ON 02-FEB-26 | H11: 3 months ago
A12: D | B12: OK | C12: =LEFT(F12,FIND(".",F12)-1) -> zjs_c_dmodiscountextension | D12: {=INDEX('Not Req'!$E$4:$E$71,MATCH(MID(F12,FIND(".",F12)+1,LEN(F12)-FIND(".",F12)+1),'Not Req'!$D$4:$D$71,0))} -> Data Definition | E12: =INDEX('Not Req'!$F$4:$F$71,MATCH(MID(F12,FIND(".",F12)+1,LEN(F12)-FIND(".",F12)+1),'Not Req'!$D$4:$D$71,0)) -> 4. CDS | F12: zjs_c_dmodiscountextension.ddls.asddls | G12: UPDATED ON 02-FEB-26 | H12: 3 months ago
A13: D | B13: OK | C13: =LEFT(F13,FIND(".",F13)-1) -> zjs_c_dmoinvoicesession | D13: {=INDEX('Not Req'!$E$4:$E$71,MATCH(MID(F13,FIND(".",F13)+1,LEN(F13)-FIND(".",F13)+1),'Not Req'!$D$4:$D$71,0))} -> Data Definition | E13: =INDEX('Not Req'!$F$4:$F$71,MATCH(MID(F13,FIND(".",F13)+1,LEN(F13)-FIND(".",F13)+1),'Not Req'!$D$4:$D$71,0)) -> 4. CDS | F13: zjs_c_dmoinvoicesession.ddls.asddls | G13: UPDATED ON 02-FEB-26 | H13: 3 months ago
A14: D | B14: OK | C14: =LEFT(F14,FIND(".",F14)-1) -> zjs_c_dmoinvoicesubstring | D14: {=INDEX('Not Req'!$E$4:$E$71,MATCH(MID(F14,FIND(".",F14)+1,LEN(F14)-FIND(".",F14)+1),'Not Req'!$D$4:$D$71,0))} -> Data Definition | E14: =INDEX('Not Req'!$F$4:$F$71,MATCH(MID(F14,FIND(".",F14)+1,LEN(F14)-FIND(".",F14)+1),'Not Req'!$D$4:$D$71,0)) -> 4. CDS | F14: zjs_c_dmoinvoicesubstring.ddls.asddls | G14: UPDATED ON 02-FEB-26 | H14: 3 months ago
A15: D | B15: OK | C15: =LEFT(F15,FIND(".",F15)-1) -> zjs_c_dmomaterialconversion | D15: {=INDEX('Not Req'!$E$4:$E$71,MATCH(MID(F15,FIND(".",F15)+1,LEN(F15)-FIND(".",F15)+1),'Not Req'!$D$4:$D$71,0))} -> Data Definition | E15: =INDEX('Not Req'!$F$4:$F$71,MATCH(MID(F15,FIND(".",F15)+1,LEN(F15)-FIND(".",F15)+1),'Not Req'!$D$4:$D$71,0)) -> 4. CDS | F15: zjs_c_dmomaterialconversion.ddls.asddls | G15: UPDATED ON 02-FEB-26 | H15: 3 months ago
... A139: D | B139: OK | C139: =LEFT(F139,FIND(".",F139)-1) -> zrf_matnr | D139: {=INDEX('Not Req'!$E$4:$E$71,MATCH(MID(F139,FIND(".",F139)+1,LEN(F139)-FIND(".",F139)+1),'Not Req'!$D$4:$D$71,0))} -> Description : Authorization Field | E139: =INDEX('Not Req'!$F$4:$F$71,MATCH(MID(F139,FIND(".",F139)+1,LEN(F139)-FIND(".",F139)+1),'Not Req'!$D$4:$D$71,0)) -> 99. Descriptions | F139: zrf_matnr.sia5.xml | G139: UPDATED ON 02-FEB-26 | H139: 3 months ago

Sheet ZJS_12_RAP_SALES
A2: d | B2: d | C2: Object | D2: Type | E2: Category | F2: Github Object | G2: Github Type | H2: Version
A4: D | B4: OK | C4: =LEFT(F4,FIND(".",F4)-1) -> e7ce711363fc64354a944ad5568ef6ht | D4: {=INDEX('Not Req'!$E$4:$E$71,MATCH(MID(F4,FIND(".",F4)+1,LEN(F4)-FIND(".",F4)+1),'Not Req'!$D$4:$D$71,0))} -> Authorization Defaults (TADIR) | E4: =INDEX('Not Req'!$F$4:$F$71,MATCH(MID(F4,FIND(".",F4)+1,LEN(F4)-FIND(".",F4)+1),'Not Req'!$D$4:$D$71,0)) -> 1. Authorizations | F4: e7ce711363fc64354a944ad5568ef6ht.sush.xml | G4: UPDATED ON 02-FEB-26 | H4: 3 months ago
A5: D | B5: OK | C5: =LEFT(F5,FIND(".",F5)-1) -> zjs_ui_globalsale_o4 | D5: {=INDEX('Not Req'!$E$4:$E$71,MATCH(MID(F5,FIND(".",F5)+1,LEN(F5)-FIND(".",F5)+1),'Not Req'!$D$4:$D$71,0))} -> Service Binding | E5: =INDEX('Not Req'!$F$4:$F$71,MATCH(MID(F5,FIND(".",F5)+1,LEN(F5)-FIND(".",F5)+1),'Not Req'!$D$4:$D$71,0)) -> 2. Business Services | F5: zjs_ui_globalsale_o4.srvb.xml | G5: UPDATED ON 02-FEB-26 | H5: 3 months ago
A6: D | B6: OK | C6: =LEFT(F6,FIND(".",F6)-1) -> zjs_ui_globalsale_o4 | D6: {=INDEX('Not Req'!$E$4:$E$71,MATCH(MID(F6,FIND(".",F6)+1,LEN(F6)-FIND(".",F6)+1),'Not Req'!$D$4:$D$71,0))} -> Service Definition | E6: =INDEX('Not Req'!$F$4:$F$71,MATCH(MID(F6,FIND(".",F6)+1,LEN(F6)-FIND(".",F6)+1),'Not Req'!$D$4:$D$71,0)) -> 2. Business Services | F6: zjs_ui_globalsale_o4.srvd.srvdsrv | G6: UPDATED ON 02-FEB-26 | H6: 3 months ago
A7: D | B7: OK | C7: =LEFT(F7,FIND(".",F7)-1) -> zjs_ui_globalsale_o4_0001_g4ba | D7: {=INDEX('Not Req'!$E$4:$E$71,MATCH(MID(F7,FIND(".",F7)+1,LEN(F7)-FIND(".",F7)+1),'Not Req'!$D$4:$D$71,0))} -> Inbound Service | E7: =INDEX('Not Req'!$F$4:$F$71,MATCH(MID(F7,FIND(".",F7)+1,LEN(F7)-FIND(".",F7)+1),'Not Req'!$D$4:$D$71,0)) -> 3. Cloud Communication Management | F7: zjs_ui_globalsale_o4_0001_g4ba.sco2.xml | G7: UPDATED ON 02-FEB-26 | H7: 3 months ago
A8: D | B8: OK | C8: =LEFT(F8,FIND(".",F8)-1) -> zjs_c_sainfo | D8: {=INDEX('Not Req'!$E$4:$E$71,MATCH(MID(F8,FIND(".",F8)+1,LEN(F8)-FIND(".",F8)+1),'Not Req'!$D$4:$D$71,0))} -> Access Control | E8: =INDEX('Not Req'!$F$4:$F$71,MATCH(MID(F8,FIND(".",F8)+1,LEN(F8)-FIND(".",F8)+1),'Not Req'!$D$4:$D$71,0)) -> 4. CDS | F8: zjs_c_sainfo.dcls.asdcls | G8: UPDATED ON 02-FEB-26 | H8: 3 months ago
A9: D | B9: OK | C9: =LEFT(F9,FIND(".",F9)-1) -> zjs_c_sasale | D9: {=INDEX('Not Req'!$E$4:$E$71,MATCH(MID(F9,FIND(".",F9)+1,LEN(F9)-FIND(".",F9)+1),'Not Req'!$D$4:$D$71,0))} -> Access Control | E9: =INDEX('Not Req'!$F$4:$F$71,MATCH(MID(F9,FIND(".",F9)+1,LEN(F9)-FIND(".",F9)+1),'Not Req'!$D$4:$D$71,0)) -> 4. CDS | F9: zjs_c_sasale.dcls.asdcls | G9: UPDATED ON 02-FEB-26 | H9: 3 months ago
A10: D | B10: OK | C10: =LEFT(F10,FIND(".",F10)-1) -> zjs_c_saseller | D10: {=INDEX('Not Req'!$E$4:$E$71,MATCH(MID(F10,FIND(".",F10)+1,LEN(F10)-FIND(".",F10)+1),'Not Req'!$D$4:$D$71,0))} -> Access Control | E10: =INDEX('Not Req'!$F$4:$F$71,MATCH(MID(F10,FIND(".",F10)+1,LEN(F10)-FIND(".",F10)+1),'Not Req'!$D$4:$D$71,0)) -> 4. CDS | F10: zjs_c_saseller.dcls.asdcls | G10: UPDATED ON 02-FEB-26 | H10: 3 months ago
A11: D | B11: OK | C11: =LEFT(F11,FIND(".",F11)-1) -> zjs_c_sasold | D11: {=INDEX('Not Req'!$E$4:$E$71,MATCH(MID(F11,FIND(".",F11)+1,LEN(F11)-FIND(".",F11)+1),'Not Req'!$D$4:$D$71,0))} -> Access Control | E11: =INDEX('Not Req'!$F$4:$F$71,MATCH(MID(F11,FIND(".",F11)+1,LEN(F11)-FIND(".",F11)+1),'Not Req'!$D$4:$D$71,0)) -> 4. CDS | F11: zjs_c_sasold.dcls.asdcls | G11: UPDATED ON 02-FEB-26 | H11: 3 months ago
A12: D | B12: OK | C12: =LEFT(F12,FIND(".",F12)-1) -> zjs_r_sainfo | D12: {=INDEX('Not Req'!$E$4:$E$71,MATCH(MID(F12,FIND(".",F12)+1,LEN(F12)-FIND(".",F12)+1),'Not Req'!$D$4:$D$71,0))} -> Access Control | E12: =INDEX('Not Req'!$F$4:$F$71,MATCH(MID(F12,FIND(".",F12)+1,LEN(F12)-FIND(".",F12)+1),'Not Req'!$D$4:$D$71,0)) -> 4. CDS | F12: zjs_r_sainfo.dcls.asdcls | G12: UPDATED ON 02-FEB-26 | H12: 3 months ago
A13: D | B13: OK | C13: =LEFT(F13,FIND(".",F13)-1) -> zjs_r_sasale | D13: {=INDEX('Not Req'!$E$4:$E$71,MATCH(MID(F13,FIND(".",F13)+1,LEN(F13)-FIND(".",F13)+1),'Not Req'!$D$4:$D$71,0))} -> Access Control | E13: =INDEX('Not Req'!$F$4:$F$71,MATCH(MID(F13,FIND(".",F13)+1,LEN(F13)-FIND(".",F13)+1),'Not Req'!$D$4:$D$71,0)) -> 4. CDS | F13: zjs_r_sasale.dcls.asdcls | G13: UPDATED ON 02-FEB-26 | H13: 3 months ago
A14: D | B14: OK | C14: =LEFT(F14,FIND(".",F14)-1) -> zjs_r_saseller | D14: {=INDEX('Not Req'!$E$4:$E$71,MATCH(MID(F14,FIND(".",F14)+1,LEN(F14)-FIND(".",F14)+1),'Not Req'!$D$4:$D$71,0))} -> Access Control | E14: =INDEX('Not Req'!$F$4:$F$71,MATCH(MID(F14,FIND(".",F14)+1,LEN(F14)-FIND(".",F14)+1),'Not Req'!$D$4:$D$71,0)) -> 4. CDS | F14: zjs_r_saseller.dcls.asdcls | G14: UPDATED ON 02-FEB-26 | H14: 3 months ago
A15: D | B15: OK | C15: =LEFT(F15,FIND(".",F15)-1) -> zjs_r_sasold | D15: {=INDEX('Not Req'!$E$4:$E$71,MATCH(MID(F15,FIND(".",F15)+1,LEN(F15)-FIND(".",F15)+1),'Not Req'!$D$4:$D$71,0))} -> Access Control | E15: =INDEX('Not Req'!$F$4:$F$71,MATCH(MID(F15,FIND(".",F15)+1,LEN(F15)-FIND(".",F15)+1),'Not Req'!$D$4:$D$71,0)) -> 4. CDS | F15: zjs_r_sasold.dcls.asdcls | G15: UPDATED ON 02-FEB-26 | H15: 3 months ago
... A69: D | B69: OK | C69: =LEFT(F69,FIND(".",F69)-1) -> zjs_bp_r_sasale | D69: {=INDEX('Not Req'!$E$4:$E$71,MATCH(MID(F69,FIND(".",F69)+1,LEN(F69)-FIND(".",F69)+1),'Not Req'!$D$4:$D$71,0))} -> Classes Local | E69: =INDEX('Not Req'!$F$4:$F$71,MATCH(MID(F69,FIND(".",F69)+1,LEN(F69)-FIND(".",F69)+1),'Not Req'!$D$4:$D$71,0)) -> 7. Source Code Library | F69: zjs_bp_r_sasale.clas.locals_imp.abap | G69: UPDATED ON 02-FEB-26 | H69: 3 months ago
A70: D | C70: =LEFT(F70,FIND(".",F70)-1) -> zjs_c_sainfo | D70: {=INDEX('Not Req'!$E$4:$E$71,MATCH(MID(F70,FIND(".",F70)+1,LEN(F70)-FIND(".",F70)+1),'Not Req'!$D$4:$D$71,0))} -> BaseInfo : Data Definition | E70: =INDEX('Not Req'!$F$4:$F$71,MATCH(MID(F70,FIND(".",F70)+1,LEN(F70)-FIND(".",F70)+1),'Not Req'!$D$4:$D$71,0)) -> 98. Base Info | F70: zjs_c_sainfo.ddls.baseinfo | G70: UPDATED ON 02-FEB-26 | H70: 3 months ago
A71: D | C71: =LEFT(F71,FIND(".",F71)-1) -> zjs_c_sasale | D71: {=INDEX('Not Req'!$E$4:$E$71,MATCH(MID(F71,FIND(".",F71)+1,LEN(F71)-FIND(".",F71)+1),'Not Req'!$D$4:$D$71,0))} -> BaseInfo : Data Definition | E71: =INDEX('Not Req'!$F$4:$F$71,MATCH(MID(F71,FIND(".",F71)+1,LEN(F71)-FIND(".",F71)+1),'Not Req'!$D$4:$D$71,0)) -> 98. Base Info | F71: zjs_c_sasale.ddls.baseinfo | G71: UPDATED ON 02-FEB-26 | H71: 3 months ago
A72: D | C72: =LEFT(F72,FIND(".",F72)-1) -> zjs_c_saseller | D72: {=INDEX('Not Req'!$E$4:$E$71,MATCH(MID(F72,FIND(".",F72)+1,LEN(F72)-FIND(".",F72)+1),'Not Req'!$D$4:$D$71,0))} -> BaseInfo : Data Definition | E72: =INDEX('Not Req'!$F$4:$F$71,MATCH(MID(F72,FIND(".",F72)+1,LEN(F72)-FIND(".",F72)+1),'Not Req'!$D$4:$D$71,0)) -> 98. Base Info | F72: zjs_c_saseller.ddls.baseinfo | G72: UPDATED ON 02-FEB-26 | H72: 3 months ago
A73: D | C73: =LEFT(F73,FIND(".",F73)-1) -> zjs_c_sasold | D73: {=INDEX('Not Req'!$E$4:$E$71,MATCH(MID(F73,FIND(".",F73)+1,LEN(F73)-FIND(".",F73)+1),'Not Req'!$D$4:$D$71,0))} -> BaseInfo : Data Definition | E73: =INDEX('Not Req'!$F$4:$F$71,MATCH(MID(F73,FIND(".",F73)+1,LEN(F73)-FIND(".",F73)+1),'Not Req'!$D$4:$D$71,0)) -> 98. Base Info | F73: zjs_c_sasold.ddls.baseinfo | G73: UPDATED ON 02-FEB-26 | H73: 3 months ago
A74: D | C74: =LEFT(F74,FIND(".",F74)-1) -> zjs_i_samaterialvh | D74: {=INDEX('Not Req'!$E$4:$E$71,MATCH(MID(F74,FIND(".",F74)+1,LEN(F74)-FIND(".",F74)+1),'Not Req'!$D$4:$D$71,0))} -> BaseInfo : Data Definition | E74: =INDEX('Not Req'!$F$4:$F$71,MATCH(MID(F74,FIND(".",F74)+1,LEN(F74)-FIND(".",F74)+1),'Not Req'!$D$4:$D$71,0)) -> 98. Base Info | F74: zjs_i_samaterialvh.ddls.baseinfo | G74: UPDATED ON 02-FEB-26 | H74: 3 months ago
A75: D | C75: =LEFT(F75,FIND(".",F75)-1) -> zjs_r_sainfo | D75: {=INDEX('Not Req'!$E$4:$E$71,MATCH(MID(F75,FIND(".",F75)+1,LEN(F75)-FIND(".",F75)+1),'Not Req'!$D$4:$D$71,0))} -> BaseInfo : Data Definition | E75: =INDEX('Not Req'!$F$4:$F$71,MATCH(MID(F75,FIND(".",F75)+1,LEN(F75)-FIND(".",F75)+1),'Not Req'!$D$4:$D$71,0)) -> 98. Base Info | F75: zjs_r_sainfo.ddls.baseinfo | G75: UPDATED ON 02-FEB-26 | H75: 3 months ago
A76: D | C76: =LEFT(F76,FIND(".",F76)-1) -> zjs_r_sasale | D76: {=INDEX('Not Req'!$E$4:$E$71,MATCH(MID(F76,FIND(".",F76)+1,LEN(F76)-FIND(".",F76)+1),'Not Req'!$D$4:$D$71,0))} -> BaseInfo : Data Definition | E76: =INDEX('Not Req'!$F$4:$F$71,MATCH(MID(F76,FIND(".",F76)+1,LEN(F76)-FIND(".",F76)+1),'Not Req'!$D$4:$D$71,0)) -> 98. Base Info | F76: zjs_r_sasale.ddls.baseinfo | G76: UPDATED ON 02-FEB-26 | H76: 3 months ago
A77: D | C77: =LEFT(F77,FIND(".",F77)-1) -> zjs_r_saseller | D77: {=INDEX('Not Req'!$E$4:$E$71,MATCH(MID(F77,FIND(".",F77)+1,LEN(F77)-FIND(".",F77)+1),'Not Req'!$D$4:$D$71,0))} -> BaseInfo : Data Definition | E77: =INDEX('Not Req'!$F$4:$F$71,MATCH(MID(F77,FIND(".",F77)+1,LEN(F77)-FIND(".",F77)+1),'Not Req'!$D$4:$D$71,0)) -> 98. Base Info | F77: zjs_r_saseller.ddls.baseinfo | G77: UPDATED ON 02-FEB-26 | H77: 3 months ago
A78: D | C78: =LEFT(F78,FIND(".",F78)-1) -> zjs_r_sasold | D78: {=INDEX('Not Req'!$E$4:$E$71,MATCH(MID(F78,FIND(".",F78)+1,LEN(F78)-FIND(".",F78)+1),'Not Req'!$D$4:$D$71,0))} -> BaseInfo : Data Definition | E78: =INDEX('Not Req'!$F$4:$F$71,MATCH(MID(F78,FIND(".",F78)+1,LEN(F78)-FIND(".",F78)+1),'Not Req'!$D$4:$D$71,0)) -> 98. Base Info | F78: zjs_r_sasold.ddls.baseinfo | G78: UPDATED ON 02-FEB-26 | H78: 3 months ago
A79: D | C79: =LEFT(F79,FIND(".",F79)-1) -> zjs_s_sainfo | D79: {=INDEX('Not Req'!$E$4:$E$71,MATCH(MID(F79,FIND(".",F79)+1,LEN(F79)-FIND(".",F79)+1),'Not Req'!$D$4:$D$71,0))} -> BaseInfo : Data Definition | E79: =INDEX('Not Req'!$F$4:$F$71,MATCH(MID(F79,FIND(".",F79)+1,LEN(F79)-FIND(".",F79)+1),'Not Req'!$D$4:$D$71,0)) -> 98. Base Info | F79: zjs_s_sainfo.ddls.baseinfo | G79: UPDATED ON 02-FEB-26 | H79: 3 months ago
A80: D | C80: =LEFT(F80,FIND(".",F80)-1) -> zjs_s_sasale | D80: {=INDEX('Not Req'!$E$4:$E$71,MATCH(MID(F80,FIND(".",F80)+1,LEN(F80)-FIND(".",F80)+1),'Not Req'!$D$4:$D$71,0))} -> BaseInfo : Data Definition | E80: =INDEX('Not Req'!$F$4:$F$71,MATCH(MID(F80,FIND(".",F80)+1,LEN(F80)-FIND(".",F80)+1),'Not Req'!$D$4:$D$71,0)) -> 98. Base Info | F80: zjs_s_sasale.ddls.baseinfo | G80: UPDATED ON 02-FEB-26 | H80: 3 months ago
A81: D | C81: =LEFT(F81,FIND(".",F81)-1) -> zjs_s_saseller | D81: {=INDEX('Not Req'!$E$4:$E$71,MATCH(MID(F81,FIND(".",F81)+1,LEN(F81)-FIND(".",F81)+1),'Not Req'!$D$4:$D$71,0))} -> BaseInfo : Data Definition | E81: =INDEX('Not Req'!$F$4:$F$71,MATCH(MID(F81,FIND(".",F81)+1,LEN(F81)-FIND(".",F81)+1),'Not Req'!$D$4:$D$71,0)) -> 98. Base Info | F81: zjs_s_saseller.ddls.baseinfo | G81: UPDATED ON 02-FEB-26 | H81: 3 months ago
... A117: D | C117: =LEFT(F117,FIND(".",F117)-1) -> zjs_globalsale | D117: {=INDEX('Not Req'!$E$4:$E$71,MATCH(MID(F117,FIND(".",F117)+1,LEN(F117)-FIND(".",F117)+1),'Not Req'!$D$4:$D$71,0))} -> #N/A | E117: =INDEX('Not Req'!$F$4:$F$71,MATCH(MID(F117,FIND(".",F117)+1,LEN(F117)-FIND(".",F117)+1),'Not Req'!$D$4:$D$71,0)) -> #N/A | F117: zjs_globalsale.ront.json | G117: UPDATED ON 02-FEB-26 | H117: 3 months ago

Sheet ZJS_11_RAP_CUSTOM_ACTION
A2: d | B2: d | C2: Object | D2: Type | E2: Category | F2: Github Object | G2: Github Type | H2: Version
A4: D | B4: OK | C4: =LEFT(F4,FIND(".",F4)-1) -> 054eb8e77fe0d2fb2e9f8e06b34faeht | D4: {=INDEX('Not Req'!$E$4:$E$71,MATCH(MID(F4,FIND(".",F4)+1,LEN(F4)-FIND(".",F4)+1),'Not Req'!$D$4:$D$71,0))} -> Authorization Defaults (TADIR) | E4: =INDEX('Not Req'!$F$4:$F$71,MATCH(MID(F4,FIND(".",F4)+1,LEN(F4)-FIND(".",F4)+1),'Not Req'!$D$4:$D$71,0)) -> 1. Authorizations | F4: 054eb8e77fe0d2fb2e9f8e06b34faeht.sush.xml | G4: UPDATED ON 02-FEB-26 | H4: 3 months ago
A5: D | B5: OK | C5: =LEFT(F5,FIND(".",F5)-1) -> 81ec0b0855ed7dace8b1158851d483ht | D5: {=INDEX('Not Req'!$E$4:$E$71,MATCH(MID(F5,FIND(".",F5)+1,LEN(F5)-FIND(".",F5)+1),'Not Req'!$D$4:$D$71,0))} -> Authorization Defaults (TADIR) | E5: =INDEX('Not Req'!$F$4:$F$71,MATCH(MID(F5,FIND(".",F5)+1,LEN(F5)-FIND(".",F5)+1),'Not Req'!$D$4:$D$71,0)) -> 1. Authorizations | F5: 81ec0b0855ed7dace8b1158851d483ht.sush.xml | G5: UPDATED ON 02-FEB-26 | H5: 3 months ago
A6: D | B6: OK | C6: =LEFT(F6,FIND(".",F6)-1) -> zjs_custom_action | D6: {=INDEX('Not Req'!$E$4:$E$71,MATCH(MID(F6,FIND(".",F6)+1,LEN(F6)-FIND(".",F6)+1),'Not Req'!$D$4:$D$71,0))} -> Service Definition | E6: =INDEX('Not Req'!$F$4:$F$71,MATCH(MID(F6,FIND(".",F6)+1,LEN(F6)-FIND(".",F6)+1),'Not Req'!$D$4:$D$71,0)) -> 2. Business Services | F6: zjs_custom_action.srvd.srvdsrv | G6: UPDATED ON 02-FEB-26 | H6: 3 months ago
A7: D | B7: OK | C7: =LEFT(F7,FIND(".",F7)-1) -> zjs_ui_custom_action_o2 | D7: {=INDEX('Not Req'!$E$4:$E$71,MATCH(MID(F7,FIND(".",F7)+1,LEN(F7)-FIND(".",F7)+1),'Not Req'!$D$4:$D$71,0))} -> Service Binding | E7: =INDEX('Not Req'!$F$4:$F$71,MATCH(MID(F7,FIND(".",F7)+1,LEN(F7)-FIND(".",F7)+1),'Not Req'!$D$4:$D$71,0)) -> 2. Business Services | F7: zjs_ui_custom_action_o2.srvb.xml | G7: UPDATED ON 02-FEB-26 | H7: 3 months ago
A8: D | B8: OK | C8: =LEFT(F8,FIND(".",F8)-1) -> zjs_ui_custom_action_o2_iwsg | D8: {=INDEX('Not Req'!$E$4:$E$71,MATCH(MID(F8,FIND(".",F8)+1,LEN(F8)-FIND(".",F8)+1),'Not Req'!$D$4:$D$71,0))} -> Inbound Service | E8: =INDEX('Not Req'!$F$4:$F$71,MATCH(MID(F8,FIND(".",F8)+1,LEN(F8)-FIND(".",F8)+1),'Not Req'!$D$4:$D$71,0)) -> 3. Cloud Communication Management | F8: zjs_ui_custom_action_o2_iwsg.sco2.xml | G8: UPDATED ON 02-FEB-26 | H8: 3 months ago
A9: D | B9: OK | C9: =LEFT(F9,FIND(".",F9)-1) -> zjs_r_cusactentitytp | D9: {=INDEX('Not Req'!$E$4:$E$71,MATCH(MID(F9,FIND(".",F9)+1,LEN(F9)-FIND(".",F9)+1),'Not Req'!$D$4:$D$71,0))} -> BDEF | E9: =INDEX('Not Req'!$F$4:$F$71,MATCH(MID(F9,FIND(".",F9)+1,LEN(F9)-FIND(".",F9)+1),'Not Req'!$D$4:$D$71,0)) -> 4. CDS | F9: zjs_r_cusactentitytp.bdef.asbdef | G9: UPDATED ON 02-FEB-26 | H9: 3 months ago
A10: D | B10: OK | C10: =LEFT(F10,FIND(".",F10)-1) -> zjs_r_cusactentitytp | D10: {=INDEX('Not Req'!$E$4:$E$71,MATCH(MID(F10,FIND(".",F10)+1,LEN(F10)-FIND(".",F10)+1),'Not Req'!$D$4:$D$71,0))} -> Data Definition | E10: =INDEX('Not Req'!$F$4:$F$71,MATCH(MID(F10,FIND(".",F10)+1,LEN(F10)-FIND(".",F10)+1),'Not Req'!$D$4:$D$71,0)) -> 4. CDS | F10: zjs_r_cusactentitytp.ddls.asddls | G10: UPDATED ON 02-FEB-26 | H10: 3 months ago
A11: D | B11: OK | C11: =LEFT(F11,FIND(".",F11)-1) -> zjs_dmo_cstat | D11: {=INDEX('Not Req'!$E$4:$E$71,MATCH(MID(F11,FIND(".",F11)+1,LEN(F11)-FIND(".",F11)+1),'Not Req'!$D$4:$D$71,0))} -> Table | E11: =INDEX('Not Req'!$F$4:$F$71,MATCH(MID(F11,FIND(".",F11)+1,LEN(F11)-FIND(".",F11)+1),'Not Req'!$D$4:$D$71,0)) -> 5. Dictionary | F11: zjs_dmo_cstat.tabl.xml | G11: UPDATED ON 02-FEB-26 | H11: 3 months ago
A12: D | B12: OK | C12: =LEFT(F12,FIND(".",F12)-1) -> zbp_js_demo_custom_action | D12: {=INDEX('Not Req'!$E$4:$E$71,MATCH(MID(F12,FIND(".",F12)+1,LEN(F12)-FIND(".",F12)+1),'Not Req'!$D$4:$D$71,0))} -> Classes | E12: =INDEX('Not Req'!$F$4:$F$71,MATCH(MID(F12,FIND(".",F12)+1,LEN(F12)-FIND(".",F12)+1),'Not Req'!$D$4:$D$71,0)) -> 7. Source Code Library | F12: zbp_js_demo_custom_action.clas.abap | G12: Updated 16-Mar-26 | H12: 2 months ago
A13: D | B13: OK | C13: =LEFT(F13,FIND(".",F13)-1) -> zbp_js_demo_custom_action | D13: {=INDEX('Not Req'!$E$4:$E$71,MATCH(MID(F13,FIND(".",F13)+1,LEN(F13)-FIND(".",F13)+1),'Not Req'!$D$4:$D$71,0))} -> Classes Local | E13: =INDEX('Not Req'!$F$4:$F$71,MATCH(MID(F13,FIND(".",F13)+1,LEN(F13)-FIND(".",F13)+1),'Not Req'!$D$4:$D$71,0)) -> 7. Source Code Library | F13: zbp_js_demo_custom_action.clas.locals_imp.abap | G13: UPDATED ON 02-FEB-26 | H13: 3 months ago
A14: D | B14: OK | C14: =LEFT(F14,FIND(".",F14)-1) -> zcl_js_demo_custom_action_qry | D14: {=INDEX('Not Req'!$E$4:$E$71,MATCH(MID(F14,FIND(".",F14)+1,LEN(F14)-FIND(".",F14)+1),'Not Req'!$D$4:$D$71,0))} -> Classes | E14: =INDEX('Not Req'!$F$4:$F$71,MATCH(MID(F14,FIND(".",F14)+1,LEN(F14)-FIND(".",F14)+1),'Not Req'!$D$4:$D$71,0)) -> 7. Source Code Library | F14: zcl_js_demo_custom_action_qry.clas.abap | G14: Updated 16-Mar-26 | H14: 2 months ago
A15: D | B15: OK | C15: =LEFT(F15,FIND(".",F15)-1) -> zjs_r_cusactentitytp | D15: {=INDEX('Not Req'!$E$4:$E$71,MATCH(MID(F15,FIND(".",F15)+1,LEN(F15)-FIND(".",F15)+1),'Not Req'!$D$4:$D$71,0))} -> BaseInfo : Data Definition | E15: =INDEX('Not Req'!$F$4:$F$71,MATCH(MID(F15,FIND(".",F15)+1,LEN(F15)-FIND(".",F15)+1),'Not Req'!$D$4:$D$71,0)) -> 98. Base Info | F15: zjs_r_cusactentitytp.ddls.baseinfo | G15: UPDATED ON 02-FEB-26 | H15: 3 months ago
... A21: D | B21: OK | C21: =LEFT(F21,FIND(".",F21)-1) -> zjs_r_cusactentitytp | D21: {=INDEX('Not Req'!$E$4:$E$71,MATCH(MID(F21,FIND(".",F21)+1,LEN(F21)-FIND(".",F21)+1),'Not Req'!$D$4:$D$71,0))} -> Description : Data Definition | E21: =INDEX('Not Req'!$F$4:$F$71,MATCH(MID(F21,FIND(".",F21)+1,LEN(F21)-FIND(".",F21)+1),'Not Req'!$D$4:$D$71,0)) -> 99. Descriptions | F21: zjs_r_cusactentitytp.ddls.xml | G21: UPDATED ON 02-FEB-26 | H21: 3 months ago

Sheet ZJS_10_RAP_TREE
A2: d | B2: d | C2: Object | D2: Type | E2: Category | F2: Github Object | G2: Github Type | H2: Version
A4: D | B4: OK | C4: =LEFT(F4,FIND(".",F4)-1) -> 03cee98b070e44773f34d25bf0e8a4ht | D4: {=INDEX('Not Req'!$E$4:$E$71,MATCH(MID(F4,FIND(".",F4)+1,LEN(F4)-FIND(".",F4)+1),'Not Req'!$D$4:$D$71,0))} -> Authorization Defaults (TADIR) | E4: =INDEX('Not Req'!$F$4:$F$71,MATCH(MID(F4,FIND(".",F4)+1,LEN(F4)-FIND(".",F4)+1),'Not Req'!$D$4:$D$71,0)) -> 1. Authorizations | F4: 03cee98b070e44773f34d25bf0e8a4ht.sush.xml | G4: UPDATED ON 02-FEB-26 | H4: 3 months ago
A5: D | B5: OK | C5: =LEFT(F5,FIND(".",F5)-1) -> zjs_demo_tree_team | D5: {=INDEX('Not Req'!$E$4:$E$71,MATCH(MID(F5,FIND(".",F5)+1,LEN(F5)-FIND(".",F5)+1),'Not Req'!$D$4:$D$71,0))} -> Service Definition | E5: =INDEX('Not Req'!$F$4:$F$71,MATCH(MID(F5,FIND(".",F5)+1,LEN(F5)-FIND(".",F5)+1),'Not Req'!$D$4:$D$71,0)) -> 2. Business Services | F5: zjs_demo_tree_team.srvd.srvdsrv | G5: UPDATED ON 02-FEB-26 | H5: 3 months ago
A6: D | B6: OK | C6: =LEFT(F6,FIND(".",F6)-1) -> zjs_ui_demo_tree_team_o4 | D6: {=INDEX('Not Req'!$E$4:$E$71,MATCH(MID(F6,FIND(".",F6)+1,LEN(F6)-FIND(".",F6)+1),'Not Req'!$D$4:$D$71,0))} -> Service Binding | E6: =INDEX('Not Req'!$F$4:$F$71,MATCH(MID(F6,FIND(".",F6)+1,LEN(F6)-FIND(".",F6)+1),'Not Req'!$D$4:$D$71,0)) -> 2. Business Services | F6: zjs_ui_demo_tree_team_o4.srvb.xml | G6: UPDATED ON 02-FEB-26 | H6: 3 months ago
A7: D | B7: OK | C7: =LEFT(F7,FIND(".",F7)-1) -> zjs_ui_demo_tree_team_o4_0001_g4ba | D7: {=INDEX('Not Req'!$E$4:$E$71,MATCH(MID(F7,FIND(".",F7)+1,LEN(F7)-FIND(".",F7)+1),'Not Req'!$D$4:$D$71,0))} -> Inbound Service | E7: =INDEX('Not Req'!$F$4:$F$71,MATCH(MID(F7,FIND(".",F7)+1,LEN(F7)-FIND(".",F7)+1),'Not Req'!$D$4:$D$71,0)) -> 3. Cloud Communication Management | F7: zjs_ui_demo_tree_team_o4_0001_g4ba.sco2.xml | G7: UPDATED ON 02-FEB-26 | H7: 3 months ago
A8: D | B8: OK | C8: =LEFT(F8,FIND(".",F8)-1) -> zjs_c_dmotreeteam | D8: {=INDEX('Not Req'!$E$4:$E$71,MATCH(MID(F8,FIND(".",F8)+1,LEN(F8)-FIND(".",F8)+1),'Not Req'!$D$4:$D$71,0))} -> BDEF | E8: =INDEX('Not Req'!$F$4:$F$71,MATCH(MID(F8,FIND(".",F8)+1,LEN(F8)-FIND(".",F8)+1),'Not Req'!$D$4:$D$71,0)) -> 4. CDS | F8: zjs_c_dmotreeteam.bdef.asbdef | G8: UPDATED ON 02-FEB-26 | H8: 3 months ago
A9: D | B9: OK | C9: =LEFT(F9,FIND(".",F9)-1) -> zjs_c_dmotreeteam | D9: {=INDEX('Not Req'!$E$4:$E$71,MATCH(MID(F9,FIND(".",F9)+1,LEN(F9)-FIND(".",F9)+1),'Not Req'!$D$4:$D$71,0))} -> Data Definition | E9: =INDEX('Not Req'!$F$4:$F$71,MATCH(MID(F9,FIND(".",F9)+1,LEN(F9)-FIND(".",F9)+1),'Not Req'!$D$4:$D$71,0)) -> 4. CDS | F9: zjs_c_dmotreeteam.ddls.asddls | G9: UPDATED ON 02-FEB-26 | H9: 3 months ago
A10: D | B10: OK | C10: =LEFT(F10,FIND(".",F10)-1) -> zjs_c_dmotreeteam | D10: {=INDEX('Not Req'!$E$4:$E$71,MATCH(MID(F10,FIND(".",F10)+1,LEN(F10)-FIND(".",F10)+1),'Not Req'!$D$4:$D$71,0))} -> Metadata | E10: =INDEX('Not Req'!$F$4:$F$71,MATCH(MID(F10,FIND(".",F10)+1,LEN(F10)-FIND(".",F10)+1),'Not Req'!$D$4:$D$71,0)) -> 4. CDS | F10: zjs_c_dmotreeteam.ddlx.asddlxs | G10: UPDATED ON 02-FEB-26 | H10: 3 months ago
A11: D | B11: OK | C11: =LEFT(F11,FIND(".",F11)-1) -> zjs_i_dmotreeteamhr | D11: {=INDEX('Not Req'!$E$4:$E$71,MATCH(MID(F11,FIND(".",F11)+1,LEN(F11)-FIND(".",F11)+1),'Not Req'!$D$4:$D$71,0))} -> Data Definition | E11: =INDEX('Not Req'!$F$4:$F$71,MATCH(MID(F11,FIND(".",F11)+1,LEN(F11)-FIND(".",F11)+1),'Not Req'!$D$4:$D$71,0)) -> 4. CDS | F11: zjs_i_dmotreeteamhr.ddls.asddls | G11: UPDATED ON 02-FEB-26 | H11: 3 months ago
A12: D | B12: OK | C12: =LEFT(F12,FIND(".",F12)-1) -> zjs_r_dmotreeteam | D12: {=INDEX('Not Req'!$E$4:$E$71,MATCH(MID(F12,FIND(".",F12)+1,LEN(F12)-FIND(".",F12)+1),'Not Req'!$D$4:$D$71,0))} -> BDEF | E12: =INDEX('Not Req'!$F$4:$F$71,MATCH(MID(F12,FIND(".",F12)+1,LEN(F12)-FIND(".",F12)+1),'Not Req'!$D$4:$D$71,0)) -> 4. CDS | F12: zjs_r_dmotreeteam.bdef.asbdef | G12: UPDATED ON 02-FEB-26 | H12: 3 months ago
A13: D | B13: OK | C13: =LEFT(F13,FIND(".",F13)-1) -> zjs_r_dmotreeteam | D13: {=INDEX('Not Req'!$E$4:$E$71,MATCH(MID(F13,FIND(".",F13)+1,LEN(F13)-FIND(".",F13)+1),'Not Req'!$D$4:$D$71,0))} -> Data Definition | E13: =INDEX('Not Req'!$F$4:$F$71,MATCH(MID(F13,FIND(".",F13)+1,LEN(F13)-FIND(".",F13)+1),'Not Req'!$D$4:$D$71,0)) -> 4. CDS | F13: zjs_r_dmotreeteam.ddls.asddls | G13: UPDATED ON 02-FEB-26 | H13: 3 months ago
A14: D | B14: OK | C14: =LEFT(F14,FIND(".",F14)-1) -> zjs_dmo_team_d | D14: {=INDEX('Not Req'!$E$4:$E$71,MATCH(MID(F14,FIND(".",F14)+1,LEN(F14)-FIND(".",F14)+1),'Not Req'!$D$4:$D$71,0))} -> Table | E14: =INDEX('Not Req'!$F$4:$F$71,MATCH(MID(F14,FIND(".",F14)+1,LEN(F14)-FIND(".",F14)+1),'Not Req'!$D$4:$D$71,0)) -> 5. Dictionary | F14: zjs_dmo_team_d.tabl.xml | G14: UPDATED ON 02-FEB-26 | H14: 3 months ago
A15: D | B15: OK | C15: =LEFT(F15,FIND(".",F15)-1) -> zbp_js_demo_tree_team | D15: {=INDEX('Not Req'!$E$4:$E$71,MATCH(MID(F15,FIND(".",F15)+1,LEN(F15)-FIND(".",F15)+1),'Not Req'!$D$4:$D$71,0))} -> Classes | E15: =INDEX('Not Req'!$F$4:$F$71,MATCH(MID(F15,FIND(".",F15)+1,LEN(F15)-FIND(".",F15)+1),'Not Req'!$D$4:$D$71,0)) -> 7. Source Code Library | F15: zbp_js_demo_tree_team.clas.abap | G15: Updated 16-Mar-26 | H15: 2 months ago
... A30: D | B30: OK | C30: =LEFT(F30,FIND(".",F30)-1) -> zjs_r_dmotreeteam | D30: {=INDEX('Not Req'!$E$4:$E$71,MATCH(MID(F30,FIND(".",F30)+1,LEN(F30)-FIND(".",F30)+1),'Not Req'!$D$4:$D$71,0))} -> Description : Data Definition | E30: =INDEX('Not Req'!$F$4:$F$71,MATCH(MID(F30,FIND(".",F30)+1,LEN(F30)-FIND(".",F30)+1),'Not Req'!$D$4:$D$71,0)) -> 99. Descriptions | F30: zjs_r_dmotreeteam.ddls.xml | G30: UPDATED ON 02-FEB-26 | H30: 3 months ago

Sheet ZJS_09_RAP_PATTERN_CDS
A2: d | B2: d | C2: Object | D2: Type | E2: Category | F2: Github Object | G2: Github Type | H2: Version
A4: D | B4: OK | C4: =LEFT(F4,FIND(".",F4)-1) -> 5d8914eb3ed982b15fb404c39f15c6ht | D4: {=INDEX('Not Req'!$E$4:$E$71,MATCH(MID(F4,FIND(".",F4)+1,LEN(F4)-FIND(".",F4)+1),'Not Req'!$D$4:$D$71,0))} -> Authorization Defaults (TADIR) | E4: =INDEX('Not Req'!$F$4:$F$71,MATCH(MID(F4,FIND(".",F4)+1,LEN(F4)-FIND(".",F4)+1),'Not Req'!$D$4:$D$71,0)) -> 1. Authorizations | F4: 5d8914eb3ed982b15fb404c39f15c6ht.sush.xml | G4: UPDATED ON 02-FEB-26 | H4: 3 months ago
A5: D | B5: OK | C5: =LEFT(F5,FIND(".",F5)-1) -> zjs_demo_pattern_cds | D5: {=INDEX('Not Req'!$E$4:$E$71,MATCH(MID(F5,FIND(".",F5)+1,LEN(F5)-FIND(".",F5)+1),'Not Req'!$D$4:$D$71,0))} -> Service Definition | E5: =INDEX('Not Req'!$F$4:$F$71,MATCH(MID(F5,FIND(".",F5)+1,LEN(F5)-FIND(".",F5)+1),'Not Req'!$D$4:$D$71,0)) -> 2. Business Services | F5: zjs_demo_pattern_cds.srvd.srvdsrv | G5: UPDATED ON 02-FEB-26 | H5: 3 months ago
A6: D | B6: OK | C6: =LEFT(F6,FIND(".",F6)-1) -> zjs_ui_demo_pattern_cds_o4 | D6: {=INDEX('Not Req'!$E$4:$E$71,MATCH(MID(F6,FIND(".",F6)+1,LEN(F6)-FIND(".",F6)+1),'Not Req'!$D$4:$D$71,0))} -> Service Binding | E6: =INDEX('Not Req'!$F$4:$F$71,MATCH(MID(F6,FIND(".",F6)+1,LEN(F6)-FIND(".",F6)+1),'Not Req'!$D$4:$D$71,0)) -> 2. Business Services | F6: zjs_ui_demo_pattern_cds_o4.srvb.xml | G6: UPDATED ON 02-FEB-26 | H6: 3 months ago
A7: D | B7: OK | C7: =LEFT(F7,FIND(".",F7)-1) -> zjs_ui_demo_pattern_cds_o4_0001_g4ba | D7: {=INDEX('Not Req'!$E$4:$E$71,MATCH(MID(F7,FIND(".",F7)+1,LEN(F7)-FIND(".",F7)+1),'Not Req'!$D$4:$D$71,0))} -> Inbound Service | E7: =INDEX('Not Req'!$F$4:$F$71,MATCH(MID(F7,FIND(".",F7)+1,LEN(F7)-FIND(".",F7)+1),'Not Req'!$D$4:$D$71,0)) -> 3. Cloud Communication Management | F7: zjs_ui_demo_pattern_cds_o4_0001_g4ba.sco2.xml | G7: UPDATED ON 02-FEB-26 | H7: 3 months ago
A8: D | B8: OK | C8: =LEFT(F8,FIND(".",F8)-1) -> zjs_c_cdspatterninvoice | D8: {=INDEX('Not Req'!$E$4:$E$71,MATCH(MID(F8,FIND(".",F8)+1,LEN(F8)-FIND(".",F8)+1),'Not Req'!$D$4:$D$71,0))} -> BDEF | E8: =INDEX('Not Req'!$F$4:$F$71,MATCH(MID(F8,FIND(".",F8)+1,LEN(F8)-FIND(".",F8)+1),'Not Req'!$D$4:$D$71,0)) -> 4. CDS | F8: zjs_c_cdspatterninvoice.bdef.asbdef | G8: UPDATED ON 02-FEB-26 | H8: 3 months ago
A9: D | B9: OK | C9: =LEFT(F9,FIND(".",F9)-1) -> zjs_c_cdspatterninvoice | D9: {=INDEX('Not Req'!$E$4:$E$71,MATCH(MID(F9,FIND(".",F9)+1,LEN(F9)-FIND(".",F9)+1),'Not Req'!$D$4:$D$71,0))} -> Data Definition | E9: =INDEX('Not Req'!$F$4:$F$71,MATCH(MID(F9,FIND(".",F9)+1,LEN(F9)-FIND(".",F9)+1),'Not Req'!$D$4:$D$71,0)) -> 4. CDS | F9: zjs_c_cdspatterninvoice.ddls.asddls | G9: UPDATED ON 02-FEB-26 | H9: 3 months ago
A10: D | B10: OK | C10: =LEFT(F10,FIND(".",F10)-1) -> zjs_c_cdspatterninvoice | D10: {=INDEX('Not Req'!$E$4:$E$71,MATCH(MID(F10,FIND(".",F10)+1,LEN(F10)-FIND(".",F10)+1),'Not Req'!$D$4:$D$71,0))} -> Metadata | E10: =INDEX('Not Req'!$F$4:$F$71,MATCH(MID(F10,FIND(".",F10)+1,LEN(F10)-FIND(".",F10)+1),'Not Req'!$D$4:$D$71,0)) -> 4. CDS | F10: zjs_c_cdspatterninvoice.ddlx.asddlxs | G10: UPDATED ON 02-FEB-26 | H10: 3 months ago
A11: D | B11: OK | C11: =LEFT(F11,FIND(".",F11)-1) -> zjs_c_cdspatternposition | D11: {=INDEX('Not Req'!$E$4:$E$71,MATCH(MID(F11,FIND(".",F11)+1,LEN(F11)-FIND(".",F11)+1),'Not Req'!$D$4:$D$71,0))} -> Data Definition | E11: =INDEX('Not Req'!$F$4:$F$71,MATCH(MID(F11,FIND(".",F11)+1,LEN(F11)-FIND(".",F11)+1),'Not Req'!$D$4:$D$71,0)) -> 4. CDS | F11: zjs_c_cdspatternposition.ddls.asddls | G11: UPDATED ON 02-FEB-26 | H11: 3 months ago
A12: D | B12: OK | C12: =LEFT(F12,FIND(".",F12)-1) -> zjs_c_cdspatternposition | D12: {=INDEX('Not Req'!$E$4:$E$71,MATCH(MID(F12,FIND(".",F12)+1,LEN(F12)-FIND(".",F12)+1),'Not Req'!$D$4:$D$71,0))} -> Metadata | E12: =INDEX('Not Req'!$F$4:$F$71,MATCH(MID(F12,FIND(".",F12)+1,LEN(F12)-FIND(".",F12)+1),'Not Req'!$D$4:$D$71,0)) -> 4. CDS | F12: zjs_c_cdspatternposition.ddlx.asddlxs | G12: UPDATED ON 02-FEB-26 | H12: 3 months ago
A13: D | B13: OK | C13: =LEFT(F13,FIND(".",F13)-1) -> zjs_t_cdspatterninvoice | D13: {=INDEX('Not Req'!$E$4:$E$71,MATCH(MID(F13,FIND(".",F13)+1,LEN(F13)-FIND(".",F13)+1),'Not Req'!$D$4:$D$71,0))} -> BDEF | E13: =INDEX('Not Req'!$F$4:$F$71,MATCH(MID(F13,FIND(".",F13)+1,LEN(F13)-FIND(".",F13)+1),'Not Req'!$D$4:$D$71,0)) -> 4. CDS | F13: zjs_t_cdspatterninvoice.bdef.asbdef | G13: UPDATED ON 02-FEB-26 | H13: 3 months ago
A14: D | B14: OK | C14: =LEFT(F14,FIND(".",F14)-1) -> zjs_t_cdspatterninvoice | D14: {=INDEX('Not Req'!$E$4:$E$71,MATCH(MID(F14,FIND(".",F14)+1,LEN(F14)-FIND(".",F14)+1),'Not Req'!$D$4:$D$71,0))} -> Data Definition | E14: =INDEX('Not Req'!$F$4:$F$71,MATCH(MID(F14,FIND(".",F14)+1,LEN(F14)-FIND(".",F14)+1),'Not Req'!$D$4:$D$71,0)) -> 4. CDS | F14: zjs_t_cdspatterninvoice.ddls.asddls | G14: UPDATED ON 02-FEB-26 | H14: 3 months ago
A15: D | B15: OK | C15: =LEFT(F15,FIND(".",F15)-1) -> zjs_t_cdspatternposition | D15: {=INDEX('Not Req'!$E$4:$E$71,MATCH(MID(F15,FIND(".",F15)+1,LEN(F15)-FIND(".",F15)+1),'Not Req'!$D$4:$D$71,0))} -> Data Definition | E15: =INDEX('Not Req'!$F$4:$F$71,MATCH(MID(F15,FIND(".",F15)+1,LEN(F15)-FIND(".",F15)+1),'Not Req'!$D$4:$D$71,0)) -> 4. CDS | F15: zjs_t_cdspatternposition.ddls.asddls | G15: UPDATED ON 02-FEB-26 | H15: 3 months ago
... A34: D | B34: OK | C34: =LEFT(F34,FIND(".",F34)-1) -> zjs_t_cdspatternposition | D34: {=INDEX('Not Req'!$E$4:$E$71,MATCH(MID(F34,FIND(".",F34)+1,LEN(F34)-FIND(".",F34)+1),'Not Req'!$D$4:$D$71,0))} -> Description : Data Definition | E34: =INDEX('Not Req'!$F$4:$F$71,MATCH(MID(F34,FIND(".",F34)+1,LEN(F34)-FIND(".",F34)+1),'Not Req'!$D$4:$D$71,0)) -> 99. Descriptions | F34: zjs_t_cdspatternposition.ddls.xml | G34: UPDATED ON 02-FEB-26 | H34: 3 months ago

Sheet ZJS_09_RAP_PATTERN_API
A2: d | B2: d | C2: Object | D2: Type | E2: Category | F2: Github Object | G2: Github Type | H2: Version
A4: D | B4: OK | C4: =LEFT(F4,FIND(".",F4)-1) -> 5ed994ae4fae30b6406c5a3621a7b3ht | D4: {=INDEX('Not Req'!$E$4:$E$71,MATCH(MID(F4,FIND(".",F4)+1,LEN(F4)-FIND(".",F4)+1),'Not Req'!$D$4:$D$71,0))} -> Authorization Defaults (TADIR) | E4: =INDEX('Not Req'!$F$4:$F$71,MATCH(MID(F4,FIND(".",F4)+1,LEN(F4)-FIND(".",F4)+1),'Not Req'!$D$4:$D$71,0)) -> 1. Authorizations | F4: 5ed994ae4fae30b6406c5a3621a7b3ht.sush.xml | G4: UPDATED ON 02-FEB-26 | H4: 3 months ago
A5: D | B5: OK | C5: =LEFT(F5,FIND(".",F5)-1) -> 7d403d38fb13b39a2c4a63ab3dee0fht | D5: {=INDEX('Not Req'!$E$4:$E$71,MATCH(MID(F5,FIND(".",F5)+1,LEN(F5)-FIND(".",F5)+1),'Not Req'!$D$4:$D$71,0))} -> Authorization Defaults (TADIR) | E5: =INDEX('Not Req'!$F$4:$F$71,MATCH(MID(F5,FIND(".",F5)+1,LEN(F5)-FIND(".",F5)+1),'Not Req'!$D$4:$D$71,0)) -> 1. Authorizations | F5: 7d403d38fb13b39a2c4a63ab3dee0fht.sush.xml | G5: UPDATED ON 02-FEB-26 | H5: 3 months ago
A6: D | B6: OK | C6: =LEFT(F6,FIND(".",F6)-1) -> zjs_api_location_endp_o2 | D6: {=INDEX('Not Req'!$E$4:$E$71,MATCH(MID(F6,FIND(".",F6)+1,LEN(F6)-FIND(".",F6)+1),'Not Req'!$D$4:$D$71,0))} -> Service Binding | E6: =INDEX('Not Req'!$F$4:$F$71,MATCH(MID(F6,FIND(".",F6)+1,LEN(F6)-FIND(".",F6)+1),'Not Req'!$D$4:$D$71,0)) -> 2. Business Services | F6: zjs_api_location_endp_o2.srvb.xml | G6: UPDATED ON 02-FEB-26 | H6: 3 months ago
A7: D | B7: OK | C7: =LEFT(F7,FIND(".",F7)-1) -> zjs_api_location_endpoint | D7: {=INDEX('Not Req'!$E$4:$E$71,MATCH(MID(F7,FIND(".",F7)+1,LEN(F7)-FIND(".",F7)+1),'Not Req'!$D$4:$D$71,0))} -> Service Definition | E7: =INDEX('Not Req'!$F$4:$F$71,MATCH(MID(F7,FIND(".",F7)+1,LEN(F7)-FIND(".",F7)+1),'Not Req'!$D$4:$D$71,0)) -> 2. Business Services | F7: zjs_api_location_endpoint.srvd.srvdsrv | G7: UPDATED ON 02-FEB-26 | H7: 3 months ago
A8: D | B8: OK | C8: =LEFT(F8,FIND(".",F8)-1) -> zjs_api_location_endp_o2_iwsg | D8: {=INDEX('Not Req'!$E$4:$E$71,MATCH(MID(F8,FIND(".",F8)+1,LEN(F8)-FIND(".",F8)+1),'Not Req'!$D$4:$D$71,0))} -> Inbound Service | E8: =INDEX('Not Req'!$F$4:$F$71,MATCH(MID(F8,FIND(".",F8)+1,LEN(F8)-FIND(".",F8)+1),'Not Req'!$D$4:$D$71,0)) -> 3. Cloud Communication Management | F8: zjs_api_location_endp_o2_iwsg.sco2.xml | G8: UPDATED ON 02-FEB-26 | H8: 3 months ago
A9: D | B9: OK | C9: =LEFT(F9,FIND(".",F9)-1) -> zjs_r_apilocation | D9: {=INDEX('Not Req'!$E$4:$E$71,MATCH(MID(F9,FIND(".",F9)+1,LEN(F9)-FIND(".",F9)+1),'Not Req'!$D$4:$D$71,0))} -> BDEF | E9: =INDEX('Not Req'!$F$4:$F$71,MATCH(MID(F9,FIND(".",F9)+1,LEN(F9)-FIND(".",F9)+1),'Not Req'!$D$4:$D$71,0)) -> 4. CDS | F9: zjs_r_apilocation.bdef.asbdef | G9: UPDATED ON 02-FEB-26 | H9: 3 months ago
A10: D | B10: OK | C10: =LEFT(F10,FIND(".",F10)-1) -> zjs_r_apilocation | D10: {=INDEX('Not Req'!$E$4:$E$71,MATCH(MID(F10,FIND(".",F10)+1,LEN(F10)-FIND(".",F10)+1),'Not Req'!$D$4:$D$71,0))} -> Data Definition | E10: =INDEX('Not Req'!$F$4:$F$71,MATCH(MID(F10,FIND(".",F10)+1,LEN(F10)-FIND(".",F10)+1),'Not Req'!$D$4:$D$71,0)) -> 4. CDS | F10: zjs_r_apilocation.ddls.asddls | G10: UPDATED ON 02-FEB-26 | H10: 3 months ago
A11: D | B11: OK | C11: =LEFT(F11,FIND(".",F11)-1) -> zjs_api_target | D11: {=INDEX('Not Req'!$E$4:$E$71,MATCH(MID(F11,FIND(".",F11)+1,LEN(F11)-FIND(".",F11)+1),'Not Req'!$D$4:$D$71,0))} -> Table | E11: =INDEX('Not Req'!$F$4:$F$71,MATCH(MID(F11,FIND(".",F11)+1,LEN(F11)-FIND(".",F11)+1),'Not Req'!$D$4:$D$71,0)) -> 5. Dictionary | F11: zjs_api_target.tabl.xml | G11: UPDATED ON 02-FEB-26 | H11: 3 months ago
A12: D | B12: OK | C12: =LEFT(F12,FIND(".",F12)-1) -> zbp_js_api_location | D12: {=INDEX('Not Req'!$E$4:$E$71,MATCH(MID(F12,FIND(".",F12)+1,LEN(F12)-FIND(".",F12)+1),'Not Req'!$D$4:$D$71,0))} -> Classes | E12: =INDEX('Not Req'!$F$4:$F$71,MATCH(MID(F12,FIND(".",F12)+1,LEN(F12)-FIND(".",F12)+1),'Not Req'!$D$4:$D$71,0)) -> 7. Source Code Library | F12: zbp_js_api_location.clas.abap | G12: Updated 16-Mar-26 | H12: 2 months ago
A13: D | B13: OK | C13: =LEFT(F13,FIND(".",F13)-1) -> zbp_js_api_location | D13: {=INDEX('Not Req'!$E$4:$E$71,MATCH(MID(F13,FIND(".",F13)+1,LEN(F13)-FIND(".",F13)+1),'Not Req'!$D$4:$D$71,0))} -> Classes Local | E13: =INDEX('Not Req'!$F$4:$F$71,MATCH(MID(F13,FIND(".",F13)+1,LEN(F13)-FIND(".",F13)+1),'Not Req'!$D$4:$D$71,0)) -> 7. Source Code Library | F13: zbp_js_api_location.clas.locals_imp.abap | G13: UPDATED ON 02-FEB-26 | H13: 3 months ago
A14: D | B14: OK | C14: =LEFT(F14,FIND(".",F14)-1) -> zcl_js_api_target | D14: {=INDEX('Not Req'!$E$4:$E$71,MATCH(MID(F14,FIND(".",F14)+1,LEN(F14)-FIND(".",F14)+1),'Not Req'!$D$4:$D$71,0))} -> Classes | E14: =INDEX('Not Req'!$F$4:$F$71,MATCH(MID(F14,FIND(".",F14)+1,LEN(F14)-FIND(".",F14)+1),'Not Req'!$D$4:$D$71,0)) -> 7. Source Code Library | F14: zcl_js_api_target.clas.abap | G14: Updated 16-Mar-26 | H14: 2 months ago
A15: D | B15: OK | C15: =LEFT(F15,FIND(".",F15)-1) -> zjs_r_apilocation | D15: {=INDEX('Not Req'!$E$4:$E$71,MATCH(MID(F15,FIND(".",F15)+1,LEN(F15)-FIND(".",F15)+1),'Not Req'!$D$4:$D$71,0))} -> BaseInfo : Data Definition | E15: =INDEX('Not Req'!$F$4:$F$71,MATCH(MID(F15,FIND(".",F15)+1,LEN(F15)-FIND(".",F15)+1),'Not Req'!$D$4:$D$71,0)) -> 98. Base Info | F15: zjs_r_apilocation.ddls.baseinfo | G15: UPDATED ON 02-FEB-26 | H15: 3 months ago
... A21: D | B21: OK | C21: =LEFT(F21,FIND(".",F21)-1) -> zjs_r_apilocation | D21: {=INDEX('Not Req'!$E$4:$E$71,MATCH(MID(F21,FIND(".",F21)+1,LEN(F21)-FIND(".",F21)+1),'Not Req'!$D$4:$D$71,0))} -> Description : Data Definition | E21: =INDEX('Not Req'!$F$4:$F$71,MATCH(MID(F21,FIND(".",F21)+1,LEN(F21)-FIND(".",F21)+1),'Not Req'!$D$4:$D$71,0)) -> 99. Descriptions | F21: zjs_r_apilocation.ddls.xml | G21: UPDATED ON 02-FEB-26 | H21: 3 months ago

Sheet ZJS_09_RAP_PATTERN_CUSTOM
A2: d | B2: d | C2: Object | D2: Type | E2: Category | F2: Github Object | G2: Github Type | H2: Version
A4: D | B4: OK | C4: =LEFT(F4,FIND(".",F4)-1) -> 2a6e0a4e80cd9ddbec9175325dbe71ht | D4: {=INDEX('Not Req'!$E$4:$E$71,MATCH(MID(F4,FIND(".",F4)+1,LEN(F4)-FIND(".",F4)+1),'Not Req'!$D$4:$D$71,0))} -> Authorization Defaults (TADIR) | E4: =INDEX('Not Req'!$F$4:$F$71,MATCH(MID(F4,FIND(".",F4)+1,LEN(F4)-FIND(".",F4)+1),'Not Req'!$D$4:$D$71,0)) -> 1. Authorizations | F4: 2a6e0a4e80cd9ddbec9175325dbe71ht.sush.xml | G4: UPDATED ON 02-FEB-26 | H4: 3 months ago
A5: D | B5: OK | C5: =LEFT(F5,FIND(".",F5)-1) -> 2b71dbe296db14ddca698f77f6332eht | D5: {=INDEX('Not Req'!$E$4:$E$71,MATCH(MID(F5,FIND(".",F5)+1,LEN(F5)-FIND(".",F5)+1),'Not Req'!$D$4:$D$71,0))} -> Authorization Defaults (TADIR) | E5: =INDEX('Not Req'!$F$4:$F$71,MATCH(MID(F5,FIND(".",F5)+1,LEN(F5)-FIND(".",F5)+1),'Not Req'!$D$4:$D$71,0)) -> 1. Authorizations | F5: 2b71dbe296db14ddca698f77f6332eht.sush.xml | G5: UPDATED ON 02-FEB-26 | H5: 3 months ago
A6: D | B6: OK | C6: =LEFT(F6,FIND(".",F6)-1) -> eb3ab26380a1c48a15e0dd9f2a3f97ht | D6: {=INDEX('Not Req'!$E$4:$E$71,MATCH(MID(F6,FIND(".",F6)+1,LEN(F6)-FIND(".",F6)+1),'Not Req'!$D$4:$D$71,0))} -> Authorization Defaults (TADIR) | E6: =INDEX('Not Req'!$F$4:$F$71,MATCH(MID(F6,FIND(".",F6)+1,LEN(F6)-FIND(".",F6)+1),'Not Req'!$D$4:$D$71,0)) -> 1. Authorizations | F6: eb3ab26380a1c48a15e0dd9f2a3f97ht.sush.xml | G6: UPDATED ON 02-FEB-26 | H6: 3 months ago
A7: D | B7: OK | C7: =LEFT(F7,FIND(".",F7)-1) -> zjs_dcp_swc | D7: {=INDEX('Not Req'!$E$4:$E$71,MATCH(MID(F7,FIND(".",F7)+1,LEN(F7)-FIND(".",F7)+1),'Not Req'!$D$4:$D$71,0))} -> Service Definition | E7: =INDEX('Not Req'!$F$4:$F$71,MATCH(MID(F7,FIND(".",F7)+1,LEN(F7)-FIND(".",F7)+1),'Not Req'!$D$4:$D$71,0)) -> 2. Business Services | F7: zjs_dcp_swc.srvd.srvdsrv | G7: UPDATED ON 02-FEB-26 | H7: 3 months ago
A8: D | B8: OK | C8: =LEFT(F8,FIND(".",F8)-1) -> zjs_ui_dcp_swc_o2 | D8: {=INDEX('Not Req'!$E$4:$E$71,MATCH(MID(F8,FIND(".",F8)+1,LEN(F8)-FIND(".",F8)+1),'Not Req'!$D$4:$D$71,0))} -> Service Binding | E8: =INDEX('Not Req'!$F$4:$F$71,MATCH(MID(F8,FIND(".",F8)+1,LEN(F8)-FIND(".",F8)+1),'Not Req'!$D$4:$D$71,0)) -> 2. Business Services | F8: zjs_ui_dcp_swc_o2.srvb.xml | G8: UPDATED ON 02-FEB-26 | H8: 3 months ago
A9: D | B9: OK | C9: =LEFT(F9,FIND(".",F9)-1) -> zjs_ui_dcp_swc_o4 | D9: {=INDEX('Not Req'!$E$4:$E$71,MATCH(MID(F9,FIND(".",F9)+1,LEN(F9)-FIND(".",F9)+1),'Not Req'!$D$4:$D$71,0))} -> Service Binding | E9: =INDEX('Not Req'!$F$4:$F$71,MATCH(MID(F9,FIND(".",F9)+1,LEN(F9)-FIND(".",F9)+1),'Not Req'!$D$4:$D$71,0)) -> 2. Business Services | F9: zjs_ui_dcp_swc_o4.srvb.xml | G9: UPDATED ON 02-FEB-26 | H9: 3 months ago
A10: D | B10: OK | C10: =LEFT(F10,FIND(".",F10)-1) -> zjs_ui_dcp_swc_o2_iwsg | D10: {=INDEX('Not Req'!$E$4:$E$71,MATCH(MID(F10,FIND(".",F10)+1,LEN(F10)-FIND(".",F10)+1),'Not Req'!$D$4:$D$71,0))} -> Inbound Service | E10: =INDEX('Not Req'!$F$4:$F$71,MATCH(MID(F10,FIND(".",F10)+1,LEN(F10)-FIND(".",F10)+1),'Not Req'!$D$4:$D$71,0)) -> 3. Cloud Communication Management | F10: zjs_ui_dcp_swc_o2_iwsg.sco2.xml | G10: UPDATED ON 02-FEB-26 | H10: 3 months ago
A11: D | B11: OK | C11: =LEFT(F11,FIND(".",F11)-1) -> zjs_ui_dcp_swc_o4_0001_g4ba | D11: {=INDEX('Not Req'!$E$4:$E$71,MATCH(MID(F11,FIND(".",F11)+1,LEN(F11)-FIND(".",F11)+1),'Not Req'!$D$4:$D$71,0))} -> Inbound Service | E11: =INDEX('Not Req'!$F$4:$F$71,MATCH(MID(F11,FIND(".",F11)+1,LEN(F11)-FIND(".",F11)+1),'Not Req'!$D$4:$D$71,0)) -> 3. Cloud Communication Management | F11: zjs_ui_dcp_swc_o4_0001_g4ba.sco2.xml | G11: UPDATED ON 02-FEB-26 | H11: 3 months ago
A12: D | B12: OK | C12: =LEFT(F12,FIND(".",F12)-1) -> zjs_i_cpstagingvh | D12: {=INDEX('Not Req'!$E$4:$E$71,MATCH(MID(F12,FIND(".",F12)+1,LEN(F12)-FIND(".",F12)+1),'Not Req'!$D$4:$D$71,0))} -> Data Definition | E12: =INDEX('Not Req'!$F$4:$F$71,MATCH(MID(F12,FIND(".",F12)+1,LEN(F12)-FIND(".",F12)+1),'Not Req'!$D$4:$D$71,0)) -> 4. CDS | F12: zjs_i_cpstagingvh.ddls.asddls | G12: UPDATED ON 02-FEB-26 | H12: 3 months ago
A13: D | B13: OK | C13: =LEFT(F13,FIND(".",F13)-1) -> zjs_i_dcpapplicationvh | D13: {=INDEX('Not Req'!$E$4:$E$71,MATCH(MID(F13,FIND(".",F13)+1,LEN(F13)-FIND(".",F13)+1),'Not Req'!$D$4:$D$71,0))} -> Data Definition | E13: =INDEX('Not Req'!$F$4:$F$71,MATCH(MID(F13,FIND(".",F13)+1,LEN(F13)-FIND(".",F13)+1),'Not Req'!$D$4:$D$71,0)) -> 4. CDS | F13: zjs_i_dcpapplicationvh.ddls.asddls | G13: UPDATED ON 02-FEB-26 | H13: 3 months ago
A14: D | B14: OK | C14: =LEFT(F14,FIND(".",F14)-1) -> zjs_i_dcpteamvh | D14: {=INDEX('Not Req'!$E$4:$E$71,MATCH(MID(F14,FIND(".",F14)+1,LEN(F14)-FIND(".",F14)+1),'Not Req'!$D$4:$D$71,0))} -> Data Definition | E14: =INDEX('Not Req'!$F$4:$F$71,MATCH(MID(F14,FIND(".",F14)+1,LEN(F14)-FIND(".",F14)+1),'Not Req'!$D$4:$D$71,0)) -> 4. CDS | F14: zjs_i_dcpteamvh.ddls.asddls | G14: UPDATED ON 02-FEB-26 | H14: 3 months ago
A15: D | B15: OK | C15: =LEFT(F15,FIND(".",F15)-1) -> zjs_r_dcpsoftwarecomponent | D15: {=INDEX('Not Req'!$E$4:$E$71,MATCH(MID(F15,FIND(".",F15)+1,LEN(F15)-FIND(".",F15)+1),'Not Req'!$D$4:$D$71,0))} -> BDEF | E15: =INDEX('Not Req'!$F$4:$F$71,MATCH(MID(F15,FIND(".",F15)+1,LEN(F15)-FIND(".",F15)+1),'Not Req'!$D$4:$D$71,0)) -> 4. CDS | F15: zjs_r_dcpsoftwarecomponent.bdef.asbdef | G15: UPDATED ON 02-FEB-26 | H15: 3 months ago
... A43: D | B43: OK | C43: =LEFT(F43,FIND(".",F43)-1) -> zjs_r_dcpsoftwarecomponent | D43: {=INDEX('Not Req'!$E$4:$E$71,MATCH(MID(F43,FIND(".",F43)+1,LEN(F43)-FIND(".",F43)+1),'Not Req'!$D$4:$D$71,0))} -> Description : Data Definition | E43: =INDEX('Not Req'!$F$4:$F$71,MATCH(MID(F43,FIND(".",F43)+1,LEN(F43)-FIND(".",F43)+1),'Not Req'!$D$4:$D$71,0)) -> 99. Descriptions | F43: zjs_r_dcpsoftwarecomponent.ddls.xml | G43: UPDATED ON 02-FEB-26 | H43: 3 months ago

Sheet ZJS_09_RAP_PATTERN_REPORT
A2: d | B2: d | C2: Object | D2: Type | E2: Category | F2: Github Object | G2: Github Type | H2: Version
A4: D | B4: OK | C4: =LEFT(F4,FIND(".",F4)-1) -> a318ec063e2b8d8e656eadc8082fd2ht | D4: {=INDEX('Not Req'!$E$4:$E$71,MATCH(MID(F4,FIND(".",F4)+1,LEN(F4)-FIND(".",F4)+1),'Not Req'!$D$4:$D$71,0))} -> Authorization Defaults (TADIR) | E4: =INDEX('Not Req'!$F$4:$F$71,MATCH(MID(F4,FIND(".",F4)+1,LEN(F4)-FIND(".",F4)+1),'Not Req'!$D$4:$D$71,0)) -> 1. Authorizations | F4: a318ec063e2b8d8e656eadc8082fd2ht.sush.xml | G4: UPDATED ON 02-FEB-26 | H4: 3 months ago | N4: {=_xlfn.UNIQUE(C4:C20)} -> a318ec063e2b8d8e656eadc8082fd2ht
A5: D | B5: OK | C5: =LEFT(F5,FIND(".",F5)-1) -> zjs_demo_drp_currency | D5: {=INDEX('Not Req'!$E$4:$E$71,MATCH(MID(F5,FIND(".",F5)+1,LEN(F5)-FIND(".",F5)+1),'Not Req'!$D$4:$D$71,0))} -> Service Definition | E5: =INDEX('Not Req'!$F$4:$F$71,MATCH(MID(F5,FIND(".",F5)+1,LEN(F5)-FIND(".",F5)+1),'Not Req'!$D$4:$D$71,0)) -> 2. Business Services | F5: zjs_demo_drp_currency.srvd.srvdsrv | G5: UPDATED ON 02-FEB-26 | H5: 3 months ago | N5: zjs_demo_drp_currency
A6: D | B6: OK | C6: =LEFT(F6,FIND(".",F6)-1) -> zjs_ui_demo_drp_currency_o4 | D6: {=INDEX('Not Req'!$E$4:$E$71,MATCH(MID(F6,FIND(".",F6)+1,LEN(F6)-FIND(".",F6)+1),'Not Req'!$D$4:$D$71,0))} -> Service Binding | E6: =INDEX('Not Req'!$F$4:$F$71,MATCH(MID(F6,FIND(".",F6)+1,LEN(F6)-FIND(".",F6)+1),'Not Req'!$D$4:$D$71,0)) -> 2. Business Services | F6: zjs_ui_demo_drp_currency_o4.srvb.xml | G6: UPDATED ON 02-FEB-26 | H6: 3 months ago | N6: zjs_ui_demo_drp_currency_o4
A7: D | B7: OK | C7: =LEFT(F7,FIND(".",F7)-1) -> zjs_ui_demo_drp_currency_o4_0001_g4ba | D7: {=INDEX('Not Req'!$E$4:$E$71,MATCH(MID(F7,FIND(".",F7)+1,LEN(F7)-FIND(".",F7)+1),'Not Req'!$D$4:$D$71,0))} -> Inbound Service | E7: =INDEX('Not Req'!$F$4:$F$71,MATCH(MID(F7,FIND(".",F7)+1,LEN(F7)-FIND(".",F7)+1),'Not Req'!$D$4:$D$71,0)) -> 3. Cloud Communication Management | F7: zjs_ui_demo_drp_currency_o4_0001_g4ba.sco2.xml | G7: UPDATED ON 02-FEB-26 | H7: 3 months ago | N7: zjs_ui_demo_drp_currency_o4_0001_g4ba
A8: D | B8: OK | C8: =LEFT(F8,FIND(".",F8)-1) -> zjs_b_drpadditionalcurrency | D8: {=INDEX('Not Req'!$E$4:$E$71,MATCH(MID(F8,FIND(".",F8)+1,LEN(F8)-FIND(".",F8)+1),'Not Req'!$D$4:$D$71,0))} -> Data Definition | E8: =INDEX('Not Req'!$F$4:$F$71,MATCH(MID(F8,FIND(".",F8)+1,LEN(F8)-FIND(".",F8)+1),'Not Req'!$D$4:$D$71,0)) -> 4. CDS | F8: zjs_b_drpadditionalcurrency.ddls.asddls | G8: UPDATED ON 02-FEB-26 | H8: 3 months ago | N8: zjs_b_drpadditionalcurrency
A9: D | B9: OK | C9: =LEFT(F9,FIND(".",F9)-1) -> zjs_b_drpcurrencycountry | D9: {=INDEX('Not Req'!$E$4:$E$71,MATCH(MID(F9,FIND(".",F9)+1,LEN(F9)-FIND(".",F9)+1),'Not Req'!$D$4:$D$71,0))} -> Data Definition | E9: =INDEX('Not Req'!$F$4:$F$71,MATCH(MID(F9,FIND(".",F9)+1,LEN(F9)-FIND(".",F9)+1),'Not Req'!$D$4:$D$71,0)) -> 4. CDS | F9: zjs_b_drpcurrencycountry.ddls.asddls | G9: UPDATED ON 02-FEB-26 | H9: 3 months ago | N9: zjs_b_drpcurrencycountry
A10: D | B10: OK | C10: =LEFT(F10,FIND(".",F10)-1) -> zjs_c_drpcurrency | D10: {=INDEX('Not Req'!$E$4:$E$71,MATCH(MID(F10,FIND(".",F10)+1,LEN(F10)-FIND(".",F10)+1),'Not Req'!$D$4:$D$71,0))} -> BDEF | E10: =INDEX('Not Req'!$F$4:$F$71,MATCH(MID(F10,FIND(".",F10)+1,LEN(F10)-FIND(".",F10)+1),'Not Req'!$D$4:$D$71,0)) -> 4. CDS | F10: zjs_c_drpcurrency.bdef.asbdef | G10: UPDATED ON 02-FEB-26 | H10: 3 months ago | N10: zjs_c_drpcurrency
A11: D | B11: OK | C11: =LEFT(F11,FIND(".",F11)-1) -> zjs_c_drpcurrency | D11: {=INDEX('Not Req'!$E$4:$E$71,MATCH(MID(F11,FIND(".",F11)+1,LEN(F11)-FIND(".",F11)+1),'Not Req'!$D$4:$D$71,0))} -> Data Definition | E11: =INDEX('Not Req'!$F$4:$F$71,MATCH(MID(F11,FIND(".",F11)+1,LEN(F11)-FIND(".",F11)+1),'Not Req'!$D$4:$D$71,0)) -> 4. CDS | F11: zjs_c_drpcurrency.ddls.asddls | G11: UPDATED ON 02-FEB-26 | H11: 3 months ago | N11: zjs_c_drpcurrencycountry
A12: D | B12: OK | C12: =LEFT(F12,FIND(".",F12)-1) -> zjs_c_drpcurrency | D12: {=INDEX('Not Req'!$E$4:$E$71,MATCH(MID(F12,FIND(".",F12)+1,LEN(F12)-FIND(".",F12)+1),'Not Req'!$D$4:$D$71,0))} -> Metadata | E12: =INDEX('Not Req'!$F$4:$F$71,MATCH(MID(F12,FIND(".",F12)+1,LEN(F12)-FIND(".",F12)+1),'Not Req'!$D$4:$D$71,0)) -> 4. CDS | F12: zjs_c_drpcurrency.ddlx.asddlxs | G12: UPDATED ON 02-FEB-26 | H12: 3 months ago | N12: zjs_i_drpcurrencycountry
A13: D | B13: OK | C13: =LEFT(F13,FIND(".",F13)-1) -> zjs_c_drpcurrencycountry | D13: {=INDEX('Not Req'!$E$4:$E$71,MATCH(MID(F13,FIND(".",F13)+1,LEN(F13)-FIND(".",F13)+1),'Not Req'!$D$4:$D$71,0))} -> Data Definition | E13: =INDEX('Not Req'!$F$4:$F$71,MATCH(MID(F13,FIND(".",F13)+1,LEN(F13)-FIND(".",F13)+1),'Not Req'!$D$4:$D$71,0)) -> 4. CDS | F13: zjs_c_drpcurrencycountry.ddls.asddls | G13: UPDATED ON 02-FEB-26 | H13: 3 months ago | N13: zjs_r_drpcurrency
A14: D | B14: OK | C14: =LEFT(F14,FIND(".",F14)-1) -> zjs_c_drpcurrencycountry | D14: {=INDEX('Not Req'!$E$4:$E$71,MATCH(MID(F14,FIND(".",F14)+1,LEN(F14)-FIND(".",F14)+1),'Not Req'!$D$4:$D$71,0))} -> Metadata | E14: =INDEX('Not Req'!$F$4:$F$71,MATCH(MID(F14,FIND(".",F14)+1,LEN(F14)-FIND(".",F14)+1),'Not Req'!$D$4:$D$71,0)) -> 4. CDS | F14: zjs_c_drpcurrencycountry.ddlx.asddlxs | G14: UPDATED ON 02-FEB-26 | H14: 3 months ago | N14: zjs_s_drpeventdata
A15: D | B15: OK | C15: =LEFT(F15,FIND(".",F15)-1) -> zjs_i_drpcurrencycountry | D15: {=INDEX('Not Req'!$E$4:$E$71,MATCH(MID(F15,FIND(".",F15)+1,LEN(F15)-FIND(".",F15)+1),'Not Req'!$D$4:$D$71,0))} -> Data Definition | E15: =INDEX('Not Req'!$F$4:$F$71,MATCH(MID(F15,FIND(".",F15)+1,LEN(F15)-FIND(".",F15)+1),'Not Req'!$D$4:$D$71,0)) -> 4. CDS | F15: zjs_i_drpcurrencycountry.ddls.asddls | G15: UPDATED ON 02-FEB-26 | H15: 3 months ago | N15: zjs_s_drpexcelpopup
A16: D | B16: OK | C16: =LEFT(F16,FIND(".",F16)-1) -> zjs_r_drpcurrency | D16: {=INDEX('Not Req'!$E$4:$E$71,MATCH(MID(F16,FIND(".",F16)+1,LEN(F16)-FIND(".",F16)+1),'Not Req'!$D$4:$D$71,0))} -> BDEF | E16: =INDEX('Not Req'!$F$4:$F$71,MATCH(MID(F16,FIND(".",F16)+1,LEN(F16)-FIND(".",F16)+1),'Not Req'!$D$4:$D$71,0)) -> 4. CDS | F16: zjs_r_drpcurrency.bdef.asbdef | G16: UPDATED ON 02-FEB-26 | H16: 3 months ago
A17: D | B17: OK | C17: =LEFT(F17,FIND(".",F17)-1) -> zjs_r_drpcurrency | D17: {=INDEX('Not Req'!$E$4:$E$71,MATCH(MID(F17,FIND(".",F17)+1,LEN(F17)-FIND(".",F17)+1),'Not Req'!$D$4:$D$71,0))} -> Data Definition | E17: =INDEX('Not Req'!$F$4:$F$71,MATCH(MID(F17,FIND(".",F17)+1,LEN(F17)-FIND(".",F17)+1),'Not Req'!$D$4:$D$71,0)) -> 4. CDS | F17: zjs_r_drpcurrency.ddls.asddls | G17: UPDATED ON 02-FEB-26 | H17: 3 months ago
A18: D | B18: OK | C18: =LEFT(F18,FIND(".",F18)-1) -> zjs_s_drpeventdata | D18: {=INDEX('Not Req'!$E$4:$E$71,MATCH(MID(F18,FIND(".",F18)+1,LEN(F18)-FIND(".",F18)+1),'Not Req'!$D$4:$D$71,0))} -> Data Definition | E18: =INDEX('Not Req'!$F$4:$F$71,MATCH(MID(F18,FIND(".",F18)+1,LEN(F18)-FIND(".",F18)+1),'Not Req'!$D$4:$D$71,0)) -> 4. CDS | F18: zjs_s_drpeventdata.ddls.asddls | G18: UPDATED ON 02-FEB-26 | H18: 3 months ago
A19: D | B19: OK | C19: =LEFT(F19,FIND(".",F19)-1) -> zjs_s_drpexcelpopup | D19: {=INDEX('Not Req'!$E$4:$E$71,MATCH(MID(F19,FIND(".",F19)+1,LEN(F19)-FIND(".",F19)+1),'Not Req'!$D$4:$D$71,0))} -> BDEF | E19: =INDEX('Not Req'!$F$4:$F$71,MATCH(MID(F19,FIND(".",F19)+1,LEN(F19)-FIND(".",F19)+1),'Not Req'!$D$4:$D$71,0)) -> 4. CDS | F19: zjs_s_drpexcelpopup.bdef.asbdef | G19: UPDATED ON 02-FEB-26 | H19: 3 months ago
A20: D | B20: OK | C20: =LEFT(F20,FIND(".",F20)-1) -> zjs_s_drpexcelpopup | D20: {=INDEX('Not Req'!$E$4:$E$71,MATCH(MID(F20,FIND(".",F20)+1,LEN(F20)-FIND(".",F20)+1),'Not Req'!$D$4:$D$71,0))} -> Data Definition | E20: =INDEX('Not Req'!$F$4:$F$71,MATCH(MID(F20,FIND(".",F20)+1,LEN(F20)-FIND(".",F20)+1),'Not Req'!$D$4:$D$71,0)) -> 4. CDS | F20: zjs_s_drpexcelpopup.ddls.asddls | G20: UPDATED ON 02-FEB-26 | H20: 3 months ago
A21: D | B21: OK | C21: =LEFT(F21,FIND(".",F21)-1) -> zjs_drp_addcurr | D21: {=INDEX('Not Req'!$E$4:$E$71,MATCH(MID(F21,FIND(".",F21)+1,LEN(F21)-FIND(".",F21)+1),'Not Req'!$D$4:$D$71,0))} -> Table | E21: =INDEX('Not Req'!$F$4:$F$71,MATCH(MID(F21,FIND(".",F21)+1,LEN(F21)-FIND(".",F21)+1),'Not Req'!$D$4:$D$71,0)) -> 5. Dictionary | F21: zjs_drp_addcurr.tabl.xml | G21: UPDATED ON 02-FEB-26 | H21: 3 months ago
A22: D | B22: OK | C22: =LEFT(F22,FIND(".",F22)-1) -> zjs_drp_cound | D22: {=INDEX('Not Req'!$E$4:$E$71,MATCH(MID(F22,FIND(".",F22)+1,LEN(F22)-FIND(".",F22)+1),'Not Req'!$D$4:$D$71,0))} -> Table | E22: =INDEX('Not Req'!$F$4:$F$71,MATCH(MID(F22,FIND(".",F22)+1,LEN(F22)-FIND(".",F22)+1),'Not Req'!$D$4:$D$71,0)) -> 5. Dictionary | F22: zjs_drp_cound.tabl.xml | G22: UPDATED ON 02-FEB-26 | H22: 3 months ago
A23: D | B23: OK | C23: =LEFT(F23,FIND(".",F23)-1) -> zjs_drp_country | D23: {=INDEX('Not Req'!$E$4:$E$71,MATCH(MID(F23,FIND(".",F23)+1,LEN(F23)-FIND(".",F23)+1),'Not Req'!$D$4:$D$71,0))} -> Table | E23: =INDEX('Not Req'!$F$4:$F$71,MATCH(MID(F23,FIND(".",F23)+1,LEN(F23)-FIND(".",F23)+1),'Not Req'!$D$4:$D$71,0)) -> 5. Dictionary | F23: zjs_drp_country.tabl.xml | G23: UPDATED ON 02-FEB-26 | H23: 3 months ago
A24: D | B24: OK | C24: =LEFT(F24,FIND(".",F24)-1) -> zjs_drp_currd | D24: {=INDEX('Not Req'!$E$4:$E$71,MATCH(MID(F24,FIND(".",F24)+1,LEN(F24)-FIND(".",F24)+1),'Not Req'!$D$4:$D$71,0))} -> Table | E24: =INDEX('Not Req'!$F$4:$F$71,MATCH(MID(F24,FIND(".",F24)+1,LEN(F24)-FIND(".",F24)+1),'Not Req'!$D$4:$D$71,0)) -> 5. Dictionary | F24: zjs_drp_currd.tabl.xml | G24: UPDATED ON 02-FEB-26 | H24: 3 months ago
A25: D | B25: OK | C25: =LEFT(F25,FIND(".",F25)-1) -> zbp_js_drp_currency | D25: {=INDEX('Not Req'!$E$4:$E$71,MATCH(MID(F25,FIND(".",F25)+1,LEN(F25)-FIND(".",F25)+1),'Not Req'!$D$4:$D$71,0))} -> Classes | E25: =INDEX('Not Req'!$F$4:$F$71,MATCH(MID(F25,FIND(".",F25)+1,LEN(F25)-FIND(".",F25)+1),'Not Req'!$D$4:$D$71,0)) -> 7. Source Code Library | F25: zbp_js_drp_currency.clas.abap | G25: Updated 16-Mar-26 | H25: 2 months ago
A26: D | B26: OK | C26: =LEFT(F26,FIND(".",F26)-1) -> zbp_js_drp_currency | D26: {=INDEX('Not Req'!$E$4:$E$71,MATCH(MID(F26,FIND(".",F26)+1,LEN(F26)-FIND(".",F26)+1),'Not Req'!$D$4:$D$71,0))} -> Classes Local | E26: =INDEX('Not Req'!$F$4:$F$71,MATCH(MID(F26,FIND(".",F26)+1,LEN(F26)-FIND(".",F26)+1),'Not Req'!$D$4:$D$71,0)) -> 7. Source Code Library | F26: zbp_js_drp_currency.clas.locals_imp.abap | G26: UPDATED ON 02-FEB-26 | H26: 3 months ago
A27: D | B27: OK | C27: =LEFT(F27,FIND(".",F27)-1) -> zcl_js_drp_event_consumption | D27: {=INDEX('Not Req'!$E$4:$E$71,MATCH(MID(F27,FIND(".",F27)+1,LEN(F27)-FIND(".",F27)+1),'Not Req'!$D$4:$D$71,0))} -> Classes | E27: =INDEX('Not Req'!$F$4:$F$71,MATCH(MID(F27,FIND(".",F27)+1,LEN(F27)-FIND(".",F27)+1),'Not Req'!$D$4:$D$71,0)) -> 7. Source Code Library | F27: zcl_js_drp_event_consumption.clas.abap | G27: Updated 16-Mar-26 | H27: 2 months ago
... A55: D | B55: OK | C55: =LEFT(F55,FIND(".",F55)-1) -> zjs_s_drpexcelpopup | D55: {=INDEX('Not Req'!$E$4:$E$71,MATCH(MID(F55,FIND(".",F55)+1,LEN(F55)-FIND(".",F55)+1),'Not Req'!$D$4:$D$71,0))} -> Description : Data Definition | E55: =INDEX('Not Req'!$F$4:$F$71,MATCH(MID(F55,FIND(".",F55)+1,LEN(F55)-FIND(".",F55)+1),'Not Req'!$D$4:$D$71,0)) -> 99. Descriptions | F55: zjs_s_drpexcelpopup.ddls.xml | G55: UPDATED ON 02-FEB-26 | H55: 3 months ago

Sheet ZJS_08_RAP_GOOGLE
A2: d | B2: d | C2: Object | D2: Type | E2: Category | F2: Github Object | G2: Github Type | H2: Version
A4: D | B4: OK | C4: =LEFT(F4,FIND(".",F4)-1) -> a9930a4958e046f3c9d78fbb754e9dht | D4: {=INDEX('Not Req'!$E$4:$E$71,MATCH(MID(F4,FIND(".",F4)+1,LEN(F4)-FIND(".",F4)+1),'Not Req'!$D$4:$D$71,0))} -> Authorization Defaults (TADIR) | E4: =INDEX('Not Req'!$F$4:$F$71,MATCH(MID(F4,FIND(".",F4)+1,LEN(F4)-FIND(".",F4)+1),'Not Req'!$D$4:$D$71,0)) -> 1. Authorizations | F4: a9930a4958e046f3c9d78fbb754e9dht.sush.xml | G4: UPDATED ON 02-FEB-26 | H4: 3 months ago | N4: {=_xlfn.UNIQUE(C4:C20)} -> a9930a4958e046f3c9d78fbb754e9dht
A5: D | B5: OK | C5: =LEFT(F5,FIND(".",F5)-1) -> zjs_demo_language | D5: {=INDEX('Not Req'!$E$4:$E$71,MATCH(MID(F5,FIND(".",F5)+1,LEN(F5)-FIND(".",F5)+1),'Not Req'!$D$4:$D$71,0))} -> Service Definition | E5: =INDEX('Not Req'!$F$4:$F$71,MATCH(MID(F5,FIND(".",F5)+1,LEN(F5)-FIND(".",F5)+1),'Not Req'!$D$4:$D$71,0)) -> 2. Business Services | F5: zjs_demo_language.srvd.srvdsrv | G5: UPDATED ON 02-FEB-26 | H5: 3 months ago | N5: zjs_demo_language
A6: D | B6: OK | C6: =LEFT(F6,FIND(".",F6)-1) -> zjs_ui_demo_language_o4 | D6: {=INDEX('Not Req'!$E$4:$E$71,MATCH(MID(F6,FIND(".",F6)+1,LEN(F6)-FIND(".",F6)+1),'Not Req'!$D$4:$D$71,0))} -> Service Binding | E6: =INDEX('Not Req'!$F$4:$F$71,MATCH(MID(F6,FIND(".",F6)+1,LEN(F6)-FIND(".",F6)+1),'Not Req'!$D$4:$D$71,0)) -> 2. Business Services | F6: zjs_ui_demo_language_o4.srvb.xml | G6: UPDATED ON 02-FEB-26 | H6: 3 months ago | N6: zjs_ui_demo_language_o4
A7: D | B7: OK | C7: =LEFT(F7,FIND(".",F7)-1) -> zjs_ui_demo_language_o4_0001_g4ba | D7: {=INDEX('Not Req'!$E$4:$E$71,MATCH(MID(F7,FIND(".",F7)+1,LEN(F7)-FIND(".",F7)+1),'Not Req'!$D$4:$D$71,0))} -> Inbound Service | E7: =INDEX('Not Req'!$F$4:$F$71,MATCH(MID(F7,FIND(".",F7)+1,LEN(F7)-FIND(".",F7)+1),'Not Req'!$D$4:$D$71,0)) -> 3. Cloud Communication Management | F7: zjs_ui_demo_language_o4_0001_g4ba.sco2.xml | G7: UPDATED ON 02-FEB-26 | H7: 3 months ago | N7: zjs_ui_demo_language_o4_0001_g4ba
A8: D | B8: OK | C8: =LEFT(F8,FIND(".",F8)-1) -> zjs_c_dmolanguage | D8: {=INDEX('Not Req'!$E$4:$E$71,MATCH(MID(F8,FIND(".",F8)+1,LEN(F8)-FIND(".",F8)+1),'Not Req'!$D$4:$D$71,0))} -> BDEF | E8: =INDEX('Not Req'!$F$4:$F$71,MATCH(MID(F8,FIND(".",F8)+1,LEN(F8)-FIND(".",F8)+1),'Not Req'!$D$4:$D$71,0)) -> 4. CDS | F8: zjs_c_dmolanguage.bdef.asbdef | G8: UPDATED ON 02-FEB-26 | H8: 3 months ago | N8: zjs_c_dmolanguage
A9: D | B9: OK | C9: =LEFT(F9,FIND(".",F9)-1) -> zjs_c_dmolanguage | D9: {=INDEX('Not Req'!$E$4:$E$71,MATCH(MID(F9,FIND(".",F9)+1,LEN(F9)-FIND(".",F9)+1),'Not Req'!$D$4:$D$71,0))} -> Data Definition | E9: =INDEX('Not Req'!$F$4:$F$71,MATCH(MID(F9,FIND(".",F9)+1,LEN(F9)-FIND(".",F9)+1),'Not Req'!$D$4:$D$71,0)) -> 4. CDS | F9: zjs_c_dmolanguage.ddls.asddls | G9: UPDATED ON 02-FEB-26 | H9: 3 months ago | N9: zjs_r_dmolanguage
A10: D | B10: OK | C10: =LEFT(F10,FIND(".",F10)-1) -> zjs_c_dmolanguage | D10: {=INDEX('Not Req'!$E$4:$E$71,MATCH(MID(F10,FIND(".",F10)+1,LEN(F10)-FIND(".",F10)+1),'Not Req'!$D$4:$D$71,0))} -> Metadata | E10: =INDEX('Not Req'!$F$4:$F$71,MATCH(MID(F10,FIND(".",F10)+1,LEN(F10)-FIND(".",F10)+1),'Not Req'!$D$4:$D$71,0)) -> 4. CDS | F10: zjs_c_dmolanguage.ddlx.asddlxs | G10: UPDATED ON 02-FEB-26 | H10: 3 months ago | N10: zjs_demo_text
A11: D | B11: OK | C11: =LEFT(F11,FIND(".",F11)-1) -> zjs_r_dmolanguage | D11: {=INDEX('Not Req'!$E$4:$E$71,MATCH(MID(F11,FIND(".",F11)+1,LEN(F11)-FIND(".",F11)+1),'Not Req'!$D$4:$D$71,0))} -> BDEF | E11: =INDEX('Not Req'!$F$4:$F$71,MATCH(MID(F11,FIND(".",F11)+1,LEN(F11)-FIND(".",F11)+1),'Not Req'!$D$4:$D$71,0)) -> 4. CDS | F11: zjs_r_dmolanguage.bdef.asbdef | G11: UPDATED ON 02-FEB-26 | H11: 3 months ago | N11: zjs_dmo_lang
A12: D | B12: OK | C12: =LEFT(F12,FIND(".",F12)-1) -> zjs_r_dmolanguage | D12: {=INDEX('Not Req'!$E$4:$E$71,MATCH(MID(F12,FIND(".",F12)+1,LEN(F12)-FIND(".",F12)+1),'Not Req'!$D$4:$D$71,0))} -> Data Definition | E12: =INDEX('Not Req'!$F$4:$F$71,MATCH(MID(F12,FIND(".",F12)+1,LEN(F12)-FIND(".",F12)+1),'Not Req'!$D$4:$D$71,0)) -> 4. CDS | F12: zjs_r_dmolanguage.ddls.asddls | G12: UPDATED ON 02-FEB-26 | H12: 3 months ago | N12: zjs_dmo_lang_d
A13: D | B13: OK | C13: =LEFT(F13,FIND(".",F13)-1) -> zjs_demo_text | D13: {=INDEX('Not Req'!$E$4:$E$71,MATCH(MID(F13,FIND(".",F13)+1,LEN(F13)-FIND(".",F13)+1),'Not Req'!$D$4:$D$71,0))} -> Domain | E13: =INDEX('Not Req'!$F$4:$F$71,MATCH(MID(F13,FIND(".",F13)+1,LEN(F13)-FIND(".",F13)+1),'Not Req'!$D$4:$D$71,0)) -> 5. Dictionary | F13: zjs_demo_text.doma.xml | G13: UPDATED ON 02-FEB-26 | H13: 3 months ago | N13: zbp_js_c_demo_language
A14: D | B14: OK | C14: =LEFT(F14,FIND(".",F14)-1) -> zjs_demo_text | D14: {=INDEX('Not Req'!$E$4:$E$71,MATCH(MID(F14,FIND(".",F14)+1,LEN(F14)-FIND(".",F14)+1),'Not Req'!$D$4:$D$71,0))} -> Data Element | E14: =INDEX('Not Req'!$F$4:$F$71,MATCH(MID(F14,FIND(".",F14)+1,LEN(F14)-FIND(".",F14)+1),'Not Req'!$D$4:$D$71,0)) -> 5. Dictionary | F14: zjs_demo_text.dtel.xml | G14: UPDATED ON 02-FEB-26 | H14: 3 months ago | N14: zbp_js_r_demo_language
A15: D | B15: OK | C15: =LEFT(F15,FIND(".",F15)-1) -> zjs_dmo_lang | D15: {=INDEX('Not Req'!$E$4:$E$71,MATCH(MID(F15,FIND(".",F15)+1,LEN(F15)-FIND(".",F15)+1),'Not Req'!$D$4:$D$71,0))} -> Table | E15: =INDEX('Not Req'!$F$4:$F$71,MATCH(MID(F15,FIND(".",F15)+1,LEN(F15)-FIND(".",F15)+1),'Not Req'!$D$4:$D$71,0)) -> 5. Dictionary | F15: zjs_dmo_lang.tabl.xml | G15: UPDATED ON 02-FEB-26 | H15: 3 months ago | N15: zcl_js_demo_google_integration
A16: D | B16: OK | C16: =LEFT(F16,FIND(".",F16)-1) -> zjs_dmo_lang_d | D16: {=INDEX('Not Req'!$E$4:$E$71,MATCH(MID(F16,FIND(".",F16)+1,LEN(F16)-FIND(".",F16)+1),'Not Req'!$D$4:$D$71,0))} -> Table | E16: =INDEX('Not Req'!$F$4:$F$71,MATCH(MID(F16,FIND(".",F16)+1,LEN(F16)-FIND(".",F16)+1),'Not Req'!$D$4:$D$71,0)) -> 5. Dictionary | F16: zjs_dmo_lang_d.tabl.xml | G16: UPDATED ON 02-FEB-26 | H16: 3 months ago
A17: D | B17: OK | C17: =LEFT(F17,FIND(".",F17)-1) -> zbp_js_c_demo_language | D17: {=INDEX('Not Req'!$E$4:$E$71,MATCH(MID(F17,FIND(".",F17)+1,LEN(F17)-FIND(".",F17)+1),'Not Req'!$D$4:$D$71,0))} -> Classes | E17: =INDEX('Not Req'!$F$4:$F$71,MATCH(MID(F17,FIND(".",F17)+1,LEN(F17)-FIND(".",F17)+1),'Not Req'!$D$4:$D$71,0)) -> 7. Source Code Library | F17: zbp_js_c_demo_language.clas.abap | G17: Updated 16-Mar-26 | H17: 2 months ago
A18: D | B18: OK | C18: =LEFT(F18,FIND(".",F18)-1) -> zbp_js_r_demo_language | D18: {=INDEX('Not Req'!$E$4:$E$71,MATCH(MID(F18,FIND(".",F18)+1,LEN(F18)-FIND(".",F18)+1),'Not Req'!$D$4:$D$71,0))} -> Classes | E18: =INDEX('Not Req'!$F$4:$F$71,MATCH(MID(F18,FIND(".",F18)+1,LEN(F18)-FIND(".",F18)+1),'Not Req'!$D$4:$D$71,0)) -> 7. Source Code Library | F18: zbp_js_r_demo_language.clas.abap | G18: Updated 16-Mar-26 | H18: 2 months ago
A19: D | B19: OK | C19: =LEFT(F19,FIND(".",F19)-1) -> zbp_js_r_demo_language | D19: {=INDEX('Not Req'!$E$4:$E$71,MATCH(MID(F19,FIND(".",F19)+1,LEN(F19)-FIND(".",F19)+1),'Not Req'!$D$4:$D$71,0))} -> Classes Local | E19: =INDEX('Not Req'!$F$4:$F$71,MATCH(MID(F19,FIND(".",F19)+1,LEN(F19)-FIND(".",F19)+1),'Not Req'!$D$4:$D$71,0)) -> 7. Source Code Library | F19: zbp_js_r_demo_language.clas.locals_imp.abap | G19: UPDATED ON 02-FEB-26 | H19: 3 months ago
A20: D | B20: OK | C20: =LEFT(F20,FIND(".",F20)-1) -> zcl_js_demo_google_integration | D20: {=INDEX('Not Req'!$E$4:$E$71,MATCH(MID(F20,FIND(".",F20)+1,LEN(F20)-FIND(".",F20)+1),'Not Req'!$D$4:$D$71,0))} -> Classes | E20: =INDEX('Not Req'!$F$4:$F$71,MATCH(MID(F20,FIND(".",F20)+1,LEN(F20)-FIND(".",F20)+1),'Not Req'!$D$4:$D$71,0)) -> 7. Source Code Library | F20: zcl_js_demo_google_integration.clas.abap | G20: Updated 16-Mar-26 | H20: 2 months ago
A21: D | B21: OK | C21: =LEFT(F21,FIND(".",F21)-1) -> zcl_js_demo_google_integration | D21: {=INDEX('Not Req'!$E$4:$E$71,MATCH(MID(F21,FIND(".",F21)+1,LEN(F21)-FIND(".",F21)+1),'Not Req'!$D$4:$D$71,0))} -> Test Class | E21: =INDEX('Not Req'!$F$4:$F$71,MATCH(MID(F21,FIND(".",F21)+1,LEN(F21)-FIND(".",F21)+1),'Not Req'!$D$4:$D$71,0)) -> 7. Source Code Library | F21: zcl_js_demo_google_integration.clas.testclasses.abap | G21: UPDATED ON 02-FEB-26 | H21: 3 months ago
A22: D | B22: OK | C22: =LEFT(F22,FIND(".",F22)-1) -> zjs_c_dmolanguage | D22: {=INDEX('Not Req'!$E$4:$E$71,MATCH(MID(F22,FIND(".",F22)+1,LEN(F22)-FIND(".",F22)+1),'Not Req'!$D$4:$D$71,0))} -> BaseInfo : Data Definition | E22: =INDEX('Not Req'!$F$4:$F$71,MATCH(MID(F22,FIND(".",F22)+1,LEN(F22)-FIND(".",F22)+1),'Not Req'!$D$4:$D$71,0)) -> 98. Base Info | F22: zjs_c_dmolanguage.ddls.baseinfo | G22: UPDATED ON 02-FEB-26 | H22: 3 months ago
A23: D | B23: OK | C23: =LEFT(F23,FIND(".",F23)-1) -> zjs_r_dmolanguage | D23: {=INDEX('Not Req'!$E$4:$E$71,MATCH(MID(F23,FIND(".",F23)+1,LEN(F23)-FIND(".",F23)+1),'Not Req'!$D$4:$D$71,0))} -> BaseInfo : Data Definition | E23: =INDEX('Not Req'!$F$4:$F$71,MATCH(MID(F23,FIND(".",F23)+1,LEN(F23)-FIND(".",F23)+1),'Not Req'!$D$4:$D$71,0)) -> 98. Base Info | F23: zjs_r_dmolanguage.ddls.baseinfo | G23: UPDATED ON 02-FEB-26 | H23: 3 months ago
A24: D | B24: OK | C24: =LEFT(F24,FIND(".",F24)-1) -> package | D24: {=INDEX('Not Req'!$E$4:$E$71,MATCH(MID(F24,FIND(".",F24)+1,LEN(F24)-FIND(".",F24)+1),'Not Req'!$D$4:$D$71,0))} -> Description : Package | E24: =INDEX('Not Req'!$F$4:$F$71,MATCH(MID(F24,FIND(".",F24)+1,LEN(F24)-FIND(".",F24)+1),'Not Req'!$D$4:$D$71,0)) -> 99. Descriptions | F24: package.devc.xml | G24: UPDATED ON 02-FEB-26 | H24: 3 months ago
A25: D | B25: OK | C25: =LEFT(F25,FIND(".",F25)-1) -> zbp_js_c_demo_language | D25: {=INDEX('Not Req'!$E$4:$E$71,MATCH(MID(F25,FIND(".",F25)+1,LEN(F25)-FIND(".",F25)+1),'Not Req'!$D$4:$D$71,0))} -> Description : Classes | E25: =INDEX('Not Req'!$F$4:$F$71,MATCH(MID(F25,FIND(".",F25)+1,LEN(F25)-FIND(".",F25)+1),'Not Req'!$D$4:$D$71,0)) -> 99. Descriptions | F25: zbp_js_c_demo_language.clas.xml | G25: UPDATED ON 02-FEB-26 | H25: 3 months ago
A26: D | B26: OK | C26: =LEFT(F26,FIND(".",F26)-1) -> zbp_js_r_demo_language | D26: {=INDEX('Not Req'!$E$4:$E$71,MATCH(MID(F26,FIND(".",F26)+1,LEN(F26)-FIND(".",F26)+1),'Not Req'!$D$4:$D$71,0))} -> Description : Classes | E26: =INDEX('Not Req'!$F$4:$F$71,MATCH(MID(F26,FIND(".",F26)+1,LEN(F26)-FIND(".",F26)+1),'Not Req'!$D$4:$D$71,0)) -> 99. Descriptions | F26: zbp_js_r_demo_language.clas.xml | G26: UPDATED ON 02-FEB-26 | H26: 3 months ago
A27: D | B27: OK | C27: =LEFT(F27,FIND(".",F27)-1) -> zcl_js_demo_google_integration | D27: {=INDEX('Not Req'!$E$4:$E$71,MATCH(MID(F27,FIND(".",F27)+1,LEN(F27)-FIND(".",F27)+1),'Not Req'!$D$4:$D$71,0))} -> Description : Classes | E27: =INDEX('Not Req'!$F$4:$F$71,MATCH(MID(F27,FIND(".",F27)+1,LEN(F27)-FIND(".",F27)+1),'Not Req'!$D$4:$D$71,0)) -> 99. Descriptions | F27: zcl_js_demo_google_integration.clas.xml | G27: UPDATED ON 02-FEB-26 | H27: 3 months ago
... A33: D | B33: OK | C33: =LEFT(F33,FIND(".",F33)-1) -> zjs_r_dmolanguage | D33: {=INDEX('Not Req'!$E$4:$E$71,MATCH(MID(F33,FIND(".",F33)+1,LEN(F33)-FIND(".",F33)+1),'Not Req'!$D$4:$D$71,0))} -> Description : Data Definition | E33: =INDEX('Not Req'!$F$4:$F$71,MATCH(MID(F33,FIND(".",F33)+1,LEN(F33)-FIND(".",F33)+1),'Not Req'!$D$4:$D$71,0)) -> 99. Descriptions | F33: zjs_r_dmolanguage.ddls.xml | G33: UPDATED ON 02-FEB-26 | H33: 3 months ago

Sheet ZJS_07_RAP_GEN3
A2: d | B2: d | C2: Object | D2: Type | E2: Category | F2: Github Object | G2: Github Type | H2: Version
A4: D | B4: OK | C4: =LEFT(F4,FIND(".",F4)-1) -> 193169e62c8afa3a0777aa4fd9504cht | D4: {=INDEX('Not Req'!$E$4:$E$71,MATCH(MID(F4,FIND(".",F4)+1,LEN(F4)-FIND(".",F4)+1),'Not Req'!$D$4:$D$71,0))} -> Authorization Defaults (TADIR) | E4: =INDEX('Not Req'!$F$4:$F$71,MATCH(MID(F4,FIND(".",F4)+1,LEN(F4)-FIND(".",F4)+1),'Not Req'!$D$4:$D$71,0)) -> 1. Authorizations | F4: 193169e62c8afa3a0777aa4fd9504cht.sush.xml | G4: UPDATED ON 02-FEB-26 | H4: 3 months ago | N4: {=_xlfn.UNIQUE(C4:C20)} -> 193169e62c8afa3a0777aa4fd9504cht
A5: D | B5: OK | C5: =LEFT(F5,FIND(".",F5)-1) -> zjs_ui_g3invoice_o4 | D5: {=INDEX('Not Req'!$E$4:$E$71,MATCH(MID(F5,FIND(".",F5)+1,LEN(F5)-FIND(".",F5)+1),'Not Req'!$D$4:$D$71,0))} -> Service Binding | E5: =INDEX('Not Req'!$F$4:$F$71,MATCH(MID(F5,FIND(".",F5)+1,LEN(F5)-FIND(".",F5)+1),'Not Req'!$D$4:$D$71,0)) -> 2. Business Services | F5: zjs_ui_g3invoice_o4.srvb.xml | G5: UPDATED ON 02-FEB-26 | H5: 3 months ago | N5: zjs_ui_g3invoice_o4
A6: D | B6: OK | C6: =LEFT(F6,FIND(".",F6)-1) -> zjs_ui_g3invoice_o4 | D6: {=INDEX('Not Req'!$E$4:$E$71,MATCH(MID(F6,FIND(".",F6)+1,LEN(F6)-FIND(".",F6)+1),'Not Req'!$D$4:$D$71,0))} -> Service Definition | E6: =INDEX('Not Req'!$F$4:$F$71,MATCH(MID(F6,FIND(".",F6)+1,LEN(F6)-FIND(".",F6)+1),'Not Req'!$D$4:$D$71,0)) -> 2. Business Services | F6: zjs_ui_g3invoice_o4.srvd.srvdsrv | G6: UPDATED ON 02-FEB-26 | H6: 3 months ago | N6: zjs_ui_g3invoice_o4_0001_g4ba
A7: D | B7: OK | C7: =LEFT(F7,FIND(".",F7)-1) -> zjs_ui_g3invoice_o4_0001_g4ba | D7: {=INDEX('Not Req'!$E$4:$E$71,MATCH(MID(F7,FIND(".",F7)+1,LEN(F7)-FIND(".",F7)+1),'Not Req'!$D$4:$D$71,0))} -> Inbound Service | E7: =INDEX('Not Req'!$F$4:$F$71,MATCH(MID(F7,FIND(".",F7)+1,LEN(F7)-FIND(".",F7)+1),'Not Req'!$D$4:$D$71,0)) -> 3. Cloud Communication Management | F7: zjs_ui_g3invoice_o4_0001_g4ba.sco2.xml | G7: UPDATED ON 02-FEB-26 | H7: 3 months ago | N7: zjs_a_generatortemplate
A8: D | B8: OK | C8: =LEFT(F8,FIND(".",F8)-1) -> zjs_a_generatortemplate | D8: {=INDEX('Not Req'!$E$4:$E$71,MATCH(MID(F8,FIND(".",F8)+1,LEN(F8)-FIND(".",F8)+1),'Not Req'!$D$4:$D$71,0))} -> Data Definition | E8: =INDEX('Not Req'!$F$4:$F$71,MATCH(MID(F8,FIND(".",F8)+1,LEN(F8)-FIND(".",F8)+1),'Not Req'!$D$4:$D$71,0)) -> 4. CDS | F8: zjs_a_generatortemplate.ddls.asddls | G8: UPDATED ON 02-FEB-26 | H8: 3 months ago | N8: zjs_c_g3header
A9: D | B9: OK | C9: =LEFT(F9,FIND(".",F9)-1) -> zjs_c_g3header | D9: {=INDEX('Not Req'!$E$4:$E$71,MATCH(MID(F9,FIND(".",F9)+1,LEN(F9)-FIND(".",F9)+1),'Not Req'!$D$4:$D$71,0))} -> BDEF | E9: =INDEX('Not Req'!$F$4:$F$71,MATCH(MID(F9,FIND(".",F9)+1,LEN(F9)-FIND(".",F9)+1),'Not Req'!$D$4:$D$71,0)) -> 4. CDS | F9: zjs_c_g3header.bdef.asbdef | G9: UPDATED ON 02-FEB-26 | H9: 3 months ago | N9: zjs_c_g3note
A10: D | B10: OK | C10: =LEFT(F10,FIND(".",F10)-1) -> zjs_c_g3header | D10: {=INDEX('Not Req'!$E$4:$E$71,MATCH(MID(F10,FIND(".",F10)+1,LEN(F10)-FIND(".",F10)+1),'Not Req'!$D$4:$D$71,0))} -> Data Definition | E10: =INDEX('Not Req'!$F$4:$F$71,MATCH(MID(F10,FIND(".",F10)+1,LEN(F10)-FIND(".",F10)+1),'Not Req'!$D$4:$D$71,0)) -> 4. CDS | F10: zjs_c_g3header.ddls.asddls | G10: UPDATED ON 02-FEB-26 | H10: 3 months ago | N10: zjs_c_g3position
A11: D | B11: OK | C11: =LEFT(F11,FIND(".",F11)-1) -> zjs_c_g3header | D11: {=INDEX('Not Req'!$E$4:$E$71,MATCH(MID(F11,FIND(".",F11)+1,LEN(F11)-FIND(".",F11)+1),'Not Req'!$D$4:$D$71,0))} -> Metadata | E11: =INDEX('Not Req'!$F$4:$F$71,MATCH(MID(F11,FIND(".",F11)+1,LEN(F11)-FIND(".",F11)+1),'Not Req'!$D$4:$D$71,0)) -> 4. CDS | F11: zjs_c_g3header.ddlx.asddlxs | G11: UPDATED ON 02-FEB-26 | H11: 3 months ago | N11: zjs_r_g3header
A12: D | B12: OK | C12: =LEFT(F12,FIND(".",F12)-1) -> zjs_c_g3note | D12: {=INDEX('Not Req'!$E$4:$E$71,MATCH(MID(F12,FIND(".",F12)+1,LEN(F12)-FIND(".",F12)+1),'Not Req'!$D$4:$D$71,0))} -> Data Definition | E12: =INDEX('Not Req'!$F$4:$F$71,MATCH(MID(F12,FIND(".",F12)+1,LEN(F12)-FIND(".",F12)+1),'Not Req'!$D$4:$D$71,0)) -> 4. CDS | F12: zjs_c_g3note.ddls.asddls | G12: UPDATED ON 02-FEB-26 | H12: 3 months ago | N12: zjs_r_g3note
A13: D | B13: OK | C13: =LEFT(F13,FIND(".",F13)-1) -> zjs_c_g3note | D13: {=INDEX('Not Req'!$E$4:$E$71,MATCH(MID(F13,FIND(".",F13)+1,LEN(F13)-FIND(".",F13)+1),'Not Req'!$D$4:$D$71,0))} -> Metadata | E13: =INDEX('Not Req'!$F$4:$F$71,MATCH(MID(F13,FIND(".",F13)+1,LEN(F13)-FIND(".",F13)+1),'Not Req'!$D$4:$D$71,0)) -> 4. CDS | F13: zjs_c_g3note.ddlx.asddlxs | G13: UPDATED ON 02-FEB-26 | H13: 3 months ago | N13: zjs_r_g3position
A14: D | B14: OK | C14: =LEFT(F14,FIND(".",F14)-1) -> zjs_c_g3position | D14: {=INDEX('Not Req'!$E$4:$E$71,MATCH(MID(F14,FIND(".",F14)+1,LEN(F14)-FIND(".",F14)+1),'Not Req'!$D$4:$D$71,0))} -> Data Definition | E14: =INDEX('Not Req'!$F$4:$F$71,MATCH(MID(F14,FIND(".",F14)+1,LEN(F14)-FIND(".",F14)+1),'Not Req'!$D$4:$D$71,0)) -> 4. CDS | F14: zjs_c_g3position.ddls.asddls | G14: UPDATED ON 02-FEB-26 | H14: 3 months ago | N14: zjs_g3header
A15: D | B15: OK | C15: =LEFT(F15,FIND(".",F15)-1) -> zjs_c_g3position | D15: {=INDEX('Not Req'!$E$4:$E$71,MATCH(MID(F15,FIND(".",F15)+1,LEN(F15)-FIND(".",F15)+1),'Not Req'!$D$4:$D$71,0))} -> Metadata | E15: =INDEX('Not Req'!$F$4:$F$71,MATCH(MID(F15,FIND(".",F15)+1,LEN(F15)-FIND(".",F15)+1),'Not Req'!$D$4:$D$71,0)) -> 4. CDS | F15: zjs_c_g3position.ddlx.asddlxs | G15: UPDATED ON 02-FEB-26 | H15: 3 months ago
A16: D | B16: OK | C16: =LEFT(F16,FIND(".",F16)-1) -> zjs_r_g3header | D16: {=INDEX('Not Req'!$E$4:$E$71,MATCH(MID(F16,FIND(".",F16)+1,LEN(F16)-FIND(".",F16)+1),'Not Req'!$D$4:$D$71,0))} -> BDEF | E16: =INDEX('Not Req'!$F$4:$F$71,MATCH(MID(F16,FIND(".",F16)+1,LEN(F16)-FIND(".",F16)+1),'Not Req'!$D$4:$D$71,0)) -> 4. CDS | F16: zjs_r_g3header.bdef.asbdef | G16: UPDATED ON 02-FEB-26 | H16: 3 months ago
A17: D | B17: OK | C17: =LEFT(F17,FIND(".",F17)-1) -> zjs_r_g3header | D17: {=INDEX('Not Req'!$E$4:$E$71,MATCH(MID(F17,FIND(".",F17)+1,LEN(F17)-FIND(".",F17)+1),'Not Req'!$D$4:$D$71,0))} -> Data Definition | E17: =INDEX('Not Req'!$F$4:$F$71,MATCH(MID(F17,FIND(".",F17)+1,LEN(F17)-FIND(".",F17)+1),'Not Req'!$D$4:$D$71,0)) -> 4. CDS | F17: zjs_r_g3header.ddls.asddls | G17: UPDATED ON 02-FEB-26 | H17: 3 months ago
A18: D | B18: OK | C18: =LEFT(F18,FIND(".",F18)-1) -> zjs_r_g3note | D18: {=INDEX('Not Req'!$E$4:$E$71,MATCH(MID(F18,FIND(".",F18)+1,LEN(F18)-FIND(".",F18)+1),'Not Req'!$D$4:$D$71,0))} -> Data Definition | E18: =INDEX('Not Req'!$F$4:$F$71,MATCH(MID(F18,FIND(".",F18)+1,LEN(F18)-FIND(".",F18)+1),'Not Req'!$D$4:$D$71,0)) -> 4. CDS | F18: zjs_r_g3note.ddls.asddls | G18: UPDATED ON 02-FEB-26 | H18: 3 months ago
A19: D | B19: OK | C19: =LEFT(F19,FIND(".",F19)-1) -> zjs_r_g3position | D19: {=INDEX('Not Req'!$E$4:$E$71,MATCH(MID(F19,FIND(".",F19)+1,LEN(F19)-FIND(".",F19)+1),'Not Req'!$D$4:$D$71,0))} -> Data Definition | E19: =INDEX('Not Req'!$F$4:$F$71,MATCH(MID(F19,FIND(".",F19)+1,LEN(F19)-FIND(".",F19)+1),'Not Req'!$D$4:$D$71,0)) -> 4. CDS | F19: zjs_r_g3position.ddls.asddls | G19: UPDATED ON 02-FEB-26 | H19: 3 months ago
A20: D | B20: OK | C20: =LEFT(F20,FIND(".",F20)-1) -> zjs_g3header | D20: {=INDEX('Not Req'!$E$4:$E$71,MATCH(MID(F20,FIND(".",F20)+1,LEN(F20)-FIND(".",F20)+1),'Not Req'!$D$4:$D$71,0))} -> Table | E20: =INDEX('Not Req'!$F$4:$F$71,MATCH(MID(F20,FIND(".",F20)+1,LEN(F20)-FIND(".",F20)+1),'Not Req'!$D$4:$D$71,0)) -> 5. Dictionary | F20: zjs_g3header.tabl.xml | G20: UPDATED ON 02-FEB-26 | H20: 3 months ago
A21: D | B21: OK | C21: =LEFT(F21,FIND(".",F21)-1) -> zjs_g3header_d | D21: {=INDEX('Not Req'!$E$4:$E$71,MATCH(MID(F21,FIND(".",F21)+1,LEN(F21)-FIND(".",F21)+1),'Not Req'!$D$4:$D$71,0))} -> Table | E21: =INDEX('Not Req'!$F$4:$F$71,MATCH(MID(F21,FIND(".",F21)+1,LEN(F21)-FIND(".",F21)+1),'Not Req'!$D$4:$D$71,0)) -> 5. Dictionary | F21: zjs_g3header_d.tabl.xml | G21: UPDATED ON 02-FEB-26 | H21: 3 months ago
A22: D | B22: OK | C22: =LEFT(F22,FIND(".",F22)-1) -> zjs_g3note | D22: {=INDEX('Not Req'!$E$4:$E$71,MATCH(MID(F22,FIND(".",F22)+1,LEN(F22)-FIND(".",F22)+1),'Not Req'!$D$4:$D$71,0))} -> Table | E22: =INDEX('Not Req'!$F$4:$F$71,MATCH(MID(F22,FIND(".",F22)+1,LEN(F22)-FIND(".",F22)+1),'Not Req'!$D$4:$D$71,0)) -> 5. Dictionary | F22: zjs_g3note.tabl.xml | G22: UPDATED ON 02-FEB-26 | H22: 3 months ago
A23: D | B23: OK | C23: =LEFT(F23,FIND(".",F23)-1) -> zjs_g3note_d | D23: {=INDEX('Not Req'!$E$4:$E$71,MATCH(MID(F23,FIND(".",F23)+1,LEN(F23)-FIND(".",F23)+1),'Not Req'!$D$4:$D$71,0))} -> Table | E23: =INDEX('Not Req'!$F$4:$F$71,MATCH(MID(F23,FIND(".",F23)+1,LEN(F23)-FIND(".",F23)+1),'Not Req'!$D$4:$D$71,0)) -> 5. Dictionary | F23: zjs_g3note_d.tabl.xml | G23: UPDATED ON 02-FEB-26 | H23: 3 months ago
A24: D | B24: OK | C24: =LEFT(F24,FIND(".",F24)-1) -> zjs_g3position | D24: {=INDEX('Not Req'!$E$4:$E$71,MATCH(MID(F24,FIND(".",F24)+1,LEN(F24)-FIND(".",F24)+1),'Not Req'!$D$4:$D$71,0))} -> Table | E24: =INDEX('Not Req'!$F$4:$F$71,MATCH(MID(F24,FIND(".",F24)+1,LEN(F24)-FIND(".",F24)+1),'Not Req'!$D$4:$D$71,0)) -> 5. Dictionary | F24: zjs_g3position.tabl.xml | G24: UPDATED ON 02-FEB-26 | H24: 3 months ago
A25: D | B25: OK | C25: =LEFT(F25,FIND(".",F25)-1) -> zjs_g3position_d | D25: {=INDEX('Not Req'!$E$4:$E$71,MATCH(MID(F25,FIND(".",F25)+1,LEN(F25)-FIND(".",F25)+1),'Not Req'!$D$4:$D$71,0))} -> Table | E25: =INDEX('Not Req'!$F$4:$F$71,MATCH(MID(F25,FIND(".",F25)+1,LEN(F25)-FIND(".",F25)+1),'Not Req'!$D$4:$D$71,0)) -> 5. Dictionary | F25: zjs_g3position_d.tabl.xml | G25: UPDATED ON 02-FEB-26 | H25: 3 months ago
A26: D | B26: OK | C26: =LEFT(F26,FIND(".",F26)-1) -> zjs_bp_c_g3header | D26: {=INDEX('Not Req'!$E$4:$E$71,MATCH(MID(F26,FIND(".",F26)+1,LEN(F26)-FIND(".",F26)+1),'Not Req'!$D$4:$D$71,0))} -> Classes | E26: =INDEX('Not Req'!$F$4:$F$71,MATCH(MID(F26,FIND(".",F26)+1,LEN(F26)-FIND(".",F26)+1),'Not Req'!$D$4:$D$71,0)) -> 7. Source Code Library | F26: zjs_bp_c_g3header.clas.abap | G26: Updated 16-Mar-26 | H26: 2 months ago
... A28: D | B28: OK | C28: =LEFT(F28,FIND(".",F28)-1) -> zjs_bp_r_g3header | D28: {=INDEX('Not Req'!$E$4:$E$71,MATCH(MID(F28,FIND(".",F28)+1,LEN(F28)-FIND(".",F28)+1),'Not Req'!$D$4:$D$71,0))} -> Classes Local | E28: =INDEX('Not Req'!$F$4:$F$71,MATCH(MID(F28,FIND(".",F28)+1,LEN(F28)-FIND(".",F28)+1),'Not Req'!$D$4:$D$71,0)) -> 7. Source Code Library | F28: zjs_bp_r_g3header.clas.locals_imp.abap | G28: UPDATED ON 02-FEB-26 | H28: 3 months ago
A29: D | C29: =LEFT(F29,FIND(".",F29)-1) -> zjs_a_generatortemplate | D29: {=INDEX('Not Req'!$E$4:$E$71,MATCH(MID(F29,FIND(".",F29)+1,LEN(F29)-FIND(".",F29)+1),'Not Req'!$D$4:$D$71,0))} -> BaseInfo : Data Definition | E29: =INDEX('Not Req'!$F$4:$F$71,MATCH(MID(F29,FIND(".",F29)+1,LEN(F29)-FIND(".",F29)+1),'Not Req'!$D$4:$D$71,0)) -> 98. Base Info | F29: zjs_a_generatortemplate.ddls.baseinfo | G29: UPDATED ON 02-FEB-26 | H29: 3 months ago
A30: D | C30: =LEFT(F30,FIND(".",F30)-1) -> zjs_c_g3header | D30: {=INDEX('Not Req'!$E$4:$E$71,MATCH(MID(F30,FIND(".",F30)+1,LEN(F30)-FIND(".",F30)+1),'Not Req'!$D$4:$D$71,0))} -> BaseInfo : Data Definition | E30: =INDEX('Not Req'!$F$4:$F$71,MATCH(MID(F30,FIND(".",F30)+1,LEN(F30)-FIND(".",F30)+1),'Not Req'!$D$4:$D$71,0)) -> 98. Base Info | F30: zjs_c_g3header.ddls.baseinfo | G30: UPDATED ON 02-FEB-26 | H30: 3 months ago
A31: D | C31: =LEFT(F31,FIND(".",F31)-1) -> zjs_c_g3note | D31: {=INDEX('Not Req'!$E$4:$E$71,MATCH(MID(F31,FIND(".",F31)+1,LEN(F31)-FIND(".",F31)+1),'Not Req'!$D$4:$D$71,0))} -> BaseInfo : Data Definition | E31: =INDEX('Not Req'!$F$4:$F$71,MATCH(MID(F31,FIND(".",F31)+1,LEN(F31)-FIND(".",F31)+1),'Not Req'!$D$4:$D$71,0)) -> 98. Base Info | F31: zjs_c_g3note.ddls.baseinfo | G31: UPDATED ON 02-FEB-26 | H31: 3 months ago
A32: D | C32: =LEFT(F32,FIND(".",F32)-1) -> zjs_c_g3position | D32: {=INDEX('Not Req'!$E$4:$E$71,MATCH(MID(F32,FIND(".",F32)+1,LEN(F32)-FIND(".",F32)+1),'Not Req'!$D$4:$D$71,0))} -> BaseInfo : Data Definition | E32: =INDEX('Not Req'!$F$4:$F$71,MATCH(MID(F32,FIND(".",F32)+1,LEN(F32)-FIND(".",F32)+1),'Not Req'!$D$4:$D$71,0)) -> 98. Base Info | F32: zjs_c_g3position.ddls.baseinfo | G32: UPDATED ON 02-FEB-26 | H32: 3 months ago
A33: D | C33: =LEFT(F33,FIND(".",F33)-1) -> zjs_r_g3header | D33: {=INDEX('Not Req'!$E$4:$E$71,MATCH(MID(F33,FIND(".",F33)+1,LEN(F33)-FIND(".",F33)+1),'Not Req'!$D$4:$D$71,0))} -> BaseInfo : Data Definition | E33: =INDEX('Not Req'!$F$4:$F$71,MATCH(MID(F33,FIND(".",F33)+1,LEN(F33)-FIND(".",F33)+1),'Not Req'!$D$4:$D$71,0)) -> 98. Base Info | F33: zjs_r_g3header.ddls.baseinfo | G33: UPDATED ON 02-FEB-26 | H33: 3 months ago
A34: D | C34: =LEFT(F34,FIND(".",F34)-1) -> zjs_r_g3note | D34: {=INDEX('Not Req'!$E$4:$E$71,MATCH(MID(F34,FIND(".",F34)+1,LEN(F34)-FIND(".",F34)+1),'Not Req'!$D$4:$D$71,0))} -> BaseInfo : Data Definition | E34: =INDEX('Not Req'!$F$4:$F$71,MATCH(MID(F34,FIND(".",F34)+1,LEN(F34)-FIND(".",F34)+1),'Not Req'!$D$4:$D$71,0)) -> 98. Base Info | F34: zjs_r_g3note.ddls.baseinfo | G34: UPDATED ON 02-FEB-26 | H34: 3 months ago
A35: D | C35: =LEFT(F35,FIND(".",F35)-1) -> zjs_r_g3position | D35: {=INDEX('Not Req'!$E$4:$E$71,MATCH(MID(F35,FIND(".",F35)+1,LEN(F35)-FIND(".",F35)+1),'Not Req'!$D$4:$D$71,0))} -> BaseInfo : Data Definition | E35: =INDEX('Not Req'!$F$4:$F$71,MATCH(MID(F35,FIND(".",F35)+1,LEN(F35)-FIND(".",F35)+1),'Not Req'!$D$4:$D$71,0)) -> 98. Base Info | F35: zjs_r_g3position.ddls.baseinfo | G35: UPDATED ON 02-FEB-26 | H35: 3 months ago
A36: D | C36: =LEFT(F36,FIND(".",F36)-1) -> package | D36: {=INDEX('Not Req'!$E$4:$E$71,MATCH(MID(F36,FIND(".",F36)+1,LEN(F36)-FIND(".",F36)+1),'Not Req'!$D$4:$D$71,0))} -> Description : Package | E36: =INDEX('Not Req'!$F$4:$F$71,MATCH(MID(F36,FIND(".",F36)+1,LEN(F36)-FIND(".",F36)+1),'Not Req'!$D$4:$D$71,0)) -> 99. Descriptions | F36: package.devc.xml | G36: UPDATED ON 02-FEB-26 | H36: 3 months ago
A37: D | C37: =LEFT(F37,FIND(".",F37)-1) -> zjs_a_generatortemplate | D37: {=INDEX('Not Req'!$E$4:$E$71,MATCH(MID(F37,FIND(".",F37)+1,LEN(F37)-FIND(".",F37)+1),'Not Req'!$D$4:$D$71,0))} -> Description : Data Definition | E37: =INDEX('Not Req'!$F$4:$F$71,MATCH(MID(F37,FIND(".",F37)+1,LEN(F37)-FIND(".",F37)+1),'Not Req'!$D$4:$D$71,0)) -> 99. Descriptions | F37: zjs_a_generatortemplate.ddls.xml | G37: UPDATED ON 02-FEB-26 | H37: 3 months ago
A38: D | C38: =LEFT(F38,FIND(".",F38)-1) -> zjs_bp_c_g3header | D38: {=INDEX('Not Req'!$E$4:$E$71,MATCH(MID(F38,FIND(".",F38)+1,LEN(F38)-FIND(".",F38)+1),'Not Req'!$D$4:$D$71,0))} -> Description : Classes | E38: =INDEX('Not Req'!$F$4:$F$71,MATCH(MID(F38,FIND(".",F38)+1,LEN(F38)-FIND(".",F38)+1),'Not Req'!$D$4:$D$71,0)) -> 99. Descriptions | F38: zjs_bp_c_g3header.clas.xml | G38: UPDATED ON 02-FEB-26 | H38: 3 months ago
A39: D | C39: =LEFT(F39,FIND(".",F39)-1) -> zjs_bp_r_g3header | D39: {=INDEX('Not Req'!$E$4:$E$71,MATCH(MID(F39,FIND(".",F39)+1,LEN(F39)-FIND(".",F39)+1),'Not Req'!$D$4:$D$71,0))} -> Description : Classes | E39: =INDEX('Not Req'!$F$4:$F$71,MATCH(MID(F39,FIND(".",F39)+1,LEN(F39)-FIND(".",F39)+1),'Not Req'!$D$4:$D$71,0)) -> 99. Descriptions | F39: zjs_bp_r_g3header.clas.xml | G39: UPDATED ON 02-FEB-26 | H39: 3 months ago
A40: D | C40: =LEFT(F40,FIND(".",F40)-1) -> zjs_c_g3header | D40: {=INDEX('Not Req'!$E$4:$E$71,MATCH(MID(F40,FIND(".",F40)+1,LEN(F40)-FIND(".",F40)+1),'Not Req'!$D$4:$D$71,0))} -> Description : BDEF | E40: =INDEX('Not Req'!$F$4:$F$71,MATCH(MID(F40,FIND(".",F40)+1,LEN(F40)-FIND(".",F40)+1),'Not Req'!$D$4:$D$71,0)) -> 99. Descriptions | F40: zjs_c_g3header.bdef.xml | G40: UPDATED ON 02-FEB-26 | H40: 3 months ago
... A53: D | C53: =LEFT(F53,FIND(".",F53)-1) -> zjs_g3invoice | D53: {=INDEX('Not Req'!$E$4:$E$71,MATCH(MID(F53,FIND(".",F53)+1,LEN(F53)-FIND(".",F53)+1),'Not Req'!$D$4:$D$71,0))} -> #N/A | E53: =INDEX('Not Req'!$F$4:$F$71,MATCH(MID(F53,FIND(".",F53)+1,LEN(F53)-FIND(".",F53)+1),'Not Req'!$D$4:$D$71,0)) -> #N/A | F53: zjs_g3invoice.ront.json | G53: UPDATED ON 02-FEB-26 | H53: 3 months ago

Sheet ZJS_05_RAP_GEN1
B2: d | C2: Object | D2: Type | E2: Category | F2: Github Object | G2: Github Type | H2: Version
A4: D | B4: OK | C4: =LEFT(F4,FIND(".",F4)-1) -> 1da11e2293e8b184128a6b6a7c242bht | D4: {=INDEX('Not Req'!$E$4:$E$71,MATCH(MID(F4,FIND(".",F4)+1,LEN(F4)-FIND(".",F4)+1),'Not Req'!$D$4:$D$71,0))} -> Authorization Defaults (TADIR) | E4: =INDEX('Not Req'!$F$4:$F$71,MATCH(MID(F4,FIND(".",F4)+1,LEN(F4)-FIND(".",F4)+1),'Not Req'!$D$4:$D$71,0)) -> 1. Authorizations | F4: 1da11e2293e8b184128a6b6a7c242bht.sush.xml | G4: UPDATED ON 02-FEB-26 | H4: 3 months ago | N4: {=_xlfn.UNIQUE(C4:C20)} -> 1da11e2293e8b184128a6b6a7c242bht
A5: D | B5: OK | C5: =LEFT(F5,FIND(".",F5)-1) -> zjs_demo_gen1 | D5: {=INDEX('Not Req'!$E$4:$E$71,MATCH(MID(F5,FIND(".",F5)+1,LEN(F5)-FIND(".",F5)+1),'Not Req'!$D$4:$D$71,0))} -> Service Definition | E5: =INDEX('Not Req'!$F$4:$F$71,MATCH(MID(F5,FIND(".",F5)+1,LEN(F5)-FIND(".",F5)+1),'Not Req'!$D$4:$D$71,0)) -> 2. Business Services | F5: zjs_demo_gen1.srvd.srvdsrv | G5: UPDATED ON 02-FEB-26 | H5: 3 months ago | N5: zjs_demo_gen1
A6: D | B6: OK | C6: =LEFT(F6,FIND(".",F6)-1) -> zjs_ui_demo_gen1_o4 | D6: {=INDEX('Not Req'!$E$4:$E$71,MATCH(MID(F6,FIND(".",F6)+1,LEN(F6)-FIND(".",F6)+1),'Not Req'!$D$4:$D$71,0))} -> Service Binding | E6: =INDEX('Not Req'!$F$4:$F$71,MATCH(MID(F6,FIND(".",F6)+1,LEN(F6)-FIND(".",F6)+1),'Not Req'!$D$4:$D$71,0)) -> 2. Business Services | F6: zjs_ui_demo_gen1_o4.srvb.xml | G6: UPDATED ON 02-FEB-26 | H6: 3 months ago | N6: zjs_ui_demo_gen1_o4
A7: D | B7: OK | C7: =LEFT(F7,FIND(".",F7)-1) -> zjs_ui_demo_gen1_o4_0001_g4ba | D7: {=INDEX('Not Req'!$E$4:$E$71,MATCH(MID(F7,FIND(".",F7)+1,LEN(F7)-FIND(".",F7)+1),'Not Req'!$D$4:$D$71,0))} -> Inbound Service | E7: =INDEX('Not Req'!$F$4:$F$71,MATCH(MID(F7,FIND(".",F7)+1,LEN(F7)-FIND(".",F7)+1),'Not Req'!$D$4:$D$71,0)) -> 3. Cloud Communication Management | F7: zjs_ui_demo_gen1_o4_0001_g4ba.sco2.xml | G7: UPDATED ON 02-FEB-26 | H7: 3 months ago | N7: zjs_ui_demo_gen1_o4_0001_g4ba
A8: D | B8: OK | C8: =LEFT(F8,FIND(".",F8)-1) -> zjs_c_dmogen1 | D8: {=INDEX('Not Req'!$E$4:$E$71,MATCH(MID(F8,FIND(".",F8)+1,LEN(F8)-FIND(".",F8)+1),'Not Req'!$D$4:$D$71,0))} -> BDEF | E8: =INDEX('Not Req'!$F$4:$F$71,MATCH(MID(F8,FIND(".",F8)+1,LEN(F8)-FIND(".",F8)+1),'Not Req'!$D$4:$D$71,0)) -> 4. CDS | F8: zjs_c_dmogen1.bdef.asbdef | G8: UPDATED ON 02-FEB-26 | H8: 3 months ago | N8: zjs_c_dmogen1
A9: D | B9: OK | C9: =LEFT(F9,FIND(".",F9)-1) -> zjs_c_dmogen1 | D9: {=INDEX('Not Req'!$E$4:$E$71,MATCH(MID(F9,FIND(".",F9)+1,LEN(F9)-FIND(".",F9)+1),'Not Req'!$D$4:$D$71,0))} -> Data Definition | E9: =INDEX('Not Req'!$F$4:$F$71,MATCH(MID(F9,FIND(".",F9)+1,LEN(F9)-FIND(".",F9)+1),'Not Req'!$D$4:$D$71,0)) -> 4. CDS | F9: zjs_c_dmogen1.ddls.asddls | G9: UPDATED ON 02-FEB-26 | H9: 3 months ago | N9: zjs_r_dmogen1
A10: D | B10: OK | C10: =LEFT(F10,FIND(".",F10)-1) -> zjs_c_dmogen1 | D10: {=INDEX('Not Req'!$E$4:$E$71,MATCH(MID(F10,FIND(".",F10)+1,LEN(F10)-FIND(".",F10)+1),'Not Req'!$D$4:$D$71,0))} -> Metadata | E10: =INDEX('Not Req'!$F$4:$F$71,MATCH(MID(F10,FIND(".",F10)+1,LEN(F10)-FIND(".",F10)+1),'Not Req'!$D$4:$D$71,0)) -> 4. CDS | F10: zjs_c_dmogen1.ddlx.asddlxs | G10: UPDATED ON 02-FEB-26 | H10: 3 months ago | N10: zjs_demo_description
A11: D | B11: OK | C11: =LEFT(F11,FIND(".",F11)-1) -> zjs_r_dmogen1 | D11: {=INDEX('Not Req'!$E$4:$E$71,MATCH(MID(F11,FIND(".",F11)+1,LEN(F11)-FIND(".",F11)+1),'Not Req'!$D$4:$D$71,0))} -> BDEF | E11: =INDEX('Not Req'!$F$4:$F$71,MATCH(MID(F11,FIND(".",F11)+1,LEN(F11)-FIND(".",F11)+1),'Not Req'!$D$4:$D$71,0)) -> 4. CDS | F11: zjs_r_dmogen1.bdef.asbdef | G11: UPDATED ON 02-FEB-26 | H11: 3 months ago | N11: zjs_demo_key
A12: D | B12: OK | C12: =LEFT(F12,FIND(".",F12)-1) -> zjs_r_dmogen1 | D12: {=INDEX('Not Req'!$E$4:$E$71,MATCH(MID(F12,FIND(".",F12)+1,LEN(F12)-FIND(".",F12)+1),'Not Req'!$D$4:$D$71,0))} -> Data Definition | E12: =INDEX('Not Req'!$F$4:$F$71,MATCH(MID(F12,FIND(".",F12)+1,LEN(F12)-FIND(".",F12)+1),'Not Req'!$D$4:$D$71,0)) -> 4. CDS | F12: zjs_r_dmogen1.ddls.asddls | G12: UPDATED ON 02-FEB-26 | H12: 3 months ago | N12: zjs_demo_price
A13: D | B13: OK | C13: =LEFT(F13,FIND(".",F13)-1) -> zjs_demo_description | D13: {=INDEX('Not Req'!$E$4:$E$71,MATCH(MID(F13,FIND(".",F13)+1,LEN(F13)-FIND(".",F13)+1),'Not Req'!$D$4:$D$71,0))} -> Data Element | E13: =INDEX('Not Req'!$F$4:$F$71,MATCH(MID(F13,FIND(".",F13)+1,LEN(F13)-FIND(".",F13)+1),'Not Req'!$D$4:$D$71,0)) -> 5. Dictionary | F13: zjs_demo_description.dtel.xml | G13: UPDATED ON 02-FEB-26 | H13: 3 months ago | N13: zjs_dmo_gen1
A14: D | B14: OK | C14: =LEFT(F14,FIND(".",F14)-1) -> zjs_demo_key | D14: {=INDEX('Not Req'!$E$4:$E$71,MATCH(MID(F14,FIND(".",F14)+1,LEN(F14)-FIND(".",F14)+1),'Not Req'!$D$4:$D$71,0))} -> Domain | E14: =INDEX('Not Req'!$F$4:$F$71,MATCH(MID(F14,FIND(".",F14)+1,LEN(F14)-FIND(".",F14)+1),'Not Req'!$D$4:$D$71,0)) -> 5. Dictionary | F14: zjs_demo_key.doma.xml | G14: UPDATED ON 02-FEB-26 | H14: 3 months ago | N14: zjs_dmo_gen1_d
A15: D | B15: OK | C15: =LEFT(F15,FIND(".",F15)-1) -> zjs_demo_key | D15: {=INDEX('Not Req'!$E$4:$E$71,MATCH(MID(F15,FIND(".",F15)+1,LEN(F15)-FIND(".",F15)+1),'Not Req'!$D$4:$D$71,0))} -> Data Element | E15: =INDEX('Not Req'!$F$4:$F$71,MATCH(MID(F15,FIND(".",F15)+1,LEN(F15)-FIND(".",F15)+1),'Not Req'!$D$4:$D$71,0)) -> 5. Dictionary | F15: zjs_demo_key.dtel.xml | G15: UPDATED ON 02-FEB-26 | H15: 3 months ago | N15: zbp_js_demo_simple_gen1
A16: D | B16: OK | C16: =LEFT(F16,FIND(".",F16)-1) -> zjs_demo_price | D16: {=INDEX('Not Req'!$E$4:$E$71,MATCH(MID(F16,FIND(".",F16)+1,LEN(F16)-FIND(".",F16)+1),'Not Req'!$D$4:$D$71,0))} -> Data Element | E16: =INDEX('Not Req'!$F$4:$F$71,MATCH(MID(F16,FIND(".",F16)+1,LEN(F16)-FIND(".",F16)+1),'Not Req'!$D$4:$D$71,0)) -> 5. Dictionary | F16: zjs_demo_price.dtel.xml | G16: UPDATED ON 02-FEB-26 | H16: 3 months ago
A17: D | B17: OK | C17: =LEFT(F17,FIND(".",F17)-1) -> zjs_dmo_gen1 | D17: {=INDEX('Not Req'!$E$4:$E$71,MATCH(MID(F17,FIND(".",F17)+1,LEN(F17)-FIND(".",F17)+1),'Not Req'!$D$4:$D$71,0))} -> Table | E17: =INDEX('Not Req'!$F$4:$F$71,MATCH(MID(F17,FIND(".",F17)+1,LEN(F17)-FIND(".",F17)+1),'Not Req'!$D$4:$D$71,0)) -> 5. Dictionary | F17: zjs_dmo_gen1.tabl.xml | G17: UPDATED ON 02-FEB-26 | H17: 3 months ago
A18: D | B18: OK | C18: =LEFT(F18,FIND(".",F18)-1) -> zjs_dmo_gen1_d | D18: {=INDEX('Not Req'!$E$4:$E$71,MATCH(MID(F18,FIND(".",F18)+1,LEN(F18)-FIND(".",F18)+1),'Not Req'!$D$4:$D$71,0))} -> Table | E18: =INDEX('Not Req'!$F$4:$F$71,MATCH(MID(F18,FIND(".",F18)+1,LEN(F18)-FIND(".",F18)+1),'Not Req'!$D$4:$D$71,0)) -> 5. Dictionary | F18: zjs_dmo_gen1_d.tabl.xml | G18: UPDATED ON 02-FEB-26 | H18: 3 months ago
A19: D | B19: OK | C19: =LEFT(F19,FIND(".",F19)-1) -> zbp_js_demo_simple_gen1 | D19: {=INDEX('Not Req'!$E$4:$E$71,MATCH(MID(F19,FIND(".",F19)+1,LEN(F19)-FIND(".",F19)+1),'Not Req'!$D$4:$D$71,0))} -> Classes | E19: =INDEX('Not Req'!$F$4:$F$71,MATCH(MID(F19,FIND(".",F19)+1,LEN(F19)-FIND(".",F19)+1),'Not Req'!$D$4:$D$71,0)) -> 7. Source Code Library | F19: zbp_js_demo_simple_gen1.clas.abap | G19: Updated 16-Mar-26 | H19: 2 months ago
A20: D | B20: OK | C20: =LEFT(F20,FIND(".",F20)-1) -> zbp_js_demo_simple_gen1 | D20: {=INDEX('Not Req'!$E$4:$E$71,MATCH(MID(F20,FIND(".",F20)+1,LEN(F20)-FIND(".",F20)+1),'Not Req'!$D$4:$D$71,0))} -> Classes Local | E20: =INDEX('Not Req'!$F$4:$F$71,MATCH(MID(F20,FIND(".",F20)+1,LEN(F20)-FIND(".",F20)+1),'Not Req'!$D$4:$D$71,0)) -> 7. Source Code Library | F20: zbp_js_demo_simple_gen1.clas.locals_imp.abap | G20: UPDATED ON 02-FEB-26 | H20: 3 months ago
A21: D | C21: =LEFT(F21,FIND(".",F21)-1) -> zjs_c_dmogen1 | D21: {=INDEX('Not Req'!$E$4:$E$71,MATCH(MID(F21,FIND(".",F21)+1,LEN(F21)-FIND(".",F21)+1),'Not Req'!$D$4:$D$71,0))} -> BaseInfo : Data Definition | E21: =INDEX('Not Req'!$F$4:$F$71,MATCH(MID(F21,FIND(".",F21)+1,LEN(F21)-FIND(".",F21)+1),'Not Req'!$D$4:$D$71,0)) -> 98. Base Info | F21: zjs_c_dmogen1.ddls.baseinfo | G21: UPDATED ON 02-FEB-26 | H21: 3 months ago
A22: D | C22: =LEFT(F22,FIND(".",F22)-1) -> zjs_r_dmogen1 | D22: {=INDEX('Not Req'!$E$4:$E$71,MATCH(MID(F22,FIND(".",F22)+1,LEN(F22)-FIND(".",F22)+1),'Not Req'!$D$4:$D$71,0))} -> BaseInfo : Data Definition | E22: =INDEX('Not Req'!$F$4:$F$71,MATCH(MID(F22,FIND(".",F22)+1,LEN(F22)-FIND(".",F22)+1),'Not Req'!$D$4:$D$71,0)) -> 98. Base Info | F22: zjs_r_dmogen1.ddls.baseinfo | G22: UPDATED ON 02-FEB-26 | H22: 3 months ago
A23: D | C23: =LEFT(F23,FIND(".",F23)-1) -> package | D23: {=INDEX('Not Req'!$E$4:$E$71,MATCH(MID(F23,FIND(".",F23)+1,LEN(F23)-FIND(".",F23)+1),'Not Req'!$D$4:$D$71,0))} -> Description : Package | E23: =INDEX('Not Req'!$F$4:$F$71,MATCH(MID(F23,FIND(".",F23)+1,LEN(F23)-FIND(".",F23)+1),'Not Req'!$D$4:$D$71,0)) -> 99. Descriptions | F23: package.devc.xml | G23: UPDATED ON 02-FEB-26 | H23: 3 months ago
A24: D | C24: =LEFT(F24,FIND(".",F24)-1) -> zbp_js_demo_simple_gen1 | D24: {=INDEX('Not Req'!$E$4:$E$71,MATCH(MID(F24,FIND(".",F24)+1,LEN(F24)-FIND(".",F24)+1),'Not Req'!$D$4:$D$71,0))} -> Description : Classes | E24: =INDEX('Not Req'!$F$4:$F$71,MATCH(MID(F24,FIND(".",F24)+1,LEN(F24)-FIND(".",F24)+1),'Not Req'!$D$4:$D$71,0)) -> 99. Descriptions | F24: zbp_js_demo_simple_gen1.clas.xml | G24: UPDATED ON 02-FEB-26 | H24: 3 months ago
A25: D | C25: =LEFT(F25,FIND(".",F25)-1) -> zjs_c_dmogen1 | D25: {=INDEX('Not Req'!$E$4:$E$71,MATCH(MID(F25,FIND(".",F25)+1,LEN(F25)-FIND(".",F25)+1),'Not Req'!$D$4:$D$71,0))} -> Description : BDEF | E25: =INDEX('Not Req'!$F$4:$F$71,MATCH(MID(F25,FIND(".",F25)+1,LEN(F25)-FIND(".",F25)+1),'Not Req'!$D$4:$D$71,0)) -> 99. Descriptions | F25: zjs_c_dmogen1.bdef.xml | G25: UPDATED ON 02-FEB-26 | H25: 3 months ago
A26: D | C26: =LEFT(F26,FIND(".",F26)-1) -> zjs_c_dmogen1 | D26: {=INDEX('Not Req'!$E$4:$E$71,MATCH(MID(F26,FIND(".",F26)+1,LEN(F26)-FIND(".",F26)+1),'Not Req'!$D$4:$D$71,0))} -> Description : Data Definition | E26: =INDEX('Not Req'!$F$4:$F$71,MATCH(MID(F26,FIND(".",F26)+1,LEN(F26)-FIND(".",F26)+1),'Not Req'!$D$4:$D$71,0)) -> 99. Descriptions | F26: zjs_c_dmogen1.ddls.xml | G26: UPDATED ON 02-FEB-26 | H26: 3 months ago
A27: D | C27: =LEFT(F27,FIND(".",F27)-1) -> zjs_c_dmogen1 | D27: {=INDEX('Not Req'!$E$4:$E$71,MATCH(MID(F27,FIND(".",F27)+1,LEN(F27)-FIND(".",F27)+1),'Not Req'!$D$4:$D$71,0))} -> Description : Metadata | E27: =INDEX('Not Req'!$F$4:$F$71,MATCH(MID(F27,FIND(".",F27)+1,LEN(F27)-FIND(".",F27)+1),'Not Req'!$D$4:$D$71,0)) -> 99. Descriptions | F27: zjs_c_dmogen1.ddlx.xml | G27: UPDATED ON 02-FEB-26 | H27: 3 months ago
A28: D | C28: =LEFT(F28,FIND(".",F28)-1) -> zjs_demo_gen1 | D28: {=INDEX('Not Req'!$E$4:$E$71,MATCH(MID(F28,FIND(".",F28)+1,LEN(F28)-FIND(".",F28)+1),'Not Req'!$D$4:$D$71,0))} -> Description : Service Definition | E28: =INDEX('Not Req'!$F$4:$F$71,MATCH(MID(F28,FIND(".",F28)+1,LEN(F28)-FIND(".",F28)+1),'Not Req'!$D$4:$D$71,0)) -> 99. Descriptions | F28: zjs_demo_gen1.srvd.xml | G28: UPDATED ON 02-FEB-26 | H28: 3 months ago
A29: D | C29: =LEFT(F29,FIND(".",F29)-1) -> zjs_r_dmogen1 | D29: {=INDEX('Not Req'!$E$4:$E$71,MATCH(MID(F29,FIND(".",F29)+1,LEN(F29)-FIND(".",F29)+1),'Not Req'!$D$4:$D$71,0))} -> Description : BDEF | E29: =INDEX('Not Req'!$F$4:$F$71,MATCH(MID(F29,FIND(".",F29)+1,LEN(F29)-FIND(".",F29)+1),'Not Req'!$D$4:$D$71,0)) -> 99. Descriptions | F29: zjs_r_dmogen1.bdef.xml | G29: UPDATED ON 02-FEB-26 | H29: 3 months ago
A30: D | C30: =LEFT(F30,FIND(".",F30)-1) -> zjs_r_dmogen1 | D30: {=INDEX('Not Req'!$E$4:$E$71,MATCH(MID(F30,FIND(".",F30)+1,LEN(F30)-FIND(".",F30)+1),'Not Req'!$D$4:$D$71,0))} -> Description : Data Definition | E30: =INDEX('Not Req'!$F$4:$F$71,MATCH(MID(F30,FIND(".",F30)+1,LEN(F30)-FIND(".",F30)+1),'Not Req'!$D$4:$D$71,0)) -> 99. Descriptions | F30: zjs_r_dmogen1.ddls.xml | G30: UPDATED ON 02-FEB-26 | H30: 3 months ago

Sheet ZJS_04_RAP_INTERFACE
B2: d | C2: Object | D2: Type | E2: Category | F2: Github Object | G2: Github Type | H2: Version
B4: OK | C4: =LEFT(F4,FIND(".",F4)-1) -> zjs_demo_rap_onpremise_odata | D4: {=INDEX('Not Req'!$E$4:$E$71,MATCH(MID(F4,FIND(".",F4)+1,LEN(F4)-FIND(".",F4)+1),'Not Req'!$D$4:$D$71,0))} -> Service Definition | E4: =INDEX('Not Req'!$F$4:$F$71,MATCH(MID(F4,FIND(".",F4)+1,LEN(F4)-FIND(".",F4)+1),'Not Req'!$D$4:$D$71,0)) -> 2. Business Services | F4: zjs_demo_rap_onpremise_odata.srvd.srvdsrv | G4: UPDATED ON 02-FEB-26 | H4: 3 months ago | N4: {=_xlfn.UNIQUE(C4:C20)} -> zjs_demo_rap_onpremise_odata
B5: OK | C5: =LEFT(F5,FIND(".",F5)-1) -> zjs_rap_companynames | D5: {=INDEX('Not Req'!$E$4:$E$71,MATCH(MID(F5,FIND(".",F5)+1,LEN(F5)-FIND(".",F5)+1),'Not Req'!$D$4:$D$71,0))} -> BDEF | E5: =INDEX('Not Req'!$F$4:$F$71,MATCH(MID(F5,FIND(".",F5)+1,LEN(F5)-FIND(".",F5)+1),'Not Req'!$D$4:$D$71,0)) -> 4. CDS | F5: zjs_rap_companynames.bdef.asbdef | G5: UPDATED ON 02-FEB-26 | H5: 3 months ago | N5: zjs_rap_companynames
B6: OK | C6: =LEFT(F6,FIND(".",F6)-1) -> zjs_rap_companynames | D6: {=INDEX('Not Req'!$E$4:$E$71,MATCH(MID(F6,FIND(".",F6)+1,LEN(F6)-FIND(".",F6)+1),'Not Req'!$D$4:$D$71,0))} -> Data Definition | E6: =INDEX('Not Req'!$F$4:$F$71,MATCH(MID(F6,FIND(".",F6)+1,LEN(F6)-FIND(".",F6)+1),'Not Req'!$D$4:$D$71,0)) -> 4. CDS | F6: zjs_rap_companynames.ddls.asddls | G6: UPDATED ON 02-FEB-26 | H6: 3 months ago | N6: zcl_js_demo_odata_actions
B7: OK | C7: =LEFT(F7,FIND(".",F7)-1) -> zcl_js_demo_odata_actions | D7: {=INDEX('Not Req'!$E$4:$E$71,MATCH(MID(F7,FIND(".",F7)+1,LEN(F7)-FIND(".",F7)+1),'Not Req'!$D$4:$D$71,0))} -> Classes | E7: =INDEX('Not Req'!$F$4:$F$71,MATCH(MID(F7,FIND(".",F7)+1,LEN(F7)-FIND(".",F7)+1),'Not Req'!$D$4:$D$71,0)) -> 7. Source Code Library | F7: zcl_js_demo_odata_actions.clas.abap | G7: Updated 16-Mar-26 | H7: 2 months ago | N7: zcl_js_demo_rap_onprem_newv2
B8: OK | C8: =LEFT(F8,FIND(".",F8)-1) -> zcl_js_demo_rap_onprem_newv2 | D8: {=INDEX('Not Req'!$E$4:$E$71,MATCH(MID(F8,FIND(".",F8)+1,LEN(F8)-FIND(".",F8)+1),'Not Req'!$D$4:$D$71,0))} -> Classes | E8: =INDEX('Not Req'!$F$4:$F$71,MATCH(MID(F8,FIND(".",F8)+1,LEN(F8)-FIND(".",F8)+1),'Not Req'!$D$4:$D$71,0)) -> 7. Source Code Library | F8: zcl_js_demo_rap_onprem_newv2.clas.abap | G8: UPDATED ON 02-FEB-26 | H8: 3 months ago | N8: zcl_js_demo_read_func
B9: OK | C9: =LEFT(F9,FIND(".",F9)-1) -> zcl_js_demo_read_func | D9: {=INDEX('Not Req'!$E$4:$E$71,MATCH(MID(F9,FIND(".",F9)+1,LEN(F9)-FIND(".",F9)+1),'Not Req'!$D$4:$D$71,0))} -> Classes | E9: =INDEX('Not Req'!$F$4:$F$71,MATCH(MID(F9,FIND(".",F9)+1,LEN(F9)-FIND(".",F9)+1),'Not Req'!$D$4:$D$71,0)) -> 7. Source Code Library | F9: zcl_js_demo_read_func.clas.abap | G9: UPDATED ON 02-FEB-26 | H9: 3 months ago | N9: zcl_js_demo_read_odata
B10: OK | C10: =LEFT(F10,FIND(".",F10)-1) -> zcl_js_demo_read_odata | D10: {=INDEX('Not Req'!$E$4:$E$71,MATCH(MID(F10,FIND(".",F10)+1,LEN(F10)-FIND(".",F10)+1),'Not Req'!$D$4:$D$71,0))} -> Classes | E10: =INDEX('Not Req'!$F$4:$F$71,MATCH(MID(F10,FIND(".",F10)+1,LEN(F10)-FIND(".",F10)+1),'Not Req'!$D$4:$D$71,0)) -> 7. Source Code Library | F10: zcl_js_demo_read_odata.clas.abap | G10: UPDATED ON 02-FEB-26 | H10: 3 months ago | N10: zcl_js_demo_read_odata_new
B11: OK | C11: =LEFT(F11,FIND(".",F11)-1) -> zcl_js_demo_read_odata_new | D11: {=INDEX('Not Req'!$E$4:$E$71,MATCH(MID(F11,FIND(".",F11)+1,LEN(F11)-FIND(".",F11)+1),'Not Req'!$D$4:$D$71,0))} -> Classes | E11: =INDEX('Not Req'!$F$4:$F$71,MATCH(MID(F11,FIND(".",F11)+1,LEN(F11)-FIND(".",F11)+1),'Not Req'!$D$4:$D$71,0)) -> 7. Source Code Library | F11: zcl_js_demo_read_odata_new.clas.abap | G11: Updated 16-Mar-26 | H11: 2 months ago | N11: zjs_demo_rap_onprem_func
B12: OK | C12: =LEFT(F12,FIND(".",F12)-1) -> zjs_demo_rap_onprem_func | D12: {=INDEX('Not Req'!$E$4:$E$71,MATCH(MID(F12,FIND(".",F12)+1,LEN(F12)-FIND(".",F12)+1),'Not Req'!$D$4:$D$71,0))} -> Classes | E12: =INDEX('Not Req'!$F$4:$F$71,MATCH(MID(F12,FIND(".",F12)+1,LEN(F12)-FIND(".",F12)+1),'Not Req'!$D$4:$D$71,0)) -> 7. Source Code Library | F12: zjs_demo_rap_onprem_func.clas.abap | G12: Updated 16-Mar-26 | H12: 2 months ago | N12: package
B13: OK | C13: =LEFT(F13,FIND(".",F13)-1) -> package | D13: {=INDEX('Not Req'!$E$4:$E$71,MATCH(MID(F13,FIND(".",F13)+1,LEN(F13)-FIND(".",F13)+1),'Not Req'!$D$4:$D$71,0))} -> Description : Package | E13: =INDEX('Not Req'!$F$4:$F$71,MATCH(MID(F13,FIND(".",F13)+1,LEN(F13)-FIND(".",F13)+1),'Not Req'!$D$4:$D$71,0)) -> 99. Descriptions | F13: package.devc.xml | G13: UPDATED ON 02-FEB-26 | H13: 3 months ago
C14: =LEFT(F14,FIND(".",F14)-1) -> zcl_js_demo_odata_actions | D14: {=INDEX('Not Req'!$E$4:$E$71,MATCH(MID(F14,FIND(".",F14)+1,LEN(F14)-FIND(".",F14)+1),'Not Req'!$D$4:$D$71,0))} -> Description : Classes | E14: =INDEX('Not Req'!$F$4:$F$71,MATCH(MID(F14,FIND(".",F14)+1,LEN(F14)-FIND(".",F14)+1),'Not Req'!$D$4:$D$71,0)) -> 99. Descriptions | F14: zcl_js_demo_odata_actions.clas.xml | G14: UPDATED ON 02-FEB-26 | H14: 3 months ago
C15: =LEFT(F15,FIND(".",F15)-1) -> zcl_js_demo_rap_onprem_newv2 | D15: {=INDEX('Not Req'!$E$4:$E$71,MATCH(MID(F15,FIND(".",F15)+1,LEN(F15)-FIND(".",F15)+1),'Not Req'!$D$4:$D$71,0))} -> Description : Classes | E15: =INDEX('Not Req'!$F$4:$F$71,MATCH(MID(F15,FIND(".",F15)+1,LEN(F15)-FIND(".",F15)+1),'Not Req'!$D$4:$D$71,0)) -> 99. Descriptions | F15: zcl_js_demo_rap_onprem_newv2.clas.xml | G15: UPDATED ON 02-FEB-26 | H15: 3 months ago
C16: =LEFT(F16,FIND(".",F16)-1) -> zcl_js_demo_read_func | D16: {=INDEX('Not Req'!$E$4:$E$71,MATCH(MID(F16,FIND(".",F16)+1,LEN(F16)-FIND(".",F16)+1),'Not Req'!$D$4:$D$71,0))} -> Description : Classes | E16: =INDEX('Not Req'!$F$4:$F$71,MATCH(MID(F16,FIND(".",F16)+1,LEN(F16)-FIND(".",F16)+1),'Not Req'!$D$4:$D$71,0)) -> 99. Descriptions | F16: zcl_js_demo_read_func.clas.xml | G16: UPDATED ON 02-FEB-26 | H16: 3 months ago
C17: =LEFT(F17,FIND(".",F17)-1) -> zcl_js_demo_read_odata | D17: {=INDEX('Not Req'!$E$4:$E$71,MATCH(MID(F17,FIND(".",F17)+1,LEN(F17)-FIND(".",F17)+1),'Not Req'!$D$4:$D$71,0))} -> Description : Classes | E17: =INDEX('Not Req'!$F$4:$F$71,MATCH(MID(F17,FIND(".",F17)+1,LEN(F17)-FIND(".",F17)+1),'Not Req'!$D$4:$D$71,0)) -> 99. Descriptions | F17: zcl_js_demo_read_odata.clas.xml | G17: UPDATED ON 02-FEB-26 | H17: 3 months ago
C18: =LEFT(F18,FIND(".",F18)-1) -> zcl_js_demo_read_odata_new | D18: {=INDEX('Not Req'!$E$4:$E$71,MATCH(MID(F18,FIND(".",F18)+1,LEN(F18)-FIND(".",F18)+1),'Not Req'!$D$4:$D$71,0))} -> Description : Classes | E18: =INDEX('Not Req'!$F$4:$F$71,MATCH(MID(F18,FIND(".",F18)+1,LEN(F18)-FIND(".",F18)+1),'Not Req'!$D$4:$D$71,0)) -> 99. Descriptions | F18: zcl_js_demo_read_odata_new.clas.xml | G18: UPDATED ON 02-FEB-26 | H18: 3 months ago
C19: =LEFT(F19,FIND(".",F19)-1) -> zjs_demo_rap_onprem_func | D19: {=INDEX('Not Req'!$E$4:$E$71,MATCH(MID(F19,FIND(".",F19)+1,LEN(F19)-FIND(".",F19)+1),'Not Req'!$D$4:$D$71,0))} -> Description : Classes | E19: =INDEX('Not Req'!$F$4:$F$71,MATCH(MID(F19,FIND(".",F19)+1,LEN(F19)-FIND(".",F19)+1),'Not Req'!$D$4:$D$71,0)) -> 99. Descriptions | F19: zjs_demo_rap_onprem_func.clas.xml | G19: UPDATED ON 02-FEB-26 | H19: 3 months ago
C20: =LEFT(F20,FIND(".",F20)-1) -> zjs_demo_rap_onpremise_odata | D20: {=INDEX('Not Req'!$E$4:$E$71,MATCH(MID(F20,FIND(".",F20)+1,LEN(F20)-FIND(".",F20)+1),'Not Req'!$D$4:$D$71,0))} -> Description : Service Definition | E20: =INDEX('Not Req'!$F$4:$F$71,MATCH(MID(F20,FIND(".",F20)+1,LEN(F20)-FIND(".",F20)+1),'Not Req'!$D$4:$D$71,0)) -> 99. Descriptions | F20: zjs_demo_rap_onpremise_odata.srvd.xml | G20: UPDATED ON 02-FEB-26 | H20: 3 months ago
C21: =LEFT(F21,FIND(".",F21)-1) -> zjs_rap_companynames | D21: {=INDEX('Not Req'!$E$4:$E$71,MATCH(MID(F21,FIND(".",F21)+1,LEN(F21)-FIND(".",F21)+1),'Not Req'!$D$4:$D$71,0))} -> Description : BDEF | E21: =INDEX('Not Req'!$F$4:$F$71,MATCH(MID(F21,FIND(".",F21)+1,LEN(F21)-FIND(".",F21)+1),'Not Req'!$D$4:$D$71,0)) -> 99. Descriptions | F21: zjs_rap_companynames.bdef.xml | G21: UPDATED ON 02-FEB-26 | H21: 3 months ago
C22: =LEFT(F22,FIND(".",F22)-1) -> zjs_rap_companynames | D22: {=INDEX('Not Req'!$E$4:$E$71,MATCH(MID(F22,FIND(".",F22)+1,LEN(F22)-FIND(".",F22)+1),'Not Req'!$D$4:$D$71,0))} -> Description : Data Definition | E22: =INDEX('Not Req'!$F$4:$F$71,MATCH(MID(F22,FIND(".",F22)+1,LEN(F22)-FIND(".",F22)+1),'Not Req'!$D$4:$D$71,0)) -> 99. Descriptions | F22: zjs_rap_companynames.ddls.xml | G22: UPDATED ON 02-FEB-26 | H22: 3 months ago
C23: =LEFT(F23,FIND(".",F23)-1) -> zjs_demo_comm_scenario | D23: {=INDEX('Not Req'!$E$4:$E$71,MATCH(MID(F23,FIND(".",F23)+1,LEN(F23)-FIND(".",F23)+1),'Not Req'!$D$4:$D$71,0))} -> Internal (Not Req) | E23: =INDEX('Not Req'!$F$4:$F$71,MATCH(MID(F23,FIND(".",F23)+1,LEN(F23)-FIND(".",F23)+1),'Not Req'!$D$4:$D$71,0)) -> Internal (Not Req) | F23: zjs_demo_comm_scenario.sco1.xml | G23: UPDATED ON 02-FEB-26 | H23: 3 months ago
C24: =LEFT(F24,FIND(".",F24)-1) -> zjs_rap_companynames | D24: {=INDEX('Not Req'!$E$4:$E$71,MATCH(MID(F24,FIND(".",F24)+1,LEN(F24)-FIND(".",F24)+1),'Not Req'!$D$4:$D$71,0))} -> BaseInfo : Data Definition | E24: =INDEX('Not Req'!$F$4:$F$71,MATCH(MID(F24,FIND(".",F24)+1,LEN(F24)-FIND(".",F24)+1),'Not Req'!$D$4:$D$71,0)) -> 98. Base Info | F24: zjs_rap_companynames.ddls.baseinfo | G24: UPDATED ON 02-FEB-26 | H24: 3 months ago
C25: =LEFT(F25,FIND(".",F25)-1) -> zjs_demo_outbound_service_rest | D25: {=INDEX('Not Req'!$E$4:$E$71,MATCH(MID(F25,FIND(".",F25)+1,LEN(F25)-FIND(".",F25)+1),'Not Req'!$D$4:$D$71,0))} -> #N/A | E25: =INDEX('Not Req'!$F$4:$F$71,MATCH(MID(F25,FIND(".",F25)+1,LEN(F25)-FIND(".",F25)+1),'Not Req'!$D$4:$D$71,0)) -> #N/A | F25: zjs_demo_outbound_service_rest.sco3.xml | G25: UPDATED ON 02-FEB-26 | H25: 3 months ago

Sheet ZJS_02_RAP_CUSTOM
B2: d | C2: Object | D2: Type | E2: Category | F2: Github Object | G2: Github Type | H2: Version
B4: OK | C4: =LEFT(F4,FIND(".",F4)-1) -> package | D4: {=INDEX('Not Req'!$E$4:$E$71,MATCH(MID(F4,FIND(".",F4)+1,LEN(F4)-FIND(".",F4)+1),'Not Req'!$D$4:$D$71,0))} -> Description : Package | E4: =INDEX('Not Req'!$F$4:$F$71,MATCH(MID(F4,FIND(".",F4)+1,LEN(F4)-FIND(".",F4)+1),'Not Req'!$D$4:$D$71,0)) -> 99. Descriptions | F4: package.devc.xml | G4: UPDATED ON 02-FEB-26 | H4: 3 months ago | N4: {=_xlfn.UNIQUE(C4:C20)} -> package
B5: OK | C5: =LEFT(F5,FIND(".",F5)-1) -> 076ebec5b6ca959f9efc27d6a94963ht | D5: {=INDEX('Not Req'!$E$4:$E$71,MATCH(MID(F5,FIND(".",F5)+1,LEN(F5)-FIND(".",F5)+1),'Not Req'!$D$4:$D$71,0))} -> Authorization Defaults (TADIR) | E5: =INDEX('Not Req'!$F$4:$F$71,MATCH(MID(F5,FIND(".",F5)+1,LEN(F5)-FIND(".",F5)+1),'Not Req'!$D$4:$D$71,0)) -> 1. Authorizations | F5: 076ebec5b6ca959f9efc27d6a94963ht.sush.xml | G5: UPDATED ON 02-FEB-26 | H5: 3 months ago | N5: 076ebec5b6ca959f9efc27d6a94963ht
B6: OK | C6: =LEFT(F6,FIND(".",F6)-1) -> e8c25cf413b1a9572b79acd78e1f6dht | D6: {=INDEX('Not Req'!$E$4:$E$71,MATCH(MID(F6,FIND(".",F6)+1,LEN(F6)-FIND(".",F6)+1),'Not Req'!$D$4:$D$71,0))} -> Authorization Defaults (TADIR) | E6: =INDEX('Not Req'!$F$4:$F$71,MATCH(MID(F6,FIND(".",F6)+1,LEN(F6)-FIND(".",F6)+1),'Not Req'!$D$4:$D$71,0)) -> 1. Authorizations | F6: e8c25cf413b1a9572b79acd78e1f6dht.sush.xml | G6: UPDATED ON 02-FEB-26 | H6: 3 months ago | N6: e8c25cf413b1a9572b79acd78e1f6dht
B7: OK | C7: =LEFT(F7,FIND(".",F7)-1) -> zjs_demo_company_names | D7: {=INDEX('Not Req'!$E$4:$E$71,MATCH(MID(F7,FIND(".",F7)+1,LEN(F7)-FIND(".",F7)+1),'Not Req'!$D$4:$D$71,0))} -> Service Definition | E7: =INDEX('Not Req'!$F$4:$F$71,MATCH(MID(F7,FIND(".",F7)+1,LEN(F7)-FIND(".",F7)+1),'Not Req'!$D$4:$D$71,0)) -> 2. Business Services | F7: zjs_demo_company_names.srvd.srvdsrv | G7: UPDATED ON 02-FEB-26 | H7: 3 months ago | N7: zjs_demo_company_names
B8: OK | C8: =LEFT(F8,FIND(".",F8)-1) -> zjs_ui_demo_com_names_o2 | D8: {=INDEX('Not Req'!$E$4:$E$71,MATCH(MID(F8,FIND(".",F8)+1,LEN(F8)-FIND(".",F8)+1),'Not Req'!$D$4:$D$71,0))} -> Service Binding | E8: =INDEX('Not Req'!$F$4:$F$71,MATCH(MID(F8,FIND(".",F8)+1,LEN(F8)-FIND(".",F8)+1),'Not Req'!$D$4:$D$71,0)) -> 2. Business Services | F8: zjs_ui_demo_com_names_o2.srvb.xml | G8: UPDATED ON 02-FEB-26 | H8: 3 months ago | N8: zjs_ui_demo_com_names_o2
B9: OK | C9: =LEFT(F9,FIND(".",F9)-1) -> zjs_ui_demo_com_names_o2_iwsg | D9: {=INDEX('Not Req'!$E$4:$E$71,MATCH(MID(F9,FIND(".",F9)+1,LEN(F9)-FIND(".",F9)+1),'Not Req'!$D$4:$D$71,0))} -> Inbound Service | E9: =INDEX('Not Req'!$F$4:$F$71,MATCH(MID(F9,FIND(".",F9)+1,LEN(F9)-FIND(".",F9)+1),'Not Req'!$D$4:$D$71,0)) -> 3. Cloud Communication Management | F9: zjs_ui_demo_com_names_o2_iwsg.sco2.xml | G9: UPDATED ON 02-FEB-26 | H9: 3 months ago | N9: zjs_ui_demo_com_names_o2_iwsg
B10: OK | C10: =LEFT(F10,FIND(".",F10)-1) -> zjs_r_rapcustomcompanynames | D10: {=INDEX('Not Req'!$E$4:$E$71,MATCH(MID(F10,FIND(".",F10)+1,LEN(F10)-FIND(".",F10)+1),'Not Req'!$D$4:$D$71,0))} -> BDEF | E10: =INDEX('Not Req'!$F$4:$F$71,MATCH(MID(F10,FIND(".",F10)+1,LEN(F10)-FIND(".",F10)+1),'Not Req'!$D$4:$D$71,0)) -> 4. CDS | F10: zjs_r_rapcustomcompanynames.bdef.asbdef | G10: UPDATED ON 02-FEB-26 | H10: 3 months ago | N10: zjs_r_rapcustomcompanynames
B11: OK | C11: =LEFT(F11,FIND(".",F11)-1) -> zjs_r_rapcustomcompanynames | D11: {=INDEX('Not Req'!$E$4:$E$71,MATCH(MID(F11,FIND(".",F11)+1,LEN(F11)-FIND(".",F11)+1),'Not Req'!$D$4:$D$71,0))} -> Data Definition | E11: =INDEX('Not Req'!$F$4:$F$71,MATCH(MID(F11,FIND(".",F11)+1,LEN(F11)-FIND(".",F11)+1),'Not Req'!$D$4:$D$71,0)) -> 4. CDS | F11: zjs_r_rapcustomcompanynames.ddls.asddls | G11: UPDATED ON 02-FEB-26 | H11: 3 months ago | N11: zbp_js_demo_company_names
B12: OK | C12: =LEFT(F12,FIND(".",F12)-1) -> zbp_js_demo_company_names | D12: {=INDEX('Not Req'!$E$4:$E$71,MATCH(MID(F12,FIND(".",F12)+1,LEN(F12)-FIND(".",F12)+1),'Not Req'!$D$4:$D$71,0))} -> Classes | E12: =INDEX('Not Req'!$F$4:$F$71,MATCH(MID(F12,FIND(".",F12)+1,LEN(F12)-FIND(".",F12)+1),'Not Req'!$D$4:$D$71,0)) -> 7. Source Code Library | F12: zbp_js_demo_company_names.clas.abap | G12: Updated 16-Mar-26 | H12: 2 months ago | N12: zcl_js_demo_custom_company_qry
B13: OK | C13: =LEFT(F13,FIND(".",F13)-1) -> zbp_js_demo_company_names | D13: {=INDEX('Not Req'!$E$4:$E$71,MATCH(MID(F13,FIND(".",F13)+1,LEN(F13)-FIND(".",F13)+1),'Not Req'!$D$4:$D$71,0))} -> Classes Local | E13: =INDEX('Not Req'!$F$4:$F$71,MATCH(MID(F13,FIND(".",F13)+1,LEN(F13)-FIND(".",F13)+1),'Not Req'!$D$4:$D$71,0)) -> 7. Source Code Library | F13: zbp_js_demo_company_names.clas.locals_imp.abap | G13: UPDATED ON 02-FEB-26 | H13: 3 months ago
B14: OK | C14: =LEFT(F14,FIND(".",F14)-1) -> zcl_js_demo_custom_company_qry | D14: {=INDEX('Not Req'!$E$4:$E$71,MATCH(MID(F14,FIND(".",F14)+1,LEN(F14)-FIND(".",F14)+1),'Not Req'!$D$4:$D$71,0))} -> Classes | E14: =INDEX('Not Req'!$F$4:$F$71,MATCH(MID(F14,FIND(".",F14)+1,LEN(F14)-FIND(".",F14)+1),'Not Req'!$D$4:$D$71,0)) -> 7. Source Code Library | F14: zcl_js_demo_custom_company_qry.clas.abap | G14: Updated 16-Mar-26 | H14: 2 months ago
C15: =LEFT(F15,FIND(".",F15)-1) -> zbp_js_demo_company_names | D15: {=INDEX('Not Req'!$E$4:$E$71,MATCH(MID(F15,FIND(".",F15)+1,LEN(F15)-FIND(".",F15)+1),'Not Req'!$D$4:$D$71,0))} -> Description : Classes | E15: =INDEX('Not Req'!$F$4:$F$71,MATCH(MID(F15,FIND(".",F15)+1,LEN(F15)-FIND(".",F15)+1),'Not Req'!$D$4:$D$71,0)) -> 99. Descriptions | F15: zbp_js_demo_company_names.clas.xml | G15: UPDATED ON 02-FEB-26 | H15: 3 months ago
C16: =LEFT(F16,FIND(".",F16)-1) -> zcl_js_demo_custom_company_qry | D16: {=INDEX('Not Req'!$E$4:$E$71,MATCH(MID(F16,FIND(".",F16)+1,LEN(F16)-FIND(".",F16)+1),'Not Req'!$D$4:$D$71,0))} -> Description : Classes | E16: =INDEX('Not Req'!$F$4:$F$71,MATCH(MID(F16,FIND(".",F16)+1,LEN(F16)-FIND(".",F16)+1),'Not Req'!$D$4:$D$71,0)) -> 99. Descriptions | F16: zcl_js_demo_custom_company_qry.clas.xml | G16: UPDATED ON 02-FEB-26 | H16: 3 months ago
C17: =LEFT(F17,FIND(".",F17)-1) -> zjs_demo_company_names | D17: {=INDEX('Not Req'!$E$4:$E$71,MATCH(MID(F17,FIND(".",F17)+1,LEN(F17)-FIND(".",F17)+1),'Not Req'!$D$4:$D$71,0))} -> Description : Service Definition | E17: =INDEX('Not Req'!$F$4:$F$71,MATCH(MID(F17,FIND(".",F17)+1,LEN(F17)-FIND(".",F17)+1),'Not Req'!$D$4:$D$71,0)) -> 99. Descriptions | F17: zjs_demo_company_names.srvd.xml | G17: UPDATED ON 02-FEB-26 | H17: 3 months ago
C18: =LEFT(F18,FIND(".",F18)-1) -> zjs_r_rapcustomcompanynames | D18: {=INDEX('Not Req'!$E$4:$E$71,MATCH(MID(F18,FIND(".",F18)+1,LEN(F18)-FIND(".",F18)+1),'Not Req'!$D$4:$D$71,0))} -> Description : BDEF | E18: =INDEX('Not Req'!$F$4:$F$71,MATCH(MID(F18,FIND(".",F18)+1,LEN(F18)-FIND(".",F18)+1),'Not Req'!$D$4:$D$71,0)) -> 99. Descriptions | F18: zjs_r_rapcustomcompanynames.bdef.xml | G18: UPDATED ON 02-FEB-26 | H18: 3 months ago
C19: =LEFT(F19,FIND(".",F19)-1) -> zjs_r_rapcustomcompanynames | D19: {=INDEX('Not Req'!$E$4:$E$71,MATCH(MID(F19,FIND(".",F19)+1,LEN(F19)-FIND(".",F19)+1),'Not Req'!$D$4:$D$71,0))} -> BaseInfo : Data Definition | E19: =INDEX('Not Req'!$F$4:$F$71,MATCH(MID(F19,FIND(".",F19)+1,LEN(F19)-FIND(".",F19)+1),'Not Req'!$D$4:$D$71,0)) -> 98. Base Info | F19: zjs_r_rapcustomcompanynames.ddls.baseinfo | G19: UPDATED ON 02-FEB-26 | H19: 3 months ago
C20: =LEFT(F20,FIND(".",F20)-1) -> zjs_r_rapcustomcompanynames | D20: {=INDEX('Not Req'!$E$4:$E$71,MATCH(MID(F20,FIND(".",F20)+1,LEN(F20)-FIND(".",F20)+1),'Not Req'!$D$4:$D$71,0))} -> Description : Data Definition | E20: =INDEX('Not Req'!$F$4:$F$71,MATCH(MID(F20,FIND(".",F20)+1,LEN(F20)-FIND(".",F20)+1),'Not Req'!$D$4:$D$71,0)) -> 99. Descriptions | F20: zjs_r_rapcustomcompanynames.ddls.xml | G20: UPDATED ON 02-FEB-26 | H20: 3 months ago

Sheet ZJS_02_RAP_UNMANAGED
B2: d | C2: Object | D2: Type | E2: Category | F2: Github Object | G2: Github Type | H2: Version
B4: OK | C4: =LEFT(F4,FIND(".",F4)-1) -> package | D4: {=INDEX('Not Req'!$E$4:$E$71,MATCH(MID(F4,FIND(".",F4)+1,LEN(F4)-FIND(".",F4)+1),'Not Req'!$D$4:$D$71,0))} -> Description : Package | E4: =INDEX('Not Req'!$F$4:$F$71,MATCH(MID(F4,FIND(".",F4)+1,LEN(F4)-FIND(".",F4)+1),'Not Req'!$D$4:$D$71,0)) -> 99. Descriptions | F4: package.devc.xml | G4: UPDATED ON 02-FEB-26 | H4: 3 months ago | N4: {=_xlfn.UNIQUE(C4:C21)} -> package
B5: OK | C5: =LEFT(F5,FIND(".",F5)-1) -> 12f0684f025461cdd56fff01ae2095ht | D5: {=INDEX('Not Req'!$E$4:$E$71,MATCH(MID(F5,FIND(".",F5)+1,LEN(F5)-FIND(".",F5)+1),'Not Req'!$D$4:$D$71,0))} -> Authorization Defaults (TADIR) | E5: =INDEX('Not Req'!$F$4:$F$71,MATCH(MID(F5,FIND(".",F5)+1,LEN(F5)-FIND(".",F5)+1),'Not Req'!$D$4:$D$71,0)) -> 1. Authorizations | F5: 12f0684f025461cdd56fff01ae2095ht.sush.xml | G5: UPDATED ON 02-FEB-26 | H5: 3 months ago | N5: 12f0684f025461cdd56fff01ae2095ht
B6: OK | C6: =LEFT(F6,FIND(".",F6)-1) -> 7f22578e4e946e5a39d404fa38fdecht | D6: {=INDEX('Not Req'!$E$4:$E$71,MATCH(MID(F6,FIND(".",F6)+1,LEN(F6)-FIND(".",F6)+1),'Not Req'!$D$4:$D$71,0))} -> Authorization Defaults (TADIR) | E6: =INDEX('Not Req'!$F$4:$F$71,MATCH(MID(F6,FIND(".",F6)+1,LEN(F6)-FIND(".",F6)+1),'Not Req'!$D$4:$D$71,0)) -> 1. Authorizations | F6: 7f22578e4e946e5a39d404fa38fdecht.sush.xml | G6: UPDATED ON 02-FEB-26 | H6: 3 months ago | N6: 7f22578e4e946e5a39d404fa38fdecht
B7: OK | C7: =LEFT(F7,FIND(".",F7)-1) -> zjs_demo_unmanaged | D7: {=INDEX('Not Req'!$E$4:$E$71,MATCH(MID(F7,FIND(".",F7)+1,LEN(F7)-FIND(".",F7)+1),'Not Req'!$D$4:$D$71,0))} -> Service Definition | E7: =INDEX('Not Req'!$F$4:$F$71,MATCH(MID(F7,FIND(".",F7)+1,LEN(F7)-FIND(".",F7)+1),'Not Req'!$D$4:$D$71,0)) -> 2. Business Services | F7: zjs_demo_unmanaged.srvd.srvdsrv | G7: UPDATED ON 02-FEB-26 | H7: 3 months ago | N7: zjs_demo_unmanaged
B8: OK | C8: =LEFT(F8,FIND(".",F8)-1) -> zjs_ui_demo_unmanaged_o2 | D8: {=INDEX('Not Req'!$E$4:$E$71,MATCH(MID(F8,FIND(".",F8)+1,LEN(F8)-FIND(".",F8)+1),'Not Req'!$D$4:$D$71,0))} -> Service Binding | E8: =INDEX('Not Req'!$F$4:$F$71,MATCH(MID(F8,FIND(".",F8)+1,LEN(F8)-FIND(".",F8)+1),'Not Req'!$D$4:$D$71,0)) -> 2. Business Services | F8: zjs_ui_demo_unmanaged_o2.srvb.xml | G8: UPDATED ON 02-FEB-26 | H8: 3 months ago | N8: zjs_ui_demo_unmanaged_o2
B9: OK | C9: =LEFT(F9,FIND(".",F9)-1) -> zjs_ui_demo_unmanaged_o2_iwsg | D9: {=INDEX('Not Req'!$E$4:$E$71,MATCH(MID(F9,FIND(".",F9)+1,LEN(F9)-FIND(".",F9)+1),'Not Req'!$D$4:$D$71,0))} -> Inbound Service | E9: =INDEX('Not Req'!$F$4:$F$71,MATCH(MID(F9,FIND(".",F9)+1,LEN(F9)-FIND(".",F9)+1),'Not Req'!$D$4:$D$71,0)) -> 3. Cloud Communication Management | F9: zjs_ui_demo_unmanaged_o2_iwsg.sco2.xml | G9: UPDATED ON 02-FEB-26 | H9: 3 months ago | N9: zjs_ui_demo_unmanaged_o2_iwsg
B10: OK | C10: =LEFT(F10,FIND(".",F10)-1) -> zjs_c_dmounmanaged | D10: {=INDEX('Not Req'!$E$4:$E$71,MATCH(MID(F10,FIND(".",F10)+1,LEN(F10)-FIND(".",F10)+1),'Not Req'!$D$4:$D$71,0))} -> BDEF | E10: =INDEX('Not Req'!$F$4:$F$71,MATCH(MID(F10,FIND(".",F10)+1,LEN(F10)-FIND(".",F10)+1),'Not Req'!$D$4:$D$71,0)) -> 4. CDS | F10: zjs_c_dmounmanaged.bdef.asbdef | G10: UPDATED ON 02-FEB-26 | H10: 3 months ago | N10: zjs_c_dmounmanaged
B11: OK | C11: =LEFT(F11,FIND(".",F11)-1) -> zjs_c_dmounmanaged | D11: {=INDEX('Not Req'!$E$4:$E$71,MATCH(MID(F11,FIND(".",F11)+1,LEN(F11)-FIND(".",F11)+1),'Not Req'!$D$4:$D$71,0))} -> Data Definition | E11: =INDEX('Not Req'!$F$4:$F$71,MATCH(MID(F11,FIND(".",F11)+1,LEN(F11)-FIND(".",F11)+1),'Not Req'!$D$4:$D$71,0)) -> 4. CDS | F11: zjs_c_dmounmanaged.ddls.asddls | G11: UPDATED ON 02-FEB-26 | H11: 3 months ago | N11: zjs_r_dmounmanaged
B12: OK | C12: =LEFT(F12,FIND(".",F12)-1) -> zjs_r_dmounmanaged | D12: {=INDEX('Not Req'!$E$4:$E$71,MATCH(MID(F12,FIND(".",F12)+1,LEN(F12)-FIND(".",F12)+1),'Not Req'!$D$4:$D$71,0))} -> BDEF | E12: =INDEX('Not Req'!$F$4:$F$71,MATCH(MID(F12,FIND(".",F12)+1,LEN(F12)-FIND(".",F12)+1),'Not Req'!$D$4:$D$71,0)) -> 4. CDS | F12: zjs_r_dmounmanaged.bdef.asbdef | G12: UPDATED ON 02-FEB-26 | H12: 3 months ago | N12: zjs_dmo_un_data
B13: OK | C13: =LEFT(F13,FIND(".",F13)-1) -> zjs_r_dmounmanaged | D13: {=INDEX('Not Req'!$E$4:$E$71,MATCH(MID(F13,FIND(".",F13)+1,LEN(F13)-FIND(".",F13)+1),'Not Req'!$D$4:$D$71,0))} -> Data Definition | E13: =INDEX('Not Req'!$F$4:$F$71,MATCH(MID(F13,FIND(".",F13)+1,LEN(F13)-FIND(".",F13)+1),'Not Req'!$D$4:$D$71,0)) -> 4. CDS | F13: zjs_r_dmounmanaged.ddls.asddls | G13: UPDATED ON 02-FEB-26 | H13: 3 months ago | N13: zjs_dmo_unmgnd
B14: OK | C14: =LEFT(F14,FIND(".",F14)-1) -> zjs_dmo_un_data | D14: {=INDEX('Not Req'!$E$4:$E$71,MATCH(MID(F14,FIND(".",F14)+1,LEN(F14)-FIND(".",F14)+1),'Not Req'!$D$4:$D$71,0))} -> Table | E14: =INDEX('Not Req'!$F$4:$F$71,MATCH(MID(F14,FIND(".",F14)+1,LEN(F14)-FIND(".",F14)+1),'Not Req'!$D$4:$D$71,0)) -> 5. Dictionary | F14: zjs_dmo_un_data.tabl.xml | G14: UPDATED ON 02-FEB-26 | H14: 3 months ago | N14: zbp_js_demo_unmanaged
B15: OK | C15: =LEFT(F15,FIND(".",F15)-1) -> zjs_dmo_unmgnd | D15: {=INDEX('Not Req'!$E$4:$E$71,MATCH(MID(F15,FIND(".",F15)+1,LEN(F15)-FIND(".",F15)+1),'Not Req'!$D$4:$D$71,0))} -> Table | E15: =INDEX('Not Req'!$F$4:$F$71,MATCH(MID(F15,FIND(".",F15)+1,LEN(F15)-FIND(".",F15)+1),'Not Req'!$D$4:$D$71,0)) -> 5. Dictionary | F15: zjs_dmo_unmgnd.tabl.xml | G15: UPDATED ON 02-FEB-26 | H15: 3 months ago | N15: zcl_js_demo_rap_data_handler
B16: OK | C16: =LEFT(F16,FIND(".",F16)-1) -> zbp_js_demo_unmanaged | D16: {=INDEX('Not Req'!$E$4:$E$71,MATCH(MID(F16,FIND(".",F16)+1,LEN(F16)-FIND(".",F16)+1),'Not Req'!$D$4:$D$71,0))} -> Classes | E16: =INDEX('Not Req'!$F$4:$F$71,MATCH(MID(F16,FIND(".",F16)+1,LEN(F16)-FIND(".",F16)+1),'Not Req'!$D$4:$D$71,0)) -> 7. Source Code Library | F16: zbp_js_demo_unmanaged.clas.abap | G16: Updated 16-Mar-26 | H16: 2 months ago | N16: zcl_js_demo_unmanaged_data
... B18: OK | C18: =LEFT(F18,FIND(".",F18)-1) -> zcl_js_demo_rap_data_handler | D18: {=INDEX('Not Req'!$E$4:$E$71,MATCH(MID(F18,FIND(".",F18)+1,LEN(F18)-FIND(".",F18)+1),'Not Req'!$D$4:$D$71,0))} -> Classes | E18: =INDEX('Not Req'!$F$4:$F$71,MATCH(MID(F18,FIND(".",F18)+1,LEN(F18)-FIND(".",F18)+1),'Not Req'!$D$4:$D$71,0)) -> 7. Source Code Library | F18: zcl_js_demo_rap_data_handler.clas.abap | G18: Updated 16-Mar-26 | H18: 2 months ago | N18: zif_js_demo_rap_data_handler
B19: OK | C19: =LEFT(F19,FIND(".",F19)-1) -> zcl_js_demo_unmanaged_data | D19: {=INDEX('Not Req'!$E$4:$E$71,MATCH(MID(F19,FIND(".",F19)+1,LEN(F19)-FIND(".",F19)+1),'Not Req'!$D$4:$D$71,0))} -> Classes | E19: =INDEX('Not Req'!$F$4:$F$71,MATCH(MID(F19,FIND(".",F19)+1,LEN(F19)-FIND(".",F19)+1),'Not Req'!$D$4:$D$71,0)) -> 7. Source Code Library | F19: zcl_js_demo_unmanaged_data.clas.abap | G19: UPDATED ON 02-FEB-26 | H19: 3 months ago
B20: OK | C20: =LEFT(F20,FIND(".",F20)-1) -> zcl_js_demo_unmanaged_query | D20: {=INDEX('Not Req'!$E$4:$E$71,MATCH(MID(F20,FIND(".",F20)+1,LEN(F20)-FIND(".",F20)+1),'Not Req'!$D$4:$D$71,0))} -> Classes | E20: =INDEX('Not Req'!$F$4:$F$71,MATCH(MID(F20,FIND(".",F20)+1,LEN(F20)-FIND(".",F20)+1),'Not Req'!$D$4:$D$71,0)) -> 7. Source Code Library | F20: zcl_js_demo_unmanaged_query.clas.abap | G20: UPDATED ON 02-FEB-26 | H20: 3 months ago
B21: OK | C21: =LEFT(F21,FIND(".",F21)-1) -> zif_js_demo_rap_data_handler | D21: {=INDEX('Not Req'!$E$4:$E$71,MATCH(MID(F21,FIND(".",F21)+1,LEN(F21)-FIND(".",F21)+1),'Not Req'!$D$4:$D$71,0))} -> Interface | E21: =INDEX('Not Req'!$F$4:$F$71,MATCH(MID(F21,FIND(".",F21)+1,LEN(F21)-FIND(".",F21)+1),'Not Req'!$D$4:$D$71,0)) -> 7. Source Code Library | F21: zif_js_demo_rap_data_handler.intf.abap | G21: UPDATED ON 02-FEB-26 | H21: 3 months ago
C22: =LEFT(F22,FIND(".",F22)-1) -> zbp_js_demo_unmanaged | D22: {=INDEX('Not Req'!$E$4:$E$71,MATCH(MID(F22,FIND(".",F22)+1,LEN(F22)-FIND(".",F22)+1),'Not Req'!$D$4:$D$71,0))} -> Description : Classes | E22: =INDEX('Not Req'!$F$4:$F$71,MATCH(MID(F22,FIND(".",F22)+1,LEN(F22)-FIND(".",F22)+1),'Not Req'!$D$4:$D$71,0)) -> 99. Descriptions | F22: zbp_js_demo_unmanaged.clas.xml | G22: UPDATED ON 02-FEB-26 | H22: 3 months ago
C23: =LEFT(F23,FIND(".",F23)-1) -> zcl_js_demo_rap_data_handler | D23: {=INDEX('Not Req'!$E$4:$E$71,MATCH(MID(F23,FIND(".",F23)+1,LEN(F23)-FIND(".",F23)+1),'Not Req'!$D$4:$D$71,0))} -> Description : Classes | E23: =INDEX('Not Req'!$F$4:$F$71,MATCH(MID(F23,FIND(".",F23)+1,LEN(F23)-FIND(".",F23)+1),'Not Req'!$D$4:$D$71,0)) -> 99. Descriptions | F23: zcl_js_demo_rap_data_handler.clas.xml | G23: UPDATED ON 02-FEB-26 | H23: 3 months ago
C24: =LEFT(F24,FIND(".",F24)-1) -> zcl_js_demo_unmanaged_data | D24: {=INDEX('Not Req'!$E$4:$E$71,MATCH(MID(F24,FIND(".",F24)+1,LEN(F24)-FIND(".",F24)+1),'Not Req'!$D$4:$D$71,0))} -> Description : Classes | E24: =INDEX('Not Req'!$F$4:$F$71,MATCH(MID(F24,FIND(".",F24)+1,LEN(F24)-FIND(".",F24)+1),'Not Req'!$D$4:$D$71,0)) -> 99. Descriptions | F24: zcl_js_demo_unmanaged_data.clas.xml | G24: UPDATED ON 02-FEB-26 | H24: 3 months ago
C25: =LEFT(F25,FIND(".",F25)-1) -> zcl_js_demo_unmanaged_query | D25: {=INDEX('Not Req'!$E$4:$E$71,MATCH(MID(F25,FIND(".",F25)+1,LEN(F25)-FIND(".",F25)+1),'Not Req'!$D$4:$D$71,0))} -> Description : Classes | E25: =INDEX('Not Req'!$F$4:$F$71,MATCH(MID(F25,FIND(".",F25)+1,LEN(F25)-FIND(".",F25)+1),'Not Req'!$D$4:$D$71,0)) -> 99. Descriptions | F25: zcl_js_demo_unmanaged_query.clas.xml | G25: UPDATED ON 02-FEB-26 | H25: 3 months ago
C26: =LEFT(F26,FIND(".",F26)-1) -> zif_js_demo_rap_data_handler | D26: {=INDEX('Not Req'!$E$4:$E$71,MATCH(MID(F26,FIND(".",F26)+1,LEN(F26)-FIND(".",F26)+1),'Not Req'!$D$4:$D$71,0))} -> Description : Interface | E26: =INDEX('Not Req'!$F$4:$F$71,MATCH(MID(F26,FIND(".",F26)+1,LEN(F26)-FIND(".",F26)+1),'Not Req'!$D$4:$D$71,0)) -> Internal (Not Req) | F26: zif_js_demo_rap_data_handler.intf.xml | G26: UPDATED ON 02-FEB-26 | H26: 3 months ago
C27: =LEFT(F27,FIND(".",F27)-1) -> zjs_c_dmounmanaged | D27: {=INDEX('Not Req'!$E$4:$E$71,MATCH(MID(F27,FIND(".",F27)+1,LEN(F27)-FIND(".",F27)+1),'Not Req'!$D$4:$D$71,0))} -> Description : BDEF | E27: =INDEX('Not Req'!$F$4:$F$71,MATCH(MID(F27,FIND(".",F27)+1,LEN(F27)-FIND(".",F27)+1),'Not Req'!$D$4:$D$71,0)) -> 99. Descriptions | F27: zjs_c_dmounmanaged.bdef.xml | G27: UPDATED ON 02-FEB-26 | H27: 3 months ago
C28: =LEFT(F28,FIND(".",F28)-1) -> zjs_c_dmounmanaged | D28: {=INDEX('Not Req'!$E$4:$E$71,MATCH(MID(F28,FIND(".",F28)+1,LEN(F28)-FIND(".",F28)+1),'Not Req'!$D$4:$D$71,0))} -> BaseInfo : Data Definition | E28: =INDEX('Not Req'!$F$4:$F$71,MATCH(MID(F28,FIND(".",F28)+1,LEN(F28)-FIND(".",F28)+1),'Not Req'!$D$4:$D$71,0)) -> 98. Base Info | F28: zjs_c_dmounmanaged.ddls.baseinfo | G28: UPDATED ON 02-FEB-26 | H28: 3 months ago
C29: =LEFT(F29,FIND(".",F29)-1) -> zjs_c_dmounmanaged | D29: {=INDEX('Not Req'!$E$4:$E$71,MATCH(MID(F29,FIND(".",F29)+1,LEN(F29)-FIND(".",F29)+1),'Not Req'!$D$4:$D$71,0))} -> Description : Data Definition | E29: =INDEX('Not Req'!$F$4:$F$71,MATCH(MID(F29,FIND(".",F29)+1,LEN(F29)-FIND(".",F29)+1),'Not Req'!$D$4:$D$71,0)) -> 99. Descriptions | F29: zjs_c_dmounmanaged.ddls.xml | G29: UPDATED ON 02-FEB-26 | H29: 3 months ago
C30: =LEFT(F30,FIND(".",F30)-1) -> zjs_demo_unmanaged | D30: {=INDEX('Not Req'!$E$4:$E$71,MATCH(MID(F30,FIND(".",F30)+1,LEN(F30)-FIND(".",F30)+1),'Not Req'!$D$4:$D$71,0))} -> Description : Service Definition | E30: =INDEX('Not Req'!$F$4:$F$71,MATCH(MID(F30,FIND(".",F30)+1,LEN(F30)-FIND(".",F30)+1),'Not Req'!$D$4:$D$71,0)) -> 99. Descriptions | F30: zjs_demo_unmanaged.srvd.xml | G30: UPDATED ON 02-FEB-26 | H30: 3 months ago
C31: =LEFT(F31,FIND(".",F31)-1) -> zjs_r_dmounmanaged | D31: {=INDEX('Not Req'!$E$4:$E$71,MATCH(MID(F31,FIND(".",F31)+1,LEN(F31)-FIND(".",F31)+1),'Not Req'!$D$4:$D$71,0))} -> Description : BDEF | E31: =INDEX('Not Req'!$F$4:$F$71,MATCH(MID(F31,FIND(".",F31)+1,LEN(F31)-FIND(".",F31)+1),'Not Req'!$D$4:$D$71,0)) -> 99. Descriptions | F31: zjs_r_dmounmanaged.bdef.xml | G31: UPDATED ON 02-FEB-26 | H31: 3 months ago
C32: =LEFT(F32,FIND(".",F32)-1) -> zjs_r_dmounmanaged | D32: {=INDEX('Not Req'!$E$4:$E$71,MATCH(MID(F32,FIND(".",F32)+1,LEN(F32)-FIND(".",F32)+1),'Not Req'!$D$4:$D$71,0))} -> BaseInfo : Data Definition | E32: =INDEX('Not Req'!$F$4:$F$71,MATCH(MID(F32,FIND(".",F32)+1,LEN(F32)-FIND(".",F32)+1),'Not Req'!$D$4:$D$71,0)) -> 98. Base Info | F32: zjs_r_dmounmanaged.ddls.baseinfo | G32: UPDATED ON 02-FEB-26 | H32: 3 months ago
A33: D | C33: =LEFT(F33,FIND(".",F33)-1) -> zjs_r_dmounmanaged | D33: {=INDEX('Not Req'!$E$4:$E$71,MATCH(MID(F33,FIND(".",F33)+1,LEN(F33)-FIND(".",F33)+1),'Not Req'!$D$4:$D$71,0))} -> Description : Data Definition | E33: =INDEX('Not Req'!$F$4:$F$71,MATCH(MID(F33,FIND(".",F33)+1,LEN(F33)-FIND(".",F33)+1),'Not Req'!$D$4:$D$71,0)) -> 99. Descriptions | F33: zjs_r_dmounmanaged.ddls.xml | G33: UPDATED ON 02-FEB-26 | H33: 3 months ago

Sheet ZJS_02_RAP_COMPLEX
B2: d | C2: Object | D2: Type | E2: Category | F2: Github Object | G2: Github Type | H2: Version
B4: OK | C4: =LEFT(F4,FIND(".",F4)-1) -> package | D4: {=INDEX('Not Req'!$E$4:$E$71,MATCH(MID(F4,FIND(".",F4)+1,LEN(F4)-FIND(".",F4)+1),'Not Req'!$D$4:$D$71,0))} -> Description : Package | E4: =INDEX('Not Req'!$F$4:$F$71,MATCH(MID(F4,FIND(".",F4)+1,LEN(F4)-FIND(".",F4)+1),'Not Req'!$D$4:$D$71,0)) -> 99. Descriptions | F4: package.devc.xml | G4: UPDATED ON 02-FEB-26 | H4: 3 months ago | N4: {=_xlfn.UNIQUE(C4:C21)} -> package
B5: OK | C5: =LEFT(F5,FIND(".",F5)-1) -> 871f1084ff2d23ecba0049b09ec419ht | D5: {=INDEX('Not Req'!$E$4:$E$71,MATCH(MID(F5,FIND(".",F5)+1,LEN(F5)-FIND(".",F5)+1),'Not Req'!$D$4:$D$71,0))} -> Authorization Defaults (TADIR) | E5: =INDEX('Not Req'!$F$4:$F$71,MATCH(MID(F5,FIND(".",F5)+1,LEN(F5)-FIND(".",F5)+1),'Not Req'!$D$4:$D$71,0)) -> 1. Authorizations | F5: 871f1084ff2d23ecba0049b09ec419ht.sush.xml | G5: UPDATED ON 02-FEB-26 | H5: 3 months ago | N5: 871f1084ff2d23ecba0049b09ec419ht
B6: OK | C6: =LEFT(F6,FIND(".",F6)-1) -> 8943dc9d0559847ffa52270c9ac949ht | D6: {=INDEX('Not Req'!$E$4:$E$71,MATCH(MID(F6,FIND(".",F6)+1,LEN(F6)-FIND(".",F6)+1),'Not Req'!$D$4:$D$71,0))} -> Authorization Defaults (TADIR) | E6: =INDEX('Not Req'!$F$4:$F$71,MATCH(MID(F6,FIND(".",F6)+1,LEN(F6)-FIND(".",F6)+1),'Not Req'!$D$4:$D$71,0)) -> 1. Authorizations | F6: 8943dc9d0559847ffa52270c9ac949ht.sush.xml | G6: UPDATED ON 02-FEB-26 | H6: 3 months ago | N6: 8943dc9d0559847ffa52270c9ac949ht
B7: OK | C7: =LEFT(F7,FIND(".",F7)-1) -> dea30bfb2457df4bdf19766546a2d4ht | D7: {=INDEX('Not Req'!$E$4:$E$71,MATCH(MID(F7,FIND(".",F7)+1,LEN(F7)-FIND(".",F7)+1),'Not Req'!$D$4:$D$71,0))} -> Authorization Defaults (TADIR) | E7: =INDEX('Not Req'!$F$4:$F$71,MATCH(MID(F7,FIND(".",F7)+1,LEN(F7)-FIND(".",F7)+1),'Not Req'!$D$4:$D$71,0)) -> 1. Authorizations | F7: dea30bfb2457df4bdf19766546a2d4ht.sush.xml | G7: UPDATED ON 02-FEB-26 | H7: 3 months ago | N7: dea30bfb2457df4bdf19766546a2d4ht
B8: OK | C8: =LEFT(F8,FIND(".",F8)-1) -> zjs_api_rapc_invoice_o4 | D8: {=INDEX('Not Req'!$E$4:$E$71,MATCH(MID(F8,FIND(".",F8)+1,LEN(F8)-FIND(".",F8)+1),'Not Req'!$D$4:$D$71,0))} -> Service Binding | E8: =INDEX('Not Req'!$F$4:$F$71,MATCH(MID(F8,FIND(".",F8)+1,LEN(F8)-FIND(".",F8)+1),'Not Req'!$D$4:$D$71,0)) -> 2. Business Services | F8: zjs_api_rapc_invoice_o4.srvb.xml | G8: UPDATED ON 02-FEB-26 | H8: 3 months ago | N8: zjs_api_rapc_invoice_o4
B9: OK | C9: =LEFT(F9,FIND(".",F9)-1) -> zjs_rapc_invoice | D9: {=INDEX('Not Req'!$E$4:$E$71,MATCH(MID(F9,FIND(".",F9)+1,LEN(F9)-FIND(".",F9)+1),'Not Req'!$D$4:$D$71,0))} -> Service Definition | E9: =INDEX('Not Req'!$F$4:$F$71,MATCH(MID(F9,FIND(".",F9)+1,LEN(F9)-FIND(".",F9)+1),'Not Req'!$D$4:$D$71,0)) -> 2. Business Services | F9: zjs_rapc_invoice.srvd.srvdsrv | G9: UPDATED ON 02-FEB-26 | H9: 3 months ago | N9: zjs_rapc_invoice
B10: OK | C10: =LEFT(F10,FIND(".",F10)-1) -> zjs_ui_rapc_invoice_o2 | D10: {=INDEX('Not Req'!$E$4:$E$71,MATCH(MID(F10,FIND(".",F10)+1,LEN(F10)-FIND(".",F10)+1),'Not Req'!$D$4:$D$71,0))} -> Service Binding | E10: =INDEX('Not Req'!$F$4:$F$71,MATCH(MID(F10,FIND(".",F10)+1,LEN(F10)-FIND(".",F10)+1),'Not Req'!$D$4:$D$71,0)) -> 2. Business Services | F10: zjs_ui_rapc_invoice_o2.srvb.xml | G10: UPDATED ON 02-FEB-26 | H10: 3 months ago | N10: zjs_ui_rapc_invoice_o2
B11: OK | C11: =LEFT(F11,FIND(".",F11)-1) -> zjs_api_rapc_invoice_o4_0001_g4ba | D11: {=INDEX('Not Req'!$E$4:$E$71,MATCH(MID(F11,FIND(".",F11)+1,LEN(F11)-FIND(".",F11)+1),'Not Req'!$D$4:$D$71,0))} -> Inbound Service | E11: =INDEX('Not Req'!$F$4:$F$71,MATCH(MID(F11,FIND(".",F11)+1,LEN(F11)-FIND(".",F11)+1),'Not Req'!$D$4:$D$71,0)) -> 3. Cloud Communication Management | F11: zjs_api_rapc_invoice_o4_0001_g4ba.sco2.xml | G11: UPDATED ON 02-FEB-26 | H11: 3 months ago | N11: zjs_api_rapc_invoice_o4_0001_g4ba
B12: OK | C12: =LEFT(F12,FIND(".",F12)-1) -> zjs_ui_rapc_invoice_o2_iwsg | D12: {=INDEX('Not Req'!$E$4:$E$71,MATCH(MID(F12,FIND(".",F12)+1,LEN(F12)-FIND(".",F12)+1),'Not Req'!$D$4:$D$71,0))} -> Inbound Service | E12: =INDEX('Not Req'!$F$4:$F$71,MATCH(MID(F12,FIND(".",F12)+1,LEN(F12)-FIND(".",F12)+1),'Not Req'!$D$4:$D$71,0)) -> 3. Cloud Communication Management | F12: zjs_ui_rapc_invoice_o2_iwsg.sco2.xml | G12: UPDATED ON 02-FEB-26 | H12: 3 months ago | N12: zjs_ui_rapc_invoice_o2_iwsg
B13: OK | C13: =LEFT(F13,FIND(".",F13)-1) -> zjs_c_rapcinvoice | D13: {=INDEX('Not Req'!$E$4:$E$71,MATCH(MID(F13,FIND(".",F13)+1,LEN(F13)-FIND(".",F13)+1),'Not Req'!$D$4:$D$71,0))} -> BDEF | E13: =INDEX('Not Req'!$F$4:$F$71,MATCH(MID(F13,FIND(".",F13)+1,LEN(F13)-FIND(".",F13)+1),'Not Req'!$D$4:$D$71,0)) -> 4. CDS | F13: zjs_c_rapcinvoice.bdef.asbdef | G13: UPDATED ON 02-FEB-26 | H13: 3 months ago | N13: zjs_c_rapcinvoice
B14: OK | C14: =LEFT(F14,FIND(".",F14)-1) -> zjs_c_rapcinvoice | D14: {=INDEX('Not Req'!$E$4:$E$71,MATCH(MID(F14,FIND(".",F14)+1,LEN(F14)-FIND(".",F14)+1),'Not Req'!$D$4:$D$71,0))} -> Data Definition | E14: =INDEX('Not Req'!$F$4:$F$71,MATCH(MID(F14,FIND(".",F14)+1,LEN(F14)-FIND(".",F14)+1),'Not Req'!$D$4:$D$71,0)) -> 4. CDS | F14: zjs_c_rapcinvoice.ddls.asddls | G14: UPDATED ON 02-FEB-26 | H14: 3 months ago | N14: zjs_c_rapcposition
B15: OK | C15: =LEFT(F15,FIND(".",F15)-1) -> zjs_c_rapcinvoice | D15: {=INDEX('Not Req'!$E$4:$E$71,MATCH(MID(F15,FIND(".",F15)+1,LEN(F15)-FIND(".",F15)+1),'Not Req'!$D$4:$D$71,0))} -> Metadata | E15: =INDEX('Not Req'!$F$4:$F$71,MATCH(MID(F15,FIND(".",F15)+1,LEN(F15)-FIND(".",F15)+1),'Not Req'!$D$4:$D$71,0)) -> 4. CDS | F15: zjs_c_rapcinvoice.ddlx.asddlxs | G15: UPDATED ON 02-FEB-26 | H15: 3 months ago | N15: zjs_i_rapcmailpopup
B16: OK | C16: =LEFT(F16,FIND(".",F16)-1) -> zjs_c_rapcposition | D16: {=INDEX('Not Req'!$E$4:$E$71,MATCH(MID(F16,FIND(".",F16)+1,LEN(F16)-FIND(".",F16)+1),'Not Req'!$D$4:$D$71,0))} -> Data Definition | E16: =INDEX('Not Req'!$F$4:$F$71,MATCH(MID(F16,FIND(".",F16)+1,LEN(F16)-FIND(".",F16)+1),'Not Req'!$D$4:$D$71,0)) -> 4. CDS | F16: zjs_c_rapcposition.ddls.asddls | G16: UPDATED ON 02-FEB-26 | H16: 3 months ago | N16: zjs_i_rapcmaterial
... B18: OK | C18: =LEFT(F18,FIND(".",F18)-1) -> zjs_i_rapcmailpopup | D18: {=INDEX('Not Req'!$E$4:$E$71,MATCH(MID(F18,FIND(".",F18)+1,LEN(F18)-FIND(".",F18)+1),'Not Req'!$D$4:$D$71,0))} -> Data Definition | E18: =INDEX('Not Req'!$F$4:$F$71,MATCH(MID(F18,FIND(".",F18)+1,LEN(F18)-FIND(".",F18)+1),'Not Req'!$D$4:$D$71,0)) -> 4. CDS | F18: zjs_i_rapcmailpopup.ddls.asddls | G18: UPDATED ON 02-FEB-26 | H18: 3 months ago | N18: zjs_r_rapcinvoice
B19: OK | C19: =LEFT(F19,FIND(".",F19)-1) -> zjs_i_rapcmaterial | D19: {=INDEX('Not Req'!$E$4:$E$71,MATCH(MID(F19,FIND(".",F19)+1,LEN(F19)-FIND(".",F19)+1),'Not Req'!$D$4:$D$71,0))} -> Data Definition | E19: =INDEX('Not Req'!$F$4:$F$71,MATCH(MID(F19,FIND(".",F19)+1,LEN(F19)-FIND(".",F19)+1),'Not Req'!$D$4:$D$71,0)) -> 4. CDS | F19: zjs_i_rapcmaterial.ddls.asddls | G19: UPDATED ON 02-FEB-26 | H19: 3 months ago
B20: OK | C20: =LEFT(F20,FIND(".",F20)-1) -> zjs_i_rapcposition | D20: {=INDEX('Not Req'!$E$4:$E$71,MATCH(MID(F20,FIND(".",F20)+1,LEN(F20)-FIND(".",F20)+1),'Not Req'!$D$4:$D$71,0))} -> Data Definition | E20: =INDEX('Not Req'!$F$4:$F$71,MATCH(MID(F20,FIND(".",F20)+1,LEN(F20)-FIND(".",F20)+1),'Not Req'!$D$4:$D$71,0)) -> 4. CDS | F20: zjs_i_rapcposition.ddls.asddls | G20: UPDATED ON 02-FEB-26 | H20: 3 months ago
B21: OK | C21: =LEFT(F21,FIND(".",F21)-1) -> zjs_r_rapcinvoice | D21: {=INDEX('Not Req'!$E$4:$E$71,MATCH(MID(F21,FIND(".",F21)+1,LEN(F21)-FIND(".",F21)+1),'Not Req'!$D$4:$D$71,0))} -> BDEF | E21: =INDEX('Not Req'!$F$4:$F$71,MATCH(MID(F21,FIND(".",F21)+1,LEN(F21)-FIND(".",F21)+1),'Not Req'!$D$4:$D$71,0)) -> 4. CDS | F21: zjs_r_rapcinvoice.bdef.asbdef | G21: UPDATED ON 02-FEB-26 | H21: 3 months ago
B22: OK | C22: =LEFT(F22,FIND(".",F22)-1) -> zjs_r_rapcinvoice | D22: {=INDEX('Not Req'!$E$4:$E$71,MATCH(MID(F22,FIND(".",F22)+1,LEN(F22)-FIND(".",F22)+1),'Not Req'!$D$4:$D$71,0))} -> Data Definition | E22: =INDEX('Not Req'!$F$4:$F$71,MATCH(MID(F22,FIND(".",F22)+1,LEN(F22)-FIND(".",F22)+1),'Not Req'!$D$4:$D$71,0)) -> 4. CDS | F22: zjs_r_rapcinvoice.ddls.asddls | G22: UPDATED ON 02-FEB-26 | H22: 3 months ago
B23: OK | C23: =LEFT(F23,FIND(".",F23)-1) -> zjs_s_rapcreateinvoice | D23: {=INDEX('Not Req'!$E$4:$E$71,MATCH(MID(F23,FIND(".",F23)+1,LEN(F23)-FIND(".",F23)+1),'Not Req'!$D$4:$D$71,0))} -> BDEF | E23: =INDEX('Not Req'!$F$4:$F$71,MATCH(MID(F23,FIND(".",F23)+1,LEN(F23)-FIND(".",F23)+1),'Not Req'!$D$4:$D$71,0)) -> 4. CDS | F23: zjs_s_rapcreateinvoice.bdef.asbdef | G23: UPDATED ON 02-FEB-26 | H23: 3 months ago
B24: OK | C24: =LEFT(F24,FIND(".",F24)-1) -> zjs_s_rapcreateinvoice | D24: {=INDEX('Not Req'!$E$4:$E$71,MATCH(MID(F24,FIND(".",F24)+1,LEN(F24)-FIND(".",F24)+1),'Not Req'!$D$4:$D$71,0))} -> Data Definition | E24: =INDEX('Not Req'!$F$4:$F$71,MATCH(MID(F24,FIND(".",F24)+1,LEN(F24)-FIND(".",F24)+1),'Not Req'!$D$4:$D$71,0)) -> 4. CDS | F24: zjs_s_rapcreateinvoice.ddls.asddls | G24: UPDATED ON 02-FEB-26 | H24: 3 months ago
B25: OK | C25: =LEFT(F25,FIND(".",F25)-1) -> zjs_s_rapcreateposition | D25: {=INDEX('Not Req'!$E$4:$E$71,MATCH(MID(F25,FIND(".",F25)+1,LEN(F25)-FIND(".",F25)+1),'Not Req'!$D$4:$D$71,0))} -> Data Definition | E25: =INDEX('Not Req'!$F$4:$F$71,MATCH(MID(F25,FIND(".",F25)+1,LEN(F25)-FIND(".",F25)+1),'Not Req'!$D$4:$D$71,0)) -> 4. CDS | F25: zjs_s_rapcreateposition.ddls.asddls | G25: UPDATED ON 02-FEB-26 | H25: 3 months ago
C26: =LEFT(F26,FIND(".",F26)-1) -> zbp_js_rapcinvoice | D26: {=INDEX('Not Req'!$E$4:$E$71,MATCH(MID(F26,FIND(".",F26)+1,LEN(F26)-FIND(".",F26)+1),'Not Req'!$D$4:$D$71,0))} -> Classes Local | E26: =INDEX('Not Req'!$F$4:$F$71,MATCH(MID(F26,FIND(".",F26)+1,LEN(F26)-FIND(".",F26)+1),'Not Req'!$D$4:$D$71,0)) -> 7. Source Code Library | F26: zbp_js_rapcinvoice.clas.locals_imp.abap | G26: UPDATED ON 02-FEB-26 | H26: 3 months ago
C27: =LEFT(F27,FIND(".",F27)-1) -> zbp_js_rapcinvoice | D27: {=INDEX('Not Req'!$E$4:$E$71,MATCH(MID(F27,FIND(".",F27)+1,LEN(F27)-FIND(".",F27)+1),'Not Req'!$D$4:$D$71,0))} -> Classes | E27: =INDEX('Not Req'!$F$4:$F$71,MATCH(MID(F27,FIND(".",F27)+1,LEN(F27)-FIND(".",F27)+1),'Not Req'!$D$4:$D$71,0)) -> 7. Source Code Library | F27: zbp_js_rapcinvoice.clas.abap | G27: Updated 16-Mar-26 | H27: 2 months ago
C28: =LEFT(F28,FIND(".",F28)-1) -> zcl_js_demo_crap_eml | D28: {=INDEX('Not Req'!$E$4:$E$71,MATCH(MID(F28,FIND(".",F28)+1,LEN(F28)-FIND(".",F28)+1),'Not Req'!$D$4:$D$71,0))} -> Classes | E28: =INDEX('Not Req'!$F$4:$F$71,MATCH(MID(F28,FIND(".",F28)+1,LEN(F28)-FIND(".",F28)+1),'Not Req'!$D$4:$D$71,0)) -> 7. Source Code Library | F28: zcl_js_demo_crap_eml.clas.abap | G28: Updated 16-Mar-26 | H28: 2 months ago
C29: =LEFT(F29,FIND(".",F29)-1) -> zcl_js_demo_crap_mail | D29: {=INDEX('Not Req'!$E$4:$E$71,MATCH(MID(F29,FIND(".",F29)+1,LEN(F29)-FIND(".",F29)+1),'Not Req'!$D$4:$D$71,0))} -> Classes | E29: =INDEX('Not Req'!$F$4:$F$71,MATCH(MID(F29,FIND(".",F29)+1,LEN(F29)-FIND(".",F29)+1),'Not Req'!$D$4:$D$71,0)) -> 7. Source Code Library | F29: zcl_js_demo_crap_mail.clas.abap | G29: UPDATED ON 02-FEB-26 | H29: 3 months ago
C30: =LEFT(F30,FIND(".",F30)-1) -> zcl_js_demo_crap_ve_exit | D30: {=INDEX('Not Req'!$E$4:$E$71,MATCH(MID(F30,FIND(".",F30)+1,LEN(F30)-FIND(".",F30)+1),'Not Req'!$D$4:$D$71,0))} -> Classes | E30: =INDEX('Not Req'!$F$4:$F$71,MATCH(MID(F30,FIND(".",F30)+1,LEN(F30)-FIND(".",F30)+1),'Not Req'!$D$4:$D$71,0)) -> 7. Source Code Library | F30: zcl_js_demo_crap_ve_exit.clas.abap | G30: UPDATED ON 02-FEB-26 | H30: 3 months ago
C31: =LEFT(F31,FIND(".",F31)-1) -> zcl_js_demo_eml_deep_action | D31: {=INDEX('Not Req'!$E$4:$E$71,MATCH(MID(F31,FIND(".",F31)+1,LEN(F31)-FIND(".",F31)+1),'Not Req'!$D$4:$D$71,0))} -> Classes | E31: =INDEX('Not Req'!$F$4:$F$71,MATCH(MID(F31,FIND(".",F31)+1,LEN(F31)-FIND(".",F31)+1),'Not Req'!$D$4:$D$71,0)) -> 7. Source Code Library | F31: zcl_js_demo_eml_deep_action.clas.abap | G31: Updated 16-Mar-26 | H31: 2 months ago
C32: =LEFT(F32,FIND(".",F32)-1) -> zbp_js_rapcinvoice | D32: {=INDEX('Not Req'!$E$4:$E$71,MATCH(MID(F32,FIND(".",F32)+1,LEN(F32)-FIND(".",F32)+1),'Not Req'!$D$4:$D$71,0))} -> Description : Classes | E32: =INDEX('Not Req'!$F$4:$F$71,MATCH(MID(F32,FIND(".",F32)+1,LEN(F32)-FIND(".",F32)+1),'Not Req'!$D$4:$D$71,0)) -> 99. Descriptions | F32: zbp_js_rapcinvoice.clas.xml | G32: UPDATED ON 02-FEB-26 | H32: 3 months ago
C33: =LEFT(F33,FIND(".",F33)-1) -> zcl_js_demo_crap_eml | D33: {=INDEX('Not Req'!$E$4:$E$71,MATCH(MID(F33,FIND(".",F33)+1,LEN(F33)-FIND(".",F33)+1),'Not Req'!$D$4:$D$71,0))} -> Description : Classes | E33: =INDEX('Not Req'!$F$4:$F$71,MATCH(MID(F33,FIND(".",F33)+1,LEN(F33)-FIND(".",F33)+1),'Not Req'!$D$4:$D$71,0)) -> 99. Descriptions | F33: zcl_js_demo_crap_eml.clas.xml | G33: UPDATED ON 02-FEB-26 | H33: 3 months ago
C34: =LEFT(F34,FIND(".",F34)-1) -> zcl_js_demo_crap_mail | D34: {=INDEX('Not Req'!$E$4:$E$71,MATCH(MID(F34,FIND(".",F34)+1,LEN(F34)-FIND(".",F34)+1),'Not Req'!$D$4:$D$71,0))} -> Description : Classes | E34: =INDEX('Not Req'!$F$4:$F$71,MATCH(MID(F34,FIND(".",F34)+1,LEN(F34)-FIND(".",F34)+1),'Not Req'!$D$4:$D$71,0)) -> 99. Descriptions | F34: zcl_js_demo_crap_mail.clas.xml | G34: UPDATED ON 02-FEB-26 | H34: 3 months ago
C35: =LEFT(F35,FIND(".",F35)-1) -> zcl_js_demo_crap_ve_exit | D35: {=INDEX('Not Req'!$E$4:$E$71,MATCH(MID(F35,FIND(".",F35)+1,LEN(F35)-FIND(".",F35)+1),'Not Req'!$D$4:$D$71,0))} -> Description : Classes | E35: =INDEX('Not Req'!$F$4:$F$71,MATCH(MID(F35,FIND(".",F35)+1,LEN(F35)-FIND(".",F35)+1),'Not Req'!$D$4:$D$71,0)) -> 99. Descriptions | F35: zcl_js_demo_crap_ve_exit.clas.xml | G35: UPDATED ON 02-FEB-26 | H35: 3 months ago
C36: =LEFT(F36,FIND(".",F36)-1) -> zcl_js_demo_eml_deep_action | D36: {=INDEX('Not Req'!$E$4:$E$71,MATCH(MID(F36,FIND(".",F36)+1,LEN(F36)-FIND(".",F36)+1),'Not Req'!$D$4:$D$71,0))} -> Description : Classes | E36: =INDEX('Not Req'!$F$4:$F$71,MATCH(MID(F36,FIND(".",F36)+1,LEN(F36)-FIND(".",F36)+1),'Not Req'!$D$4:$D$71,0)) -> 99. Descriptions | F36: zcl_js_demo_eml_deep_action.clas.xml | G36: UPDATED ON 02-FEB-26 | H36: 3 months ago
C37: =LEFT(F37,FIND(".",F37)-1) -> zjs_c_rapcinvoice | D37: {=INDEX('Not Req'!$E$4:$E$71,MATCH(MID(F37,FIND(".",F37)+1,LEN(F37)-FIND(".",F37)+1),'Not Req'!$D$4:$D$71,0))} -> Description : BDEF | E37: =INDEX('Not Req'!$F$4:$F$71,MATCH(MID(F37,FIND(".",F37)+1,LEN(F37)-FIND(".",F37)+1),'Not Req'!$D$4:$D$71,0)) -> 99. Descriptions | F37: zjs_c_rapcinvoice.bdef.xml | G37: UPDATED ON 02-FEB-26 | H37: 3 months ago
... C57: =LEFT(F57,FIND(".",F57)-1) -> zjs_s_rapcreateposition | D57: {=INDEX('Not Req'!$E$4:$E$71,MATCH(MID(F57,FIND(".",F57)+1,LEN(F57)-FIND(".",F57)+1),'Not Req'!$D$4:$D$71,0))} -> BaseInfo : Data Definition | E57: =INDEX('Not Req'!$F$4:$F$71,MATCH(MID(F57,FIND(".",F57)+1,LEN(F57)-FIND(".",F57)+1),'Not Req'!$D$4:$D$71,0)) -> 98. Base Info | F57: zjs_s_rapcreateposition.ddls.baseinfo | G57: UPDATED ON 02-FEB-26 | H57: 3 months ago
A58: D | C58: =LEFT(F58,FIND(".",F58)-1) -> zjs_s_rapcreateposition | D58: {=INDEX('Not Req'!$E$4:$E$71,MATCH(MID(F58,FIND(".",F58)+1,LEN(F58)-FIND(".",F58)+1),'Not Req'!$D$4:$D$71,0))} -> Description : Data Definition | E58: =INDEX('Not Req'!$F$4:$F$71,MATCH(MID(F58,FIND(".",F58)+1,LEN(F58)-FIND(".",F58)+1),'Not Req'!$D$4:$D$71,0)) -> 99. Descriptions | F58: zjs_s_rapcreateposition.ddls.xml | G58: UPDATED ON 02-FEB-26 | H58: 3 months ago

Sheet ZJS_01_RAP_SIMPLE
B2: d | C2: Object | D2: Type | E2: Category | F2: Github Object | G2: Github Type | H2: Version
B4: OK | C4: =LEFT(F4,FIND(".",F4)-1) -> package | D4: {=INDEX('Not Req'!$E$4:$E$71,MATCH(MID(F4,FIND(".",F4)+1,LEN(F4)-FIND(".",F4)+1),'Not Req'!$D$4:$D$71,0))} -> Description : Package | E4: =INDEX('Not Req'!$F$4:$F$71,MATCH(MID(F4,FIND(".",F4)+1,LEN(F4)-FIND(".",F4)+1),'Not Req'!$D$4:$D$71,0)) -> 99. Descriptions | F4: package.devc.xml | G4: UPDATED ON 02-FEB-26 | H4: 3 months ago | N4: {=_xlfn.UNIQUE(C4:C21)} -> package
B5: OK | C5: =LEFT(F5,FIND(".",F5)-1) -> zjs_dmo_dpartner | D5: {=INDEX('Not Req'!$E$4:$E$71,MATCH(MID(F5,FIND(".",F5)+1,LEN(F5)-FIND(".",F5)+1),'Not Req'!$D$4:$D$71,0))} -> Table | E5: =INDEX('Not Req'!$F$4:$F$71,MATCH(MID(F5,FIND(".",F5)+1,LEN(F5)-FIND(".",F5)+1),'Not Req'!$D$4:$D$71,0)) -> 5. Dictionary | F5: zjs_dmo_dpartner.tabl.xml | G5: UPDATED ON 02-FEB-26 | H5: 3 months ago | N5: zjs_dmo_dpartner
B6: OK | C6: =LEFT(F6,FIND(".",F6)-1) -> zjs_c_countryvh | D6: {=INDEX('Not Req'!$E$4:$E$71,MATCH(MID(F6,FIND(".",F6)+1,LEN(F6)-FIND(".",F6)+1),'Not Req'!$D$4:$D$71,0))} -> Data Definition | E6: =INDEX('Not Req'!$F$4:$F$71,MATCH(MID(F6,FIND(".",F6)+1,LEN(F6)-FIND(".",F6)+1),'Not Req'!$D$4:$D$71,0)) -> 4. CDS | F6: zjs_c_countryvh.ddls.asddls | G6: UPDATED ON 02-FEB-26 | H6: 3 months ago | N6: zjs_c_countryvh
B7: OK | C7: =LEFT(F7,FIND(".",F7)-1) -> zjs_c_rappartner | D7: {=INDEX('Not Req'!$E$4:$E$71,MATCH(MID(F7,FIND(".",F7)+1,LEN(F7)-FIND(".",F7)+1),'Not Req'!$D$4:$D$71,0))} -> BDEF | E7: =INDEX('Not Req'!$F$4:$F$71,MATCH(MID(F7,FIND(".",F7)+1,LEN(F7)-FIND(".",F7)+1),'Not Req'!$D$4:$D$71,0)) -> 4. CDS | F7: zjs_c_rappartner.bdef.asbdef | G7: UPDATED ON 02-FEB-26 | H7: 3 months ago | N7: zjs_c_rappartner
B8: OK | C8: =LEFT(F8,FIND(".",F8)-1) -> zjs_c_rappartner | D8: {=INDEX('Not Req'!$E$4:$E$71,MATCH(MID(F8,FIND(".",F8)+1,LEN(F8)-FIND(".",F8)+1),'Not Req'!$D$4:$D$71,0))} -> Data Definition | E8: =INDEX('Not Req'!$F$4:$F$71,MATCH(MID(F8,FIND(".",F8)+1,LEN(F8)-FIND(".",F8)+1),'Not Req'!$D$4:$D$71,0)) -> 4. CDS | F8: zjs_c_rappartner.ddls.asddls | G8: UPDATED ON 02-FEB-26 | H8: 3 months ago | N8: zjs_i_popupentity
B9: OK | C9: =LEFT(F9,FIND(".",F9)-1) -> zjs_c_rappartner | D9: {=INDEX('Not Req'!$E$4:$E$71,MATCH(MID(F9,FIND(".",F9)+1,LEN(F9)-FIND(".",F9)+1),'Not Req'!$D$4:$D$71,0))} -> Metadata | E9: =INDEX('Not Req'!$F$4:$F$71,MATCH(MID(F9,FIND(".",F9)+1,LEN(F9)-FIND(".",F9)+1),'Not Req'!$D$4:$D$71,0)) -> 4. CDS | F9: zjs_c_rappartner.ddlx.asddlxs | G9: UPDATED ON 02-FEB-26 | H9: 3 months ago | N9: zjs_i_rapcityvh
B10: OK | C10: =LEFT(F10,FIND(".",F10)-1) -> zjs_i_popupentity | D10: {=INDEX('Not Req'!$E$4:$E$71,MATCH(MID(F10,FIND(".",F10)+1,LEN(F10)-FIND(".",F10)+1),'Not Req'!$D$4:$D$71,0))} -> Data Definition | E10: =INDEX('Not Req'!$F$4:$F$71,MATCH(MID(F10,FIND(".",F10)+1,LEN(F10)-FIND(".",F10)+1),'Not Req'!$D$4:$D$71,0)) -> 4. CDS | F10: zjs_i_popupentity.ddls.asddls | G10: UPDATED ON 02-FEB-26 | H10: 3 months ago | N10: zjs_i_rapcustomentitycnames
B11: OK | C11: =LEFT(F11,FIND(".",F11)-1) -> zjs_i_rapcityvh | D11: {=INDEX('Not Req'!$E$4:$E$71,MATCH(MID(F11,FIND(".",F11)+1,LEN(F11)-FIND(".",F11)+1),'Not Req'!$D$4:$D$71,0))} -> Data Definition | E11: =INDEX('Not Req'!$F$4:$F$71,MATCH(MID(F11,FIND(".",F11)+1,LEN(F11)-FIND(".",F11)+1),'Not Req'!$D$4:$D$71,0)) -> 4. CDS | F11: zjs_i_rapcityvh.ddls.asddls | G11: UPDATED ON 02-FEB-26 | H11: 3 months ago | N11: zjs_i_rappartner
B12: OK | C12: =LEFT(F12,FIND(".",F12)-1) -> zjs_i_rapcustomentitycnames | D12: {=INDEX('Not Req'!$E$4:$E$71,MATCH(MID(F12,FIND(".",F12)+1,LEN(F12)-FIND(".",F12)+1),'Not Req'!$D$4:$D$71,0))} -> Data Definition | E12: =INDEX('Not Req'!$F$4:$F$71,MATCH(MID(F12,FIND(".",F12)+1,LEN(F12)-FIND(".",F12)+1),'Not Req'!$D$4:$D$71,0)) -> 4. CDS | F12: zjs_i_rapcustomentitycnames.ddls.asddls | G12: UPDATED ON 02-FEB-26 | H12: 3 months ago | N12: zbp_js_demo_rappartner
B13: OK | C13: =LEFT(F13,FIND(".",F13)-1) -> zjs_i_rappartner | D13: {=INDEX('Not Req'!$E$4:$E$71,MATCH(MID(F13,FIND(".",F13)+1,LEN(F13)-FIND(".",F13)+1),'Not Req'!$D$4:$D$71,0))} -> BDEF | E13: =INDEX('Not Req'!$F$4:$F$71,MATCH(MID(F13,FIND(".",F13)+1,LEN(F13)-FIND(".",F13)+1),'Not Req'!$D$4:$D$71,0)) -> 4. CDS | F13: zjs_i_rappartner.bdef.asbdef | G13: UPDATED ON 02-FEB-26 | H13: 3 months ago | N13: zcl_js_demo_action_eml
B14: OK | C14: =LEFT(F14,FIND(".",F14)-1) -> zjs_i_rappartner | D14: {=INDEX('Not Req'!$E$4:$E$71,MATCH(MID(F14,FIND(".",F14)+1,LEN(F14)-FIND(".",F14)+1),'Not Req'!$D$4:$D$71,0))} -> Data Definition | E14: =INDEX('Not Req'!$F$4:$F$71,MATCH(MID(F14,FIND(".",F14)+1,LEN(F14)-FIND(".",F14)+1),'Not Req'!$D$4:$D$71,0)) -> 4. CDS | F14: zjs_i_rappartner.ddls.asddls | G14: UPDATED ON 02-FEB-26 | H14: 3 months ago | N14: zcl_js_demo_adjust_data
B15: OK | C15: =LEFT(F15,FIND(".",F15)-1) -> zjs_i_rappartner | D15: {=INDEX('Not Req'!$E$4:$E$71,MATCH(MID(F15,FIND(".",F15)+1,LEN(F15)-FIND(".",F15)+1),'Not Req'!$D$4:$D$71,0))} -> Metadata | E15: =INDEX('Not Req'!$F$4:$F$71,MATCH(MID(F15,FIND(".",F15)+1,LEN(F15)-FIND(".",F15)+1),'Not Req'!$D$4:$D$71,0)) -> 4. CDS | F15: zjs_i_rappartner.ddlx.asddlxs | G15: UPDATED ON 02-FEB-26 | H15: 3 months ago | N15: zcl_js_demo_city_query
B16: OK | C16: =LEFT(F16,FIND(".",F16)-1) -> zbp_js_demo_rappartner | D16: {=INDEX('Not Req'!$E$4:$E$71,MATCH(MID(F16,FIND(".",F16)+1,LEN(F16)-FIND(".",F16)+1),'Not Req'!$D$4:$D$71,0))} -> Classes | E16: =INDEX('Not Req'!$F$4:$F$71,MATCH(MID(F16,FIND(".",F16)+1,LEN(F16)-FIND(".",F16)+1),'Not Req'!$D$4:$D$71,0)) -> 7. Source Code Library | F16: zbp_js_demo_rappartner.clas.abap | G16: Updated 16-Mar-26 | H16: 2 months ago | N16: zcl_js_demo_cust_cname_query
B17: OK | C17: =LEFT(F17,FIND(".",F17)-1) -> zbp_js_demo_rappartner | D17: {=INDEX('Not Req'!$E$4:$E$71,MATCH(MID(F17,FIND(".",F17)+1,LEN(F17)-FIND(".",F17)+1),'Not Req'!$D$4:$D$71,0))} -> Classes Local | E17: =INDEX('Not Req'!$F$4:$F$71,MATCH(MID(F17,FIND(".",F17)+1,LEN(F17)-FIND(".",F17)+1),'Not Req'!$D$4:$D$71,0)) -> 7. Source Code Library | F17: zbp_js_demo_rappartner.clas.locals_imp.abap | G17: UPDATED ON 02-FEB-26 | H17: 3 months ago
B18: OK | C18: =LEFT(F18,FIND(".",F18)-1) -> zcl_js_demo_action_eml | D18: {=INDEX('Not Req'!$E$4:$E$71,MATCH(MID(F18,FIND(".",F18)+1,LEN(F18)-FIND(".",F18)+1),'Not Req'!$D$4:$D$71,0))} -> Classes | E18: =INDEX('Not Req'!$F$4:$F$71,MATCH(MID(F18,FIND(".",F18)+1,LEN(F18)-FIND(".",F18)+1),'Not Req'!$D$4:$D$71,0)) -> 7. Source Code Library | F18: zcl_js_demo_action_eml.clas.abap | G18: Updated 16-Mar-26 | H18: 2 months ago
B19: OK | C19: =LEFT(F19,FIND(".",F19)-1) -> zcl_js_demo_adjust_data | D19: {=INDEX('Not Req'!$E$4:$E$71,MATCH(MID(F19,FIND(".",F19)+1,LEN(F19)-FIND(".",F19)+1),'Not Req'!$D$4:$D$71,0))} -> Classes | E19: =INDEX('Not Req'!$F$4:$F$71,MATCH(MID(F19,FIND(".",F19)+1,LEN(F19)-FIND(".",F19)+1),'Not Req'!$D$4:$D$71,0)) -> 7. Source Code Library | F19: zcl_js_demo_adjust_data.clas.abap | G19: Updated 16-Mar-26 | H19: 2 months ago
B20: OK | C20: =LEFT(F20,FIND(".",F20)-1) -> zcl_js_demo_city_query | D20: {=INDEX('Not Req'!$E$4:$E$71,MATCH(MID(F20,FIND(".",F20)+1,LEN(F20)-FIND(".",F20)+1),'Not Req'!$D$4:$D$71,0))} -> Classes | E20: =INDEX('Not Req'!$F$4:$F$71,MATCH(MID(F20,FIND(".",F20)+1,LEN(F20)-FIND(".",F20)+1),'Not Req'!$D$4:$D$71,0)) -> 7. Source Code Library | F20: zcl_js_demo_city_query.clas.abap | G20: Updated 16-Mar-26 | H20: 2 months ago
B21: OK | C21: =LEFT(F21,FIND(".",F21)-1) -> zcl_js_demo_cust_cname_query | D21: {=INDEX('Not Req'!$E$4:$E$71,MATCH(MID(F21,FIND(".",F21)+1,LEN(F21)-FIND(".",F21)+1),'Not Req'!$D$4:$D$71,0))} -> Classes | E21: =INDEX('Not Req'!$F$4:$F$71,MATCH(MID(F21,FIND(".",F21)+1,LEN(F21)-FIND(".",F21)+1),'Not Req'!$D$4:$D$71,0)) -> 7. Source Code Library | F21: zcl_js_demo_cust_cname_query.clas.abap | G21: Updated 16-Mar-26 | H21: 2 months ago
B22: OK | C22: =LEFT(F22,FIND(".",F22)-1) -> zcl_js_demo_simple_eml | D22: {=INDEX('Not Req'!$E$4:$E$71,MATCH(MID(F22,FIND(".",F22)+1,LEN(F22)-FIND(".",F22)+1),'Not Req'!$D$4:$D$71,0))} -> Classes | E22: =INDEX('Not Req'!$F$4:$F$71,MATCH(MID(F22,FIND(".",F22)+1,LEN(F22)-FIND(".",F22)+1),'Not Req'!$D$4:$D$71,0)) -> 7. Source Code Library | F22: zcl_js_demo_simple_eml.clas.abap | G22: Updated 16-Mar-26 | H22: 2 months ago
B23: OK | C23: =LEFT(F23,FIND(".",F23)-1) -> zcl_js_demo_unit_cleanup | D23: {=INDEX('Not Req'!$E$4:$E$71,MATCH(MID(F23,FIND(".",F23)+1,LEN(F23)-FIND(".",F23)+1),'Not Req'!$D$4:$D$71,0))} -> Classes | E23: =INDEX('Not Req'!$F$4:$F$71,MATCH(MID(F23,FIND(".",F23)+1,LEN(F23)-FIND(".",F23)+1),'Not Req'!$D$4:$D$71,0)) -> 7. Source Code Library | F23: zcl_js_demo_unit_cleanup.clas.abap | G23: UPDATED ON 02-FEB-26 | H23: 3 months ago
B24: OK | C24: =LEFT(F24,FIND(".",F24)-1) -> zcl_js_demo_unit_rap | D24: {=INDEX('Not Req'!$E$4:$E$71,MATCH(MID(F24,FIND(".",F24)+1,LEN(F24)-FIND(".",F24)+1),'Not Req'!$D$4:$D$71,0))} -> Classes | E24: =INDEX('Not Req'!$F$4:$F$71,MATCH(MID(F24,FIND(".",F24)+1,LEN(F24)-FIND(".",F24)+1),'Not Req'!$D$4:$D$71,0)) -> 7. Source Code Library | F24: zcl_js_demo_unit_rap.clas.abap | G24: UPDATED ON 02-FEB-26 | H24: 3 months ago
B25: OK | C25: =LEFT(F25,FIND(".",F25)-1) -> zcl_js_demo_unit_service | D25: {=INDEX('Not Req'!$E$4:$E$71,MATCH(MID(F25,FIND(".",F25)+1,LEN(F25)-FIND(".",F25)+1),'Not Req'!$D$4:$D$71,0))} -> Classes | E25: =INDEX('Not Req'!$F$4:$F$71,MATCH(MID(F25,FIND(".",F25)+1,LEN(F25)-FIND(".",F25)+1),'Not Req'!$D$4:$D$71,0)) -> 7. Source Code Library | F25: zcl_js_demo_unit_service.clas.abap | G25: UPDATED ON 02-FEB-26 | H25: 3 months ago
B26: OK | C26: =LEFT(F26,FIND(".",F26)-1) -> 3b345eadd2f8152746fc46db03ff9bht | D26: {=INDEX('Not Req'!$E$4:$E$71,MATCH(MID(F26,FIND(".",F26)+1,LEN(F26)-FIND(".",F26)+1),'Not Req'!$D$4:$D$71,0))} -> Authorization Defaults (TADIR) | E26: =INDEX('Not Req'!$F$4:$F$71,MATCH(MID(F26,FIND(".",F26)+1,LEN(F26)-FIND(".",F26)+1),'Not Req'!$D$4:$D$71,0)) -> 1. Authorizations | F26: 3b345eadd2f8152746fc46db03ff9bht.sush.xml | G26: UPDATED ON 02-FEB-26 | H26: 3 months ago
B27: OK | C27: =LEFT(F27,FIND(".",F27)-1) -> 5b018e30b17bb99599d361a8b6980cht | D27: {=INDEX('Not Req'!$E$4:$E$71,MATCH(MID(F27,FIND(".",F27)+1,LEN(F27)-FIND(".",F27)+1),'Not Req'!$D$4:$D$71,0))} -> Authorization Defaults (TADIR) | E27: =INDEX('Not Req'!$F$4:$F$71,MATCH(MID(F27,FIND(".",F27)+1,LEN(F27)-FIND(".",F27)+1),'Not Req'!$D$4:$D$71,0)) -> 1. Authorizations | F27: 5b018e30b17bb99599d361a8b6980cht.sush.xml | G27: UPDATED ON 02-FEB-26 | H27: 3 months ago
B28: OK | C28: =LEFT(F28,FIND(".",F28)-1) -> 739bcc242cce9512442327863bbd87ht | D28: {=INDEX('Not Req'!$E$4:$E$71,MATCH(MID(F28,FIND(".",F28)+1,LEN(F28)-FIND(".",F28)+1),'Not Req'!$D$4:$D$71,0))} -> Authorization Defaults (TADIR) | E28: =INDEX('Not Req'!$F$4:$F$71,MATCH(MID(F28,FIND(".",F28)+1,LEN(F28)-FIND(".",F28)+1),'Not Req'!$D$4:$D$71,0)) -> 1. Authorizations | F28: 739bcc242cce9512442327863bbd87ht.sush.xml | G28: UPDATED ON 02-FEB-26 | H28: 3 months ago
... B37: OK | C37: =LEFT(F37,FIND(".",F37)-1) -> zjs_ui_simple_partner_o4_0001_g4ba | D37: {=INDEX('Not Req'!$E$4:$E$71,MATCH(MID(F37,FIND(".",F37)+1,LEN(F37)-FIND(".",F37)+1),'Not Req'!$D$4:$D$71,0))} -> Inbound Service | E37: =INDEX('Not Req'!$F$4:$F$71,MATCH(MID(F37,FIND(".",F37)+1,LEN(F37)-FIND(".",F37)+1),'Not Req'!$D$4:$D$71,0)) -> 3. Cloud Communication Management | F37: zjs_ui_simple_partner_o4_0001_g4ba.sco2.xml | G37: UPDATED ON 02-FEB-26 | H37: 3 months ago
C38: =LEFT(F38,FIND(".",F38)-1) -> zbp_js_demo_rappartner | D38: {=INDEX('Not Req'!$E$4:$E$71,MATCH(MID(F38,FIND(".",F38)+1,LEN(F38)-FIND(".",F38)+1),'Not Req'!$D$4:$D$71,0))} -> Description : Classes | E38: =INDEX('Not Req'!$F$4:$F$71,MATCH(MID(F38,FIND(".",F38)+1,LEN(F38)-FIND(".",F38)+1),'Not Req'!$D$4:$D$71,0)) -> 99. Descriptions | F38: zbp_js_demo_rappartner.clas.xml | G38: UPDATED ON 02-FEB-26 | H38: 3 months ago
C39: =LEFT(F39,FIND(".",F39)-1) -> zcl_js_demo_action_eml | D39: {=INDEX('Not Req'!$E$4:$E$71,MATCH(MID(F39,FIND(".",F39)+1,LEN(F39)-FIND(".",F39)+1),'Not Req'!$D$4:$D$71,0))} -> Description : Classes | E39: =INDEX('Not Req'!$F$4:$F$71,MATCH(MID(F39,FIND(".",F39)+1,LEN(F39)-FIND(".",F39)+1),'Not Req'!$D$4:$D$71,0)) -> 99. Descriptions | F39: zcl_js_demo_action_eml.clas.xml | G39: UPDATED ON 02-FEB-26 | H39: 3 months ago
C40: =LEFT(F40,FIND(".",F40)-1) -> zcl_js_demo_adjust_data | D40: {=INDEX('Not Req'!$E$4:$E$71,MATCH(MID(F40,FIND(".",F40)+1,LEN(F40)-FIND(".",F40)+1),'Not Req'!$D$4:$D$71,0))} -> Description : Classes | E40: =INDEX('Not Req'!$F$4:$F$71,MATCH(MID(F40,FIND(".",F40)+1,LEN(F40)-FIND(".",F40)+1),'Not Req'!$D$4:$D$71,0)) -> 99. Descriptions | F40: zcl_js_demo_adjust_data.clas.xml | G40: UPDATED ON 02-FEB-26 | H40: 3 months ago
C41: =LEFT(F41,FIND(".",F41)-1) -> zcl_js_demo_city_query | D41: {=INDEX('Not Req'!$E$4:$E$71,MATCH(MID(F41,FIND(".",F41)+1,LEN(F41)-FIND(".",F41)+1),'Not Req'!$D$4:$D$71,0))} -> Description : Classes | E41: =INDEX('Not Req'!$F$4:$F$71,MATCH(MID(F41,FIND(".",F41)+1,LEN(F41)-FIND(".",F41)+1),'Not Req'!$D$4:$D$71,0)) -> 99. Descriptions | F41: zcl_js_demo_city_query.clas.xml | G41: UPDATED ON 02-FEB-26 | H41: 3 months ago
C42: =LEFT(F42,FIND(".",F42)-1) -> zcl_js_demo_cust_cname_query | D42: {=INDEX('Not Req'!$E$4:$E$71,MATCH(MID(F42,FIND(".",F42)+1,LEN(F42)-FIND(".",F42)+1),'Not Req'!$D$4:$D$71,0))} -> Description : Classes | E42: =INDEX('Not Req'!$F$4:$F$71,MATCH(MID(F42,FIND(".",F42)+1,LEN(F42)-FIND(".",F42)+1),'Not Req'!$D$4:$D$71,0)) -> 99. Descriptions | F42: zcl_js_demo_cust_cname_query.clas.xml | G42: UPDATED ON 02-FEB-26 | H42: 3 months ago
C43: =LEFT(F43,FIND(".",F43)-1) -> zcl_js_demo_simple_eml | D43: {=INDEX('Not Req'!$E$4:$E$71,MATCH(MID(F43,FIND(".",F43)+1,LEN(F43)-FIND(".",F43)+1),'Not Req'!$D$4:$D$71,0))} -> Description : Classes | E43: =INDEX('Not Req'!$F$4:$F$71,MATCH(MID(F43,FIND(".",F43)+1,LEN(F43)-FIND(".",F43)+1),'Not Req'!$D$4:$D$71,0)) -> 99. Descriptions | F43: zcl_js_demo_simple_eml.clas.xml | G43: UPDATED ON 02-FEB-26 | H43: 3 months ago
C44: =LEFT(F44,FIND(".",F44)-1) -> zcl_js_demo_unit_cleanup | D44: {=INDEX('Not Req'!$E$4:$E$71,MATCH(MID(F44,FIND(".",F44)+1,LEN(F44)-FIND(".",F44)+1),'Not Req'!$D$4:$D$71,0))} -> Description : Classes | E44: =INDEX('Not Req'!$F$4:$F$71,MATCH(MID(F44,FIND(".",F44)+1,LEN(F44)-FIND(".",F44)+1),'Not Req'!$D$4:$D$71,0)) -> 99. Descriptions | F44: zcl_js_demo_unit_cleanup.clas.xml | G44: UPDATED ON 02-FEB-26 | H44: 3 months ago
C45: =LEFT(F45,FIND(".",F45)-1) -> zcl_js_demo_unit_rap | D45: {=INDEX('Not Req'!$E$4:$E$71,MATCH(MID(F45,FIND(".",F45)+1,LEN(F45)-FIND(".",F45)+1),'Not Req'!$D$4:$D$71,0))} -> Description : Classes | E45: =INDEX('Not Req'!$F$4:$F$71,MATCH(MID(F45,FIND(".",F45)+1,LEN(F45)-FIND(".",F45)+1),'Not Req'!$D$4:$D$71,0)) -> 99. Descriptions | F45: zcl_js_demo_unit_rap.clas.xml | G45: UPDATED ON 02-FEB-26 | H45: 3 months ago
C46: =LEFT(F46,FIND(".",F46)-1) -> zcl_js_demo_unit_service | D46: {=INDEX('Not Req'!$E$4:$E$71,MATCH(MID(F46,FIND(".",F46)+1,LEN(F46)-FIND(".",F46)+1),'Not Req'!$D$4:$D$71,0))} -> Description : Classes | E46: =INDEX('Not Req'!$F$4:$F$71,MATCH(MID(F46,FIND(".",F46)+1,LEN(F46)-FIND(".",F46)+1),'Not Req'!$D$4:$D$71,0)) -> 99. Descriptions | F46: zcl_js_demo_unit_service.clas.xml | G46: UPDATED ON 02-FEB-26 | H46: 3 months ago
C47: =LEFT(F47,FIND(".",F47)-1) -> zjs_c_countryvh | D47: {=INDEX('Not Req'!$E$4:$E$71,MATCH(MID(F47,FIND(".",F47)+1,LEN(F47)-FIND(".",F47)+1),'Not Req'!$D$4:$D$71,0))} -> BaseInfo : Data Definition | E47: =INDEX('Not Req'!$F$4:$F$71,MATCH(MID(F47,FIND(".",F47)+1,LEN(F47)-FIND(".",F47)+1),'Not Req'!$D$4:$D$71,0)) -> 98. Base Info | F47: zjs_c_countryvh.ddls.baseinfo | G47: UPDATED ON 02-FEB-26 | H47: 3 months ago
C48: =LEFT(F48,FIND(".",F48)-1) -> zjs_c_countryvh | D48: {=INDEX('Not Req'!$E$4:$E$71,MATCH(MID(F48,FIND(".",F48)+1,LEN(F48)-FIND(".",F48)+1),'Not Req'!$D$4:$D$71,0))} -> Description : Data Definition | E48: =INDEX('Not Req'!$F$4:$F$71,MATCH(MID(F48,FIND(".",F48)+1,LEN(F48)-FIND(".",F48)+1),'Not Req'!$D$4:$D$71,0)) -> 99. Descriptions | F48: zjs_c_countryvh.ddls.xml | G48: UPDATED ON 02-FEB-26 | H48: 3 months ago
C49: =LEFT(F49,FIND(".",F49)-1) -> zjs_c_rappartner | D49: {=INDEX('Not Req'!$E$4:$E$71,MATCH(MID(F49,FIND(".",F49)+1,LEN(F49)-FIND(".",F49)+1),'Not Req'!$D$4:$D$71,0))} -> Description : BDEF | E49: =INDEX('Not Req'!$F$4:$F$71,MATCH(MID(F49,FIND(".",F49)+1,LEN(F49)-FIND(".",F49)+1),'Not Req'!$D$4:$D$71,0)) -> 99. Descriptions | F49: zjs_c_rappartner.bdef.xml | G49: UPDATED ON 02-FEB-26 | H49: 3 months ago
... C63: =LEFT(F63,FIND(".",F63)-1) -> zjs_simple_partner | D63: {=INDEX('Not Req'!$E$4:$E$71,MATCH(MID(F63,FIND(".",F63)+1,LEN(F63)-FIND(".",F63)+1),'Not Req'!$D$4:$D$71,0))} -> Description : Service Definition | E63: =INDEX('Not Req'!$F$4:$F$71,MATCH(MID(F63,FIND(".",F63)+1,LEN(F63)-FIND(".",F63)+1),'Not Req'!$D$4:$D$71,0)) -> 99. Descriptions | F63: zjs_simple_partner.srvd.xml | G63: UPDATED ON 02-FEB-26 | H63: 3 months ago

Sheet ZC_UPLOAD_EXCEL
B2: d | C2: Object | D2: Type | E2: Category | F2: Github Object | G2: Github Type | H2: Version
B4: OK | C4: =LEFT(F4,FIND(".",F4)-1) -> package | D4: {=INDEX('Not Req'!$E$4:$E$71,MATCH(MID(F4,FIND(".",F4)+1,LEN(F4)-FIND(".",F4)+1),'Not Req'!$D$4:$D$71,0))} -> Description : Package | E4: =INDEX('Not Req'!$F$4:$F$71,MATCH(MID(F4,FIND(".",F4)+1,LEN(F4)-FIND(".",F4)+1),'Not Req'!$D$4:$D$71,0)) -> 99. Descriptions | F4: package.devc.xml | G4: UPDATED ON 02-FEB-26 | H4: 3 months ago | N4: {=_xlfn.UNIQUE(C4:C21)} -> package
B5: OK | C5: =LEFT(F5,FIND(".",F5)-1) -> zdjs_cre_upld | D5: {=INDEX('Not Req'!$E$4:$E$71,MATCH(MID(F5,FIND(".",F5)+1,LEN(F5)-FIND(".",F5)+1),'Not Req'!$D$4:$D$71,0))} -> Table | E5: =INDEX('Not Req'!$F$4:$F$71,MATCH(MID(F5,FIND(".",F5)+1,LEN(F5)-FIND(".",F5)+1),'Not Req'!$D$4:$D$71,0)) -> 5. Dictionary | F5: zdjs_cre_upld.tabl.xml | G5: UPDATED ON 02-FEB-26 | H5: 3 months ago | N5: zdjs_cre_upld
B6: OK | C6: =LEFT(F6,FIND(".",F6)-1) -> zdjs_cre_upld_2 | D6: {=INDEX('Not Req'!$E$4:$E$71,MATCH(MID(F6,FIND(".",F6)+1,LEN(F6)-FIND(".",F6)+1),'Not Req'!$D$4:$D$71,0))} -> Table | E6: =INDEX('Not Req'!$F$4:$F$71,MATCH(MID(F6,FIND(".",F6)+1,LEN(F6)-FIND(".",F6)+1),'Not Req'!$D$4:$D$71,0)) -> 5. Dictionary | F6: zdjs_cre_upld_2.tabl.xml | G6: Updated 16-Mar-26 | H6: 2 months ago | N6: zdjs_cre_upld_2
B7: OK | C7: =LEFT(F7,FIND(".",F7)-1) -> zdjs_cre_upld_d | D7: {=INDEX('Not Req'!$E$4:$E$71,MATCH(MID(F7,FIND(".",F7)+1,LEN(F7)-FIND(".",F7)+1),'Not Req'!$D$4:$D$71,0))} -> Table | E7: =INDEX('Not Req'!$F$4:$F$71,MATCH(MID(F7,FIND(".",F7)+1,LEN(F7)-FIND(".",F7)+1),'Not Req'!$D$4:$D$71,0)) -> 5. Dictionary | F7: zdjs_cre_upld_d.tabl.xml | G7: UPDATED ON 02-FEB-26 | H7: 3 months ago | N7: zdjs_cre_upld_d
B8: OK | C8: =LEFT(F8,FIND(".",F8)-1) -> zjs_st_upld_excel | D8: {=INDEX('Not Req'!$E$4:$E$71,MATCH(MID(F8,FIND(".",F8)+1,LEN(F8)-FIND(".",F8)+1),'Not Req'!$D$4:$D$71,0))} -> Table | E8: =INDEX('Not Req'!$F$4:$F$71,MATCH(MID(F8,FIND(".",F8)+1,LEN(F8)-FIND(".",F8)+1),'Not Req'!$D$4:$D$71,0)) -> 5. Dictionary | F8: zjs_st_upld_excel.tabl.xml | G8: UPDATED ON 02-FEB-26 | H8: 3 months ago | N8: zjs_st_upld_excel
B9: OK | C9: =LEFT(F9,FIND(".",F9)-1) -> zcjs_c_cre_upld | D9: {=INDEX('Not Req'!$E$4:$E$71,MATCH(MID(F9,FIND(".",F9)+1,LEN(F9)-FIND(".",F9)+1),'Not Req'!$D$4:$D$71,0))} -> BDEF | E9: =INDEX('Not Req'!$F$4:$F$71,MATCH(MID(F9,FIND(".",F9)+1,LEN(F9)-FIND(".",F9)+1),'Not Req'!$D$4:$D$71,0)) -> 4. CDS | F9: zcjs_c_cre_upld.bdef.asbdef | G9: UPDATED ON 02-FEB-26 | H9: 3 months ago | N9: zcjs_c_cre_upld
B10: OK | C10: =LEFT(F10,FIND(".",F10)-1) -> zcjs_c_cre_upld | D10: {=INDEX('Not Req'!$E$4:$E$71,MATCH(MID(F10,FIND(".",F10)+1,LEN(F10)-FIND(".",F10)+1),'Not Req'!$D$4:$D$71,0))} -> Data Definition | E10: =INDEX('Not Req'!$F$4:$F$71,MATCH(MID(F10,FIND(".",F10)+1,LEN(F10)-FIND(".",F10)+1),'Not Req'!$D$4:$D$71,0)) -> 4. CDS | F10: zcjs_c_cre_upld.ddls.asddls | G10: UPDATED ON 02-FEB-26 | H10: 3 months ago | N10: zcjs_r_cre_upld
B11: OK | C11: =LEFT(F11,FIND(".",F11)-1) -> zcjs_c_cre_upld | D11: {=INDEX('Not Req'!$E$4:$E$71,MATCH(MID(F11,FIND(".",F11)+1,LEN(F11)-FIND(".",F11)+1),'Not Req'!$D$4:$D$71,0))} -> Metadata | E11: =INDEX('Not Req'!$F$4:$F$71,MATCH(MID(F11,FIND(".",F11)+1,LEN(F11)-FIND(".",F11)+1),'Not Req'!$D$4:$D$71,0)) -> 4. CDS | F11: zcjs_c_cre_upld.ddlx.asddlxs | G11: UPDATED ON 02-FEB-26 | H11: 3 months ago | N11: zbp_cjs_c_cre_upld
B12: OK | C12: =LEFT(F12,FIND(".",F12)-1) -> zcjs_r_cre_upld | D12: {=INDEX('Not Req'!$E$4:$E$71,MATCH(MID(F12,FIND(".",F12)+1,LEN(F12)-FIND(".",F12)+1),'Not Req'!$D$4:$D$71,0))} -> BDEF | E12: =INDEX('Not Req'!$F$4:$F$71,MATCH(MID(F12,FIND(".",F12)+1,LEN(F12)-FIND(".",F12)+1),'Not Req'!$D$4:$D$71,0)) -> 4. CDS | F12: zcjs_r_cre_upld.bdef.asbdef | G12: UPDATED ON 02-FEB-26 | H12: 3 months ago | N12: zbp_r_cre_upld
B13: OK | C13: =LEFT(F13,FIND(".",F13)-1) -> zcjs_r_cre_upld | D13: {=INDEX('Not Req'!$E$4:$E$71,MATCH(MID(F13,FIND(".",F13)+1,LEN(F13)-FIND(".",F13)+1),'Not Req'!$D$4:$D$71,0))} -> Data Definition | E13: =INDEX('Not Req'!$F$4:$F$71,MATCH(MID(F13,FIND(".",F13)+1,LEN(F13)-FIND(".",F13)+1),'Not Req'!$D$4:$D$71,0)) -> 4. CDS | F13: zcjs_r_cre_upld.ddls.asddls | G13: UPDATED ON 02-FEB-26 | H13: 3 months ago | N13: zjs_db_master_data
B14: OK | C14: =LEFT(F14,FIND(".",F14)-1) -> zbp_cjs_c_cre_upld | D14: {=INDEX('Not Req'!$E$4:$E$71,MATCH(MID(F14,FIND(".",F14)+1,LEN(F14)-FIND(".",F14)+1),'Not Req'!$D$4:$D$71,0))} -> Classes | E14: =INDEX('Not Req'!$F$4:$F$71,MATCH(MID(F14,FIND(".",F14)+1,LEN(F14)-FIND(".",F14)+1),'Not Req'!$D$4:$D$71,0)) -> 7. Source Code Library | F14: zbp_cjs_c_cre_upld.clas.abap | G14: UPDATED ON 02-FEB-26 | H14: 3 months ago | N14: zjs_api_cre_upld_v4
B15: OK | C15: =LEFT(F15,FIND(".",F15)-1) -> zbp_r_cre_upld | D15: {=INDEX('Not Req'!$E$4:$E$71,MATCH(MID(F15,FIND(".",F15)+1,LEN(F15)-FIND(".",F15)+1),'Not Req'!$D$4:$D$71,0))} -> Classes | E15: =INDEX('Not Req'!$F$4:$F$71,MATCH(MID(F15,FIND(".",F15)+1,LEN(F15)-FIND(".",F15)+1),'Not Req'!$D$4:$D$71,0)) -> 7. Source Code Library | F15: zbp_r_cre_upld.clas.abap | G15: UPDATED ON 02-FEB-26 | H15: 3 months ago | N15: zui_cre_upld_o4
B16: OK | C16: =LEFT(F16,FIND(".",F16)-1) -> zbp_r_cre_upld | D16: {=INDEX('Not Req'!$E$4:$E$71,MATCH(MID(F16,FIND(".",F16)+1,LEN(F16)-FIND(".",F16)+1),'Not Req'!$D$4:$D$71,0))} -> Classes Local | E16: =INDEX('Not Req'!$F$4:$F$71,MATCH(MID(F16,FIND(".",F16)+1,LEN(F16)-FIND(".",F16)+1),'Not Req'!$D$4:$D$71,0)) -> 7. Source Code Library | F16: zbp_r_cre_upld.clas.locals_imp.abap | G16: UPDATED ON 02-FEB-26 | H16: 3 months ago | N16: zjs_api_cre_upld_v4_0001_g4ba
B17: OK | C17: =LEFT(F17,FIND(".",F17)-1) -> zjs_db_master_data | D17: {=INDEX('Not Req'!$E$4:$E$71,MATCH(MID(F17,FIND(".",F17)+1,LEN(F17)-FIND(".",F17)+1),'Not Req'!$D$4:$D$71,0))} -> Classes | E17: =INDEX('Not Req'!$F$4:$F$71,MATCH(MID(F17,FIND(".",F17)+1,LEN(F17)-FIND(".",F17)+1),'Not Req'!$D$4:$D$71,0)) -> 7. Source Code Library | F17: zjs_db_master_data.clas.abap | G17: Updated 16-Mar-26 | H17: 2 months ago
B18: OK | C18: =LEFT(F18,FIND(".",F18)-1) -> zjs_api_cre_upld_v4 | D18: {=INDEX('Not Req'!$E$4:$E$71,MATCH(MID(F18,FIND(".",F18)+1,LEN(F18)-FIND(".",F18)+1),'Not Req'!$D$4:$D$71,0))} -> Service Binding | E18: =INDEX('Not Req'!$F$4:$F$71,MATCH(MID(F18,FIND(".",F18)+1,LEN(F18)-FIND(".",F18)+1),'Not Req'!$D$4:$D$71,0)) -> 2. Business Services | F18: zjs_api_cre_upld_v4.srvb.xml | G18: UPDATED ON 02-FEB-26 | H18: 3 months ago
B19: OK | C19: =LEFT(F19,FIND(".",F19)-1) -> zui_cre_upld_o4 | D19: {=INDEX('Not Req'!$E$4:$E$71,MATCH(MID(F19,FIND(".",F19)+1,LEN(F19)-FIND(".",F19)+1),'Not Req'!$D$4:$D$71,0))} -> Service Binding | E19: =INDEX('Not Req'!$F$4:$F$71,MATCH(MID(F19,FIND(".",F19)+1,LEN(F19)-FIND(".",F19)+1),'Not Req'!$D$4:$D$71,0)) -> 2. Business Services | F19: zui_cre_upld_o4.srvb.xml | G19: UPDATED ON 02-FEB-26 | H19: 3 months ago
B20: OK | C20: =LEFT(F20,FIND(".",F20)-1) -> zui_cre_upld_o4 | D20: {=INDEX('Not Req'!$E$4:$E$71,MATCH(MID(F20,FIND(".",F20)+1,LEN(F20)-FIND(".",F20)+1),'Not Req'!$D$4:$D$71,0))} -> Service Definition | E20: =INDEX('Not Req'!$F$4:$F$71,MATCH(MID(F20,FIND(".",F20)+1,LEN(F20)-FIND(".",F20)+1),'Not Req'!$D$4:$D$71,0)) -> 2. Business Services | F20: zui_cre_upld_o4.srvd.srvdsrv | G20: UPDATED ON 02-FEB-26 | H20: 3 months ago
B21: OK | C21: =LEFT(F21,FIND(".",F21)-1) -> zjs_api_cre_upld_v4_0001_g4ba | D21: {=INDEX('Not Req'!$E$4:$E$71,MATCH(MID(F21,FIND(".",F21)+1,LEN(F21)-FIND(".",F21)+1),'Not Req'!$D$4:$D$71,0))} -> Inbound Service | E21: =INDEX('Not Req'!$F$4:$F$71,MATCH(MID(F21,FIND(".",F21)+1,LEN(F21)-FIND(".",F21)+1),'Not Req'!$D$4:$D$71,0)) -> 3. Cloud Communication Management | F21: zjs_api_cre_upld_v4_0001_g4ba.sco2.xml | G21: UPDATED ON 02-FEB-26 | H21: 3 months ago
B22: OK | C22: =LEFT(F22,FIND(".",F22)-1) -> zui_cre_upld_o4_0001_g4ba | D22: {=INDEX('Not Req'!$E$4:$E$71,MATCH(MID(F22,FIND(".",F22)+1,LEN(F22)-FIND(".",F22)+1),'Not Req'!$D$4:$D$71,0))} -> Inbound Service | E22: =INDEX('Not Req'!$F$4:$F$71,MATCH(MID(F22,FIND(".",F22)+1,LEN(F22)-FIND(".",F22)+1),'Not Req'!$D$4:$D$71,0)) -> 3. Cloud Communication Management | F22: zui_cre_upld_o4_0001_g4ba.sco2.xml | G22: UPDATED ON 02-FEB-26 | H22: 3 months ago
B23: OK | C23: =LEFT(F23,FIND(".",F23)-1) -> 117515a7a870646dee4f758989a02cht | D23: {=INDEX('Not Req'!$E$4:$E$71,MATCH(MID(F23,FIND(".",F23)+1,LEN(F23)-FIND(".",F23)+1),'Not Req'!$D$4:$D$71,0))} -> Authorization Defaults (TADIR) | E23: =INDEX('Not Req'!$F$4:$F$71,MATCH(MID(F23,FIND(".",F23)+1,LEN(F23)-FIND(".",F23)+1),'Not Req'!$D$4:$D$71,0)) -> 1. Authorizations | F23: 117515a7a870646dee4f758989a02cht.sush.xml | G23: UPDATED ON 02-FEB-26 | H23: 3 months ago
B24: OK | C24: =LEFT(F24,FIND(".",F24)-1) -> a130cd232681fd3437349554e56dd7ht | D24: {=INDEX('Not Req'!$E$4:$E$71,MATCH(MID(F24,FIND(".",F24)+1,LEN(F24)-FIND(".",F24)+1),'Not Req'!$D$4:$D$71,0))} -> Authorization Defaults (TADIR) | E24: =INDEX('Not Req'!$F$4:$F$71,MATCH(MID(F24,FIND(".",F24)+1,LEN(F24)-FIND(".",F24)+1),'Not Req'!$D$4:$D$71,0)) -> 1. Authorizations | F24: a130cd232681fd3437349554e56dd7ht.sush.xml | G24: UPDATED ON 02-FEB-26 | H24: 3 months ago
B25: OK | C25: =LEFT(F25,FIND(".",F25)-1) -> zbp_cjs_c_cre_upld | D25: {=INDEX('Not Req'!$E$4:$E$71,MATCH(MID(F25,FIND(".",F25)+1,LEN(F25)-FIND(".",F25)+1),'Not Req'!$D$4:$D$71,0))} -> Description : Classes | E25: =INDEX('Not Req'!$F$4:$F$71,MATCH(MID(F25,FIND(".",F25)+1,LEN(F25)-FIND(".",F25)+1),'Not Req'!$D$4:$D$71,0)) -> 99. Descriptions | F25: zbp_cjs_c_cre_upld.clas.xml | G25: UPDATED ON 02-FEB-26 | H25: 3 months ago
B26: OK | C26: =LEFT(F26,FIND(".",F26)-1) -> zbp_r_cre_upld | D26: {=INDEX('Not Req'!$E$4:$E$71,MATCH(MID(F26,FIND(".",F26)+1,LEN(F26)-FIND(".",F26)+1),'Not Req'!$D$4:$D$71,0))} -> Description : Classes | E26: =INDEX('Not Req'!$F$4:$F$71,MATCH(MID(F26,FIND(".",F26)+1,LEN(F26)-FIND(".",F26)+1),'Not Req'!$D$4:$D$71,0)) -> 99. Descriptions | F26: zbp_r_cre_upld.clas.xml | G26: UPDATED ON 02-FEB-26 | H26: 3 months ago
B27: OK | C27: =LEFT(F27,FIND(".",F27)-1) -> zcjs_c_cre_upld | D27: {=INDEX('Not Req'!$E$4:$E$71,MATCH(MID(F27,FIND(".",F27)+1,LEN(F27)-FIND(".",F27)+1),'Not Req'!$D$4:$D$71,0))} -> Description : BDEF | E27: =INDEX('Not Req'!$F$4:$F$71,MATCH(MID(F27,FIND(".",F27)+1,LEN(F27)-FIND(".",F27)+1),'Not Req'!$D$4:$D$71,0)) -> 99. Descriptions | F27: zcjs_c_cre_upld.bdef.xml | G27: UPDATED ON 02-FEB-26 | H27: 3 months ago
B28: OK | C28: =LEFT(F28,FIND(".",F28)-1) -> zcjs_c_cre_upld | D28: {=INDEX('Not Req'!$E$4:$E$71,MATCH(MID(F28,FIND(".",F28)+1,LEN(F28)-FIND(".",F28)+1),'Not Req'!$D$4:$D$71,0))} -> BaseInfo : Data Definition | E28: =INDEX('Not Req'!$F$4:$F$71,MATCH(MID(F28,FIND(".",F28)+1,LEN(F28)-FIND(".",F28)+1),'Not Req'!$D$4:$D$71,0)) -> 98. Base Info | F28: zcjs_c_cre_upld.ddls.baseinfo | G28: UPDATED ON 02-FEB-26 | H28: 3 months ago
... B34: OK | C34: =LEFT(F34,FIND(".",F34)-1) -> zjs_db_master_data | D34: {=INDEX('Not Req'!$E$4:$E$71,MATCH(MID(F34,FIND(".",F34)+1,LEN(F34)-FIND(".",F34)+1),'Not Req'!$D$4:$D$71,0))} -> Description : Classes | E34: =INDEX('Not Req'!$F$4:$F$71,MATCH(MID(F34,FIND(".",F34)+1,LEN(F34)-FIND(".",F34)+1),'Not Req'!$D$4:$D$71,0)) -> 99. Descriptions | F34: zjs_db_master_data.clas.xml | G34: Updated 16-Mar-26 | H34: 2 months ago
A35: D | B35: OK | C35: =LEFT(F35,FIND(".",F35)-1) -> zui_cre_upld_o4 | D35: {=INDEX('Not Req'!$E$4:$E$71,MATCH(MID(F35,FIND(".",F35)+1,LEN(F35)-FIND(".",F35)+1),'Not Req'!$D$4:$D$71,0))} -> Description : Service Definition | E35: =INDEX('Not Req'!$F$4:$F$71,MATCH(MID(F35,FIND(".",F35)+1,LEN(F35)-FIND(".",F35)+1),'Not Req'!$D$4:$D$71,0)) -> 99. Descriptions | F35: zui_cre_upld_o4.srvd.xml | G35: UPDATED ON 02-FEB-26 | H35: 3 months ago

Sheet Change Status Reques (2)
B2: d | C2: Object | D2: Type | E2: Category | F2: Github Object | G2: Github Type | H2: Version
B4: OK | C4: =LEFT(F4,FIND(".",F4)-1) -> package | D4: {=INDEX('Not Req'!$E$4:$E$71,MATCH(MID(F4,FIND(".",F4)+1,LEN(F4)-FIND(".",F4)+1),'Not Req'!$D$4:$D$71,0))} -> Description : Package | E4: =INDEX('Not Req'!$F$4:$F$71,MATCH(MID(F4,FIND(".",F4)+1,LEN(F4)-FIND(".",F4)+1),'Not Req'!$D$4:$D$71,0)) -> 99. Descriptions | F4: package.devc.xml | G4: UPDATED ON 02-FEB-26 | H4: 3 months ago | N4: {=_xlfn.UNIQUE(C4:C21)} -> package
B5: OK | C5: =LEFT(F5,FIND(".",F5)-1) -> zdjs_d_items | D5: {=INDEX('Not Req'!$E$4:$E$71,MATCH(MID(F5,FIND(".",F5)+1,LEN(F5)-FIND(".",F5)+1),'Not Req'!$D$4:$D$71,0))} -> Table | E5: =INDEX('Not Req'!$F$4:$F$71,MATCH(MID(F5,FIND(".",F5)+1,LEN(F5)-FIND(".",F5)+1),'Not Req'!$D$4:$D$71,0)) -> 5. Dictionary | F5: zdjs_d_items.tabl.xml | G5: UPDATED ON 02-FEB-26 | H5: 3 months ago | N5: zdjs_d_items
B6: OK | C6: =LEFT(F6,FIND(".",F6)-1) -> zdjs_d_items2 | D6: {=INDEX('Not Req'!$E$4:$E$71,MATCH(MID(F6,FIND(".",F6)+1,LEN(F6)-FIND(".",F6)+1),'Not Req'!$D$4:$D$71,0))} -> Table | E6: =INDEX('Not Req'!$F$4:$F$71,MATCH(MID(F6,FIND(".",F6)+1,LEN(F6)-FIND(".",F6)+1),'Not Req'!$D$4:$D$71,0)) -> 5. Dictionary | F6: zdjs_d_items2.tabl.xml | G6: UPDATED ON 02-FEB-26 | H6: 3 months ago | N6: zdjs_d_items2
B7: OK | C7: =LEFT(F7,FIND(".",F7)-1) -> zdjs_items2 | D7: {=INDEX('Not Req'!$E$4:$E$71,MATCH(MID(F7,FIND(".",F7)+1,LEN(F7)-FIND(".",F7)+1),'Not Req'!$D$4:$D$71,0))} -> Table | E7: =INDEX('Not Req'!$F$4:$F$71,MATCH(MID(F7,FIND(".",F7)+1,LEN(F7)-FIND(".",F7)+1),'Not Req'!$D$4:$D$71,0)) -> 5. Dictionary | F7: zdjs_items2.tabl.xml | G7: UPDATED ON 02-FEB-26 | H7: 3 months ago | N7: zdjs_items2
B8: OK | C8: =LEFT(F8,FIND(".",F8)-1) -> zdse_d_invoice | D8: {=INDEX('Not Req'!$E$4:$E$71,MATCH(MID(F8,FIND(".",F8)+1,LEN(F8)-FIND(".",F8)+1),'Not Req'!$D$4:$D$71,0))} -> Table | E8: =INDEX('Not Req'!$F$4:$F$71,MATCH(MID(F8,FIND(".",F8)+1,LEN(F8)-FIND(".",F8)+1),'Not Req'!$D$4:$D$71,0)) -> 5. Dictionary | F8: zdse_d_invoice.tabl.xml | G8: UPDATED ON 02-FEB-26 | H8: 3 months ago | N8: zdse_d_invoice
B9: OK | C9: =LEFT(F9,FIND(".",F9)-1) -> zdse_invoice | D9: {=INDEX('Not Req'!$E$4:$E$71,MATCH(MID(F9,FIND(".",F9)+1,LEN(F9)-FIND(".",F9)+1),'Not Req'!$D$4:$D$71,0))} -> Table | E9: =INDEX('Not Req'!$F$4:$F$71,MATCH(MID(F9,FIND(".",F9)+1,LEN(F9)-FIND(".",F9)+1),'Not Req'!$D$4:$D$71,0)) -> 5. Dictionary | F9: zdse_invoice.tabl.xml | G9: UPDATED ON 02-FEB-26 | H9: 3 months ago | N9: zdse_invoice
B10: OK | C10: =LEFT(F10,FIND(".",F10)-1) -> zmse_c_rapcinvoice | D10: {=INDEX('Not Req'!$E$4:$E$71,MATCH(MID(F10,FIND(".",F10)+1,LEN(F10)-FIND(".",F10)+1),'Not Req'!$D$4:$D$71,0))} -> Metadata | E10: =INDEX('Not Req'!$F$4:$F$71,MATCH(MID(F10,FIND(".",F10)+1,LEN(F10)-FIND(".",F10)+1),'Not Req'!$D$4:$D$71,0)) -> 4. CDS | F10: zmse_c_rapcinvoice.ddlx.asddlxs | G10: UPDATED ON 02-FEB-26 | H10: 3 months ago | N10: zmse_c_rapcinvoice
B11: OK | C11: =LEFT(F11,FIND(".",F11)-1) -> zmse_c_rapcitems | D11: {=INDEX('Not Req'!$E$4:$E$71,MATCH(MID(F11,FIND(".",F11)+1,LEN(F11)-FIND(".",F11)+1),'Not Req'!$D$4:$D$71,0))} -> Metadata | E11: =INDEX('Not Req'!$F$4:$F$71,MATCH(MID(F11,FIND(".",F11)+1,LEN(F11)-FIND(".",F11)+1),'Not Req'!$D$4:$D$71,0)) -> 4. CDS | F11: zmse_c_rapcitems.ddlx.asddlxs | G11: UPDATED ON 02-FEB-26 | H11: 3 months ago | N11: zmse_c_rapcitems
B12: OK | C12: =LEFT(F12,FIND(".",F12)-1) -> zmse_c_rapcitems2 | D12: {=INDEX('Not Req'!$E$4:$E$71,MATCH(MID(F12,FIND(".",F12)+1,LEN(F12)-FIND(".",F12)+1),'Not Req'!$D$4:$D$71,0))} -> Metadata | E12: =INDEX('Not Req'!$F$4:$F$71,MATCH(MID(F12,FIND(".",F12)+1,LEN(F12)-FIND(".",F12)+1),'Not Req'!$D$4:$D$71,0)) -> 4. CDS | F12: zmse_c_rapcitems2.ddlx.asddlxs | G12: UPDATED ON 02-FEB-26 | H12: 3 months ago | N12: zmse_c_rapcitems2
B13: OK | C13: =LEFT(F13,FIND(".",F13)-1) -> zse_c_rapcinvoice | D13: {=INDEX('Not Req'!$E$4:$E$71,MATCH(MID(F13,FIND(".",F13)+1,LEN(F13)-FIND(".",F13)+1),'Not Req'!$D$4:$D$71,0))} -> BDEF | E13: =INDEX('Not Req'!$F$4:$F$71,MATCH(MID(F13,FIND(".",F13)+1,LEN(F13)-FIND(".",F13)+1),'Not Req'!$D$4:$D$71,0)) -> 4. CDS | F13: zse_c_rapcinvoice.bdef.asbdef | G13: UPDATED ON 02-FEB-26 | H13: 3 months ago | N13: zse_c_rapcinvoice
B14: OK | C14: =LEFT(F14,FIND(".",F14)-1) -> zse_c_rapcinvoice | D14: {=INDEX('Not Req'!$E$4:$E$71,MATCH(MID(F14,FIND(".",F14)+1,LEN(F14)-FIND(".",F14)+1),'Not Req'!$D$4:$D$71,0))} -> Data Definition | E14: =INDEX('Not Req'!$F$4:$F$71,MATCH(MID(F14,FIND(".",F14)+1,LEN(F14)-FIND(".",F14)+1),'Not Req'!$D$4:$D$71,0)) -> 4. CDS | F14: zse_c_rapcinvoice.ddls.asddls | G14: UPDATED ON 02-FEB-26 | H14: 3 months ago | N14: zse_c_rapcitems
B15: OK | C15: =LEFT(F15,FIND(".",F15)-1) -> zse_c_rapcitems | D15: {=INDEX('Not Req'!$E$4:$E$71,MATCH(MID(F15,FIND(".",F15)+1,LEN(F15)-FIND(".",F15)+1),'Not Req'!$D$4:$D$71,0))} -> Data Definition | E15: =INDEX('Not Req'!$F$4:$F$71,MATCH(MID(F15,FIND(".",F15)+1,LEN(F15)-FIND(".",F15)+1),'Not Req'!$D$4:$D$71,0)) -> 4. CDS | F15: zse_c_rapcitems.ddls.asddls | G15: UPDATED ON 02-FEB-26 | H15: 3 months ago | N15: zse_c_rapcitems2
B16: OK | C16: =LEFT(F16,FIND(".",F16)-1) -> zse_c_rapcitems2 | D16: {=INDEX('Not Req'!$E$4:$E$71,MATCH(MID(F16,FIND(".",F16)+1,LEN(F16)-FIND(".",F16)+1),'Not Req'!$D$4:$D$71,0))} -> Data Definition | E16: =INDEX('Not Req'!$F$4:$F$71,MATCH(MID(F16,FIND(".",F16)+1,LEN(F16)-FIND(".",F16)+1),'Not Req'!$D$4:$D$71,0)) -> 4. CDS | F16: zse_c_rapcitems2.ddls.asddls | G16: UPDATED ON 02-FEB-26 | H16: 3 months ago | N16: zse_i_rapcinvoice
... B19: OK | C19: =LEFT(F19,FIND(".",F19)-1) -> zse_i_rapcitems | D19: {=INDEX('Not Req'!$E$4:$E$71,MATCH(MID(F19,FIND(".",F19)+1,LEN(F19)-FIND(".",F19)+1),'Not Req'!$D$4:$D$71,0))} -> Data Definition | E19: =INDEX('Not Req'!$F$4:$F$71,MATCH(MID(F19,FIND(".",F19)+1,LEN(F19)-FIND(".",F19)+1),'Not Req'!$D$4:$D$71,0)) -> 4. CDS | F19: zse_i_rapcitems.ddls.asddls | G19: UPDATED ON 02-FEB-26 | H19: 3 months ago | N19: zse_i_rapcmaterial
B20: OK | C20: =LEFT(F20,FIND(".",F20)-1) -> zse_i_rapcitems2 | D20: {=INDEX('Not Req'!$E$4:$E$71,MATCH(MID(F20,FIND(".",F20)+1,LEN(F20)-FIND(".",F20)+1),'Not Req'!$D$4:$D$71,0))} -> Data Definition | E20: =INDEX('Not Req'!$F$4:$F$71,MATCH(MID(F20,FIND(".",F20)+1,LEN(F20)-FIND(".",F20)+1),'Not Req'!$D$4:$D$71,0)) -> 4. CDS | F20: zse_i_rapcitems2.ddls.asddls | G20: UPDATED ON 02-FEB-26 | H20: 3 months ago
B21: OK | C21: =LEFT(F21,FIND(".",F21)-1) -> zse_i_rapcmaterial | D21: {=INDEX('Not Req'!$E$4:$E$71,MATCH(MID(F21,FIND(".",F21)+1,LEN(F21)-FIND(".",F21)+1),'Not Req'!$D$4:$D$71,0))} -> Data Definition | E21: =INDEX('Not Req'!$F$4:$F$71,MATCH(MID(F21,FIND(".",F21)+1,LEN(F21)-FIND(".",F21)+1),'Not Req'!$D$4:$D$71,0)) -> 4. CDS | F21: zse_i_rapcmaterial.ddls.asddls | G21: UPDATED ON 02-FEB-26 | H21: 3 months ago
B22: OK | C22: =LEFT(F22,FIND(".",F22)-1) -> zse_s_rapcreate_items | D22: {=INDEX('Not Req'!$E$4:$E$71,MATCH(MID(F22,FIND(".",F22)+1,LEN(F22)-FIND(".",F22)+1),'Not Req'!$D$4:$D$71,0))} -> Data Definition | E22: =INDEX('Not Req'!$F$4:$F$71,MATCH(MID(F22,FIND(".",F22)+1,LEN(F22)-FIND(".",F22)+1),'Not Req'!$D$4:$D$71,0)) -> 4. CDS | F22: zse_s_rapcreate_items.ddls.asddls | G22: UPDATED ON 02-FEB-26 | H22: 3 months ago
B23: OK | C23: =LEFT(F23,FIND(".",F23)-1) -> zse_s_rapcreateinvoice | D23: {=INDEX('Not Req'!$E$4:$E$71,MATCH(MID(F23,FIND(".",F23)+1,LEN(F23)-FIND(".",F23)+1),'Not Req'!$D$4:$D$71,0))} -> BDEF | E23: =INDEX('Not Req'!$F$4:$F$71,MATCH(MID(F23,FIND(".",F23)+1,LEN(F23)-FIND(".",F23)+1),'Not Req'!$D$4:$D$71,0)) -> 4. CDS | F23: zse_s_rapcreateinvoice.bdef.asbdef | G23: UPDATED ON 02-FEB-26 | H23: 3 months ago
B24: OK | C24: =LEFT(F24,FIND(".",F24)-1) -> zse_s_rapcreateinvoice | D24: {=INDEX('Not Req'!$E$4:$E$71,MATCH(MID(F24,FIND(".",F24)+1,LEN(F24)-FIND(".",F24)+1),'Not Req'!$D$4:$D$71,0))} -> Data Definition | E24: =INDEX('Not Req'!$F$4:$F$71,MATCH(MID(F24,FIND(".",F24)+1,LEN(F24)-FIND(".",F24)+1),'Not Req'!$D$4:$D$71,0)) -> 4. CDS | F24: zse_s_rapcreateinvoice.ddls.asddls | G24: UPDATED ON 02-FEB-26 | H24: 3 months ago
B25: OK | C25: =LEFT(F25,FIND(".",F25)-1) -> zbp_se_i_rapcinvoice | D25: {=INDEX('Not Req'!$E$4:$E$71,MATCH(MID(F25,FIND(".",F25)+1,LEN(F25)-FIND(".",F25)+1),'Not Req'!$D$4:$D$71,0))} -> Classes | E25: =INDEX('Not Req'!$F$4:$F$71,MATCH(MID(F25,FIND(".",F25)+1,LEN(F25)-FIND(".",F25)+1),'Not Req'!$D$4:$D$71,0)) -> 7. Source Code Library | F25: zbp_se_i_rapcinvoice.clas.abap | G25: UPDATED ON 02-FEB-26 | H25: 3 months ago
B26: OK | C26: =LEFT(F26,FIND(".",F26)-1) -> zbp_se_i_rapcinvoice | D26: {=INDEX('Not Req'!$E$4:$E$71,MATCH(MID(F26,FIND(".",F26)+1,LEN(F26)-FIND(".",F26)+1),'Not Req'!$D$4:$D$71,0))} -> Classes Local | E26: =INDEX('Not Req'!$F$4:$F$71,MATCH(MID(F26,FIND(".",F26)+1,LEN(F26)-FIND(".",F26)+1),'Not Req'!$D$4:$D$71,0)) -> 7. Source Code Library | F26: zbp_se_i_rapcinvoice.clas.locals_imp.abap | G26: UPDATED ON 02-FEB-26 | H26: 3 months ago
B27: OK | C27: =LEFT(F27,FIND(".",F27)-1) -> zcl_js_eml_deep_action | D27: {=INDEX('Not Req'!$E$4:$E$71,MATCH(MID(F27,FIND(".",F27)+1,LEN(F27)-FIND(".",F27)+1),'Not Req'!$D$4:$D$71,0))} -> Classes | E27: =INDEX('Not Req'!$F$4:$F$71,MATCH(MID(F27,FIND(".",F27)+1,LEN(F27)-FIND(".",F27)+1),'Not Req'!$D$4:$D$71,0)) -> 7. Source Code Library | F27: zcl_js_eml_deep_action.clas.abap | G27: Updated 16-Mar-26 | H27: 2 months ago
B28: OK | C28: =LEFT(F28,FIND(".",F28)-1) -> zcljs_virtual_invoice_se | D28: {=INDEX('Not Req'!$E$4:$E$71,MATCH(MID(F28,FIND(".",F28)+1,LEN(F28)-FIND(".",F28)+1),'Not Req'!$D$4:$D$71,0))} -> Classes | E28: =INDEX('Not Req'!$F$4:$F$71,MATCH(MID(F28,FIND(".",F28)+1,LEN(F28)-FIND(".",F28)+1),'Not Req'!$D$4:$D$71,0)) -> 7. Source Code Library | F28: zcljs_virtual_invoice_se.clas.abap | G28: UPDATED ON 02-FEB-26 | H28: 3 months ago
B29: OK | C29: =LEFT(F29,FIND(".",F29)-1) -> zse_complex_entity | D29: {=INDEX('Not Req'!$E$4:$E$71,MATCH(MID(F29,FIND(".",F29)+1,LEN(F29)-FIND(".",F29)+1),'Not Req'!$D$4:$D$71,0))} -> Service Definition | E29: =INDEX('Not Req'!$F$4:$F$71,MATCH(MID(F29,FIND(".",F29)+1,LEN(F29)-FIND(".",F29)+1),'Not Req'!$D$4:$D$71,0)) -> 2. Business Services | F29: zse_complex_entity.srvd.srvdsrv | G29: UPDATED ON 02-FEB-26 | H29: 3 months ago
B30: OK | C30: =LEFT(F30,FIND(".",F30)-1) -> zse_complex_entity_v4 | D30: {=INDEX('Not Req'!$E$4:$E$71,MATCH(MID(F30,FIND(".",F30)+1,LEN(F30)-FIND(".",F30)+1),'Not Req'!$D$4:$D$71,0))} -> Service Binding | E30: =INDEX('Not Req'!$F$4:$F$71,MATCH(MID(F30,FIND(".",F30)+1,LEN(F30)-FIND(".",F30)+1),'Not Req'!$D$4:$D$71,0)) -> 2. Business Services | F30: zse_complex_entity_v4.srvb.xml | G30: UPDATED ON 02-FEB-26 | H30: 3 months ago
C31: =LEFT(F31,FIND(".",F31)-1) -> 9c760cf4b81f6b69bf1e92c1336a71ht | D31: {=INDEX('Not Req'!$E$4:$E$71,MATCH(MID(F31,FIND(".",F31)+1,LEN(F31)-FIND(".",F31)+1),'Not Req'!$D$4:$D$71,0))} -> Authorization Defaults (TADIR) | E31: =INDEX('Not Req'!$F$4:$F$71,MATCH(MID(F31,FIND(".",F31)+1,LEN(F31)-FIND(".",F31)+1),'Not Req'!$D$4:$D$71,0)) -> 1. Authorizations | F31: 9c760cf4b81f6b69bf1e92c1336a71ht.sush.xml | G31: UPDATED ON 02-FEB-26 | H31: 3 months ago
C32: =LEFT(F32,FIND(".",F32)-1) -> zbp_se_i_rapcinvoice | D32: {=INDEX('Not Req'!$E$4:$E$71,MATCH(MID(F32,FIND(".",F32)+1,LEN(F32)-FIND(".",F32)+1),'Not Req'!$D$4:$D$71,0))} -> Description : Classes | E32: =INDEX('Not Req'!$F$4:$F$71,MATCH(MID(F32,FIND(".",F32)+1,LEN(F32)-FIND(".",F32)+1),'Not Req'!$D$4:$D$71,0)) -> 99. Descriptions | F32: zbp_se_i_rapcinvoice.clas.xml | G32: UPDATED ON 02-FEB-26 | H32: 3 months ago
C33: =LEFT(F33,FIND(".",F33)-1) -> zcl_js_eml_deep_action | D33: {=INDEX('Not Req'!$E$4:$E$71,MATCH(MID(F33,FIND(".",F33)+1,LEN(F33)-FIND(".",F33)+1),'Not Req'!$D$4:$D$71,0))} -> Description : Classes | E33: =INDEX('Not Req'!$F$4:$F$71,MATCH(MID(F33,FIND(".",F33)+1,LEN(F33)-FIND(".",F33)+1),'Not Req'!$D$4:$D$71,0)) -> 99. Descriptions | F33: zcl_js_eml_deep_action.clas.xml | G33: UPDATED ON 02-FEB-26 | H33: 3 months ago
C34: =LEFT(F34,FIND(".",F34)-1) -> zcljs_virtual_invoice_se | D34: {=INDEX('Not Req'!$E$4:$E$71,MATCH(MID(F34,FIND(".",F34)+1,LEN(F34)-FIND(".",F34)+1),'Not Req'!$D$4:$D$71,0))} -> Description : Classes | E34: =INDEX('Not Req'!$F$4:$F$71,MATCH(MID(F34,FIND(".",F34)+1,LEN(F34)-FIND(".",F34)+1),'Not Req'!$D$4:$D$71,0)) -> 99. Descriptions | F34: zcljs_virtual_invoice_se.clas.xml | G34: UPDATED ON 02-FEB-26 | H34: 3 months ago
C35: =LEFT(F35,FIND(".",F35)-1) -> zmse_c_rapcinvoice | D35: {=INDEX('Not Req'!$E$4:$E$71,MATCH(MID(F35,FIND(".",F35)+1,LEN(F35)-FIND(".",F35)+1),'Not Req'!$D$4:$D$71,0))} -> Description : Metadata | E35: =INDEX('Not Req'!$F$4:$F$71,MATCH(MID(F35,FIND(".",F35)+1,LEN(F35)-FIND(".",F35)+1),'Not Req'!$D$4:$D$71,0)) -> 99. Descriptions | F35: zmse_c_rapcinvoice.ddlx.xml | G35: UPDATED ON 02-FEB-26 | H35: 3 months ago
C36: =LEFT(F36,FIND(".",F36)-1) -> zmse_c_rapcitems | D36: {=INDEX('Not Req'!$E$4:$E$71,MATCH(MID(F36,FIND(".",F36)+1,LEN(F36)-FIND(".",F36)+1),'Not Req'!$D$4:$D$71,0))} -> Description : Metadata | E36: =INDEX('Not Req'!$F$4:$F$71,MATCH(MID(F36,FIND(".",F36)+1,LEN(F36)-FIND(".",F36)+1),'Not Req'!$D$4:$D$71,0)) -> 99. Descriptions | F36: zmse_c_rapcitems.ddlx.xml | G36: UPDATED ON 02-FEB-26 | H36: 3 months ago
C37: =LEFT(F37,FIND(".",F37)-1) -> zmse_c_rapcitems2 | D37: {=INDEX('Not Req'!$E$4:$E$71,MATCH(MID(F37,FIND(".",F37)+1,LEN(F37)-FIND(".",F37)+1),'Not Req'!$D$4:$D$71,0))} -> Description : Metadata | E37: =INDEX('Not Req'!$F$4:$F$71,MATCH(MID(F37,FIND(".",F37)+1,LEN(F37)-FIND(".",F37)+1),'Not Req'!$D$4:$D$71,0)) -> 99. Descriptions | F37: zmse_c_rapcitems2.ddlx.xml | G37: UPDATED ON 02-FEB-26 | H37: 3 months ago
C38: =LEFT(F38,FIND(".",F38)-1) -> zse_c_rapcinvoice | D38: {=INDEX('Not Req'!$E$4:$E$71,MATCH(MID(F38,FIND(".",F38)+1,LEN(F38)-FIND(".",F38)+1),'Not Req'!$D$4:$D$71,0))} -> Description : BDEF | E38: =INDEX('Not Req'!$F$4:$F$71,MATCH(MID(F38,FIND(".",F38)+1,LEN(F38)-FIND(".",F38)+1),'Not Req'!$D$4:$D$71,0)) -> 99. Descriptions | F38: zse_c_rapcinvoice.bdef.xml | G38: UPDATED ON 02-FEB-26 | H38: 3 months ago
C39: =LEFT(F39,FIND(".",F39)-1) -> zse_c_rapcinvoice | D39: {=INDEX('Not Req'!$E$4:$E$71,MATCH(MID(F39,FIND(".",F39)+1,LEN(F39)-FIND(".",F39)+1),'Not Req'!$D$4:$D$71,0))} -> BaseInfo : Data Definition | E39: =INDEX('Not Req'!$F$4:$F$71,MATCH(MID(F39,FIND(".",F39)+1,LEN(F39)-FIND(".",F39)+1),'Not Req'!$D$4:$D$71,0)) -> 98. Base Info | F39: zse_c_rapcinvoice.ddls.baseinfo | G39: UPDATED ON 02-FEB-26 | H39: 3 months ago
C40: =LEFT(F40,FIND(".",F40)-1) -> zse_c_rapcinvoice | D40: {=INDEX('Not Req'!$E$4:$E$71,MATCH(MID(F40,FIND(".",F40)+1,LEN(F40)-FIND(".",F40)+1),'Not Req'!$D$4:$D$71,0))} -> Description : Data Definition | E40: =INDEX('Not Req'!$F$4:$F$71,MATCH(MID(F40,FIND(".",F40)+1,LEN(F40)-FIND(".",F40)+1),'Not Req'!$D$4:$D$71,0)) -> 99. Descriptions | F40: zse_c_rapcinvoice.ddls.xml | G40: UPDATED ON 02-FEB-26 | H40: 3 months ago
C41: =LEFT(F41,FIND(".",F41)-1) -> zse_c_rapcitems | D41: {=INDEX('Not Req'!$E$4:$E$71,MATCH(MID(F41,FIND(".",F41)+1,LEN(F41)-FIND(".",F41)+1),'Not Req'!$D$4:$D$71,0))} -> BaseInfo : Data Definition | E41: =INDEX('Not Req'!$F$4:$F$71,MATCH(MID(F41,FIND(".",F41)+1,LEN(F41)-FIND(".",F41)+1),'Not Req'!$D$4:$D$71,0)) -> 98. Base Info | F41: zse_c_rapcitems.ddls.baseinfo | G41: UPDATED ON 02-FEB-26 | H41: 3 months ago
C42: =LEFT(F42,FIND(".",F42)-1) -> zse_c_rapcitems | D42: {=INDEX('Not Req'!$E$4:$E$71,MATCH(MID(F42,FIND(".",F42)+1,LEN(F42)-FIND(".",F42)+1),'Not Req'!$D$4:$D$71,0))} -> Description : Data Definition | E42: =INDEX('Not Req'!$F$4:$F$71,MATCH(MID(F42,FIND(".",F42)+1,LEN(F42)-FIND(".",F42)+1),'Not Req'!$D$4:$D$71,0)) -> 99. Descriptions | F42: zse_c_rapcitems.ddls.xml | G42: UPDATED ON 02-FEB-26 | H42: 3 months ago
... C45: =LEFT(F45,FIND(".",F45)-1) -> zse_complex_entity | D45: {=INDEX('Not Req'!$E$4:$E$71,MATCH(MID(F45,FIND(".",F45)+1,LEN(F45)-FIND(".",F45)+1),'Not Req'!$D$4:$D$71,0))} -> Description : Service Definition | E45: =INDEX('Not Req'!$F$4:$F$71,MATCH(MID(F45,FIND(".",F45)+1,LEN(F45)-FIND(".",F45)+1),'Not Req'!$D$4:$D$71,0)) -> 99. Descriptions | F45: zse_complex_entity.srvd.xml | G45: UPDATED ON 02-FEB-26 | H45: 3 months ago
B46: OK | C46: =LEFT(F46,FIND(".",F46)-1) -> zse_complex_entity_v4_0001_g4ba | D46: {=INDEX('Not Req'!$E$4:$E$71,MATCH(MID(F46,FIND(".",F46)+1,LEN(F46)-FIND(".",F46)+1),'Not Req'!$D$4:$D$71,0))} -> Inbound Service | E46: =INDEX('Not Req'!$F$4:$F$71,MATCH(MID(F46,FIND(".",F46)+1,LEN(F46)-FIND(".",F46)+1),'Not Req'!$D$4:$D$71,0)) -> 3. Cloud Communication Management | F46: zse_complex_entity_v4_0001_g4ba.sco2.xml | G46: UPDATED ON 02-FEB-26 | H46: 3 months ago
C47: =LEFT(F47,FIND(".",F47)-1) -> zse_i_rapcinvoice | D47: {=INDEX('Not Req'!$E$4:$E$71,MATCH(MID(F47,FIND(".",F47)+1,LEN(F47)-FIND(".",F47)+1),'Not Req'!$D$4:$D$71,0))} -> Description : BDEF | E47: =INDEX('Not Req'!$F$4:$F$71,MATCH(MID(F47,FIND(".",F47)+1,LEN(F47)-FIND(".",F47)+1),'Not Req'!$D$4:$D$71,0)) -> 99. Descriptions | F47: zse_i_rapcinvoice.bdef.xml | G47: UPDATED ON 02-FEB-26 | H47: 3 months ago
C48: =LEFT(F48,FIND(".",F48)-1) -> zse_i_rapcinvoice | D48: {=INDEX('Not Req'!$E$4:$E$71,MATCH(MID(F48,FIND(".",F48)+1,LEN(F48)-FIND(".",F48)+1),'Not Req'!$D$4:$D$71,0))} -> BaseInfo : Data Definition | E48: =INDEX('Not Req'!$F$4:$F$71,MATCH(MID(F48,FIND(".",F48)+1,LEN(F48)-FIND(".",F48)+1),'Not Req'!$D$4:$D$71,0)) -> 98. Base Info | F48: zse_i_rapcinvoice.ddls.baseinfo | G48: UPDATED ON 02-FEB-26 | H48: 3 months ago
C49: =LEFT(F49,FIND(".",F49)-1) -> zse_i_rapcinvoice | D49: {=INDEX('Not Req'!$E$4:$E$71,MATCH(MID(F49,FIND(".",F49)+1,LEN(F49)-FIND(".",F49)+1),'Not Req'!$D$4:$D$71,0))} -> Description : Data Definition | E49: =INDEX('Not Req'!$F$4:$F$71,MATCH(MID(F49,FIND(".",F49)+1,LEN(F49)-FIND(".",F49)+1),'Not Req'!$D$4:$D$71,0)) -> 99. Descriptions | F49: zse_i_rapcinvoice.ddls.xml | G49: UPDATED ON 02-FEB-26 | H49: 3 months ago
C50: =LEFT(F50,FIND(".",F50)-1) -> zse_i_rapcitems | D50: {=INDEX('Not Req'!$E$4:$E$71,MATCH(MID(F50,FIND(".",F50)+1,LEN(F50)-FIND(".",F50)+1),'Not Req'!$D$4:$D$71,0))} -> BaseInfo : Data Definition | E50: =INDEX('Not Req'!$F$4:$F$71,MATCH(MID(F50,FIND(".",F50)+1,LEN(F50)-FIND(".",F50)+1),'Not Req'!$D$4:$D$71,0)) -> 98. Base Info | F50: zse_i_rapcitems.ddls.baseinfo | G50: UPDATED ON 02-FEB-26 | H50: 3 months ago
C51: =LEFT(F51,FIND(".",F51)-1) -> zse_i_rapcitems | D51: {=INDEX('Not Req'!$E$4:$E$71,MATCH(MID(F51,FIND(".",F51)+1,LEN(F51)-FIND(".",F51)+1),'Not Req'!$D$4:$D$71,0))} -> Description : Data Definition | E51: =INDEX('Not Req'!$F$4:$F$71,MATCH(MID(F51,FIND(".",F51)+1,LEN(F51)-FIND(".",F51)+1),'Not Req'!$D$4:$D$71,0)) -> 99. Descriptions | F51: zse_i_rapcitems.ddls.xml | G51: UPDATED ON 02-FEB-26 | H51: 3 months ago
