Workbook

Sheet RAP Sales
B2: d | C2: Object | D2: Type | E2: Category | F2: Github Object | G2: Github Type | H2: Version
B4: 1 | C4: =LEFT(F4,FIND(".",F4)-1) -> package | D4: {=INDEX('Not Req'!$E$4:$E$72,MATCH(MID(F4,FIND(".",F4)+1,LEN(F4)-FIND(".",F4)+1),'Not Req'!$D$4:$D$72,0))} -> Description : Package | E4: =INDEX('Not Req'!$F$4:$F$72,MATCH(MID(F4,FIND(".",F4)+1,LEN(F4)-FIND(".",F4)+1),'Not Req'!$D$4:$D$72,0)) -> 0. Package | F4: package.devc.xml | G4: Sales configuration | H4: 3 weeks ago | N4: {=_xlfn.UNIQUE(C4:C21)} -> package
C5: =LEFT(F5,FIND(".",F5)-1) -> zbs_demo_sa_amount | D5: {=INDEX('Not Req'!$E$4:$E$72,MATCH(MID(F5,FIND(".",F5)+1,LEN(F5)-FIND(".",F5)+1),'Not Req'!$D$4:$D$72,0))} -> Data Element | E5: =INDEX('Not Req'!$F$4:$F$72,MATCH(MID(F5,FIND(".",F5)+1,LEN(F5)-FIND(".",F5)+1),'Not Req'!$D$4:$D$72,0)) -> 1. Dictionary | F5: zbs_demo_sa_amount.dtel.xml | G5: Sale App Creation | H5: 2 weeks ago | N5: zbs_demo_sa_amount
C6: =LEFT(F6,FIND(".",F6)-1) -> zbs_demo_sa_comment | D6: {=INDEX('Not Req'!$E$4:$E$72,MATCH(MID(F6,FIND(".",F6)+1,LEN(F6)-FIND(".",F6)+1),'Not Req'!$D$4:$D$72,0))} -> Data Element | E6: =INDEX('Not Req'!$F$4:$F$72,MATCH(MID(F6,FIND(".",F6)+1,LEN(F6)-FIND(".",F6)+1),'Not Req'!$D$4:$D$72,0)) -> 1. Dictionary | F6: zbs_demo_sa_comment.dtel.xml | G6: Sale App Creation | H6: 2 weeks ago | N6: zbs_demo_sa_comment
C7: =LEFT(F7,FIND(".",F7)-1) -> zbs_demo_sa_currency | D7: {=INDEX('Not Req'!$E$4:$E$72,MATCH(MID(F7,FIND(".",F7)+1,LEN(F7)-FIND(".",F7)+1),'Not Req'!$D$4:$D$72,0))} -> Data Element | E7: =INDEX('Not Req'!$F$4:$F$72,MATCH(MID(F7,FIND(".",F7)+1,LEN(F7)-FIND(".",F7)+1),'Not Req'!$D$4:$D$72,0)) -> 1. Dictionary | F7: zbs_demo_sa_currency.dtel.xml | G7: Sale App Creation | H7: 2 weeks ago | N7: zbs_demo_sa_currency
C8: =LEFT(F8,FIND(".",F8)-1) -> zbs_demo_sa_date | D8: {=INDEX('Not Req'!$E$4:$E$72,MATCH(MID(F8,FIND(".",F8)+1,LEN(F8)-FIND(".",F8)+1),'Not Req'!$D$4:$D$72,0))} -> Data Element | E8: =INDEX('Not Req'!$F$4:$F$72,MATCH(MID(F8,FIND(".",F8)+1,LEN(F8)-FIND(".",F8)+1),'Not Req'!$D$4:$D$72,0)) -> 1. Dictionary | F8: zbs_demo_sa_date.dtel.xml | G8: Sale App Creation | H8: 2 weeks ago | N8: zbs_demo_sa_date
C9: =LEFT(F9,FIND(".",F9)-1) -> zbs_demo_sa_material | D9: {=INDEX('Not Req'!$E$4:$E$72,MATCH(MID(F9,FIND(".",F9)+1,LEN(F9)-FIND(".",F9)+1),'Not Req'!$D$4:$D$72,0))} -> Data Element | E9: =INDEX('Not Req'!$F$4:$F$72,MATCH(MID(F9,FIND(".",F9)+1,LEN(F9)-FIND(".",F9)+1),'Not Req'!$D$4:$D$72,0)) -> 1. Dictionary | F9: zbs_demo_sa_material.dtel.xml | G9: Sale App Creation | H9: 2 weeks ago | N9: zbs_demo_sa_material
C10: =LEFT(F10,FIND(".",F10)-1) -> zbs_demo_sa_partner | D10: {=INDEX('Not Req'!$E$4:$E$72,MATCH(MID(F10,FIND(".",F10)+1,LEN(F10)-FIND(".",F10)+1),'Not Req'!$D$4:$D$72,0))} -> Data Element | E10: =INDEX('Not Req'!$F$4:$F$72,MATCH(MID(F10,FIND(".",F10)+1,LEN(F10)-FIND(".",F10)+1),'Not Req'!$D$4:$D$72,0)) -> 1. Dictionary | F10: zbs_demo_sa_partner.dtel.xml | G10: Sale App Creation | H10: 2 weeks ago | N10: zbs_demo_sa_partner
C11: =LEFT(F11,FIND(".",F11)-1) -> zbs_demo_sa_quantity | D11: {=INDEX('Not Req'!$E$4:$E$72,MATCH(MID(F11,FIND(".",F11)+1,LEN(F11)-FIND(".",F11)+1),'Not Req'!$D$4:$D$72,0))} -> Data Element | E11: =INDEX('Not Req'!$F$4:$F$72,MATCH(MID(F11,FIND(".",F11)+1,LEN(F11)-FIND(".",F11)+1),'Not Req'!$D$4:$D$72,0)) -> 1. Dictionary | F11: zbs_demo_sa_quantity.dtel.xml | G11: Sale App Creation | H11: 2 weeks ago | N11: zbs_demo_sa_quantity
C12: =LEFT(F12,FIND(".",F12)-1) -> zbs_demo_sa_quota | D12: {=INDEX('Not Req'!$E$4:$E$72,MATCH(MID(F12,FIND(".",F12)+1,LEN(F12)-FIND(".",F12)+1),'Not Req'!$D$4:$D$72,0))} -> Data Element | E12: =INDEX('Not Req'!$F$4:$F$72,MATCH(MID(F12,FIND(".",F12)+1,LEN(F12)-FIND(".",F12)+1),'Not Req'!$D$4:$D$72,0)) -> 1. Dictionary | F12: zbs_demo_sa_quota.dtel.xml | G12: Sale App Creation | H12: 2 weeks ago | N12: zbs_demo_sa_quota
C13: =LEFT(F13,FIND(".",F13)-1) -> zbs_demo_sa_text | D13: {=INDEX('Not Req'!$E$4:$E$72,MATCH(MID(F13,FIND(".",F13)+1,LEN(F13)-FIND(".",F13)+1),'Not Req'!$D$4:$D$72,0))} -> Data Element | E13: =INDEX('Not Req'!$F$4:$F$72,MATCH(MID(F13,FIND(".",F13)+1,LEN(F13)-FIND(".",F13)+1),'Not Req'!$D$4:$D$72,0)) -> 1. Dictionary | F13: zbs_demo_sa_text.dtel.xml | G13: Sale App Creation | H13: 2 weeks ago | N13: zbs_demo_sa_text
C14: =LEFT(F14,FIND(".",F14)-1) -> zbs_demo_sa_unit | D14: {=INDEX('Not Req'!$E$4:$E$72,MATCH(MID(F14,FIND(".",F14)+1,LEN(F14)-FIND(".",F14)+1),'Not Req'!$D$4:$D$72,0))} -> Data Element | E14: =INDEX('Not Req'!$F$4:$F$72,MATCH(MID(F14,FIND(".",F14)+1,LEN(F14)-FIND(".",F14)+1),'Not Req'!$D$4:$D$72,0)) -> 1. Dictionary | F14: zbs_demo_sa_unit.dtel.xml | G14: Sale App Creation | H14: 2 weeks ago | N14: zbs_demo_sa_unit
C15: =LEFT(F15,FIND(".",F15)-1) -> zbs_demo_sa_user | D15: {=INDEX('Not Req'!$E$4:$E$72,MATCH(MID(F15,FIND(".",F15)+1,LEN(F15)-FIND(".",F15)+1),'Not Req'!$D$4:$D$72,0))} -> Data Element | E15: =INDEX('Not Req'!$F$4:$F$72,MATCH(MID(F15,FIND(".",F15)+1,LEN(F15)-FIND(".",F15)+1),'Not Req'!$D$4:$D$72,0)) -> 1. Dictionary | F15: zbs_demo_sa_user.dtel.xml | G15: Sale App Creation | H15: 2 weeks ago | N15: zbs_demo_sa_user
C16: =LEFT(F16,FIND(".",F16)-1) -> zbs_demo_sa_amount | D16: {=INDEX('Not Req'!$E$4:$E$72,MATCH(MID(F16,FIND(".",F16)+1,LEN(F16)-FIND(".",F16)+1),'Not Req'!$D$4:$D$72,0))} -> Domain | E16: =INDEX('Not Req'!$F$4:$F$72,MATCH(MID(F16,FIND(".",F16)+1,LEN(F16)-FIND(".",F16)+1),'Not Req'!$D$4:$D$72,0)) -> 1. Dictionary | F16: zbs_demo_sa_amount.doma.xml | G16: Sale App Creation | H16: 2 weeks ago
C17: =LEFT(F17,FIND(".",F17)-1) -> zbs_demo_sa_comment | D17: {=INDEX('Not Req'!$E$4:$E$72,MATCH(MID(F17,FIND(".",F17)+1,LEN(F17)-FIND(".",F17)+1),'Not Req'!$D$4:$D$72,0))} -> Domain | E17: =INDEX('Not Req'!$F$4:$F$72,MATCH(MID(F17,FIND(".",F17)+1,LEN(F17)-FIND(".",F17)+1),'Not Req'!$D$4:$D$72,0)) -> 1. Dictionary | F17: zbs_demo_sa_comment.doma.xml | G17: Sale App Creation | H17: 2 weeks ago
C18: =LEFT(F18,FIND(".",F18)-1) -> zbs_demo_sa_currency | D18: {=INDEX('Not Req'!$E$4:$E$72,MATCH(MID(F18,FIND(".",F18)+1,LEN(F18)-FIND(".",F18)+1),'Not Req'!$D$4:$D$72,0))} -> Domain | E18: =INDEX('Not Req'!$F$4:$F$72,MATCH(MID(F18,FIND(".",F18)+1,LEN(F18)-FIND(".",F18)+1),'Not Req'!$D$4:$D$72,0)) -> 1. Dictionary | F18: zbs_demo_sa_currency.doma.xml | G18: Sale App Creation | H18: 2 weeks ago
C19: =LEFT(F19,FIND(".",F19)-1) -> zbs_demo_sa_date | D19: {=INDEX('Not Req'!$E$4:$E$72,MATCH(MID(F19,FIND(".",F19)+1,LEN(F19)-FIND(".",F19)+1),'Not Req'!$D$4:$D$72,0))} -> Domain | E19: =INDEX('Not Req'!$F$4:$F$72,MATCH(MID(F19,FIND(".",F19)+1,LEN(F19)-FIND(".",F19)+1),'Not Req'!$D$4:$D$72,0)) -> 1. Dictionary | F19: zbs_demo_sa_date.doma.xml | G19: Sale App Creation | H19: 2 weeks ago
C20: =LEFT(F20,FIND(".",F20)-1) -> zbs_demo_sa_material | D20: {=INDEX('Not Req'!$E$4:$E$72,MATCH(MID(F20,FIND(".",F20)+1,LEN(F20)-FIND(".",F20)+1),'Not Req'!$D$4:$D$72,0))} -> Domain | E20: =INDEX('Not Req'!$F$4:$F$72,MATCH(MID(F20,FIND(".",F20)+1,LEN(F20)-FIND(".",F20)+1),'Not Req'!$D$4:$D$72,0)) -> 1. Dictionary | F20: zbs_demo_sa_material.doma.xml | G20: Sale App Creation | H20: 2 weeks ago
C21: =LEFT(F21,FIND(".",F21)-1) -> zbs_demo_sa_partner | D21: {=INDEX('Not Req'!$E$4:$E$72,MATCH(MID(F21,FIND(".",F21)+1,LEN(F21)-FIND(".",F21)+1),'Not Req'!$D$4:$D$72,0))} -> Domain | E21: =INDEX('Not Req'!$F$4:$F$72,MATCH(MID(F21,FIND(".",F21)+1,LEN(F21)-FIND(".",F21)+1),'Not Req'!$D$4:$D$72,0)) -> 1. Dictionary | F21: zbs_demo_sa_partner.doma.xml | G21: Sale App Creation | H21: 2 weeks ago
C22: =LEFT(F22,FIND(".",F22)-1) -> zbs_demo_sa_quantity | D22: {=INDEX('Not Req'!$E$4:$E$72,MATCH(MID(F22,FIND(".",F22)+1,LEN(F22)-FIND(".",F22)+1),'Not Req'!$D$4:$D$72,0))} -> Domain | E22: =INDEX('Not Req'!$F$4:$F$72,MATCH(MID(F22,FIND(".",F22)+1,LEN(F22)-FIND(".",F22)+1),'Not Req'!$D$4:$D$72,0)) -> 1. Dictionary | F22: zbs_demo_sa_quantity.doma.xml | G22: Sale App Creation | H22: 2 weeks ago
C23: =LEFT(F23,FIND(".",F23)-1) -> zbs_demo_sa_quota | D23: {=INDEX('Not Req'!$E$4:$E$72,MATCH(MID(F23,FIND(".",F23)+1,LEN(F23)-FIND(".",F23)+1),'Not Req'!$D$4:$D$72,0))} -> Domain | E23: =INDEX('Not Req'!$F$4:$F$72,MATCH(MID(F23,FIND(".",F23)+1,LEN(F23)-FIND(".",F23)+1),'Not Req'!$D$4:$D$72,0)) -> 1. Dictionary | F23: zbs_demo_sa_quota.doma.xml | G23: Sale App Creation | H23: 2 weeks ago
C24: =LEFT(F24,FIND(".",F24)-1) -> zbs_demo_sa_text | D24: {=INDEX('Not Req'!$E$4:$E$72,MATCH(MID(F24,FIND(".",F24)+1,LEN(F24)-FIND(".",F24)+1),'Not Req'!$D$4:$D$72,0))} -> Domain | E24: =INDEX('Not Req'!$F$4:$F$72,MATCH(MID(F24,FIND(".",F24)+1,LEN(F24)-FIND(".",F24)+1),'Not Req'!$D$4:$D$72,0)) -> 1. Dictionary | F24: zbs_demo_sa_text.doma.xml | G24: Sale App Creation | H24: 2 weeks ago
C25: =LEFT(F25,FIND(".",F25)-1) -> zbs_demo_sa_unit | D25: {=INDEX('Not Req'!$E$4:$E$72,MATCH(MID(F25,FIND(".",F25)+1,LEN(F25)-FIND(".",F25)+1),'Not Req'!$D$4:$D$72,0))} -> Domain | E25: =INDEX('Not Req'!$F$4:$F$72,MATCH(MID(F25,FIND(".",F25)+1,LEN(F25)-FIND(".",F25)+1),'Not Req'!$D$4:$D$72,0)) -> 1. Dictionary | F25: zbs_demo_sa_unit.doma.xml | G25: Sale App Creation | H25: 2 weeks ago
C26: =LEFT(F26,FIND(".",F26)-1) -> zbs_demo_sa_user | D26: {=INDEX('Not Req'!$E$4:$E$72,MATCH(MID(F26,FIND(".",F26)+1,LEN(F26)-FIND(".",F26)+1),'Not Req'!$D$4:$D$72,0))} -> Domain | E26: =INDEX('Not Req'!$F$4:$F$72,MATCH(MID(F26,FIND(".",F26)+1,LEN(F26)-FIND(".",F26)+1),'Not Req'!$D$4:$D$72,0)) -> 1. Dictionary | F26: zbs_demo_sa_user.doma.xml | G26: Sale App Creation | H26: 2 weeks ago
C27: =LEFT(F27,FIND(".",F27)-1) -> zbs_sainfo | D27: {=INDEX('Not Req'!$E$4:$E$72,MATCH(MID(F27,FIND(".",F27)+1,LEN(F27)-FIND(".",F27)+1),'Not Req'!$D$4:$D$72,0))} -> Table | E27: =INDEX('Not Req'!$F$4:$F$72,MATCH(MID(F27,FIND(".",F27)+1,LEN(F27)-FIND(".",F27)+1),'Not Req'!$D$4:$D$72,0)) -> 1. Dictionary | F27: zbs_sainfo.tabl.xml | G27: Sale App Creation | H27: 2 weeks ago
... C118: =LEFT(F118,FIND(".",F118)-1) -> zbs_globalsale | D118: {=INDEX('Not Req'!$E$4:$E$72,MATCH(MID(F118,FIND(".",F118)+1,LEN(F118)-FIND(".",F118)+1),'Not Req'!$D$4:$D$72,0))} -> #N/A | E118: =INDEX('Not Req'!$F$4:$F$72,MATCH(MID(F118,FIND(".",F118)+1,LEN(F118)-FIND(".",F118)+1),'Not Req'!$D$4:$D$72,0)) -> #N/A | F118: zbs_globalsale.nont.json | G118: Sale App Creation | H118: 2 weeks ago
A119: d | B119: d | C119: =LEFT(F119,FIND(".",F119)-1) -> zbs_globalsale | D119: {=INDEX('Not Req'!$E$4:$E$72,MATCH(MID(F119,FIND(".",F119)+1,LEN(F119)-FIND(".",F119)+1),'Not Req'!$D$4:$D$72,0))} -> #N/A | E119: =INDEX('Not Req'!$F$4:$F$72,MATCH(MID(F119,FIND(".",F119)+1,LEN(F119)-FIND(".",F119)+1),'Not Req'!$D$4:$D$72,0)) -> #N/A | F119: zbs_globalsale.ront.json | G119: Sale App Creation | H119: 2 weeks ago

Sheet CUSTOM ACTION
B2: d | C2: Object | D2: Type | E2: Category | F2: Github Object | G2: Github Type | H2: Version
B4: 1 | C4: =LEFT(F4,FIND(".",F4)-1) -> package | D4: {=INDEX('Not Req'!$E$4:$E$72,MATCH(MID(F4,FIND(".",F4)+1,LEN(F4)-FIND(".",F4)+1),'Not Req'!$D$4:$D$72,0))} -> Description : Package | E4: =INDEX('Not Req'!$F$4:$F$72,MATCH(MID(F4,FIND(".",F4)+1,LEN(F4)-FIND(".",F4)+1),'Not Req'!$D$4:$D$72,0)) -> 0. Package | F4: package.devc.xml | G4: CDS Pattern | H4: 2 months ago | N4: {=_xlfn.UNIQUE(C4:C21)} -> package
C5: =LEFT(F5,FIND(".",F5)-1) -> zbs_dmo_cstat | D5: {=INDEX('Not Req'!$E$4:$E$72,MATCH(MID(F5,FIND(".",F5)+1,LEN(F5)-FIND(".",F5)+1),'Not Req'!$D$4:$D$72,0))} -> Table | E5: =INDEX('Not Req'!$F$4:$F$72,MATCH(MID(F5,FIND(".",F5)+1,LEN(F5)-FIND(".",F5)+1),'Not Req'!$D$4:$D$72,0)) -> 1. Dictionary | F5: zbs_dmo_cstat.tabl.xml | G5: Custom Action | H5: 6 months ago | N5: zbs_dmo_cstat
C6: =LEFT(F6,FIND(".",F6)-1) -> zbs_r_cusactentitytp | D6: {=INDEX('Not Req'!$E$4:$E$72,MATCH(MID(F6,FIND(".",F6)+1,LEN(F6)-FIND(".",F6)+1),'Not Req'!$D$4:$D$72,0))} -> BDEF | E6: =INDEX('Not Req'!$F$4:$F$72,MATCH(MID(F6,FIND(".",F6)+1,LEN(F6)-FIND(".",F6)+1),'Not Req'!$D$4:$D$72,0)) -> 2. CDS | F6: zbs_r_cusactentitytp.bdef.asbdef | G6: Custom Action | H6: 6 months ago | N6: zbs_r_cusactentitytp
C7: =LEFT(F7,FIND(".",F7)-1) -> zbs_r_cusactentitytp | D7: {=INDEX('Not Req'!$E$4:$E$72,MATCH(MID(F7,FIND(".",F7)+1,LEN(F7)-FIND(".",F7)+1),'Not Req'!$D$4:$D$72,0))} -> Data Definition | E7: =INDEX('Not Req'!$F$4:$F$72,MATCH(MID(F7,FIND(".",F7)+1,LEN(F7)-FIND(".",F7)+1),'Not Req'!$D$4:$D$72,0)) -> 2. CDS | F7: zbs_r_cusactentitytp.ddls.asddls | G7: Custom Action | H7: 6 months ago | N7: zbp_bs_demo_custom_action
C8: =LEFT(F8,FIND(".",F8)-1) -> zbs_r_cusactentitytp | D8: {=INDEX('Not Req'!$E$4:$E$72,MATCH(MID(F8,FIND(".",F8)+1,LEN(F8)-FIND(".",F8)+1),'Not Req'!$D$4:$D$72,0))} -> Description : BDEF | E8: =INDEX('Not Req'!$F$4:$F$72,MATCH(MID(F8,FIND(".",F8)+1,LEN(F8)-FIND(".",F8)+1),'Not Req'!$D$4:$D$72,0)) -> 2. CDS | F8: zbs_r_cusactentitytp.bdef.xml | G8: Custom Action | H8: 6 months ago | N8: zcl_bs_demo_custom_action_qry
C9: =LEFT(F9,FIND(".",F9)-1) -> zbs_r_cusactentitytp | D9: {=INDEX('Not Req'!$E$4:$E$72,MATCH(MID(F9,FIND(".",F9)+1,LEN(F9)-FIND(".",F9)+1),'Not Req'!$D$4:$D$72,0))} -> Description : Data Definition | E9: =INDEX('Not Req'!$F$4:$F$72,MATCH(MID(F9,FIND(".",F9)+1,LEN(F9)-FIND(".",F9)+1),'Not Req'!$D$4:$D$72,0)) -> 2. CDS | F9: zbs_r_cusactentitytp.ddls.xml | G9: Custom Action | H9: 6 months ago | N9: zbs_custom_action
C10: =LEFT(F10,FIND(".",F10)-1) -> zbp_bs_demo_custom_action | D10: {=INDEX('Not Req'!$E$4:$E$72,MATCH(MID(F10,FIND(".",F10)+1,LEN(F10)-FIND(".",F10)+1),'Not Req'!$D$4:$D$72,0))} -> Classes | E10: =INDEX('Not Req'!$F$4:$F$72,MATCH(MID(F10,FIND(".",F10)+1,LEN(F10)-FIND(".",F10)+1),'Not Req'!$D$4:$D$72,0)) -> 3. Source Code Library | F10: zbp_bs_demo_custom_action.clas.abap | G10: Custom Action | H10: 6 months ago | N10: bee6b00074f6699624012d396997aaht
C11: =LEFT(F11,FIND(".",F11)-1) -> zcl_bs_demo_custom_action_qry | D11: {=INDEX('Not Req'!$E$4:$E$72,MATCH(MID(F11,FIND(".",F11)+1,LEN(F11)-FIND(".",F11)+1),'Not Req'!$D$4:$D$72,0))} -> Classes | E11: =INDEX('Not Req'!$F$4:$F$72,MATCH(MID(F11,FIND(".",F11)+1,LEN(F11)-FIND(".",F11)+1),'Not Req'!$D$4:$D$72,0)) -> 3. Source Code Library | F11: zcl_bs_demo_custom_action_qry.clas.abap | G11: Custom Action | H11: 6 months ago | N11: fb1872bf9b30d1c7c1e4e51bc7fc70ht
C12: =LEFT(F12,FIND(".",F12)-1) -> zbp_bs_demo_custom_action | D12: {=INDEX('Not Req'!$E$4:$E$72,MATCH(MID(F12,FIND(".",F12)+1,LEN(F12)-FIND(".",F12)+1),'Not Req'!$D$4:$D$72,0))} -> Classes Local | E12: =INDEX('Not Req'!$F$4:$F$72,MATCH(MID(F12,FIND(".",F12)+1,LEN(F12)-FIND(".",F12)+1),'Not Req'!$D$4:$D$72,0)) -> 3. Source Code Library | F12: zbp_bs_demo_custom_action.clas.locals_imp.abap | G12: Custom Action | H12: 6 months ago | N12: zbs_ui_custom_action_o2
C13: =LEFT(F13,FIND(".",F13)-1) -> zbp_bs_demo_custom_action | D13: {=INDEX('Not Req'!$E$4:$E$72,MATCH(MID(F13,FIND(".",F13)+1,LEN(F13)-FIND(".",F13)+1),'Not Req'!$D$4:$D$72,0))} -> Description : Classes | E13: =INDEX('Not Req'!$F$4:$F$72,MATCH(MID(F13,FIND(".",F13)+1,LEN(F13)-FIND(".",F13)+1),'Not Req'!$D$4:$D$72,0)) -> 3. Source Code Library | F13: zbp_bs_demo_custom_action.clas.xml | G13: Custom Action | H13: 6 months ago | N13: zbs_ui_custom_action_o2_iwsg
C14: =LEFT(F14,FIND(".",F14)-1) -> zcl_bs_demo_custom_action_qry | D14: {=INDEX('Not Req'!$E$4:$E$72,MATCH(MID(F14,FIND(".",F14)+1,LEN(F14)-FIND(".",F14)+1),'Not Req'!$D$4:$D$72,0))} -> Description : Classes | E14: =INDEX('Not Req'!$F$4:$F$72,MATCH(MID(F14,FIND(".",F14)+1,LEN(F14)-FIND(".",F14)+1),'Not Req'!$D$4:$D$72,0)) -> 3. Source Code Library | F14: zcl_bs_demo_custom_action_qry.clas.xml | G14: Custom Action | H14: 6 months ago
C15: =LEFT(F15,FIND(".",F15)-1) -> zbs_custom_action | D15: {=INDEX('Not Req'!$E$4:$E$72,MATCH(MID(F15,FIND(".",F15)+1,LEN(F15)-FIND(".",F15)+1),'Not Req'!$D$4:$D$72,0))} -> Service Definition | E15: =INDEX('Not Req'!$F$4:$F$72,MATCH(MID(F15,FIND(".",F15)+1,LEN(F15)-FIND(".",F15)+1),'Not Req'!$D$4:$D$72,0)) -> Business Services | F15: zbs_custom_action.srvd.srvdsrv | G15: Custom Action | H15: 6 months ago
C16: =LEFT(F16,FIND(".",F16)-1) -> bee6b00074f6699624012d396997aaht | D16: {=INDEX('Not Req'!$E$4:$E$72,MATCH(MID(F16,FIND(".",F16)+1,LEN(F16)-FIND(".",F16)+1),'Not Req'!$D$4:$D$72,0))} -> Internal (Not Req) | E16: =INDEX('Not Req'!$F$4:$F$72,MATCH(MID(F16,FIND(".",F16)+1,LEN(F16)-FIND(".",F16)+1),'Not Req'!$D$4:$D$72,0)) -> Internal (Not Req) | F16: bee6b00074f6699624012d396997aaht.sush.xml | G16: Custom Action | H16: 6 months ago
C17: =LEFT(F17,FIND(".",F17)-1) -> fb1872bf9b30d1c7c1e4e51bc7fc70ht | D17: {=INDEX('Not Req'!$E$4:$E$72,MATCH(MID(F17,FIND(".",F17)+1,LEN(F17)-FIND(".",F17)+1),'Not Req'!$D$4:$D$72,0))} -> Internal (Not Req) | E17: =INDEX('Not Req'!$F$4:$F$72,MATCH(MID(F17,FIND(".",F17)+1,LEN(F17)-FIND(".",F17)+1),'Not Req'!$D$4:$D$72,0)) -> Internal (Not Req) | F17: fb1872bf9b30d1c7c1e4e51bc7fc70ht.sush.xml | G17: Custom Action | H17: 6 months ago
C18: =LEFT(F18,FIND(".",F18)-1) -> zbs_custom_action | D18: {=INDEX('Not Req'!$E$4:$E$72,MATCH(MID(F18,FIND(".",F18)+1,LEN(F18)-FIND(".",F18)+1),'Not Req'!$D$4:$D$72,0))} -> Internal (Not Req) | E18: =INDEX('Not Req'!$F$4:$F$72,MATCH(MID(F18,FIND(".",F18)+1,LEN(F18)-FIND(".",F18)+1),'Not Req'!$D$4:$D$72,0)) -> Internal (Not Req) | F18: zbs_custom_action.srvd.xml | G18: Custom Action | H18: 6 months ago
C19: =LEFT(F19,FIND(".",F19)-1) -> zbs_r_cusactentitytp | D19: {=INDEX('Not Req'!$E$4:$E$72,MATCH(MID(F19,FIND(".",F19)+1,LEN(F19)-FIND(".",F19)+1),'Not Req'!$D$4:$D$72,0))} -> Internal (Not Req) | E19: =INDEX('Not Req'!$F$4:$F$72,MATCH(MID(F19,FIND(".",F19)+1,LEN(F19)-FIND(".",F19)+1),'Not Req'!$D$4:$D$72,0)) -> Internal (Not Req) | F19: zbs_r_cusactentitytp.ddls.baseinfo | G19: Custom Action | H19: 6 months ago
C20: =LEFT(F20,FIND(".",F20)-1) -> zbs_ui_custom_action_o2 | D20: {=INDEX('Not Req'!$E$4:$E$72,MATCH(MID(F20,FIND(".",F20)+1,LEN(F20)-FIND(".",F20)+1),'Not Req'!$D$4:$D$72,0))} -> Internal (Not Req) | E20: =INDEX('Not Req'!$F$4:$F$72,MATCH(MID(F20,FIND(".",F20)+1,LEN(F20)-FIND(".",F20)+1),'Not Req'!$D$4:$D$72,0)) -> Internal (Not Req) | F20: zbs_ui_custom_action_o2.srvb.xml | G20: Custom Action | H20: 6 months ago
C21: =LEFT(F21,FIND(".",F21)-1) -> zbs_ui_custom_action_o2_iwsg | D21: {=INDEX('Not Req'!$E$4:$E$72,MATCH(MID(F21,FIND(".",F21)+1,LEN(F21)-FIND(".",F21)+1),'Not Req'!$D$4:$D$72,0))} -> Internal (Not Req) | E21: =INDEX('Not Req'!$F$4:$F$72,MATCH(MID(F21,FIND(".",F21)+1,LEN(F21)-FIND(".",F21)+1),'Not Req'!$D$4:$D$72,0)) -> Internal (Not Req) | F21: zbs_ui_custom_action_o2_iwsg.sco2.xml | G21: Custom Action | H21: 6 months ago
A22: D | B22: D | C22: =LEFT(F22,FIND(".",F22)-1) -> zbs_ui_custom_action_o2_iwsg_ibs | D22: {=INDEX('Not Req'!$E$4:$E$72,MATCH(MID(F22,FIND(".",F22)+1,LEN(F22)-FIND(".",F22)+1),'Not Req'!$D$4:$D$72,0))} -> Internal (Not Req) | E22: =INDEX('Not Req'!$F$4:$F$72,MATCH(MID(F22,FIND(".",F22)+1,LEN(F22)-FIND(".",F22)+1),'Not Req'!$D$4:$D$72,0)) -> Internal (Not Req) | F22: zbs_ui_custom_action_o2_iwsg_ibs.sia6.xml | G22: Custom Action | H22: 6 months ago

Sheet RAP TREE
B2: d | C2: Object | D2: Type | E2: Category | F2: Github Object | G2: Github Type | H2: Version
B4: 1 | C4: =LEFT(F4,FIND(".",F4)-1) -> package | D4: {=INDEX('Not Req'!$E$4:$E$72,MATCH(MID(F4,FIND(".",F4)+1,LEN(F4)-FIND(".",F4)+1),'Not Req'!$D$4:$D$72,0))} -> Description : Package | E4: =INDEX('Not Req'!$F$4:$F$72,MATCH(MID(F4,FIND(".",F4)+1,LEN(F4)-FIND(".",F4)+1),'Not Req'!$D$4:$D$72,0)) -> 0. Package | F4: package.devc.xml | G4: CDS Pattern | H4: 2 months ago | N4: {=_xlfn.UNIQUE(C4:C21)} -> package
C5: =LEFT(F5,FIND(".",F5)-1) -> zbs_dmo_team_d | D5: {=INDEX('Not Req'!$E$4:$E$72,MATCH(MID(F5,FIND(".",F5)+1,LEN(F5)-FIND(".",F5)+1),'Not Req'!$D$4:$D$72,0))} -> Table | E5: =INDEX('Not Req'!$F$4:$F$72,MATCH(MID(F5,FIND(".",F5)+1,LEN(F5)-FIND(".",F5)+1),'Not Req'!$D$4:$D$72,0)) -> 1. Dictionary | F5: zbs_dmo_team_d.tabl.xml | G5: Tree View | H5: 10 months ago | N5: zbs_dmo_team_d
C6: =LEFT(F6,FIND(".",F6)-1) -> zbs_c_dmotreeteam | D6: {=INDEX('Not Req'!$E$4:$E$72,MATCH(MID(F6,FIND(".",F6)+1,LEN(F6)-FIND(".",F6)+1),'Not Req'!$D$4:$D$72,0))} -> BDEF | E6: =INDEX('Not Req'!$F$4:$F$72,MATCH(MID(F6,FIND(".",F6)+1,LEN(F6)-FIND(".",F6)+1),'Not Req'!$D$4:$D$72,0)) -> 2. CDS | F6: zbs_c_dmotreeteam.bdef.asbdef | G6: Tree View | H6: 10 months ago | N6: zbs_c_dmotreeteam
C7: =LEFT(F7,FIND(".",F7)-1) -> zbs_r_dmotreeteam | D7: {=INDEX('Not Req'!$E$4:$E$72,MATCH(MID(F7,FIND(".",F7)+1,LEN(F7)-FIND(".",F7)+1),'Not Req'!$D$4:$D$72,0))} -> BDEF | E7: =INDEX('Not Req'!$F$4:$F$72,MATCH(MID(F7,FIND(".",F7)+1,LEN(F7)-FIND(".",F7)+1),'Not Req'!$D$4:$D$72,0)) -> 2. CDS | F7: zbs_r_dmotreeteam.bdef.asbdef | G7: Tree Deletion | H7: 9 months ago | N7: zbs_r_dmotreeteam
C8: =LEFT(F8,FIND(".",F8)-1) -> zbs_c_dmotreeteam | D8: {=INDEX('Not Req'!$E$4:$E$72,MATCH(MID(F8,FIND(".",F8)+1,LEN(F8)-FIND(".",F8)+1),'Not Req'!$D$4:$D$72,0))} -> Data Definition | E8: =INDEX('Not Req'!$F$4:$F$72,MATCH(MID(F8,FIND(".",F8)+1,LEN(F8)-FIND(".",F8)+1),'Not Req'!$D$4:$D$72,0)) -> 2. CDS | F8: zbs_c_dmotreeteam.ddls.asddls | G8: Tree View | H8: 10 months ago | N8: zbs_i_dmotreeteamhr
C9: =LEFT(F9,FIND(".",F9)-1) -> zbs_i_dmotreeteamhr | D9: {=INDEX('Not Req'!$E$4:$E$72,MATCH(MID(F9,FIND(".",F9)+1,LEN(F9)-FIND(".",F9)+1),'Not Req'!$D$4:$D$72,0))} -> Data Definition | E9: =INDEX('Not Req'!$F$4:$F$72,MATCH(MID(F9,FIND(".",F9)+1,LEN(F9)-FIND(".",F9)+1),'Not Req'!$D$4:$D$72,0)) -> 2. CDS | F9: zbs_i_dmotreeteamhr.ddls.asddls | G9: Tree View | H9: 10 months ago | N9: zbp_bs_demo_tree_team
C10: =LEFT(F10,FIND(".",F10)-1) -> zbs_r_dmotreeteam | D10: {=INDEX('Not Req'!$E$4:$E$72,MATCH(MID(F10,FIND(".",F10)+1,LEN(F10)-FIND(".",F10)+1),'Not Req'!$D$4:$D$72,0))} -> Data Definition | E10: =INDEX('Not Req'!$F$4:$F$72,MATCH(MID(F10,FIND(".",F10)+1,LEN(F10)-FIND(".",F10)+1),'Not Req'!$D$4:$D$72,0)) -> 2. CDS | F10: zbs_r_dmotreeteam.ddls.asddls | G10: Tree View | H10: 10 months ago | N10: zbp_bs_demo_tree_teamc
C11: =LEFT(F11,FIND(".",F11)-1) -> zbs_c_dmotreeteam | D11: {=INDEX('Not Req'!$E$4:$E$72,MATCH(MID(F11,FIND(".",F11)+1,LEN(F11)-FIND(".",F11)+1),'Not Req'!$D$4:$D$72,0))} -> Description : BDEF | E11: =INDEX('Not Req'!$F$4:$F$72,MATCH(MID(F11,FIND(".",F11)+1,LEN(F11)-FIND(".",F11)+1),'Not Req'!$D$4:$D$72,0)) -> 2. CDS | F11: zbs_c_dmotreeteam.bdef.xml | G11: Tree View | H11: 10 months ago
C12: =LEFT(F12,FIND(".",F12)-1) -> zbs_r_dmotreeteam | D12: {=INDEX('Not Req'!$E$4:$E$72,MATCH(MID(F12,FIND(".",F12)+1,LEN(F12)-FIND(".",F12)+1),'Not Req'!$D$4:$D$72,0))} -> Description : BDEF | E12: =INDEX('Not Req'!$F$4:$F$72,MATCH(MID(F12,FIND(".",F12)+1,LEN(F12)-FIND(".",F12)+1),'Not Req'!$D$4:$D$72,0)) -> 2. CDS | F12: zbs_r_dmotreeteam.bdef.xml | G12: Tree View | H12: 10 months ago
C13: =LEFT(F13,FIND(".",F13)-1) -> zbs_c_dmotreeteam | D13: {=INDEX('Not Req'!$E$4:$E$72,MATCH(MID(F13,FIND(".",F13)+1,LEN(F13)-FIND(".",F13)+1),'Not Req'!$D$4:$D$72,0))} -> Description : Data Definition | E13: =INDEX('Not Req'!$F$4:$F$72,MATCH(MID(F13,FIND(".",F13)+1,LEN(F13)-FIND(".",F13)+1),'Not Req'!$D$4:$D$72,0)) -> 2. CDS | F13: zbs_c_dmotreeteam.ddls.xml | G13: Tree View | H13: 10 months ago
C14: =LEFT(F14,FIND(".",F14)-1) -> zbs_i_dmotreeteamhr | D14: {=INDEX('Not Req'!$E$4:$E$72,MATCH(MID(F14,FIND(".",F14)+1,LEN(F14)-FIND(".",F14)+1),'Not Req'!$D$4:$D$72,0))} -> Description : Data Definition | E14: =INDEX('Not Req'!$F$4:$F$72,MATCH(MID(F14,FIND(".",F14)+1,LEN(F14)-FIND(".",F14)+1),'Not Req'!$D$4:$D$72,0)) -> 2. CDS | F14: zbs_i_dmotreeteamhr.ddls.xml | G14: Tree View | H14: 10 months ago
C15: =LEFT(F15,FIND(".",F15)-1) -> zbs_r_dmotreeteam | D15: {=INDEX('Not Req'!$E$4:$E$72,MATCH(MID(F15,FIND(".",F15)+1,LEN(F15)-FIND(".",F15)+1),'Not Req'!$D$4:$D$72,0))} -> Description : Data Definition | E15: =INDEX('Not Req'!$F$4:$F$72,MATCH(MID(F15,FIND(".",F15)+1,LEN(F15)-FIND(".",F15)+1),'Not Req'!$D$4:$D$72,0)) -> 2. CDS | F15: zbs_r_dmotreeteam.ddls.xml | G15: Tree View | H15: 10 months ago
C16: =LEFT(F16,FIND(".",F16)-1) -> zbs_c_dmotreeteam | D16: {=INDEX('Not Req'!$E$4:$E$72,MATCH(MID(F16,FIND(".",F16)+1,LEN(F16)-FIND(".",F16)+1),'Not Req'!$D$4:$D$72,0))} -> Description : Metadata | E16: =INDEX('Not Req'!$F$4:$F$72,MATCH(MID(F16,FIND(".",F16)+1,LEN(F16)-FIND(".",F16)+1),'Not Req'!$D$4:$D$72,0)) -> 2. CDS | F16: zbs_c_dmotreeteam.ddlx.xml | G16: Tree View | H16: 10 months ago
C17: =LEFT(F17,FIND(".",F17)-1) -> zbs_c_dmotreeteam | D17: {=INDEX('Not Req'!$E$4:$E$72,MATCH(MID(F17,FIND(".",F17)+1,LEN(F17)-FIND(".",F17)+1),'Not Req'!$D$4:$D$72,0))} -> Metadata | E17: =INDEX('Not Req'!$F$4:$F$72,MATCH(MID(F17,FIND(".",F17)+1,LEN(F17)-FIND(".",F17)+1),'Not Req'!$D$4:$D$72,0)) -> 2. CDS | F17: zbs_c_dmotreeteam.ddlx.asddlxs | G17: Tree View | H17: 10 months ago
C18: =LEFT(F18,FIND(".",F18)-1) -> zbp_bs_demo_tree_team | D18: {=INDEX('Not Req'!$E$4:$E$72,MATCH(MID(F18,FIND(".",F18)+1,LEN(F18)-FIND(".",F18)+1),'Not Req'!$D$4:$D$72,0))} -> Classes | E18: =INDEX('Not Req'!$F$4:$F$72,MATCH(MID(F18,FIND(".",F18)+1,LEN(F18)-FIND(".",F18)+1),'Not Req'!$D$4:$D$72,0)) -> 3. Source Code Library | F18: zbp_bs_demo_tree_team.clas.abap | G18: Tree View | H18: 10 months ago
C19: =LEFT(F19,FIND(".",F19)-1) -> zbp_bs_demo_tree_teamc | D19: {=INDEX('Not Req'!$E$4:$E$72,MATCH(MID(F19,FIND(".",F19)+1,LEN(F19)-FIND(".",F19)+1),'Not Req'!$D$4:$D$72,0))} -> Classes | E19: =INDEX('Not Req'!$F$4:$F$72,MATCH(MID(F19,FIND(".",F19)+1,LEN(F19)-FIND(".",F19)+1),'Not Req'!$D$4:$D$72,0)) -> 3. Source Code Library | F19: zbp_bs_demo_tree_teamc.clas.abap | G19: Tree View | H19: 10 months ago
C20: =LEFT(F20,FIND(".",F20)-1) -> zbp_bs_demo_tree_team | D20: {=INDEX('Not Req'!$E$4:$E$72,MATCH(MID(F20,FIND(".",F20)+1,LEN(F20)-FIND(".",F20)+1),'Not Req'!$D$4:$D$72,0))} -> Classes Local | E20: =INDEX('Not Req'!$F$4:$F$72,MATCH(MID(F20,FIND(".",F20)+1,LEN(F20)-FIND(".",F20)+1),'Not Req'!$D$4:$D$72,0)) -> 3. Source Code Library | F20: zbp_bs_demo_tree_team.clas.locals_imp.abap | G20: Tree Deletion | H20: 9 months ago
C21: =LEFT(F21,FIND(".",F21)-1) -> zbp_bs_demo_tree_team | D21: {=INDEX('Not Req'!$E$4:$E$72,MATCH(MID(F21,FIND(".",F21)+1,LEN(F21)-FIND(".",F21)+1),'Not Req'!$D$4:$D$72,0))} -> Description : Classes | E21: =INDEX('Not Req'!$F$4:$F$72,MATCH(MID(F21,FIND(".",F21)+1,LEN(F21)-FIND(".",F21)+1),'Not Req'!$D$4:$D$72,0)) -> 3. Source Code Library | F21: zbp_bs_demo_tree_team.clas.xml | G21: Tree View | H21: 10 months ago
A22: D | B22: D | C22: =LEFT(F22,FIND(".",F22)-1) -> zbp_bs_demo_tree_teamc | D22: {=INDEX('Not Req'!$E$4:$E$72,MATCH(MID(F22,FIND(".",F22)+1,LEN(F22)-FIND(".",F22)+1),'Not Req'!$D$4:$D$72,0))} -> Description : Classes | E22: =INDEX('Not Req'!$F$4:$F$72,MATCH(MID(F22,FIND(".",F22)+1,LEN(F22)-FIND(".",F22)+1),'Not Req'!$D$4:$D$72,0)) -> 3. Source Code Library | F22: zbp_bs_demo_tree_teamc.clas.xml | G22: Tree View | H22: 10 months ago
C23: =LEFT(F23,FIND(".",F23)-1) -> zbs_demo_tree_team | D23: {=INDEX('Not Req'!$E$4:$E$72,MATCH(MID(F23,FIND(".",F23)+1,LEN(F23)-FIND(".",F23)+1),'Not Req'!$D$4:$D$72,0))} -> Service Definition | E23: =INDEX('Not Req'!$F$4:$F$72,MATCH(MID(F23,FIND(".",F23)+1,LEN(F23)-FIND(".",F23)+1),'Not Req'!$D$4:$D$72,0)) -> Business Services | F23: zbs_demo_tree_team.srvd.srvdsrv | G23: Tree View | H23: 10 months ago
C24: =LEFT(F24,FIND(".",F24)-1) -> 04b39c4b139bc1cc065f421ae4eb0dht | D24: {=INDEX('Not Req'!$E$4:$E$72,MATCH(MID(F24,FIND(".",F24)+1,LEN(F24)-FIND(".",F24)+1),'Not Req'!$D$4:$D$72,0))} -> Internal (Not Req) | E24: =INDEX('Not Req'!$F$4:$F$72,MATCH(MID(F24,FIND(".",F24)+1,LEN(F24)-FIND(".",F24)+1),'Not Req'!$D$4:$D$72,0)) -> Internal (Not Req) | F24: 04b39c4b139bc1cc065f421ae4eb0dht.sush.xml | G24: Tree View | H24: 10 months ago
C25: =LEFT(F25,FIND(".",F25)-1) -> zbs_c_dmotreeteam | D25: {=INDEX('Not Req'!$E$4:$E$72,MATCH(MID(F25,FIND(".",F25)+1,LEN(F25)-FIND(".",F25)+1),'Not Req'!$D$4:$D$72,0))} -> Internal (Not Req) | E25: =INDEX('Not Req'!$F$4:$F$72,MATCH(MID(F25,FIND(".",F25)+1,LEN(F25)-FIND(".",F25)+1),'Not Req'!$D$4:$D$72,0)) -> Internal (Not Req) | F25: zbs_c_dmotreeteam.ddls.baseinfo | G25: Tree View | H25: 10 months ago
C26: =LEFT(F26,FIND(".",F26)-1) -> zbs_demo_tree_team | D26: {=INDEX('Not Req'!$E$4:$E$72,MATCH(MID(F26,FIND(".",F26)+1,LEN(F26)-FIND(".",F26)+1),'Not Req'!$D$4:$D$72,0))} -> Internal (Not Req) | E26: =INDEX('Not Req'!$F$4:$F$72,MATCH(MID(F26,FIND(".",F26)+1,LEN(F26)-FIND(".",F26)+1),'Not Req'!$D$4:$D$72,0)) -> Internal (Not Req) | F26: zbs_demo_tree_team.srvd.xml | G26: Tree View | H26: 10 months ago
C27: =LEFT(F27,FIND(".",F27)-1) -> zbs_i_dmotreeteamhr | D27: {=INDEX('Not Req'!$E$4:$E$72,MATCH(MID(F27,FIND(".",F27)+1,LEN(F27)-FIND(".",F27)+1),'Not Req'!$D$4:$D$72,0))} -> Internal (Not Req) | E27: =INDEX('Not Req'!$F$4:$F$72,MATCH(MID(F27,FIND(".",F27)+1,LEN(F27)-FIND(".",F27)+1),'Not Req'!$D$4:$D$72,0)) -> Internal (Not Req) | F27: zbs_i_dmotreeteamhr.ddls.baseinfo | G27: Tree View | H27: 10 months ago
C28: =LEFT(F28,FIND(".",F28)-1) -> zbs_r_dmotreeteam | D28: {=INDEX('Not Req'!$E$4:$E$72,MATCH(MID(F28,FIND(".",F28)+1,LEN(F28)-FIND(".",F28)+1),'Not Req'!$D$4:$D$72,0))} -> Internal (Not Req) | E28: =INDEX('Not Req'!$F$4:$F$72,MATCH(MID(F28,FIND(".",F28)+1,LEN(F28)-FIND(".",F28)+1),'Not Req'!$D$4:$D$72,0)) -> Internal (Not Req) | F28: zbs_r_dmotreeteam.ddls.baseinfo | G28: Tree View | H28: 10 months ago
C29: =LEFT(F29,FIND(".",F29)-1) -> zbs_ui_demo_tree_team_o4 | D29: {=INDEX('Not Req'!$E$4:$E$72,MATCH(MID(F29,FIND(".",F29)+1,LEN(F29)-FIND(".",F29)+1),'Not Req'!$D$4:$D$72,0))} -> Internal (Not Req) | E29: =INDEX('Not Req'!$F$4:$F$72,MATCH(MID(F29,FIND(".",F29)+1,LEN(F29)-FIND(".",F29)+1),'Not Req'!$D$4:$D$72,0)) -> Internal (Not Req) | F29: zbs_ui_demo_tree_team_o4.srvb.xml | G29: Tree View | H29: 10 months ago
C30: =LEFT(F30,FIND(".",F30)-1) -> zbs_ui_demo_tree_team_o4_0001_g4ba | D30: {=INDEX('Not Req'!$E$4:$E$72,MATCH(MID(F30,FIND(".",F30)+1,LEN(F30)-FIND(".",F30)+1),'Not Req'!$D$4:$D$72,0))} -> Internal (Not Req) | E30: =INDEX('Not Req'!$F$4:$F$72,MATCH(MID(F30,FIND(".",F30)+1,LEN(F30)-FIND(".",F30)+1),'Not Req'!$D$4:$D$72,0)) -> Internal (Not Req) | F30: zbs_ui_demo_tree_team_o4_0001_g4ba.sco2.xml | G30: Tree View | H30: 10 months ago
A31: d | B31: d | C31: =LEFT(F31,FIND(".",F31)-1) -> zbs_ui_demo_tree_team_o4__00001_ibs | D31: {=INDEX('Not Req'!$E$4:$E$72,MATCH(MID(F31,FIND(".",F31)+1,LEN(F31)-FIND(".",F31)+1),'Not Req'!$D$4:$D$72,0))} -> Internal (Not Req) | E31: =INDEX('Not Req'!$F$4:$F$72,MATCH(MID(F31,FIND(".",F31)+1,LEN(F31)-FIND(".",F31)+1),'Not Req'!$D$4:$D$72,0)) -> Internal (Not Req) | F31: zbs_ui_demo_tree_team_o4__00001_ibs.sia6.xml | G31: Tree View | H31: 10 months ago

Sheet PATTERN CDS
B2: d | C2: Object | D2: Type | E2: Category | F2: Github Object | G2: Github Type | H2: Version
B4: 1 | C4: =LEFT(F4,FIND(".",F4)-1) -> package | D4: {=INDEX('Not Req'!$E$4:$E$72,MATCH(MID(F4,FIND(".",F4)+1,LEN(F4)-FIND(".",F4)+1),'Not Req'!$D$4:$D$72,0))} -> Description : Package | E4: =INDEX('Not Req'!$F$4:$F$72,MATCH(MID(F4,FIND(".",F4)+1,LEN(F4)-FIND(".",F4)+1),'Not Req'!$D$4:$D$72,0)) -> 0. Package | F4: package.devc.xml | G4: CDS Pattern | H4: 2 months ago | N4: {=_xlfn.UNIQUE(C4:C21)} -> package
C5: =LEFT(F5,FIND(".",F5)-1) -> zbs_cp_invoice_d | D5: {=INDEX('Not Req'!$E$4:$E$72,MATCH(MID(F5,FIND(".",F5)+1,LEN(F5)-FIND(".",F5)+1),'Not Req'!$D$4:$D$72,0))} -> Table | E5: =INDEX('Not Req'!$F$4:$F$72,MATCH(MID(F5,FIND(".",F5)+1,LEN(F5)-FIND(".",F5)+1),'Not Req'!$D$4:$D$72,0)) -> 1. Dictionary | F5: zbs_cp_invoice_d.tabl.xml | G5: CDS Pattern | H5: 2 months ago | N5: zbs_cp_invoice_d
C6: =LEFT(F6,FIND(".",F6)-1) -> zbs_cp_pos_d | D6: {=INDEX('Not Req'!$E$4:$E$72,MATCH(MID(F6,FIND(".",F6)+1,LEN(F6)-FIND(".",F6)+1),'Not Req'!$D$4:$D$72,0))} -> Table | E6: =INDEX('Not Req'!$F$4:$F$72,MATCH(MID(F6,FIND(".",F6)+1,LEN(F6)-FIND(".",F6)+1),'Not Req'!$D$4:$D$72,0)) -> 1. Dictionary | F6: zbs_cp_pos_d.tabl.xml | G6: CDS Pattern | H6: 2 months ago | N6: zbs_cp_pos_d
C7: =LEFT(F7,FIND(".",F7)-1) -> zbs_c_cdspatterninvoice | D7: {=INDEX('Not Req'!$E$4:$E$72,MATCH(MID(F7,FIND(".",F7)+1,LEN(F7)-FIND(".",F7)+1),'Not Req'!$D$4:$D$72,0))} -> BDEF | E7: =INDEX('Not Req'!$F$4:$F$72,MATCH(MID(F7,FIND(".",F7)+1,LEN(F7)-FIND(".",F7)+1),'Not Req'!$D$4:$D$72,0)) -> 2. CDS | F7: zbs_c_cdspatterninvoice.bdef.asbdef | G7: CDS Pattern | H7: 2 months ago | N7: zbs_c_cdspatterninvoice
C8: =LEFT(F8,FIND(".",F8)-1) -> zbs_t_cdspatterninvoice | D8: {=INDEX('Not Req'!$E$4:$E$72,MATCH(MID(F8,FIND(".",F8)+1,LEN(F8)-FIND(".",F8)+1),'Not Req'!$D$4:$D$72,0))} -> BDEF | E8: =INDEX('Not Req'!$F$4:$F$72,MATCH(MID(F8,FIND(".",F8)+1,LEN(F8)-FIND(".",F8)+1),'Not Req'!$D$4:$D$72,0)) -> 2. CDS | F8: zbs_t_cdspatterninvoice.bdef.asbdef | G8: CDS Pattern | H8: 2 months ago | N8: zbs_t_cdspatterninvoice
C9: =LEFT(F9,FIND(".",F9)-1) -> zbs_c_cdspatterninvoice | D9: {=INDEX('Not Req'!$E$4:$E$72,MATCH(MID(F9,FIND(".",F9)+1,LEN(F9)-FIND(".",F9)+1),'Not Req'!$D$4:$D$72,0))} -> Data Definition | E9: =INDEX('Not Req'!$F$4:$F$72,MATCH(MID(F9,FIND(".",F9)+1,LEN(F9)-FIND(".",F9)+1),'Not Req'!$D$4:$D$72,0)) -> 2. CDS | F9: zbs_c_cdspatterninvoice.ddls.asddls | G9: CDS Pattern | H9: 2 months ago | N9: zbs_c_cdspatternposition
C10: =LEFT(F10,FIND(".",F10)-1) -> zbs_c_cdspatternposition | D10: {=INDEX('Not Req'!$E$4:$E$72,MATCH(MID(F10,FIND(".",F10)+1,LEN(F10)-FIND(".",F10)+1),'Not Req'!$D$4:$D$72,0))} -> Data Definition | E10: =INDEX('Not Req'!$F$4:$F$72,MATCH(MID(F10,FIND(".",F10)+1,LEN(F10)-FIND(".",F10)+1),'Not Req'!$D$4:$D$72,0)) -> 2. CDS | F10: zbs_c_cdspatternposition.ddls.asddls | G10: CDS Pattern | H10: 2 months ago | N10: zbs_t_cdspatternposition
C11: =LEFT(F11,FIND(".",F11)-1) -> zbs_t_cdspatterninvoice | D11: {=INDEX('Not Req'!$E$4:$E$72,MATCH(MID(F11,FIND(".",F11)+1,LEN(F11)-FIND(".",F11)+1),'Not Req'!$D$4:$D$72,0))} -> Data Definition | E11: =INDEX('Not Req'!$F$4:$F$72,MATCH(MID(F11,FIND(".",F11)+1,LEN(F11)-FIND(".",F11)+1),'Not Req'!$D$4:$D$72,0)) -> 2. CDS | F11: zbs_t_cdspatterninvoice.ddls.asddls | G11: CDS Pattern | H11: 2 months ago
C12: =LEFT(F12,FIND(".",F12)-1) -> zbs_t_cdspatternposition | D12: {=INDEX('Not Req'!$E$4:$E$72,MATCH(MID(F12,FIND(".",F12)+1,LEN(F12)-FIND(".",F12)+1),'Not Req'!$D$4:$D$72,0))} -> Data Definition | E12: =INDEX('Not Req'!$F$4:$F$72,MATCH(MID(F12,FIND(".",F12)+1,LEN(F12)-FIND(".",F12)+1),'Not Req'!$D$4:$D$72,0)) -> 2. CDS | F12: zbs_t_cdspatternposition.ddls.asddls | G12: CDS Pattern | H12: 2 months ago
C13: =LEFT(F13,FIND(".",F13)-1) -> zbs_c_cdspatterninvoice | D13: {=INDEX('Not Req'!$E$4:$E$72,MATCH(MID(F13,FIND(".",F13)+1,LEN(F13)-FIND(".",F13)+1),'Not Req'!$D$4:$D$72,0))} -> Description : BDEF | E13: =INDEX('Not Req'!$F$4:$F$72,MATCH(MID(F13,FIND(".",F13)+1,LEN(F13)-FIND(".",F13)+1),'Not Req'!$D$4:$D$72,0)) -> 2. CDS | F13: zbs_c_cdspatterninvoice.bdef.xml | G13: CDS Pattern | H13: 2 months ago
C14: =LEFT(F14,FIND(".",F14)-1) -> zbs_t_cdspatterninvoice | D14: {=INDEX('Not Req'!$E$4:$E$72,MATCH(MID(F14,FIND(".",F14)+1,LEN(F14)-FIND(".",F14)+1),'Not Req'!$D$4:$D$72,0))} -> Description : BDEF | E14: =INDEX('Not Req'!$F$4:$F$72,MATCH(MID(F14,FIND(".",F14)+1,LEN(F14)-FIND(".",F14)+1),'Not Req'!$D$4:$D$72,0)) -> 2. CDS | F14: zbs_t_cdspatterninvoice.bdef.xml | G14: CDS Pattern | H14: 2 months ago
C15: =LEFT(F15,FIND(".",F15)-1) -> zbs_c_cdspatterninvoice | D15: {=INDEX('Not Req'!$E$4:$E$72,MATCH(MID(F15,FIND(".",F15)+1,LEN(F15)-FIND(".",F15)+1),'Not Req'!$D$4:$D$72,0))} -> Description : Data Definition | E15: =INDEX('Not Req'!$F$4:$F$72,MATCH(MID(F15,FIND(".",F15)+1,LEN(F15)-FIND(".",F15)+1),'Not Req'!$D$4:$D$72,0)) -> 2. CDS | F15: zbs_c_cdspatterninvoice.ddls.xml | G15: CDS Pattern | H15: 2 months ago
C16: =LEFT(F16,FIND(".",F16)-1) -> zbs_c_cdspatternposition | D16: {=INDEX('Not Req'!$E$4:$E$72,MATCH(MID(F16,FIND(".",F16)+1,LEN(F16)-FIND(".",F16)+1),'Not Req'!$D$4:$D$72,0))} -> Description : Data Definition | E16: =INDEX('Not Req'!$F$4:$F$72,MATCH(MID(F16,FIND(".",F16)+1,LEN(F16)-FIND(".",F16)+1),'Not Req'!$D$4:$D$72,0)) -> 2. CDS | F16: zbs_c_cdspatternposition.ddls.xml | G16: CDS Pattern | H16: 2 months ago
C17: =LEFT(F17,FIND(".",F17)-1) -> zbs_t_cdspatterninvoice | D17: {=INDEX('Not Req'!$E$4:$E$72,MATCH(MID(F17,FIND(".",F17)+1,LEN(F17)-FIND(".",F17)+1),'Not Req'!$D$4:$D$72,0))} -> Description : Data Definition | E17: =INDEX('Not Req'!$F$4:$F$72,MATCH(MID(F17,FIND(".",F17)+1,LEN(F17)-FIND(".",F17)+1),'Not Req'!$D$4:$D$72,0)) -> 2. CDS | F17: zbs_t_cdspatterninvoice.ddls.xml | G17: CDS Pattern | H17: 2 months ago
C18: =LEFT(F18,FIND(".",F18)-1) -> zbs_t_cdspatternposition | D18: {=INDEX('Not Req'!$E$4:$E$72,MATCH(MID(F18,FIND(".",F18)+1,LEN(F18)-FIND(".",F18)+1),'Not Req'!$D$4:$D$72,0))} -> Description : Data Definition | E18: =INDEX('Not Req'!$F$4:$F$72,MATCH(MID(F18,FIND(".",F18)+1,LEN(F18)-FIND(".",F18)+1),'Not Req'!$D$4:$D$72,0)) -> 2. CDS | F18: zbs_t_cdspatternposition.ddls.xml | G18: CDS Pattern | H18: 2 months ago
C19: =LEFT(F19,FIND(".",F19)-1) -> zbs_c_cdspatterninvoice | D19: {=INDEX('Not Req'!$E$4:$E$72,MATCH(MID(F19,FIND(".",F19)+1,LEN(F19)-FIND(".",F19)+1),'Not Req'!$D$4:$D$72,0))} -> Description : Metadata | E19: =INDEX('Not Req'!$F$4:$F$72,MATCH(MID(F19,FIND(".",F19)+1,LEN(F19)-FIND(".",F19)+1),'Not Req'!$D$4:$D$72,0)) -> 2. CDS | F19: zbs_c_cdspatterninvoice.ddlx.xml | G19: CDS Pattern | H19: 2 months ago
C20: =LEFT(F20,FIND(".",F20)-1) -> zbs_c_cdspatternposition | D20: {=INDEX('Not Req'!$E$4:$E$72,MATCH(MID(F20,FIND(".",F20)+1,LEN(F20)-FIND(".",F20)+1),'Not Req'!$D$4:$D$72,0))} -> Description : Metadata | E20: =INDEX('Not Req'!$F$4:$F$72,MATCH(MID(F20,FIND(".",F20)+1,LEN(F20)-FIND(".",F20)+1),'Not Req'!$D$4:$D$72,0)) -> 2. CDS | F20: zbs_c_cdspatternposition.ddlx.xml | G20: CDS Pattern | H20: 2 months ago
C21: =LEFT(F21,FIND(".",F21)-1) -> zbs_c_cdspatterninvoice | D21: {=INDEX('Not Req'!$E$4:$E$72,MATCH(MID(F21,FIND(".",F21)+1,LEN(F21)-FIND(".",F21)+1),'Not Req'!$D$4:$D$72,0))} -> Metadata | E21: =INDEX('Not Req'!$F$4:$F$72,MATCH(MID(F21,FIND(".",F21)+1,LEN(F21)-FIND(".",F21)+1),'Not Req'!$D$4:$D$72,0)) -> 2. CDS | F21: zbs_c_cdspatterninvoice.ddlx.asddlxs | G21: CDS Pattern | H21: 2 months ago
A22: D | B22: D | C22: =LEFT(F22,FIND(".",F22)-1) -> zbs_c_cdspatternposition | D22: {=INDEX('Not Req'!$E$4:$E$72,MATCH(MID(F22,FIND(".",F22)+1,LEN(F22)-FIND(".",F22)+1),'Not Req'!$D$4:$D$72,0))} -> Metadata | E22: =INDEX('Not Req'!$F$4:$F$72,MATCH(MID(F22,FIND(".",F22)+1,LEN(F22)-FIND(".",F22)+1),'Not Req'!$D$4:$D$72,0)) -> 2. CDS | F22: zbs_c_cdspatternposition.ddlx.asddlxs | G22: CDS Pattern | H22: 2 months ago
C23: =LEFT(F23,FIND(".",F23)-1) -> zbp_bs_cdspattern_invoice | D23: {=INDEX('Not Req'!$E$4:$E$72,MATCH(MID(F23,FIND(".",F23)+1,LEN(F23)-FIND(".",F23)+1),'Not Req'!$D$4:$D$72,0))} -> Classes | E23: =INDEX('Not Req'!$F$4:$F$72,MATCH(MID(F23,FIND(".",F23)+1,LEN(F23)-FIND(".",F23)+1),'Not Req'!$D$4:$D$72,0)) -> 3. Source Code Library | F23: zbp_bs_cdspattern_invoice.clas.abap | G23: CDS Pattern | H23: 2 months ago
C24: =LEFT(F24,FIND(".",F24)-1) -> zbp_bs_cdspattern_invoice | D24: {=INDEX('Not Req'!$E$4:$E$72,MATCH(MID(F24,FIND(".",F24)+1,LEN(F24)-FIND(".",F24)+1),'Not Req'!$D$4:$D$72,0))} -> Classes Local | E24: =INDEX('Not Req'!$F$4:$F$72,MATCH(MID(F24,FIND(".",F24)+1,LEN(F24)-FIND(".",F24)+1),'Not Req'!$D$4:$D$72,0)) -> 3. Source Code Library | F24: zbp_bs_cdspattern_invoice.clas.locals_imp.abap | G24: CDS Pattern | H24: 2 months ago
C25: =LEFT(F25,FIND(".",F25)-1) -> zbp_bs_cdspattern_invoice | D25: {=INDEX('Not Req'!$E$4:$E$72,MATCH(MID(F25,FIND(".",F25)+1,LEN(F25)-FIND(".",F25)+1),'Not Req'!$D$4:$D$72,0))} -> Description : Classes | E25: =INDEX('Not Req'!$F$4:$F$72,MATCH(MID(F25,FIND(".",F25)+1,LEN(F25)-FIND(".",F25)+1),'Not Req'!$D$4:$D$72,0)) -> 3. Source Code Library | F25: zbp_bs_cdspattern_invoice.clas.xml | G25: CDS Pattern | H25: 2 months ago
C26: =LEFT(F26,FIND(".",F26)-1) -> zbs_demo_pattern_cds | D26: {=INDEX('Not Req'!$E$4:$E$72,MATCH(MID(F26,FIND(".",F26)+1,LEN(F26)-FIND(".",F26)+1),'Not Req'!$D$4:$D$72,0))} -> Service Definition | E26: =INDEX('Not Req'!$F$4:$F$72,MATCH(MID(F26,FIND(".",F26)+1,LEN(F26)-FIND(".",F26)+1),'Not Req'!$D$4:$D$72,0)) -> Business Services | F26: zbs_demo_pattern_cds.srvd.srvdsrv | G26: CDS Pattern | H26: 2 months ago
C27: =LEFT(F27,FIND(".",F27)-1) -> 12de3d43ab9bc726d7070e59867b1eht | D27: {=INDEX('Not Req'!$E$4:$E$72,MATCH(MID(F27,FIND(".",F27)+1,LEN(F27)-FIND(".",F27)+1),'Not Req'!$D$4:$D$72,0))} -> Internal (Not Req) | E27: =INDEX('Not Req'!$F$4:$F$72,MATCH(MID(F27,FIND(".",F27)+1,LEN(F27)-FIND(".",F27)+1),'Not Req'!$D$4:$D$72,0)) -> Internal (Not Req) | F27: 12de3d43ab9bc726d7070e59867b1eht.sush.xml | G27: CDS Pattern | H27: 2 months ago
C28: =LEFT(F28,FIND(".",F28)-1) -> zbs_c_cdspatterninvoice | D28: {=INDEX('Not Req'!$E$4:$E$72,MATCH(MID(F28,FIND(".",F28)+1,LEN(F28)-FIND(".",F28)+1),'Not Req'!$D$4:$D$72,0))} -> Internal (Not Req) | E28: =INDEX('Not Req'!$F$4:$F$72,MATCH(MID(F28,FIND(".",F28)+1,LEN(F28)-FIND(".",F28)+1),'Not Req'!$D$4:$D$72,0)) -> Internal (Not Req) | F28: zbs_c_cdspatterninvoice.ddls.baseinfo | G28: CDS Pattern | H28: 2 months ago
C29: =LEFT(F29,FIND(".",F29)-1) -> zbs_c_cdspatternposition | D29: {=INDEX('Not Req'!$E$4:$E$72,MATCH(MID(F29,FIND(".",F29)+1,LEN(F29)-FIND(".",F29)+1),'Not Req'!$D$4:$D$72,0))} -> Internal (Not Req) | E29: =INDEX('Not Req'!$F$4:$F$72,MATCH(MID(F29,FIND(".",F29)+1,LEN(F29)-FIND(".",F29)+1),'Not Req'!$D$4:$D$72,0)) -> Internal (Not Req) | F29: zbs_c_cdspatternposition.ddls.baseinfo | G29: CDS Pattern | H29: 2 months ago
C30: =LEFT(F30,FIND(".",F30)-1) -> zbs_demo_pattern_cds | D30: {=INDEX('Not Req'!$E$4:$E$72,MATCH(MID(F30,FIND(".",F30)+1,LEN(F30)-FIND(".",F30)+1),'Not Req'!$D$4:$D$72,0))} -> Internal (Not Req) | E30: =INDEX('Not Req'!$F$4:$F$72,MATCH(MID(F30,FIND(".",F30)+1,LEN(F30)-FIND(".",F30)+1),'Not Req'!$D$4:$D$72,0)) -> Internal (Not Req) | F30: zbs_demo_pattern_cds.srvd.xml | G30: CDS Pattern | H30: 2 months ago
C31: =LEFT(F31,FIND(".",F31)-1) -> zbs_t_cdspatterninvoice | D31: {=INDEX('Not Req'!$E$4:$E$72,MATCH(MID(F31,FIND(".",F31)+1,LEN(F31)-FIND(".",F31)+1),'Not Req'!$D$4:$D$72,0))} -> Internal (Not Req) | E31: =INDEX('Not Req'!$F$4:$F$72,MATCH(MID(F31,FIND(".",F31)+1,LEN(F31)-FIND(".",F31)+1),'Not Req'!$D$4:$D$72,0)) -> Internal (Not Req) | F31: zbs_t_cdspatterninvoice.ddls.baseinfo | G31: CDS Pattern | H31: 2 months ago
C32: =LEFT(F32,FIND(".",F32)-1) -> zbs_t_cdspatternposition | D32: {=INDEX('Not Req'!$E$4:$E$72,MATCH(MID(F32,FIND(".",F32)+1,LEN(F32)-FIND(".",F32)+1),'Not Req'!$D$4:$D$72,0))} -> Internal (Not Req) | E32: =INDEX('Not Req'!$F$4:$F$72,MATCH(MID(F32,FIND(".",F32)+1,LEN(F32)-FIND(".",F32)+1),'Not Req'!$D$4:$D$72,0)) -> Internal (Not Req) | F32: zbs_t_cdspatternposition.ddls.baseinfo | G32: CDS Pattern | H32: 2 months ago
C33: =LEFT(F33,FIND(".",F33)-1) -> zbs_ui_demo_pattern_cds_o4 | D33: {=INDEX('Not Req'!$E$4:$E$72,MATCH(MID(F33,FIND(".",F33)+1,LEN(F33)-FIND(".",F33)+1),'Not Req'!$D$4:$D$72,0))} -> Internal (Not Req) | E33: =INDEX('Not Req'!$F$4:$F$72,MATCH(MID(F33,FIND(".",F33)+1,LEN(F33)-FIND(".",F33)+1),'Not Req'!$D$4:$D$72,0)) -> Internal (Not Req) | F33: zbs_ui_demo_pattern_cds_o4.srvb.xml | G33: CDS Pattern | H33: 2 months ago
A34: DD | B34: DD | C34: =LEFT(F34,FIND(".",F34)-1) -> zbs_ui_demo_pattern_cds_o4_0001_g4ba | D34: {=INDEX('Not Req'!$E$4:$E$72,MATCH(MID(F34,FIND(".",F34)+1,LEN(F34)-FIND(".",F34)+1),'Not Req'!$D$4:$D$72,0))} -> Internal (Not Req) | E34: =INDEX('Not Req'!$F$4:$F$72,MATCH(MID(F34,FIND(".",F34)+1,LEN(F34)-FIND(".",F34)+1),'Not Req'!$D$4:$D$72,0)) -> Internal (Not Req) | F34: zbs_ui_demo_pattern_cds_o4_0001_g4ba.sco2.xml | G34: CDS Pattern | H34: 2 months ago

Sheet PATTERN API
B2: d | C2: Object | D2: Type | E2: Category | F2: Github Object | G2: Github Type | H2: Version
B4: 1 | C4: =LEFT(F4,FIND(".",F4)-1) -> package | D4: {=INDEX('Not Req'!$E$4:$E$72,MATCH(MID(F4,FIND(".",F4)+1,LEN(F4)-FIND(".",F4)+1),'Not Req'!$D$4:$D$72,0))} -> Description : Package | E4: =INDEX('Not Req'!$F$4:$F$72,MATCH(MID(F4,FIND(".",F4)+1,LEN(F4)-FIND(".",F4)+1),'Not Req'!$D$4:$D$72,0)) -> 0. Package | F4: package.devc.xml | G4: CDS Pattern | H4: 2 months ago | N4: {=_xlfn.UNIQUE(C4:C21)} -> package
C5: =LEFT(F5,FIND(".",F5)-1) -> zbs_api_target | D5: {=INDEX('Not Req'!$E$4:$E$72,MATCH(MID(F5,FIND(".",F5)+1,LEN(F5)-FIND(".",F5)+1),'Not Req'!$D$4:$D$72,0))} -> Table | E5: =INDEX('Not Req'!$F$4:$F$72,MATCH(MID(F5,FIND(".",F5)+1,LEN(F5)-FIND(".",F5)+1),'Not Req'!$D$4:$D$72,0)) -> 1. Dictionary | F5: zbs_api_target.tabl.xml | G5: API Pattern | H5: 7 months ago | N5: zbs_api_target
C6: =LEFT(F6,FIND(".",F6)-1) -> zbs_r_apilocation | D6: {=INDEX('Not Req'!$E$4:$E$72,MATCH(MID(F6,FIND(".",F6)+1,LEN(F6)-FIND(".",F6)+1),'Not Req'!$D$4:$D$72,0))} -> BDEF | E6: =INDEX('Not Req'!$F$4:$F$72,MATCH(MID(F6,FIND(".",F6)+1,LEN(F6)-FIND(".",F6)+1),'Not Req'!$D$4:$D$72,0)) -> 2. CDS | F6: zbs_r_apilocation.bdef.asbdef | G6: API Pattern | H6: 7 months ago | N6: zbs_r_apilocation
C7: =LEFT(F7,FIND(".",F7)-1) -> zbs_r_apilocation | D7: {=INDEX('Not Req'!$E$4:$E$72,MATCH(MID(F7,FIND(".",F7)+1,LEN(F7)-FIND(".",F7)+1),'Not Req'!$D$4:$D$72,0))} -> Data Definition | E7: =INDEX('Not Req'!$F$4:$F$72,MATCH(MID(F7,FIND(".",F7)+1,LEN(F7)-FIND(".",F7)+1),'Not Req'!$D$4:$D$72,0)) -> 2. CDS | F7: zbs_r_apilocation.ddls.asddls | G7: API Pattern | H7: 7 months ago | N7: zbp_bs_api_location
C8: =LEFT(F8,FIND(".",F8)-1) -> zbs_r_apilocation | D8: {=INDEX('Not Req'!$E$4:$E$72,MATCH(MID(F8,FIND(".",F8)+1,LEN(F8)-FIND(".",F8)+1),'Not Req'!$D$4:$D$72,0))} -> Description : BDEF | E8: =INDEX('Not Req'!$F$4:$F$72,MATCH(MID(F8,FIND(".",F8)+1,LEN(F8)-FIND(".",F8)+1),'Not Req'!$D$4:$D$72,0)) -> 2. CDS | F8: zbs_r_apilocation.bdef.xml | G8: API Pattern | H8: 7 months ago | N8: zcl_bs_api_target
C9: =LEFT(F9,FIND(".",F9)-1) -> zbs_r_apilocation | D9: {=INDEX('Not Req'!$E$4:$E$72,MATCH(MID(F9,FIND(".",F9)+1,LEN(F9)-FIND(".",F9)+1),'Not Req'!$D$4:$D$72,0))} -> Description : Data Definition | E9: =INDEX('Not Req'!$F$4:$F$72,MATCH(MID(F9,FIND(".",F9)+1,LEN(F9)-FIND(".",F9)+1),'Not Req'!$D$4:$D$72,0)) -> 2. CDS | F9: zbs_r_apilocation.ddls.xml | G9: API Pattern | H9: 7 months ago | N9: zbs_api_location_endpoint
C10: =LEFT(F10,FIND(".",F10)-1) -> zbp_bs_api_location | D10: {=INDEX('Not Req'!$E$4:$E$72,MATCH(MID(F10,FIND(".",F10)+1,LEN(F10)-FIND(".",F10)+1),'Not Req'!$D$4:$D$72,0))} -> Classes | E10: =INDEX('Not Req'!$F$4:$F$72,MATCH(MID(F10,FIND(".",F10)+1,LEN(F10)-FIND(".",F10)+1),'Not Req'!$D$4:$D$72,0)) -> 3. Source Code Library | F10: zbp_bs_api_location.clas.abap | G10: API Pattern | H10: 7 months ago | N10: 710df9f0500c0069d677cc915293cbht
C11: =LEFT(F11,FIND(".",F11)-1) -> zcl_bs_api_target | D11: {=INDEX('Not Req'!$E$4:$E$72,MATCH(MID(F11,FIND(".",F11)+1,LEN(F11)-FIND(".",F11)+1),'Not Req'!$D$4:$D$72,0))} -> Classes | E11: =INDEX('Not Req'!$F$4:$F$72,MATCH(MID(F11,FIND(".",F11)+1,LEN(F11)-FIND(".",F11)+1),'Not Req'!$D$4:$D$72,0)) -> 3. Source Code Library | F11: zcl_bs_api_target.clas.abap | G11: API Pattern | H11: 7 months ago | N11: 782ebdfdd92774c39297d4948c3981ht
C12: =LEFT(F12,FIND(".",F12)-1) -> zbp_bs_api_location | D12: {=INDEX('Not Req'!$E$4:$E$72,MATCH(MID(F12,FIND(".",F12)+1,LEN(F12)-FIND(".",F12)+1),'Not Req'!$D$4:$D$72,0))} -> Classes Local | E12: =INDEX('Not Req'!$F$4:$F$72,MATCH(MID(F12,FIND(".",F12)+1,LEN(F12)-FIND(".",F12)+1),'Not Req'!$D$4:$D$72,0)) -> 3. Source Code Library | F12: zbp_bs_api_location.clas.locals_imp.abap | G12: API Pattern | H12: 7 months ago | N12: zbs_api_location_endp_o2
C13: =LEFT(F13,FIND(".",F13)-1) -> zbp_bs_api_location | D13: {=INDEX('Not Req'!$E$4:$E$72,MATCH(MID(F13,FIND(".",F13)+1,LEN(F13)-FIND(".",F13)+1),'Not Req'!$D$4:$D$72,0))} -> Description : Classes | E13: =INDEX('Not Req'!$F$4:$F$72,MATCH(MID(F13,FIND(".",F13)+1,LEN(F13)-FIND(".",F13)+1),'Not Req'!$D$4:$D$72,0)) -> 3. Source Code Library | F13: zbp_bs_api_location.clas.xml | G13: API Pattern | H13: 7 months ago | N13: zbs_api_location_endp_o2_iwsg
C14: =LEFT(F14,FIND(".",F14)-1) -> zcl_bs_api_target | D14: {=INDEX('Not Req'!$E$4:$E$72,MATCH(MID(F14,FIND(".",F14)+1,LEN(F14)-FIND(".",F14)+1),'Not Req'!$D$4:$D$72,0))} -> Description : Classes | E14: =INDEX('Not Req'!$F$4:$F$72,MATCH(MID(F14,FIND(".",F14)+1,LEN(F14)-FIND(".",F14)+1),'Not Req'!$D$4:$D$72,0)) -> 3. Source Code Library | F14: zcl_bs_api_target.clas.xml | G14: API Pattern | H14: 7 months ago | N14: zbs_api_location_endp_o2_iwsg_ibs
C15: =LEFT(F15,FIND(".",F15)-1) -> zbs_api_location_endpoint | D15: {=INDEX('Not Req'!$E$4:$E$72,MATCH(MID(F15,FIND(".",F15)+1,LEN(F15)-FIND(".",F15)+1),'Not Req'!$D$4:$D$72,0))} -> Service Definition | E15: =INDEX('Not Req'!$F$4:$F$72,MATCH(MID(F15,FIND(".",F15)+1,LEN(F15)-FIND(".",F15)+1),'Not Req'!$D$4:$D$72,0)) -> Business Services | F15: zbs_api_location_endpoint.srvd.srvdsrv | G15: API Pattern | H15: 7 months ago
C16: =LEFT(F16,FIND(".",F16)-1) -> 710df9f0500c0069d677cc915293cbht | D16: {=INDEX('Not Req'!$E$4:$E$72,MATCH(MID(F16,FIND(".",F16)+1,LEN(F16)-FIND(".",F16)+1),'Not Req'!$D$4:$D$72,0))} -> Internal (Not Req) | E16: =INDEX('Not Req'!$F$4:$F$72,MATCH(MID(F16,FIND(".",F16)+1,LEN(F16)-FIND(".",F16)+1),'Not Req'!$D$4:$D$72,0)) -> Internal (Not Req) | F16: 710df9f0500c0069d677cc915293cbht.sush.xml | G16: API Pattern | H16: 7 months ago
C17: =LEFT(F17,FIND(".",F17)-1) -> 782ebdfdd92774c39297d4948c3981ht | D17: {=INDEX('Not Req'!$E$4:$E$72,MATCH(MID(F17,FIND(".",F17)+1,LEN(F17)-FIND(".",F17)+1),'Not Req'!$D$4:$D$72,0))} -> Internal (Not Req) | E17: =INDEX('Not Req'!$F$4:$F$72,MATCH(MID(F17,FIND(".",F17)+1,LEN(F17)-FIND(".",F17)+1),'Not Req'!$D$4:$D$72,0)) -> Internal (Not Req) | F17: 782ebdfdd92774c39297d4948c3981ht.sush.xml | G17: API Pattern | H17: 7 months ago
C18: =LEFT(F18,FIND(".",F18)-1) -> zbs_api_location_endp_o2 | D18: {=INDEX('Not Req'!$E$4:$E$72,MATCH(MID(F18,FIND(".",F18)+1,LEN(F18)-FIND(".",F18)+1),'Not Req'!$D$4:$D$72,0))} -> Internal (Not Req) | E18: =INDEX('Not Req'!$F$4:$F$72,MATCH(MID(F18,FIND(".",F18)+1,LEN(F18)-FIND(".",F18)+1),'Not Req'!$D$4:$D$72,0)) -> Internal (Not Req) | F18: zbs_api_location_endp_o2.srvb.xml | G18: API Pattern | H18: 7 months ago
C19: =LEFT(F19,FIND(".",F19)-1) -> zbs_api_location_endp_o2_iwsg | D19: {=INDEX('Not Req'!$E$4:$E$72,MATCH(MID(F19,FIND(".",F19)+1,LEN(F19)-FIND(".",F19)+1),'Not Req'!$D$4:$D$72,0))} -> Internal (Not Req) | E19: =INDEX('Not Req'!$F$4:$F$72,MATCH(MID(F19,FIND(".",F19)+1,LEN(F19)-FIND(".",F19)+1),'Not Req'!$D$4:$D$72,0)) -> Internal (Not Req) | F19: zbs_api_location_endp_o2_iwsg.sco2.xml | G19: API Pattern | H19: 7 months ago
C20: =LEFT(F20,FIND(".",F20)-1) -> zbs_api_location_endp_o2_iwsg_ibs | D20: {=INDEX('Not Req'!$E$4:$E$72,MATCH(MID(F20,FIND(".",F20)+1,LEN(F20)-FIND(".",F20)+1),'Not Req'!$D$4:$D$72,0))} -> Internal (Not Req) | E20: =INDEX('Not Req'!$F$4:$F$72,MATCH(MID(F20,FIND(".",F20)+1,LEN(F20)-FIND(".",F20)+1),'Not Req'!$D$4:$D$72,0)) -> Internal (Not Req) | F20: zbs_api_location_endp_o2_iwsg_ibs.sia6.xml | G20: API Pattern | H20: 7 months ago
C21: =LEFT(F21,FIND(".",F21)-1) -> zbs_api_location_endpoint | D21: {=INDEX('Not Req'!$E$4:$E$72,MATCH(MID(F21,FIND(".",F21)+1,LEN(F21)-FIND(".",F21)+1),'Not Req'!$D$4:$D$72,0))} -> Internal (Not Req) | E21: =INDEX('Not Req'!$F$4:$F$72,MATCH(MID(F21,FIND(".",F21)+1,LEN(F21)-FIND(".",F21)+1),'Not Req'!$D$4:$D$72,0)) -> Internal (Not Req) | F21: zbs_api_location_endpoint.srvd.xml | G21: API Pattern | H21: 7 months ago
A22: D | B22: D | C22: =LEFT(F22,FIND(".",F22)-1) -> zbs_r_apilocation | D22: {=INDEX('Not Req'!$E$4:$E$72,MATCH(MID(F22,FIND(".",F22)+1,LEN(F22)-FIND(".",F22)+1),'Not Req'!$D$4:$D$72,0))} -> Internal (Not Req) | E22: =INDEX('Not Req'!$F$4:$F$72,MATCH(MID(F22,FIND(".",F22)+1,LEN(F22)-FIND(".",F22)+1),'Not Req'!$D$4:$D$72,0)) -> Internal (Not Req) | F22: zbs_r_apilocation.ddls.baseinfo | G22: API Pattern | H22: 7 months ago

Sheet PATTERN CUSTOM
B2: d | C2: Object | D2: Type | E2: Category | F2: Github Object | G2: Github Type | H2: Version
B4: 1 | C4: =LEFT(F4,FIND(".",F4)-1) -> package | D4: {=INDEX('Not Req'!$E$4:$E$72,MATCH(MID(F4,FIND(".",F4)+1,LEN(F4)-FIND(".",F4)+1),'Not Req'!$D$4:$D$72,0))} -> Description : Package | E4: =INDEX('Not Req'!$F$4:$F$72,MATCH(MID(F4,FIND(".",F4)+1,LEN(F4)-FIND(".",F4)+1),'Not Req'!$D$4:$D$72,0)) -> 0. Package | F4: package.devc.xml | G4: CDS Pattern | H4: 2 months ago | N4: {=_xlfn.UNIQUE(C4:C21)} -> package
C5: =LEFT(F5,FIND(".",F5)-1) -> zbs_demo_dcp_appl | D5: {=INDEX('Not Req'!$E$4:$E$72,MATCH(MID(F5,FIND(".",F5)+1,LEN(F5)-FIND(".",F5)+1),'Not Req'!$D$4:$D$72,0))} -> Data Element | E5: =INDEX('Not Req'!$F$4:$F$72,MATCH(MID(F5,FIND(".",F5)+1,LEN(F5)-FIND(".",F5)+1),'Not Req'!$D$4:$D$72,0)) -> 1. Dictionary | F5: zbs_demo_dcp_appl.dtel.xml | G5: Custom Pattern (Behavior) | H5: 9 months ago | N5: zbs_demo_dcp_appl
C6: =LEFT(F6,FIND(".",F6)-1) -> zbs_demo_dcp_staging | D6: {=INDEX('Not Req'!$E$4:$E$72,MATCH(MID(F6,FIND(".",F6)+1,LEN(F6)-FIND(".",F6)+1),'Not Req'!$D$4:$D$72,0))} -> Data Element | E6: =INDEX('Not Req'!$F$4:$F$72,MATCH(MID(F6,FIND(".",F6)+1,LEN(F6)-FIND(".",F6)+1),'Not Req'!$D$4:$D$72,0)) -> 1. Dictionary | F6: zbs_demo_dcp_staging.dtel.xml | G6: Custom Pattern (Behavior) | H6: 9 months ago | N6: zbs_demo_dcp_staging
C7: =LEFT(F7,FIND(".",F7)-1) -> zbs_demo_dcp_team | D7: {=INDEX('Not Req'!$E$4:$E$72,MATCH(MID(F7,FIND(".",F7)+1,LEN(F7)-FIND(".",F7)+1),'Not Req'!$D$4:$D$72,0))} -> Data Element | E7: =INDEX('Not Req'!$F$4:$F$72,MATCH(MID(F7,FIND(".",F7)+1,LEN(F7)-FIND(".",F7)+1),'Not Req'!$D$4:$D$72,0)) -> 1. Dictionary | F7: zbs_demo_dcp_team.dtel.xml | G7: Custom Pattern (Behavior) | H7: 9 months ago | N7: zbs_demo_dcp_team
C8: =LEFT(F8,FIND(".",F8)-1) -> zbs_demo_dcp_text | D8: {=INDEX('Not Req'!$E$4:$E$72,MATCH(MID(F8,FIND(".",F8)+1,LEN(F8)-FIND(".",F8)+1),'Not Req'!$D$4:$D$72,0))} -> Data Element | E8: =INDEX('Not Req'!$F$4:$F$72,MATCH(MID(F8,FIND(".",F8)+1,LEN(F8)-FIND(".",F8)+1),'Not Req'!$D$4:$D$72,0)) -> 1. Dictionary | F8: zbs_demo_dcp_text.dtel.xml | G8: Custom Pattern (Behavior) | H8: 9 months ago | N8: zbs_demo_dcp_text
C9: =LEFT(F9,FIND(".",F9)-1) -> zbs_demo_dcp_staging | D9: {=INDEX('Not Req'!$E$4:$E$72,MATCH(MID(F9,FIND(".",F9)+1,LEN(F9)-FIND(".",F9)+1),'Not Req'!$D$4:$D$72,0))} -> Domain | E9: =INDEX('Not Req'!$F$4:$F$72,MATCH(MID(F9,FIND(".",F9)+1,LEN(F9)-FIND(".",F9)+1),'Not Req'!$D$4:$D$72,0)) -> 1. Dictionary | F9: zbs_demo_dcp_staging.doma.xml | G9: Custom Pattern (Behavior) | H9: 9 months ago | N9: zbs_dcp
C10: =LEFT(F10,FIND(".",F10)-1) -> zbs_demo_dcp_text | D10: {=INDEX('Not Req'!$E$4:$E$72,MATCH(MID(F10,FIND(".",F10)+1,LEN(F10)-FIND(".",F10)+1),'Not Req'!$D$4:$D$72,0))} -> Domain | E10: =INDEX('Not Req'!$F$4:$F$72,MATCH(MID(F10,FIND(".",F10)+1,LEN(F10)-FIND(".",F10)+1),'Not Req'!$D$4:$D$72,0)) -> 1. Dictionary | F10: zbs_demo_dcp_text.doma.xml | G10: Custom Pattern (Behavior) | H10: 9 months ago | N10: zbs_dcp_appl
C11: =LEFT(F11,FIND(".",F11)-1) -> zbs_dcp | D11: {=INDEX('Not Req'!$E$4:$E$72,MATCH(MID(F11,FIND(".",F11)+1,LEN(F11)-FIND(".",F11)+1),'Not Req'!$D$4:$D$72,0))} -> Table | E11: =INDEX('Not Req'!$F$4:$F$72,MATCH(MID(F11,FIND(".",F11)+1,LEN(F11)-FIND(".",F11)+1),'Not Req'!$D$4:$D$72,0)) -> 1. Dictionary | F11: zbs_dcp.tabl.xml | G11: Custom Pattern (Behavior) | H11: 9 months ago | N11: zbs_dcp_team
C12: =LEFT(F12,FIND(".",F12)-1) -> zbs_dcp_appl | D12: {=INDEX('Not Req'!$E$4:$E$72,MATCH(MID(F12,FIND(".",F12)+1,LEN(F12)-FIND(".",F12)+1),'Not Req'!$D$4:$D$72,0))} -> Table | E12: =INDEX('Not Req'!$F$4:$F$72,MATCH(MID(F12,FIND(".",F12)+1,LEN(F12)-FIND(".",F12)+1),'Not Req'!$D$4:$D$72,0)) -> 1. Dictionary | F12: zbs_dcp_appl.tabl.xml | G12: Optimize search | H12: 9 months ago | N12: zbs_r_dcpsoftwarecomponent
C13: =LEFT(F13,FIND(".",F13)-1) -> zbs_dcp_team | D13: {=INDEX('Not Req'!$E$4:$E$72,MATCH(MID(F13,FIND(".",F13)+1,LEN(F13)-FIND(".",F13)+1),'Not Req'!$D$4:$D$72,0))} -> Table | E13: =INDEX('Not Req'!$F$4:$F$72,MATCH(MID(F13,FIND(".",F13)+1,LEN(F13)-FIND(".",F13)+1),'Not Req'!$D$4:$D$72,0)) -> 1. Dictionary | F13: zbs_dcp_team.tabl.xml | G13: Optimize search | H13: 9 months ago | N13: zbs_i_cpstagingvh
C14: =LEFT(F14,FIND(".",F14)-1) -> zbs_r_dcpsoftwarecomponent | D14: {=INDEX('Not Req'!$E$4:$E$72,MATCH(MID(F14,FIND(".",F14)+1,LEN(F14)-FIND(".",F14)+1),'Not Req'!$D$4:$D$72,0))} -> BDEF | E14: =INDEX('Not Req'!$F$4:$F$72,MATCH(MID(F14,FIND(".",F14)+1,LEN(F14)-FIND(".",F14)+1),'Not Req'!$D$4:$D$72,0)) -> 2. CDS | F14: zbs_r_dcpsoftwarecomponent.bdef.asbdef | G14: Message length | H14: 9 months ago | N14: zbs_i_dcpapplicationvh
C15: =LEFT(F15,FIND(".",F15)-1) -> zbs_i_cpstagingvh | D15: {=INDEX('Not Req'!$E$4:$E$72,MATCH(MID(F15,FIND(".",F15)+1,LEN(F15)-FIND(".",F15)+1),'Not Req'!$D$4:$D$72,0))} -> Data Definition | E15: =INDEX('Not Req'!$F$4:$F$72,MATCH(MID(F15,FIND(".",F15)+1,LEN(F15)-FIND(".",F15)+1),'Not Req'!$D$4:$D$72,0)) -> 2. CDS | F15: zbs_i_cpstagingvh.ddls.asddls | G15: Fixed Value Help | H15: 9 months ago | N15: zbs_i_dcpteamvh
C16: =LEFT(F16,FIND(".",F16)-1) -> zbs_i_dcpapplicationvh | D16: {=INDEX('Not Req'!$E$4:$E$72,MATCH(MID(F16,FIND(".",F16)+1,LEN(F16)-FIND(".",F16)+1),'Not Req'!$D$4:$D$72,0))} -> Data Definition | E16: =INDEX('Not Req'!$F$4:$F$72,MATCH(MID(F16,FIND(".",F16)+1,LEN(F16)-FIND(".",F16)+1),'Not Req'!$D$4:$D$72,0)) -> 2. CDS | F16: zbs_i_dcpapplicationvh.ddls.asddls | G16: Optimize search | H16: 9 months ago
C17: =LEFT(F17,FIND(".",F17)-1) -> zbs_i_dcpteamvh | D17: {=INDEX('Not Req'!$E$4:$E$72,MATCH(MID(F17,FIND(".",F17)+1,LEN(F17)-FIND(".",F17)+1),'Not Req'!$D$4:$D$72,0))} -> Data Definition | E17: =INDEX('Not Req'!$F$4:$F$72,MATCH(MID(F17,FIND(".",F17)+1,LEN(F17)-FIND(".",F17)+1),'Not Req'!$D$4:$D$72,0)) -> 2. CDS | F17: zbs_i_dcpteamvh.ddls.asddls | G17: Optimize search | H17: 9 months ago
C18: =LEFT(F18,FIND(".",F18)-1) -> zbs_r_dcpsoftwarecomponent | D18: {=INDEX('Not Req'!$E$4:$E$72,MATCH(MID(F18,FIND(".",F18)+1,LEN(F18)-FIND(".",F18)+1),'Not Req'!$D$4:$D$72,0))} -> Data Definition | E18: =INDEX('Not Req'!$F$4:$F$72,MATCH(MID(F18,FIND(".",F18)+1,LEN(F18)-FIND(".",F18)+1),'Not Req'!$D$4:$D$72,0)) -> 2. CDS | F18: zbs_r_dcpsoftwarecomponent.ddls.asddls | G18: Message length | H18: 9 months ago
C19: =LEFT(F19,FIND(".",F19)-1) -> zbs_r_dcpsoftwarecomponent | D19: {=INDEX('Not Req'!$E$4:$E$72,MATCH(MID(F19,FIND(".",F19)+1,LEN(F19)-FIND(".",F19)+1),'Not Req'!$D$4:$D$72,0))} -> Description : BDEF | E19: =INDEX('Not Req'!$F$4:$F$72,MATCH(MID(F19,FIND(".",F19)+1,LEN(F19)-FIND(".",F19)+1),'Not Req'!$D$4:$D$72,0)) -> 2. CDS | F19: zbs_r_dcpsoftwarecomponent.bdef.xml | G19: Custom Pattern (Behavior) | H19: 9 months ago
C20: =LEFT(F20,FIND(".",F20)-1) -> zbs_i_cpstagingvh | D20: {=INDEX('Not Req'!$E$4:$E$72,MATCH(MID(F20,FIND(".",F20)+1,LEN(F20)-FIND(".",F20)+1),'Not Req'!$D$4:$D$72,0))} -> Description : Data Definition | E20: =INDEX('Not Req'!$F$4:$F$72,MATCH(MID(F20,FIND(".",F20)+1,LEN(F20)-FIND(".",F20)+1),'Not Req'!$D$4:$D$72,0)) -> 2. CDS | F20: zbs_i_cpstagingvh.ddls.xml | G20: Fixed Value Help | H20: 9 months ago
C21: =LEFT(F21,FIND(".",F21)-1) -> zbs_i_dcpapplicationvh | D21: {=INDEX('Not Req'!$E$4:$E$72,MATCH(MID(F21,FIND(".",F21)+1,LEN(F21)-FIND(".",F21)+1),'Not Req'!$D$4:$D$72,0))} -> Description : Data Definition | E21: =INDEX('Not Req'!$F$4:$F$72,MATCH(MID(F21,FIND(".",F21)+1,LEN(F21)-FIND(".",F21)+1),'Not Req'!$D$4:$D$72,0)) -> 2. CDS | F21: zbs_i_dcpapplicationvh.ddls.xml | G21: Optimize search | H21: 9 months ago
C22: =LEFT(F22,FIND(".",F22)-1) -> zbs_i_dcpteamvh | D22: {=INDEX('Not Req'!$E$4:$E$72,MATCH(MID(F22,FIND(".",F22)+1,LEN(F22)-FIND(".",F22)+1),'Not Req'!$D$4:$D$72,0))} -> Description : Data Definition | E22: =INDEX('Not Req'!$F$4:$F$72,MATCH(MID(F22,FIND(".",F22)+1,LEN(F22)-FIND(".",F22)+1),'Not Req'!$D$4:$D$72,0)) -> 2. CDS | F22: zbs_i_dcpteamvh.ddls.xml | G22: Optimize search | H22: 9 months ago
C23: =LEFT(F23,FIND(".",F23)-1) -> zbs_r_dcpsoftwarecomponent | D23: {=INDEX('Not Req'!$E$4:$E$72,MATCH(MID(F23,FIND(".",F23)+1,LEN(F23)-FIND(".",F23)+1),'Not Req'!$D$4:$D$72,0))} -> Description : Data Definition | E23: =INDEX('Not Req'!$F$4:$F$72,MATCH(MID(F23,FIND(".",F23)+1,LEN(F23)-FIND(".",F23)+1),'Not Req'!$D$4:$D$72,0)) -> 2. CDS | F23: zbs_r_dcpsoftwarecomponent.ddls.xml | G23: Custom Pattern | H23: 9 months ago
C24: =LEFT(F24,FIND(".",F24)-1) -> zbp_bs_dcp_softwarecomponent | D24: {=INDEX('Not Req'!$E$4:$E$72,MATCH(MID(F24,FIND(".",F24)+1,LEN(F24)-FIND(".",F24)+1),'Not Req'!$D$4:$D$72,0))} -> Classes | E24: =INDEX('Not Req'!$F$4:$F$72,MATCH(MID(F24,FIND(".",F24)+1,LEN(F24)-FIND(".",F24)+1),'Not Req'!$D$4:$D$72,0)) -> 3. Source Code Library | F24: zbp_bs_dcp_softwarecomponent.clas.abap | G24: Custom Pattern (Behavior) | H24: 9 months ago
C25: =LEFT(F25,FIND(".",F25)-1) -> zcl_bs_dcp_data_init | D25: {=INDEX('Not Req'!$E$4:$E$72,MATCH(MID(F25,FIND(".",F25)+1,LEN(F25)-FIND(".",F25)+1),'Not Req'!$D$4:$D$72,0))} -> Classes | E25: =INDEX('Not Req'!$F$4:$F$72,MATCH(MID(F25,FIND(".",F25)+1,LEN(F25)-FIND(".",F25)+1),'Not Req'!$D$4:$D$72,0)) -> 3. Source Code Library | F25: zcl_bs_dcp_data_init.clas.abap | G25: Optimize search | H25: 9 months ago
C26: =LEFT(F26,FIND(".",F26)-1) -> zcl_bs_dcp_swc_query | D26: {=INDEX('Not Req'!$E$4:$E$72,MATCH(MID(F26,FIND(".",F26)+1,LEN(F26)-FIND(".",F26)+1),'Not Req'!$D$4:$D$72,0))} -> Classes | E26: =INDEX('Not Req'!$F$4:$F$72,MATCH(MID(F26,FIND(".",F26)+1,LEN(F26)-FIND(".",F26)+1),'Not Req'!$D$4:$D$72,0)) -> 3. Source Code Library | F26: zcl_bs_dcp_swc_query.clas.abap | G26: Optimize search | H26: 9 months ago
C27: =LEFT(F27,FIND(".",F27)-1) -> zbp_bs_dcp_softwarecomponent | D27: {=INDEX('Not Req'!$E$4:$E$72,MATCH(MID(F27,FIND(".",F27)+1,LEN(F27)-FIND(".",F27)+1),'Not Req'!$D$4:$D$72,0))} -> Classes Local | E27: =INDEX('Not Req'!$F$4:$F$72,MATCH(MID(F27,FIND(".",F27)+1,LEN(F27)-FIND(".",F27)+1),'Not Req'!$D$4:$D$72,0)) -> 3. Source Code Library | F27: zbp_bs_dcp_softwarecomponent.clas.locals_imp.abap | G27: Message length | H27: 9 months ago
... C33: =LEFT(F33,FIND(".",F33)-1) -> 10f9d53951ab69ac30a6233fd7ebe6ht | D33: {=INDEX('Not Req'!$E$4:$E$72,MATCH(MID(F33,FIND(".",F33)+1,LEN(F33)-FIND(".",F33)+1),'Not Req'!$D$4:$D$72,0))} -> Internal (Not Req) | E33: =INDEX('Not Req'!$F$4:$F$72,MATCH(MID(F33,FIND(".",F33)+1,LEN(F33)-FIND(".",F33)+1),'Not Req'!$D$4:$D$72,0)) -> Internal (Not Req) | F33: 10f9d53951ab69ac30a6233fd7ebe6ht.sush.xml | G33: Custom Pattern (Behavior) | H33: 9 months ago
A34: D | B34: D | C34: =LEFT(F34,FIND(".",F34)-1) -> 364ff7aa5354e244196fb37c47ddeeht | D34: {=INDEX('Not Req'!$E$4:$E$72,MATCH(MID(F34,FIND(".",F34)+1,LEN(F34)-FIND(".",F34)+1),'Not Req'!$D$4:$D$72,0))} -> Internal (Not Req) | E34: =INDEX('Not Req'!$F$4:$F$72,MATCH(MID(F34,FIND(".",F34)+1,LEN(F34)-FIND(".",F34)+1),'Not Req'!$D$4:$D$72,0)) -> Internal (Not Req) | F34: 364ff7aa5354e244196fb37c47ddeeht.sush.xml | G34: Custom Pattern (Behavior) | H34: 9 months ago
A35: D | B35: D | C35: =LEFT(F35,FIND(".",F35)-1) -> zbs_dcp_swc | D35: {=INDEX('Not Req'!$E$4:$E$72,MATCH(MID(F35,FIND(".",F35)+1,LEN(F35)-FIND(".",F35)+1),'Not Req'!$D$4:$D$72,0))} -> Internal (Not Req) | E35: =INDEX('Not Req'!$F$4:$F$72,MATCH(MID(F35,FIND(".",F35)+1,LEN(F35)-FIND(".",F35)+1),'Not Req'!$D$4:$D$72,0)) -> Internal (Not Req) | F35: zbs_dcp_swc.srvd.xml | G35: Custom Pattern | H35: 9 months ago
A36: D | B36: D | C36: =LEFT(F36,FIND(".",F36)-1) -> zbs_i_cpstagingvh | D36: {=INDEX('Not Req'!$E$4:$E$72,MATCH(MID(F36,FIND(".",F36)+1,LEN(F36)-FIND(".",F36)+1),'Not Req'!$D$4:$D$72,0))} -> Internal (Not Req) | E36: =INDEX('Not Req'!$F$4:$F$72,MATCH(MID(F36,FIND(".",F36)+1,LEN(F36)-FIND(".",F36)+1),'Not Req'!$D$4:$D$72,0)) -> Internal (Not Req) | F36: zbs_i_cpstagingvh.ddls.baseinfo | G36: Fixed Value Help | H36: 9 months ago
A37: D | B37: D | C37: =LEFT(F37,FIND(".",F37)-1) -> zbs_i_dcpapplicationvh | D37: {=INDEX('Not Req'!$E$4:$E$72,MATCH(MID(F37,FIND(".",F37)+1,LEN(F37)-FIND(".",F37)+1),'Not Req'!$D$4:$D$72,0))} -> Internal (Not Req) | E37: =INDEX('Not Req'!$F$4:$F$72,MATCH(MID(F37,FIND(".",F37)+1,LEN(F37)-FIND(".",F37)+1),'Not Req'!$D$4:$D$72,0)) -> Internal (Not Req) | F37: zbs_i_dcpapplicationvh.ddls.baseinfo | G37: Optimize search | H37: 9 months ago
A38: D | B38: D | C38: =LEFT(F38,FIND(".",F38)-1) -> zbs_i_dcpteamvh | D38: {=INDEX('Not Req'!$E$4:$E$72,MATCH(MID(F38,FIND(".",F38)+1,LEN(F38)-FIND(".",F38)+1),'Not Req'!$D$4:$D$72,0))} -> Internal (Not Req) | E38: =INDEX('Not Req'!$F$4:$F$72,MATCH(MID(F38,FIND(".",F38)+1,LEN(F38)-FIND(".",F38)+1),'Not Req'!$D$4:$D$72,0)) -> Internal (Not Req) | F38: zbs_i_dcpteamvh.ddls.baseinfo | G38: Optimize search | H38: 9 months ago
A39: D | B39: D | C39: =LEFT(F39,FIND(".",F39)-1) -> zbs_r_dcpsoftwarecomponent | D39: {=INDEX('Not Req'!$E$4:$E$72,MATCH(MID(F39,FIND(".",F39)+1,LEN(F39)-FIND(".",F39)+1),'Not Req'!$D$4:$D$72,0))} -> Internal (Not Req) | E39: =INDEX('Not Req'!$F$4:$F$72,MATCH(MID(F39,FIND(".",F39)+1,LEN(F39)-FIND(".",F39)+1),'Not Req'!$D$4:$D$72,0)) -> Internal (Not Req) | F39: zbs_r_dcpsoftwarecomponent.ddls.baseinfo | G39: Custom Pattern | H39: 9 months ago
A40: D | B40: D | C40: =LEFT(F40,FIND(".",F40)-1) -> zbs_ui_dcp_swc_o2 | D40: {=INDEX('Not Req'!$E$4:$E$72,MATCH(MID(F40,FIND(".",F40)+1,LEN(F40)-FIND(".",F40)+1),'Not Req'!$D$4:$D$72,0))} -> Internal (Not Req) | E40: =INDEX('Not Req'!$F$4:$F$72,MATCH(MID(F40,FIND(".",F40)+1,LEN(F40)-FIND(".",F40)+1),'Not Req'!$D$4:$D$72,0)) -> Internal (Not Req) | F40: zbs_ui_dcp_swc_o2.srvb.xml | G40: Custom Pattern (Behavior) | H40: 9 months ago
A41: D | B41: D | C41: =LEFT(F41,FIND(".",F41)-1) -> zbs_ui_dcp_swc_o2_iwsg | D41: {=INDEX('Not Req'!$E$4:$E$72,MATCH(MID(F41,FIND(".",F41)+1,LEN(F41)-FIND(".",F41)+1),'Not Req'!$D$4:$D$72,0))} -> Internal (Not Req) | E41: =INDEX('Not Req'!$F$4:$F$72,MATCH(MID(F41,FIND(".",F41)+1,LEN(F41)-FIND(".",F41)+1),'Not Req'!$D$4:$D$72,0)) -> Internal (Not Req) | F41: zbs_ui_dcp_swc_o2_iwsg.sco2.xml | G41: Custom Pattern (Behavior) | H41: 9 months ago
A42: D | B42: D | C42: =LEFT(F42,FIND(".",F42)-1) -> zbs_ui_dcp_swc_o2_iwsg_ibs | D42: {=INDEX('Not Req'!$E$4:$E$72,MATCH(MID(F42,FIND(".",F42)+1,LEN(F42)-FIND(".",F42)+1),'Not Req'!$D$4:$D$72,0))} -> Internal (Not Req) | E42: =INDEX('Not Req'!$F$4:$F$72,MATCH(MID(F42,FIND(".",F42)+1,LEN(F42)-FIND(".",F42)+1),'Not Req'!$D$4:$D$72,0)) -> Internal (Not Req) | F42: zbs_ui_dcp_swc_o2_iwsg_ibs.sia6.xml | G42: Custom Pattern (Behavior) | H42: 9 months ago
A43: D | B43: D | C43: =LEFT(F43,FIND(".",F43)-1) -> zbs_ui_dcp_swc_o4 | D43: {=INDEX('Not Req'!$E$4:$E$72,MATCH(MID(F43,FIND(".",F43)+1,LEN(F43)-FIND(".",F43)+1),'Not Req'!$D$4:$D$72,0))} -> Internal (Not Req) | E43: =INDEX('Not Req'!$F$4:$F$72,MATCH(MID(F43,FIND(".",F43)+1,LEN(F43)-FIND(".",F43)+1),'Not Req'!$D$4:$D$72,0)) -> Internal (Not Req) | F43: zbs_ui_dcp_swc_o4.srvb.xml | G43: Custom Pattern | H43: 9 months ago
A44: D | B44: D | C44: =LEFT(F44,FIND(".",F44)-1) -> zbs_ui_dcp_swc_o4_0001_g4ba | D44: {=INDEX('Not Req'!$E$4:$E$72,MATCH(MID(F44,FIND(".",F44)+1,LEN(F44)-FIND(".",F44)+1),'Not Req'!$D$4:$D$72,0))} -> Internal (Not Req) | E44: =INDEX('Not Req'!$F$4:$F$72,MATCH(MID(F44,FIND(".",F44)+1,LEN(F44)-FIND(".",F44)+1),'Not Req'!$D$4:$D$72,0)) -> Internal (Not Req) | F44: zbs_ui_dcp_swc_o4_0001_g4ba.sco2.xml | G44: Custom Pattern | H44: 9 months ago
A45: D | B45: D | C45: =LEFT(F45,FIND(".",F45)-1) -> zbs_ui_dcp_swc_o4_0001_g4ba_ibs | D45: {=INDEX('Not Req'!$E$4:$E$72,MATCH(MID(F45,FIND(".",F45)+1,LEN(F45)-FIND(".",F45)+1),'Not Req'!$D$4:$D$72,0))} -> Internal (Not Req) | E45: =INDEX('Not Req'!$F$4:$F$72,MATCH(MID(F45,FIND(".",F45)+1,LEN(F45)-FIND(".",F45)+1),'Not Req'!$D$4:$D$72,0)) -> Internal (Not Req) | F45: zbs_ui_dcp_swc_o4_0001_g4ba_ibs.sia6.xml | G45: Custom Pattern | H45: 9 months ago

Sheet PATTERN REPORT
B2: d | C2: Object | D2: Type | E2: Category | F2: Github Object | G2: Github Type | H2: Version
B4: 1 | C4: =LEFT(F4,FIND(".",F4)-1) -> package | D4: {=INDEX('Not Req'!$E$4:$E$72,MATCH(MID(F4,FIND(".",F4)+1,LEN(F4)-FIND(".",F4)+1),'Not Req'!$D$4:$D$72,0))} -> Description : Package | E4: =INDEX('Not Req'!$F$4:$F$72,MATCH(MID(F4,FIND(".",F4)+1,LEN(F4)-FIND(".",F4)+1),'Not Req'!$D$4:$D$72,0)) -> 0. Package | F4: package.devc.xml | G4: CDS Pattern | H4: 2 months ago | N4: {=_xlfn.UNIQUE(C4:C21)} -> package
C5: =LEFT(F5,FIND(".",F5)-1) -> zbs_drp_addcurr | D5: {=INDEX('Not Req'!$E$4:$E$72,MATCH(MID(F5,FIND(".",F5)+1,LEN(F5)-FIND(".",F5)+1),'Not Req'!$D$4:$D$72,0))} -> Table | E5: =INDEX('Not Req'!$F$4:$F$72,MATCH(MID(F5,FIND(".",F5)+1,LEN(F5)-FIND(".",F5)+1),'Not Req'!$D$4:$D$72,0)) -> 1. Dictionary | F5: zbs_drp_addcurr.tabl.xml | G5: File Upload | H5: 2 years ago | N5: zbs_drp_addcurr
C6: =LEFT(F6,FIND(".",F6)-1) -> zbs_drp_cound | D6: {=INDEX('Not Req'!$E$4:$E$72,MATCH(MID(F6,FIND(".",F6)+1,LEN(F6)-FIND(".",F6)+1),'Not Req'!$D$4:$D$72,0))} -> Table | E6: =INDEX('Not Req'!$F$4:$F$72,MATCH(MID(F6,FIND(".",F6)+1,LEN(F6)-FIND(".",F6)+1),'Not Req'!$D$4:$D$72,0)) -> 1. Dictionary | F6: zbs_drp_cound.tabl.xml | G6: Upload excel files | H6: 2 years ago | N6: zbs_drp_cound
C7: =LEFT(F7,FIND(".",F7)-1) -> zbs_drp_country | D7: {=INDEX('Not Req'!$E$4:$E$72,MATCH(MID(F7,FIND(".",F7)+1,LEN(F7)-FIND(".",F7)+1),'Not Req'!$D$4:$D$72,0))} -> Table | E7: =INDEX('Not Req'!$F$4:$F$72,MATCH(MID(F7,FIND(".",F7)+1,LEN(F7)-FIND(".",F7)+1),'Not Req'!$D$4:$D$72,0)) -> 1. Dictionary | F7: zbs_drp_country.tabl.xml | G7: Report Pattern | H7: 2 years ago | N7: zbs_drp_country
C8: =LEFT(F8,FIND(".",F8)-1) -> zbs_drp_currd | D8: {=INDEX('Not Req'!$E$4:$E$72,MATCH(MID(F8,FIND(".",F8)+1,LEN(F8)-FIND(".",F8)+1),'Not Req'!$D$4:$D$72,0))} -> Table | E8: =INDEX('Not Req'!$F$4:$F$72,MATCH(MID(F8,FIND(".",F8)+1,LEN(F8)-FIND(".",F8)+1),'Not Req'!$D$4:$D$72,0)) -> 1. Dictionary | F8: zbs_drp_currd.tabl.xml | G8: Upload excel files | H8: 2 years ago | N8: zbs_drp_currd
C9: =LEFT(F9,FIND(".",F9)-1) -> zbs_c_drpcurrency | D9: {=INDEX('Not Req'!$E$4:$E$72,MATCH(MID(F9,FIND(".",F9)+1,LEN(F9)-FIND(".",F9)+1),'Not Req'!$D$4:$D$72,0))} -> BDEF | E9: =INDEX('Not Req'!$F$4:$F$72,MATCH(MID(F9,FIND(".",F9)+1,LEN(F9)-FIND(".",F9)+1),'Not Req'!$D$4:$D$72,0)) -> 2. CDS | F9: zbs_c_drpcurrency.bdef.asbdef | G9: Popup Default Values | H9: 2 years ago | N9: zbs_c_drpcurrency
C10: =LEFT(F10,FIND(".",F10)-1) -> zbs_r_drpcurrency | D10: {=INDEX('Not Req'!$E$4:$E$72,MATCH(MID(F10,FIND(".",F10)+1,LEN(F10)-FIND(".",F10)+1),'Not Req'!$D$4:$D$72,0))} -> BDEF | E10: =INDEX('Not Req'!$F$4:$F$72,MATCH(MID(F10,FIND(".",F10)+1,LEN(F10)-FIND(".",F10)+1),'Not Req'!$D$4:$D$72,0)) -> 2. CDS | F10: zbs_r_drpcurrency.bdef.asbdef | G10: Popup Default Values | H10: 2 years ago | N10: zbs_r_drpcurrency
C11: =LEFT(F11,FIND(".",F11)-1) -> zbs_s_drpexcelpopup | D11: {=INDEX('Not Req'!$E$4:$E$72,MATCH(MID(F11,FIND(".",F11)+1,LEN(F11)-FIND(".",F11)+1),'Not Req'!$D$4:$D$72,0))} -> BDEF | E11: =INDEX('Not Req'!$F$4:$F$72,MATCH(MID(F11,FIND(".",F11)+1,LEN(F11)-FIND(".",F11)+1),'Not Req'!$D$4:$D$72,0)) -> 2. CDS | F11: zbs_s_drpexcelpopup.bdef.asbdef | G11: Popup mandatory fields | H11: 2 years ago | N11: zbs_s_drpexcelpopup
C12: =LEFT(F12,FIND(".",F12)-1) -> zbs_b_drpadditionalcurrency | D12: {=INDEX('Not Req'!$E$4:$E$72,MATCH(MID(F12,FIND(".",F12)+1,LEN(F12)-FIND(".",F12)+1),'Not Req'!$D$4:$D$72,0))} -> Data Definition | E12: =INDEX('Not Req'!$F$4:$F$72,MATCH(MID(F12,FIND(".",F12)+1,LEN(F12)-FIND(".",F12)+1),'Not Req'!$D$4:$D$72,0)) -> 2. CDS | F12: zbs_b_drpadditionalcurrency.ddls.asddls | G12: File Upload | H12: 2 years ago | N12: zbs_b_drpadditionalcurrency
C13: =LEFT(F13,FIND(".",F13)-1) -> zbs_b_drpcurrencycountry | D13: {=INDEX('Not Req'!$E$4:$E$72,MATCH(MID(F13,FIND(".",F13)+1,LEN(F13)-FIND(".",F13)+1),'Not Req'!$D$4:$D$72,0))} -> Data Definition | E13: =INDEX('Not Req'!$F$4:$F$72,MATCH(MID(F13,FIND(".",F13)+1,LEN(F13)-FIND(".",F13)+1),'Not Req'!$D$4:$D$72,0)) -> 2. CDS | F13: zbs_b_drpcurrencycountry.ddls.asddls | G13: Report Pattern | H13: 2 years ago | N13: zbs_b_drpcurrencycountry
C14: =LEFT(F14,FIND(".",F14)-1) -> zbs_c_drpcurrency | D14: {=INDEX('Not Req'!$E$4:$E$72,MATCH(MID(F14,FIND(".",F14)+1,LEN(F14)-FIND(".",F14)+1),'Not Req'!$D$4:$D$72,0))} -> Data Definition | E14: =INDEX('Not Req'!$F$4:$F$72,MATCH(MID(F14,FIND(".",F14)+1,LEN(F14)-FIND(".",F14)+1),'Not Req'!$D$4:$D$72,0)) -> 2. CDS | F14: zbs_c_drpcurrency.ddls.asddls | G14: Variants and Filters | H14: 8 months ago | N14: zbs_c_drpcurrencycountry
C15: =LEFT(F15,FIND(".",F15)-1) -> zbs_c_drpcurrencycountry | D15: {=INDEX('Not Req'!$E$4:$E$72,MATCH(MID(F15,FIND(".",F15)+1,LEN(F15)-FIND(".",F15)+1),'Not Req'!$D$4:$D$72,0))} -> Data Definition | E15: =INDEX('Not Req'!$F$4:$F$72,MATCH(MID(F15,FIND(".",F15)+1,LEN(F15)-FIND(".",F15)+1),'Not Req'!$D$4:$D$72,0)) -> 2. CDS | F15: zbs_c_drpcurrencycountry.ddls.asddls | G15: Report Pattern | H15: 2 years ago | N15: zbs_i_drpcurrencycountry
C16: =LEFT(F16,FIND(".",F16)-1) -> zbs_i_drpcurrencycountry | D16: {=INDEX('Not Req'!$E$4:$E$72,MATCH(MID(F16,FIND(".",F16)+1,LEN(F16)-FIND(".",F16)+1),'Not Req'!$D$4:$D$72,0))} -> Data Definition | E16: =INDEX('Not Req'!$F$4:$F$72,MATCH(MID(F16,FIND(".",F16)+1,LEN(F16)-FIND(".",F16)+1),'Not Req'!$D$4:$D$72,0)) -> 2. CDS | F16: zbs_i_drpcurrencycountry.ddls.asddls | G16: Report Pattern | H16: 2 years ago | N16: zbs_s_drpeventdata
C17: =LEFT(F17,FIND(".",F17)-1) -> zbs_r_drpcurrency | D17: {=INDEX('Not Req'!$E$4:$E$72,MATCH(MID(F17,FIND(".",F17)+1,LEN(F17)-FIND(".",F17)+1),'Not Req'!$D$4:$D$72,0))} -> Data Definition | E17: =INDEX('Not Req'!$F$4:$F$72,MATCH(MID(F17,FIND(".",F17)+1,LEN(F17)-FIND(".",F17)+1),'Not Req'!$D$4:$D$72,0)) -> 2. CDS | F17: zbs_r_drpcurrency.ddls.asddls | G17: File Upload | H17: 2 years ago
C18: =LEFT(F18,FIND(".",F18)-1) -> zbs_s_drpeventdata | D18: {=INDEX('Not Req'!$E$4:$E$72,MATCH(MID(F18,FIND(".",F18)+1,LEN(F18)-FIND(".",F18)+1),'Not Req'!$D$4:$D$72,0))} -> Data Definition | E18: =INDEX('Not Req'!$F$4:$F$72,MATCH(MID(F18,FIND(".",F18)+1,LEN(F18)-FIND(".",F18)+1),'Not Req'!$D$4:$D$72,0)) -> 2. CDS | F18: zbs_s_drpeventdata.ddls.asddls | G18: Event & Consumption | H18: 2 years ago
C19: =LEFT(F19,FIND(".",F19)-1) -> zbs_s_drpexcelpopup | D19: {=INDEX('Not Req'!$E$4:$E$72,MATCH(MID(F19,FIND(".",F19)+1,LEN(F19)-FIND(".",F19)+1),'Not Req'!$D$4:$D$72,0))} -> Data Definition | E19: =INDEX('Not Req'!$F$4:$F$72,MATCH(MID(F19,FIND(".",F19)+1,LEN(F19)-FIND(".",F19)+1),'Not Req'!$D$4:$D$72,0)) -> 2. CDS | F19: zbs_s_drpexcelpopup.ddls.asddls | G19: Popup mandatory fields | H19: 2 years ago
C20: =LEFT(F20,FIND(".",F20)-1) -> zbs_c_drpcurrency | D20: {=INDEX('Not Req'!$E$4:$E$72,MATCH(MID(F20,FIND(".",F20)+1,LEN(F20)-FIND(".",F20)+1),'Not Req'!$D$4:$D$72,0))} -> Description : BDEF | E20: =INDEX('Not Req'!$F$4:$F$72,MATCH(MID(F20,FIND(".",F20)+1,LEN(F20)-FIND(".",F20)+1),'Not Req'!$D$4:$D$72,0)) -> 2. CDS | F20: zbs_c_drpcurrency.bdef.xml | G20: Report Pattern | H20: 2 years ago
C21: =LEFT(F21,FIND(".",F21)-1) -> zbs_r_drpcurrency | D21: {=INDEX('Not Req'!$E$4:$E$72,MATCH(MID(F21,FIND(".",F21)+1,LEN(F21)-FIND(".",F21)+1),'Not Req'!$D$4:$D$72,0))} -> Description : BDEF | E21: =INDEX('Not Req'!$F$4:$F$72,MATCH(MID(F21,FIND(".",F21)+1,LEN(F21)-FIND(".",F21)+1),'Not Req'!$D$4:$D$72,0)) -> 2. CDS | F21: zbs_r_drpcurrency.bdef.xml | G21: Report Pattern | H21: 2 years ago
C22: =LEFT(F22,FIND(".",F22)-1) -> zbs_s_drpexcelpopup | D22: {=INDEX('Not Req'!$E$4:$E$72,MATCH(MID(F22,FIND(".",F22)+1,LEN(F22)-FIND(".",F22)+1),'Not Req'!$D$4:$D$72,0))} -> Description : BDEF | E22: =INDEX('Not Req'!$F$4:$F$72,MATCH(MID(F22,FIND(".",F22)+1,LEN(F22)-FIND(".",F22)+1),'Not Req'!$D$4:$D$72,0)) -> 2. CDS | F22: zbs_s_drpexcelpopup.bdef.xml | G22: Popup mandatory fields | H22: 2 years ago
C23: =LEFT(F23,FIND(".",F23)-1) -> zbs_b_drpadditionalcurrency | D23: {=INDEX('Not Req'!$E$4:$E$72,MATCH(MID(F23,FIND(".",F23)+1,LEN(F23)-FIND(".",F23)+1),'Not Req'!$D$4:$D$72,0))} -> Description : Data Definition | E23: =INDEX('Not Req'!$F$4:$F$72,MATCH(MID(F23,FIND(".",F23)+1,LEN(F23)-FIND(".",F23)+1),'Not Req'!$D$4:$D$72,0)) -> 2. CDS | F23: zbs_b_drpadditionalcurrency.ddls.xml | G23: Report Pattern | H23: 2 years ago
C24: =LEFT(F24,FIND(".",F24)-1) -> zbs_b_drpcurrencycountry | D24: {=INDEX('Not Req'!$E$4:$E$72,MATCH(MID(F24,FIND(".",F24)+1,LEN(F24)-FIND(".",F24)+1),'Not Req'!$D$4:$D$72,0))} -> Description : Data Definition | E24: =INDEX('Not Req'!$F$4:$F$72,MATCH(MID(F24,FIND(".",F24)+1,LEN(F24)-FIND(".",F24)+1),'Not Req'!$D$4:$D$72,0)) -> 2. CDS | F24: zbs_b_drpcurrencycountry.ddls.xml | G24: Report Pattern | H24: 2 years ago
C25: =LEFT(F25,FIND(".",F25)-1) -> zbs_c_drpcurrency | D25: {=INDEX('Not Req'!$E$4:$E$72,MATCH(MID(F25,FIND(".",F25)+1,LEN(F25)-FIND(".",F25)+1),'Not Req'!$D$4:$D$72,0))} -> Description : Data Definition | E25: =INDEX('Not Req'!$F$4:$F$72,MATCH(MID(F25,FIND(".",F25)+1,LEN(F25)-FIND(".",F25)+1),'Not Req'!$D$4:$D$72,0)) -> 2. CDS | F25: zbs_c_drpcurrency.ddls.xml | G25: Report Pattern | H25: 2 years ago
C26: =LEFT(F26,FIND(".",F26)-1) -> zbs_c_drpcurrencycountry | D26: {=INDEX('Not Req'!$E$4:$E$72,MATCH(MID(F26,FIND(".",F26)+1,LEN(F26)-FIND(".",F26)+1),'Not Req'!$D$4:$D$72,0))} -> Description : Data Definition | E26: =INDEX('Not Req'!$F$4:$F$72,MATCH(MID(F26,FIND(".",F26)+1,LEN(F26)-FIND(".",F26)+1),'Not Req'!$D$4:$D$72,0)) -> 2. CDS | F26: zbs_c_drpcurrencycountry.ddls.xml | G26: Report Pattern | H26: 2 years ago
C27: =LEFT(F27,FIND(".",F27)-1) -> zbs_i_drpcurrencycountry | D27: {=INDEX('Not Req'!$E$4:$E$72,MATCH(MID(F27,FIND(".",F27)+1,LEN(F27)-FIND(".",F27)+1),'Not Req'!$D$4:$D$72,0))} -> Description : Data Definition | E27: =INDEX('Not Req'!$F$4:$F$72,MATCH(MID(F27,FIND(".",F27)+1,LEN(F27)-FIND(".",F27)+1),'Not Req'!$D$4:$D$72,0)) -> 2. CDS | F27: zbs_i_drpcurrencycountry.ddls.xml | G27: Report Pattern | H27: 2 years ago
C28: =LEFT(F28,FIND(".",F28)-1) -> zbs_r_drpcurrency | D28: {=INDEX('Not Req'!$E$4:$E$72,MATCH(MID(F28,FIND(".",F28)+1,LEN(F28)-FIND(".",F28)+1),'Not Req'!$D$4:$D$72,0))} -> Description : Data Definition | E28: =INDEX('Not Req'!$F$4:$F$72,MATCH(MID(F28,FIND(".",F28)+1,LEN(F28)-FIND(".",F28)+1),'Not Req'!$D$4:$D$72,0)) -> 2. CDS | F28: zbs_r_drpcurrency.ddls.xml | G28: Report Pattern | H28: 2 years ago
... C33: =LEFT(F33,FIND(".",F33)-1) -> zbs_c_drpcurrency | D33: {=INDEX('Not Req'!$E$4:$E$72,MATCH(MID(F33,FIND(".",F33)+1,LEN(F33)-FIND(".",F33)+1),'Not Req'!$D$4:$D$72,0))} -> Metadata | E33: =INDEX('Not Req'!$F$4:$F$72,MATCH(MID(F33,FIND(".",F33)+1,LEN(F33)-FIND(".",F33)+1),'Not Req'!$D$4:$D$72,0)) -> 2. CDS | F33: zbs_c_drpcurrency.ddlx.asddlxs | G33: Variants and Filters | H33: 8 months ago
A34: D | B34: D | C34: =LEFT(F34,FIND(".",F34)-1) -> zbs_c_drpcurrencycountry | D34: {=INDEX('Not Req'!$E$4:$E$72,MATCH(MID(F34,FIND(".",F34)+1,LEN(F34)-FIND(".",F34)+1),'Not Req'!$D$4:$D$72,0))} -> Metadata | E34: =INDEX('Not Req'!$F$4:$F$72,MATCH(MID(F34,FIND(".",F34)+1,LEN(F34)-FIND(".",F34)+1),'Not Req'!$D$4:$D$72,0)) -> 2. CDS | F34: zbs_c_drpcurrencycountry.ddlx.asddlxs | G34: Report Pattern | H34: 2 years ago
A35: D | B35: D | C35: =LEFT(F35,FIND(".",F35)-1) -> zbp_bs_drp_currency | D35: {=INDEX('Not Req'!$E$4:$E$72,MATCH(MID(F35,FIND(".",F35)+1,LEN(F35)-FIND(".",F35)+1),'Not Req'!$D$4:$D$72,0))} -> Classes | E35: =INDEX('Not Req'!$F$4:$F$72,MATCH(MID(F35,FIND(".",F35)+1,LEN(F35)-FIND(".",F35)+1),'Not Req'!$D$4:$D$72,0)) -> 3. Source Code Library | F35: zbp_bs_drp_currency.clas.abap | G35: Upload excel files | H35: 2 years ago
A36: D | B36: D | C36: =LEFT(F36,FIND(".",F36)-1) -> zcl_bs_drp_event_consumption | D36: {=INDEX('Not Req'!$E$4:$E$72,MATCH(MID(F36,FIND(".",F36)+1,LEN(F36)-FIND(".",F36)+1),'Not Req'!$D$4:$D$72,0))} -> Classes | E36: =INDEX('Not Req'!$F$4:$F$72,MATCH(MID(F36,FIND(".",F36)+1,LEN(F36)-FIND(".",F36)+1),'Not Req'!$D$4:$D$72,0)) -> 3. Source Code Library | F36: zcl_bs_drp_event_consumption.clas.abap | G36: Event & Consumption | H36: 2 years ago
A37: D | B37: D | C37: =LEFT(F37,FIND(".",F37)-1) -> zcx_drp_excel_error | D37: {=INDEX('Not Req'!$E$4:$E$72,MATCH(MID(F37,FIND(".",F37)+1,LEN(F37)-FIND(".",F37)+1),'Not Req'!$D$4:$D$72,0))} -> Classes | E37: =INDEX('Not Req'!$F$4:$F$72,MATCH(MID(F37,FIND(".",F37)+1,LEN(F37)-FIND(".",F37)+1),'Not Req'!$D$4:$D$72,0)) -> 3. Source Code Library | F37: zcx_drp_excel_error.clas.abap | G37: Upload excel files | H37: 2 years ago
A38: D | B38: D | C38: =LEFT(F38,FIND(".",F38)-1) -> zbp_bs_drp_currency | D38: {=INDEX('Not Req'!$E$4:$E$72,MATCH(MID(F38,FIND(".",F38)+1,LEN(F38)-FIND(".",F38)+1),'Not Req'!$D$4:$D$72,0))} -> Classes Local | E38: =INDEX('Not Req'!$F$4:$F$72,MATCH(MID(F38,FIND(".",F38)+1,LEN(F38)-FIND(".",F38)+1),'Not Req'!$D$4:$D$72,0)) -> 3. Source Code Library | F38: zbp_bs_drp_currency.clas.locals_imp.abap | G38: Popup Default Values | H38: 2 years ago
A39: D | B39: D | C39: =LEFT(F39,FIND(".",F39)-1) -> zcl_bs_drp_event_consumption | D39: {=INDEX('Not Req'!$E$4:$E$72,MATCH(MID(F39,FIND(".",F39)+1,LEN(F39)-FIND(".",F39)+1),'Not Req'!$D$4:$D$72,0))} -> Classes Local | E39: =INDEX('Not Req'!$F$4:$F$72,MATCH(MID(F39,FIND(".",F39)+1,LEN(F39)-FIND(".",F39)+1),'Not Req'!$D$4:$D$72,0)) -> 3. Source Code Library | F39: zcl_bs_drp_event_consumption.clas.locals_imp.abap | G39: Event & Consumption | H39: 2 years ago
A40: D | B40: D | C40: =LEFT(F40,FIND(".",F40)-1) -> zbp_bs_drp_currency | D40: {=INDEX('Not Req'!$E$4:$E$72,MATCH(MID(F40,FIND(".",F40)+1,LEN(F40)-FIND(".",F40)+1),'Not Req'!$D$4:$D$72,0))} -> Description : Classes | E40: =INDEX('Not Req'!$F$4:$F$72,MATCH(MID(F40,FIND(".",F40)+1,LEN(F40)-FIND(".",F40)+1),'Not Req'!$D$4:$D$72,0)) -> 3. Source Code Library | F40: zbp_bs_drp_currency.clas.xml | G40: Report Pattern | H40: 2 years ago
A41: D | B41: D | C41: =LEFT(F41,FIND(".",F41)-1) -> zcl_bs_drp_event_consumption | D41: {=INDEX('Not Req'!$E$4:$E$72,MATCH(MID(F41,FIND(".",F41)+1,LEN(F41)-FIND(".",F41)+1),'Not Req'!$D$4:$D$72,0))} -> Description : Classes | E41: =INDEX('Not Req'!$F$4:$F$72,MATCH(MID(F41,FIND(".",F41)+1,LEN(F41)-FIND(".",F41)+1),'Not Req'!$D$4:$D$72,0)) -> 3. Source Code Library | F41: zcl_bs_drp_event_consumption.clas.xml | G41: Event & Consumption | H41: 2 years ago
A42: D | B42: D | C42: =LEFT(F42,FIND(".",F42)-1) -> zcx_drp_excel_error | D42: {=INDEX('Not Req'!$E$4:$E$72,MATCH(MID(F42,FIND(".",F42)+1,LEN(F42)-FIND(".",F42)+1),'Not Req'!$D$4:$D$72,0))} -> Description : Classes | E42: =INDEX('Not Req'!$F$4:$F$72,MATCH(MID(F42,FIND(".",F42)+1,LEN(F42)-FIND(".",F42)+1),'Not Req'!$D$4:$D$72,0)) -> 3. Source Code Library | F42: zcx_drp_excel_error.clas.xml | G42: Upload excel files | H42: 2 years ago
A43: D | B43: D | C43: =LEFT(F43,FIND(".",F43)-1) -> zbs_demo_drp_currency | D43: {=INDEX('Not Req'!$E$4:$E$72,MATCH(MID(F43,FIND(".",F43)+1,LEN(F43)-FIND(".",F43)+1),'Not Req'!$D$4:$D$72,0))} -> Service Definition | E43: =INDEX('Not Req'!$F$4:$F$72,MATCH(MID(F43,FIND(".",F43)+1,LEN(F43)-FIND(".",F43)+1),'Not Req'!$D$4:$D$72,0)) -> Business Services | F43: zbs_demo_drp_currency.srvd.srvdsrv | G43: Report Pattern | H43: 2 years ago
A44: D | B44: D | C44: =LEFT(F44,FIND(".",F44)-1) -> cce61434a74ce51e89d05d58b3806aht | D44: {=INDEX('Not Req'!$E$4:$E$72,MATCH(MID(F44,FIND(".",F44)+1,LEN(F44)-FIND(".",F44)+1),'Not Req'!$D$4:$D$72,0))} -> Internal (Not Req) | E44: =INDEX('Not Req'!$F$4:$F$72,MATCH(MID(F44,FIND(".",F44)+1,LEN(F44)-FIND(".",F44)+1),'Not Req'!$D$4:$D$72,0)) -> Internal (Not Req) | F44: cce61434a74ce51e89d05d58b3806aht.sush.xml | G44: Report Pattern | H44: 2 years ago
A45: D | B45: D | C45: =LEFT(F45,FIND(".",F45)-1) -> zbs_b_drpadditionalcurrency | D45: {=INDEX('Not Req'!$E$4:$E$72,MATCH(MID(F45,FIND(".",F45)+1,LEN(F45)-FIND(".",F45)+1),'Not Req'!$D$4:$D$72,0))} -> Internal (Not Req) | E45: =INDEX('Not Req'!$F$4:$F$72,MATCH(MID(F45,FIND(".",F45)+1,LEN(F45)-FIND(".",F45)+1),'Not Req'!$D$4:$D$72,0)) -> Internal (Not Req) | F45: zbs_b_drpadditionalcurrency.ddls.baseinfo | G45: Report Pattern | H45: 2 years ago
... A56: D | B56: D | C56: =LEFT(F56,FIND(".",F56)-1) -> zbs_ui_demo_drp_currency_o4_0001_g4ba | D56: {=INDEX('Not Req'!$E$4:$E$72,MATCH(MID(F56,FIND(".",F56)+1,LEN(F56)-FIND(".",F56)+1),'Not Req'!$D$4:$D$72,0))} -> Internal (Not Req) | E56: =INDEX('Not Req'!$F$4:$F$72,MATCH(MID(F56,FIND(".",F56)+1,LEN(F56)-FIND(".",F56)+1),'Not Req'!$D$4:$D$72,0)) -> Internal (Not Req) | F56: zbs_ui_demo_drp_currency_o4_0001_g4ba.sco2.xml | G56: Report Pattern | H56: 2 years ago

Sheet RAP GOOGLE
B2: d | C2: Object | D2: Type | E2: Category | F2: Github Object | G2: Github Type | H2: Version
B4: 1 | C4: =LEFT(F4,FIND(".",F4)-1) -> package | D4: {=INDEX('Not Req'!$E$4:$E$72,MATCH(MID(F4,FIND(".",F4)+1,LEN(F4)-FIND(".",F4)+1),'Not Req'!$D$4:$D$72,0))} -> Description : Package | E4: =INDEX('Not Req'!$F$4:$F$72,MATCH(MID(F4,FIND(".",F4)+1,LEN(F4)-FIND(".",F4)+1),'Not Req'!$D$4:$D$72,0)) -> 0. Package | F4: package.devc.xml | G4: CDS Pattern | H4: 2 months ago | N4: {=_xlfn.UNIQUE(C4:C21)} -> package
C5: =LEFT(F5,FIND(".",F5)-1) -> zbs_demo_text | D5: {=INDEX('Not Req'!$E$4:$E$72,MATCH(MID(F5,FIND(".",F5)+1,LEN(F5)-FIND(".",F5)+1),'Not Req'!$D$4:$D$72,0))} -> Data Element | E5: =INDEX('Not Req'!$F$4:$F$72,MATCH(MID(F5,FIND(".",F5)+1,LEN(F5)-FIND(".",F5)+1),'Not Req'!$D$4:$D$72,0)) -> 1. Dictionary | F5: zbs_demo_text.dtel.xml | G5: Google Translate App | H5: 2 years ago | N5: zbs_demo_text
C6: =LEFT(F6,FIND(".",F6)-1) -> zbs_demo_text | D6: {=INDEX('Not Req'!$E$4:$E$72,MATCH(MID(F6,FIND(".",F6)+1,LEN(F6)-FIND(".",F6)+1),'Not Req'!$D$4:$D$72,0))} -> Domain | E6: =INDEX('Not Req'!$F$4:$F$72,MATCH(MID(F6,FIND(".",F6)+1,LEN(F6)-FIND(".",F6)+1),'Not Req'!$D$4:$D$72,0)) -> 1. Dictionary | F6: zbs_demo_text.doma.xml | G6: Google Translate App | H6: 2 years ago | N6: zbs_dmo_lang
C7: =LEFT(F7,FIND(".",F7)-1) -> zbs_dmo_lang | D7: {=INDEX('Not Req'!$E$4:$E$72,MATCH(MID(F7,FIND(".",F7)+1,LEN(F7)-FIND(".",F7)+1),'Not Req'!$D$4:$D$72,0))} -> Table | E7: =INDEX('Not Req'!$F$4:$F$72,MATCH(MID(F7,FIND(".",F7)+1,LEN(F7)-FIND(".",F7)+1),'Not Req'!$D$4:$D$72,0)) -> 1. Dictionary | F7: zbs_dmo_lang.tabl.xml | G7: Google Translate App | H7: 2 years ago | N7: zbs_dmo_lang_d
C8: =LEFT(F8,FIND(".",F8)-1) -> zbs_dmo_lang_d | D8: {=INDEX('Not Req'!$E$4:$E$72,MATCH(MID(F8,FIND(".",F8)+1,LEN(F8)-FIND(".",F8)+1),'Not Req'!$D$4:$D$72,0))} -> Table | E8: =INDEX('Not Req'!$F$4:$F$72,MATCH(MID(F8,FIND(".",F8)+1,LEN(F8)-FIND(".",F8)+1),'Not Req'!$D$4:$D$72,0)) -> 1. Dictionary | F8: zbs_dmo_lang_d.tabl.xml | G8: Google Translate App | H8: 2 years ago | N8: zbs_c_dmolanguage
C9: =LEFT(F9,FIND(".",F9)-1) -> zbs_c_dmolanguage | D9: {=INDEX('Not Req'!$E$4:$E$72,MATCH(MID(F9,FIND(".",F9)+1,LEN(F9)-FIND(".",F9)+1),'Not Req'!$D$4:$D$72,0))} -> BDEF | E9: =INDEX('Not Req'!$F$4:$F$72,MATCH(MID(F9,FIND(".",F9)+1,LEN(F9)-FIND(".",F9)+1),'Not Req'!$D$4:$D$72,0)) -> 2. CDS | F9: zbs_c_dmolanguage.bdef.asbdef | G9: Google Translate App | H9: 2 years ago | N9: zbs_r_dmolanguage
C10: =LEFT(F10,FIND(".",F10)-1) -> zbs_r_dmolanguage | D10: {=INDEX('Not Req'!$E$4:$E$72,MATCH(MID(F10,FIND(".",F10)+1,LEN(F10)-FIND(".",F10)+1),'Not Req'!$D$4:$D$72,0))} -> BDEF | E10: =INDEX('Not Req'!$F$4:$F$72,MATCH(MID(F10,FIND(".",F10)+1,LEN(F10)-FIND(".",F10)+1),'Not Req'!$D$4:$D$72,0)) -> 2. CDS | F10: zbs_r_dmolanguage.bdef.asbdef | G10: Semantic Key | H10: 2 years ago | N10: zbp_bs_c_demo_language
C11: =LEFT(F11,FIND(".",F11)-1) -> zbs_c_dmolanguage | D11: {=INDEX('Not Req'!$E$4:$E$72,MATCH(MID(F11,FIND(".",F11)+1,LEN(F11)-FIND(".",F11)+1),'Not Req'!$D$4:$D$72,0))} -> Data Definition | E11: =INDEX('Not Req'!$F$4:$F$72,MATCH(MID(F11,FIND(".",F11)+1,LEN(F11)-FIND(".",F11)+1),'Not Req'!$D$4:$D$72,0)) -> 2. CDS | F11: zbs_c_dmolanguage.ddls.asddls | G11: Semantic Key | H11: 2 years ago | N11: zbp_bs_r_demo_language
C12: =LEFT(F12,FIND(".",F12)-1) -> zbs_r_dmolanguage | D12: {=INDEX('Not Req'!$E$4:$E$72,MATCH(MID(F12,FIND(".",F12)+1,LEN(F12)-FIND(".",F12)+1),'Not Req'!$D$4:$D$72,0))} -> Data Definition | E12: =INDEX('Not Req'!$F$4:$F$72,MATCH(MID(F12,FIND(".",F12)+1,LEN(F12)-FIND(".",F12)+1),'Not Req'!$D$4:$D$72,0)) -> 2. CDS | F12: zbs_r_dmolanguage.ddls.asddls | G12: Google Translate App | H12: 2 years ago | N12: zcl_bs_demo_google_integration
C13: =LEFT(F13,FIND(".",F13)-1) -> zbs_c_dmolanguage | D13: {=INDEX('Not Req'!$E$4:$E$72,MATCH(MID(F13,FIND(".",F13)+1,LEN(F13)-FIND(".",F13)+1),'Not Req'!$D$4:$D$72,0))} -> Description : BDEF | E13: =INDEX('Not Req'!$F$4:$F$72,MATCH(MID(F13,FIND(".",F13)+1,LEN(F13)-FIND(".",F13)+1),'Not Req'!$D$4:$D$72,0)) -> 2. CDS | F13: zbs_c_dmolanguage.bdef.xml | G13: Google Translate App | H13: 2 years ago
C14: =LEFT(F14,FIND(".",F14)-1) -> zbs_r_dmolanguage | D14: {=INDEX('Not Req'!$E$4:$E$72,MATCH(MID(F14,FIND(".",F14)+1,LEN(F14)-FIND(".",F14)+1),'Not Req'!$D$4:$D$72,0))} -> Description : BDEF | E14: =INDEX('Not Req'!$F$4:$F$72,MATCH(MID(F14,FIND(".",F14)+1,LEN(F14)-FIND(".",F14)+1),'Not Req'!$D$4:$D$72,0)) -> 2. CDS | F14: zbs_r_dmolanguage.bdef.xml | G14: Google Translate App | H14: 2 years ago
C15: =LEFT(F15,FIND(".",F15)-1) -> zbs_c_dmolanguage | D15: {=INDEX('Not Req'!$E$4:$E$72,MATCH(MID(F15,FIND(".",F15)+1,LEN(F15)-FIND(".",F15)+1),'Not Req'!$D$4:$D$72,0))} -> Description : Data Definition | E15: =INDEX('Not Req'!$F$4:$F$72,MATCH(MID(F15,FIND(".",F15)+1,LEN(F15)-FIND(".",F15)+1),'Not Req'!$D$4:$D$72,0)) -> 2. CDS | F15: zbs_c_dmolanguage.ddls.xml | G15: Google Translate App | H15: 2 years ago
C16: =LEFT(F16,FIND(".",F16)-1) -> zbs_r_dmolanguage | D16: {=INDEX('Not Req'!$E$4:$E$72,MATCH(MID(F16,FIND(".",F16)+1,LEN(F16)-FIND(".",F16)+1),'Not Req'!$D$4:$D$72,0))} -> Description : Data Definition | E16: =INDEX('Not Req'!$F$4:$F$72,MATCH(MID(F16,FIND(".",F16)+1,LEN(F16)-FIND(".",F16)+1),'Not Req'!$D$4:$D$72,0)) -> 2. CDS | F16: zbs_r_dmolanguage.ddls.xml | G16: Google Translate App | H16: 2 years ago
C17: =LEFT(F17,FIND(".",F17)-1) -> zbs_c_dmolanguage | D17: {=INDEX('Not Req'!$E$4:$E$72,MATCH(MID(F17,FIND(".",F17)+1,LEN(F17)-FIND(".",F17)+1),'Not Req'!$D$4:$D$72,0))} -> Description : Metadata | E17: =INDEX('Not Req'!$F$4:$F$72,MATCH(MID(F17,FIND(".",F17)+1,LEN(F17)-FIND(".",F17)+1),'Not Req'!$D$4:$D$72,0)) -> 2. CDS | F17: zbs_c_dmolanguage.ddlx.xml | G17: Google Translate App | H17: 2 years ago
C18: =LEFT(F18,FIND(".",F18)-1) -> zbs_c_dmolanguage | D18: {=INDEX('Not Req'!$E$4:$E$72,MATCH(MID(F18,FIND(".",F18)+1,LEN(F18)-FIND(".",F18)+1),'Not Req'!$D$4:$D$72,0))} -> Metadata | E18: =INDEX('Not Req'!$F$4:$F$72,MATCH(MID(F18,FIND(".",F18)+1,LEN(F18)-FIND(".",F18)+1),'Not Req'!$D$4:$D$72,0)) -> 2. CDS | F18: zbs_c_dmolanguage.ddlx.asddlxs | G18: Google Translate App | H18: 2 years ago
C19: =LEFT(F19,FIND(".",F19)-1) -> zbp_bs_c_demo_language | D19: {=INDEX('Not Req'!$E$4:$E$72,MATCH(MID(F19,FIND(".",F19)+1,LEN(F19)-FIND(".",F19)+1),'Not Req'!$D$4:$D$72,0))} -> Classes | E19: =INDEX('Not Req'!$F$4:$F$72,MATCH(MID(F19,FIND(".",F19)+1,LEN(F19)-FIND(".",F19)+1),'Not Req'!$D$4:$D$72,0)) -> 3. Source Code Library | F19: zbp_bs_c_demo_language.clas.abap | G19: Google Translate App | H19: 2 years ago
C20: =LEFT(F20,FIND(".",F20)-1) -> zbp_bs_r_demo_language | D20: {=INDEX('Not Req'!$E$4:$E$72,MATCH(MID(F20,FIND(".",F20)+1,LEN(F20)-FIND(".",F20)+1),'Not Req'!$D$4:$D$72,0))} -> Classes | E20: =INDEX('Not Req'!$F$4:$F$72,MATCH(MID(F20,FIND(".",F20)+1,LEN(F20)-FIND(".",F20)+1),'Not Req'!$D$4:$D$72,0)) -> 3. Source Code Library | F20: zbp_bs_r_demo_language.clas.abap | G20: Google Translate App | H20: 2 years ago
C21: =LEFT(F21,FIND(".",F21)-1) -> zcl_bs_demo_google_integration | D21: {=INDEX('Not Req'!$E$4:$E$72,MATCH(MID(F21,FIND(".",F21)+1,LEN(F21)-FIND(".",F21)+1),'Not Req'!$D$4:$D$72,0))} -> Classes | E21: =INDEX('Not Req'!$F$4:$F$72,MATCH(MID(F21,FIND(".",F21)+1,LEN(F21)-FIND(".",F21)+1),'Not Req'!$D$4:$D$72,0)) -> 3. Source Code Library | F21: zcl_bs_demo_google_integration.clas.abap | G21: Delta commit | H21: 2 years ago
C22: =LEFT(F22,FIND(".",F22)-1) -> zbp_bs_r_demo_language | D22: {=INDEX('Not Req'!$E$4:$E$72,MATCH(MID(F22,FIND(".",F22)+1,LEN(F22)-FIND(".",F22)+1),'Not Req'!$D$4:$D$72,0))} -> Classes Local | E22: =INDEX('Not Req'!$F$4:$F$72,MATCH(MID(F22,FIND(".",F22)+1,LEN(F22)-FIND(".",F22)+1),'Not Req'!$D$4:$D$72,0)) -> 3. Source Code Library | F22: zbp_bs_r_demo_language.clas.locals_imp.abap | G22: Semantic Key | H22: 2 years ago
C23: =LEFT(F23,FIND(".",F23)-1) -> zbp_bs_c_demo_language | D23: {=INDEX('Not Req'!$E$4:$E$72,MATCH(MID(F23,FIND(".",F23)+1,LEN(F23)-FIND(".",F23)+1),'Not Req'!$D$4:$D$72,0))} -> Description : Classes | E23: =INDEX('Not Req'!$F$4:$F$72,MATCH(MID(F23,FIND(".",F23)+1,LEN(F23)-FIND(".",F23)+1),'Not Req'!$D$4:$D$72,0)) -> 3. Source Code Library | F23: zbp_bs_c_demo_language.clas.xml | G23: Google Translate App | H23: 2 years ago
C24: =LEFT(F24,FIND(".",F24)-1) -> zbp_bs_r_demo_language | D24: {=INDEX('Not Req'!$E$4:$E$72,MATCH(MID(F24,FIND(".",F24)+1,LEN(F24)-FIND(".",F24)+1),'Not Req'!$D$4:$D$72,0))} -> Description : Classes | E24: =INDEX('Not Req'!$F$4:$F$72,MATCH(MID(F24,FIND(".",F24)+1,LEN(F24)-FIND(".",F24)+1),'Not Req'!$D$4:$D$72,0)) -> 3. Source Code Library | F24: zbp_bs_r_demo_language.clas.xml | G24: Google Translate App | H24: 2 years ago
... C33: =LEFT(F33,FIND(".",F33)-1) -> zbs_ui_demo_language_o4_0001_g4ba | D33: {=INDEX('Not Req'!$E$4:$E$72,MATCH(MID(F33,FIND(".",F33)+1,LEN(F33)-FIND(".",F33)+1),'Not Req'!$D$4:$D$72,0))} -> Internal (Not Req) | E33: =INDEX('Not Req'!$F$4:$F$72,MATCH(MID(F33,FIND(".",F33)+1,LEN(F33)-FIND(".",F33)+1),'Not Req'!$D$4:$D$72,0)) -> Internal (Not Req) | F33: zbs_ui_demo_language_o4_0001_g4ba.sco2.xml | G33: Google Translate App | H33: 2 years ago
A34: D | B34: D | C34: =LEFT(F34,FIND(".",F34)-1) -> zbs_ui_demo_language_o4_0_00001_ibs | D34: {=INDEX('Not Req'!$E$4:$E$72,MATCH(MID(F34,FIND(".",F34)+1,LEN(F34)-FIND(".",F34)+1),'Not Req'!$D$4:$D$72,0))} -> Internal (Not Req) | E34: =INDEX('Not Req'!$F$4:$F$72,MATCH(MID(F34,FIND(".",F34)+1,LEN(F34)-FIND(".",F34)+1),'Not Req'!$D$4:$D$72,0)) -> Internal (Not Req) | F34: zbs_ui_demo_language_o4_0_00001_ibs.sia6.xml | G34: Google Translate App | H34: 2 years ago

Sheet RAP GEN 1
B2: d | C2: Object | D2: Type | E2: Category | F2: Github Object | G2: Github Type | H2: Version
B4: 1 | C4: =LEFT(F4,FIND(".",F4)-1) -> package | D4: {=INDEX('Not Req'!$E$4:$E$72,MATCH(MID(F4,FIND(".",F4)+1,LEN(F4)-FIND(".",F4)+1),'Not Req'!$D$4:$D$72,0))} -> Description : Package | E4: =INDEX('Not Req'!$F$4:$F$72,MATCH(MID(F4,FIND(".",F4)+1,LEN(F4)-FIND(".",F4)+1),'Not Req'!$D$4:$D$72,0)) -> 0. Package | F4: package.devc.xml | G4: CDS Pattern | H4: 2 months ago | N4: {=_xlfn.UNIQUE(C4:C21)} -> package
C5: =LEFT(F5,FIND(".",F5)-1) -> zbs_demo_description | D5: {=INDEX('Not Req'!$E$4:$E$72,MATCH(MID(F5,FIND(".",F5)+1,LEN(F5)-FIND(".",F5)+1),'Not Req'!$D$4:$D$72,0))} -> Data Element | E5: =INDEX('Not Req'!$F$4:$F$72,MATCH(MID(F5,FIND(".",F5)+1,LEN(F5)-FIND(".",F5)+1),'Not Req'!$D$4:$D$72,0)) -> 1. Dictionary | F5: zbs_demo_description.dtel.xml | G5: Delta commit | H5: 3 years ago | N5: zbs_demo_description
C6: =LEFT(F6,FIND(".",F6)-1) -> zbs_demo_key | D6: {=INDEX('Not Req'!$E$4:$E$72,MATCH(MID(F6,FIND(".",F6)+1,LEN(F6)-FIND(".",F6)+1),'Not Req'!$D$4:$D$72,0))} -> Data Element | E6: =INDEX('Not Req'!$F$4:$F$72,MATCH(MID(F6,FIND(".",F6)+1,LEN(F6)-FIND(".",F6)+1),'Not Req'!$D$4:$D$72,0)) -> 1. Dictionary | F6: zbs_demo_key.dtel.xml | G6: Simple RAP Generator | H6: 3 years ago | N6: zbs_demo_key
C7: =LEFT(F7,FIND(".",F7)-1) -> zbs_demo_price | D7: {=INDEX('Not Req'!$E$4:$E$72,MATCH(MID(F7,FIND(".",F7)+1,LEN(F7)-FIND(".",F7)+1),'Not Req'!$D$4:$D$72,0))} -> Data Element | E7: =INDEX('Not Req'!$F$4:$F$72,MATCH(MID(F7,FIND(".",F7)+1,LEN(F7)-FIND(".",F7)+1),'Not Req'!$D$4:$D$72,0)) -> 1. Dictionary | F7: zbs_demo_price.dtel.xml | G7: Simple RAP Generator | H7: 3 years ago | N7: zbs_demo_price
C8: =LEFT(F8,FIND(".",F8)-1) -> zbs_demo_key | D8: {=INDEX('Not Req'!$E$4:$E$72,MATCH(MID(F8,FIND(".",F8)+1,LEN(F8)-FIND(".",F8)+1),'Not Req'!$D$4:$D$72,0))} -> Domain | E8: =INDEX('Not Req'!$F$4:$F$72,MATCH(MID(F8,FIND(".",F8)+1,LEN(F8)-FIND(".",F8)+1),'Not Req'!$D$4:$D$72,0)) -> 1. Dictionary | F8: zbs_demo_key.doma.xml | G8: Delta commit | H8: 2 years ago | N8: zbs_dmo_gen1
C9: =LEFT(F9,FIND(".",F9)-1) -> zbs_dmo_gen1 | D9: {=INDEX('Not Req'!$E$4:$E$72,MATCH(MID(F9,FIND(".",F9)+1,LEN(F9)-FIND(".",F9)+1),'Not Req'!$D$4:$D$72,0))} -> Table | E9: =INDEX('Not Req'!$F$4:$F$72,MATCH(MID(F9,FIND(".",F9)+1,LEN(F9)-FIND(".",F9)+1),'Not Req'!$D$4:$D$72,0)) -> 1. Dictionary | F9: zbs_dmo_gen1.tabl.xml | G9: Simple RAP Generator | H9: 3 years ago | N9: zbs_dmo_gen1_d
C10: =LEFT(F10,FIND(".",F10)-1) -> zbs_dmo_gen1_d | D10: {=INDEX('Not Req'!$E$4:$E$72,MATCH(MID(F10,FIND(".",F10)+1,LEN(F10)-FIND(".",F10)+1),'Not Req'!$D$4:$D$72,0))} -> Table | E10: =INDEX('Not Req'!$F$4:$F$72,MATCH(MID(F10,FIND(".",F10)+1,LEN(F10)-FIND(".",F10)+1),'Not Req'!$D$4:$D$72,0)) -> 1. Dictionary | F10: zbs_dmo_gen1_d.tabl.xml | G10: Simple RAP Generator | H10: 3 years ago | N10: zbs_c_dmogen1
C11: =LEFT(F11,FIND(".",F11)-1) -> zbs_c_dmogen1 | D11: {=INDEX('Not Req'!$E$4:$E$72,MATCH(MID(F11,FIND(".",F11)+1,LEN(F11)-FIND(".",F11)+1),'Not Req'!$D$4:$D$72,0))} -> BDEF | E11: =INDEX('Not Req'!$F$4:$F$72,MATCH(MID(F11,FIND(".",F11)+1,LEN(F11)-FIND(".",F11)+1),'Not Req'!$D$4:$D$72,0)) -> 2. CDS | F11: zbs_c_dmogen1.bdef.asbdef | G11: Simple RAP Generator | H11: 3 years ago | N11: zbs_r_dmogen1
C12: =LEFT(F12,FIND(".",F12)-1) -> zbs_r_dmogen1 | D12: {=INDEX('Not Req'!$E$4:$E$72,MATCH(MID(F12,FIND(".",F12)+1,LEN(F12)-FIND(".",F12)+1),'Not Req'!$D$4:$D$72,0))} -> BDEF | E12: =INDEX('Not Req'!$F$4:$F$72,MATCH(MID(F12,FIND(".",F12)+1,LEN(F12)-FIND(".",F12)+1),'Not Req'!$D$4:$D$72,0)) -> 2. CDS | F12: zbs_r_dmogen1.bdef.asbdef | G12: Simple RAP Generator | H12: 3 years ago | N12: zbp_bs_demo_simple_gen1
C13: =LEFT(F13,FIND(".",F13)-1) -> zbs_c_dmogen1 | D13: {=INDEX('Not Req'!$E$4:$E$72,MATCH(MID(F13,FIND(".",F13)+1,LEN(F13)-FIND(".",F13)+1),'Not Req'!$D$4:$D$72,0))} -> Data Definition | E13: =INDEX('Not Req'!$F$4:$F$72,MATCH(MID(F13,FIND(".",F13)+1,LEN(F13)-FIND(".",F13)+1),'Not Req'!$D$4:$D$72,0)) -> 2. CDS | F13: zbs_c_dmogen1.ddls.asddls | G13: Simple RAP Generator | H13: 3 years ago
C14: =LEFT(F14,FIND(".",F14)-1) -> zbs_r_dmogen1 | D14: {=INDEX('Not Req'!$E$4:$E$72,MATCH(MID(F14,FIND(".",F14)+1,LEN(F14)-FIND(".",F14)+1),'Not Req'!$D$4:$D$72,0))} -> Data Definition | E14: =INDEX('Not Req'!$F$4:$F$72,MATCH(MID(F14,FIND(".",F14)+1,LEN(F14)-FIND(".",F14)+1),'Not Req'!$D$4:$D$72,0)) -> 2. CDS | F14: zbs_r_dmogen1.ddls.asddls | G14: Simple RAP Generator | H14: 3 years ago
C15: =LEFT(F15,FIND(".",F15)-1) -> zbs_c_dmogen1 | D15: {=INDEX('Not Req'!$E$4:$E$72,MATCH(MID(F15,FIND(".",F15)+1,LEN(F15)-FIND(".",F15)+1),'Not Req'!$D$4:$D$72,0))} -> Description : BDEF | E15: =INDEX('Not Req'!$F$4:$F$72,MATCH(MID(F15,FIND(".",F15)+1,LEN(F15)-FIND(".",F15)+1),'Not Req'!$D$4:$D$72,0)) -> 2. CDS | F15: zbs_c_dmogen1.bdef.xml | G15: Simple RAP Generator | H15: 3 years ago
C16: =LEFT(F16,FIND(".",F16)-1) -> zbs_r_dmogen1 | D16: {=INDEX('Not Req'!$E$4:$E$72,MATCH(MID(F16,FIND(".",F16)+1,LEN(F16)-FIND(".",F16)+1),'Not Req'!$D$4:$D$72,0))} -> Description : BDEF | E16: =INDEX('Not Req'!$F$4:$F$72,MATCH(MID(F16,FIND(".",F16)+1,LEN(F16)-FIND(".",F16)+1),'Not Req'!$D$4:$D$72,0)) -> 2. CDS | F16: zbs_r_dmogen1.bdef.xml | G16: Simple RAP Generator | H16: 3 years ago
C17: =LEFT(F17,FIND(".",F17)-1) -> zbs_c_dmogen1 | D17: {=INDEX('Not Req'!$E$4:$E$72,MATCH(MID(F17,FIND(".",F17)+1,LEN(F17)-FIND(".",F17)+1),'Not Req'!$D$4:$D$72,0))} -> Description : Data Definition | E17: =INDEX('Not Req'!$F$4:$F$72,MATCH(MID(F17,FIND(".",F17)+1,LEN(F17)-FIND(".",F17)+1),'Not Req'!$D$4:$D$72,0)) -> 2. CDS | F17: zbs_c_dmogen1.ddls.xml | G17: Simple RAP Generator | H17: 3 years ago
C18: =LEFT(F18,FIND(".",F18)-1) -> zbs_r_dmogen1 | D18: {=INDEX('Not Req'!$E$4:$E$72,MATCH(MID(F18,FIND(".",F18)+1,LEN(F18)-FIND(".",F18)+1),'Not Req'!$D$4:$D$72,0))} -> Description : Data Definition | E18: =INDEX('Not Req'!$F$4:$F$72,MATCH(MID(F18,FIND(".",F18)+1,LEN(F18)-FIND(".",F18)+1),'Not Req'!$D$4:$D$72,0)) -> 2. CDS | F18: zbs_r_dmogen1.ddls.xml | G18: Simple RAP Generator | H18: 3 years ago
C19: =LEFT(F19,FIND(".",F19)-1) -> zbs_c_dmogen1 | D19: {=INDEX('Not Req'!$E$4:$E$72,MATCH(MID(F19,FIND(".",F19)+1,LEN(F19)-FIND(".",F19)+1),'Not Req'!$D$4:$D$72,0))} -> Description : Metadata | E19: =INDEX('Not Req'!$F$4:$F$72,MATCH(MID(F19,FIND(".",F19)+1,LEN(F19)-FIND(".",F19)+1),'Not Req'!$D$4:$D$72,0)) -> 2. CDS | F19: zbs_c_dmogen1.ddlx.xml | G19: Simple RAP Generator | H19: 3 years ago
C20: =LEFT(F20,FIND(".",F20)-1) -> zbs_c_dmogen1 | D20: {=INDEX('Not Req'!$E$4:$E$72,MATCH(MID(F20,FIND(".",F20)+1,LEN(F20)-FIND(".",F20)+1),'Not Req'!$D$4:$D$72,0))} -> Metadata | E20: =INDEX('Not Req'!$F$4:$F$72,MATCH(MID(F20,FIND(".",F20)+1,LEN(F20)-FIND(".",F20)+1),'Not Req'!$D$4:$D$72,0)) -> 2. CDS | F20: zbs_c_dmogen1.ddlx.asddlxs | G20: Simple RAP Generator | H20: 3 years ago
C21: =LEFT(F21,FIND(".",F21)-1) -> zbp_bs_demo_simple_gen1 | D21: {=INDEX('Not Req'!$E$4:$E$72,MATCH(MID(F21,FIND(".",F21)+1,LEN(F21)-FIND(".",F21)+1),'Not Req'!$D$4:$D$72,0))} -> Classes | E21: =INDEX('Not Req'!$F$4:$F$72,MATCH(MID(F21,FIND(".",F21)+1,LEN(F21)-FIND(".",F21)+1),'Not Req'!$D$4:$D$72,0)) -> 3. Source Code Library | F21: zbp_bs_demo_simple_gen1.clas.abap | G21: Simple RAP Generator | H21: 3 years ago
C22: =LEFT(F22,FIND(".",F22)-1) -> zbp_bs_demo_simple_gen1 | D22: {=INDEX('Not Req'!$E$4:$E$72,MATCH(MID(F22,FIND(".",F22)+1,LEN(F22)-FIND(".",F22)+1),'Not Req'!$D$4:$D$72,0))} -> Classes Local | E22: =INDEX('Not Req'!$F$4:$F$72,MATCH(MID(F22,FIND(".",F22)+1,LEN(F22)-FIND(".",F22)+1),'Not Req'!$D$4:$D$72,0)) -> 3. Source Code Library | F22: zbp_bs_demo_simple_gen1.clas.locals_imp.abap | G22: Simple RAP Generator | H22: 3 years ago
C23: =LEFT(F23,FIND(".",F23)-1) -> zbp_bs_demo_simple_gen1 | D23: {=INDEX('Not Req'!$E$4:$E$72,MATCH(MID(F23,FIND(".",F23)+1,LEN(F23)-FIND(".",F23)+1),'Not Req'!$D$4:$D$72,0))} -> Description : Classes | E23: =INDEX('Not Req'!$F$4:$F$72,MATCH(MID(F23,FIND(".",F23)+1,LEN(F23)-FIND(".",F23)+1),'Not Req'!$D$4:$D$72,0)) -> 3. Source Code Library | F23: zbp_bs_demo_simple_gen1.clas.xml | G23: Simple RAP Generator | H23: 3 years ago
C24: =LEFT(F24,FIND(".",F24)-1) -> zbs_demo_gen1 | D24: {=INDEX('Not Req'!$E$4:$E$72,MATCH(MID(F24,FIND(".",F24)+1,LEN(F24)-FIND(".",F24)+1),'Not Req'!$D$4:$D$72,0))} -> Service Definition | E24: =INDEX('Not Req'!$F$4:$F$72,MATCH(MID(F24,FIND(".",F24)+1,LEN(F24)-FIND(".",F24)+1),'Not Req'!$D$4:$D$72,0)) -> Business Services | F24: zbs_demo_gen1.srvd.srvdsrv | G24: Simple RAP Generator | H24: 3 years ago
... C31: =LEFT(F31,FIND(".",F31)-1) -> zbs_ui_demo_gen1_o4_0001_g4ba_ibs | D31: {=INDEX('Not Req'!$E$4:$E$72,MATCH(MID(F31,FIND(".",F31)+1,LEN(F31)-FIND(".",F31)+1),'Not Req'!$D$4:$D$72,0))} -> Internal (Not Req) | E31: =INDEX('Not Req'!$F$4:$F$72,MATCH(MID(F31,FIND(".",F31)+1,LEN(F31)-FIND(".",F31)+1),'Not Req'!$D$4:$D$72,0)) -> Internal (Not Req) | F31: zbs_ui_demo_gen1_o4_0001_g4ba_ibs.sia6.xml | G31: Delta commit | H31: 2 years ago

Sheet Custom (2)
B2: d | C2: Object | D2: Type | E2: Category | F2: Github Object | G2: Github Type | H2: Version
B4: 1 | C4: =LEFT(F4,FIND(".",F4)-1) -> c856c47aced564f51dd5eb5e0776c6ht | D4: {=INDEX('Not Req'!$E$4:$E$72,MATCH(MID(F4,FIND(".",F4)+1,LEN(F4)-FIND(".",F4)+1),'Not Req'!$D$4:$D$72,0))} -> Internal (Not Req) | E4: =INDEX('Not Req'!$F$4:$F$72,MATCH(MID(F4,FIND(".",F4)+1,LEN(F4)-FIND(".",F4)+1),'Not Req'!$D$4:$D$72,0)) -> Internal (Not Req) | F4: c856c47aced564f51dd5eb5e0776c6ht.sush.xml | G4: OData interface | H4: 4 years ago | N4: {=_xlfn.UNIQUE(C4:C21)} -> c856c47aced564f51dd5eb5e0776c6ht
C5: =LEFT(F5,FIND(".",F5)-1) -> package | D5: {=INDEX('Not Req'!$E$4:$E$72,MATCH(MID(F5,FIND(".",F5)+1,LEN(F5)-FIND(".",F5)+1),'Not Req'!$D$4:$D$72,0))} -> Description : Package | E5: =INDEX('Not Req'!$F$4:$F$72,MATCH(MID(F5,FIND(".",F5)+1,LEN(F5)-FIND(".",F5)+1),'Not Req'!$D$4:$D$72,0)) -> 0. Package | F5: package.devc.xml | G5: OData interface | H5: 4 years ago | N5: package
C6: =LEFT(F6,FIND(".",F6)-1) -> zbp_demo_company_name | D6: {=INDEX('Not Req'!$E$4:$E$72,MATCH(MID(F6,FIND(".",F6)+1,LEN(F6)-FIND(".",F6)+1),'Not Req'!$D$4:$D$72,0))} -> Classes | E6: =INDEX('Not Req'!$F$4:$F$72,MATCH(MID(F6,FIND(".",F6)+1,LEN(F6)-FIND(".",F6)+1),'Not Req'!$D$4:$D$72,0)) -> 3. Source Code Library | F6: zbp_demo_company_name.clas.abap | G6: OData interface | H6: 4 years ago | N6: zbp_demo_company_name
C7: =LEFT(F7,FIND(".",F7)-1) -> zbp_demo_company_name | D7: {=INDEX('Not Req'!$E$4:$E$72,MATCH(MID(F7,FIND(".",F7)+1,LEN(F7)-FIND(".",F7)+1),'Not Req'!$D$4:$D$72,0))} -> Classes Local | E7: =INDEX('Not Req'!$F$4:$F$72,MATCH(MID(F7,FIND(".",F7)+1,LEN(F7)-FIND(".",F7)+1),'Not Req'!$D$4:$D$72,0)) -> 3. Source Code Library | F7: zbp_demo_company_name.clas.locals_imp.abap | G7: Removed function | H7: 4 years ago | N7: zbs_api_company_names_o2 0001
C8: =LEFT(F8,FIND(".",F8)-1) -> zbp_demo_company_name | D8: {=INDEX('Not Req'!$E$4:$E$72,MATCH(MID(F8,FIND(".",F8)+1,LEN(F8)-FIND(".",F8)+1),'Not Req'!$D$4:$D$72,0))} -> Description : Classes | E8: =INDEX('Not Req'!$F$4:$F$72,MATCH(MID(F8,FIND(".",F8)+1,LEN(F8)-FIND(".",F8)+1),'Not Req'!$D$4:$D$72,0)) -> 3. Source Code Library | F8: zbp_demo_company_name.clas.xml | G8: OData interface | H8: 4 years ago | N8: zbs_api_company_names_o2
C9: =LEFT(F9,FIND(".",F9)-1) -> zbs_api_company_names_o2 0001 | D9: {=INDEX('Not Req'!$E$4:$E$72,MATCH(MID(F9,FIND(".",F9)+1,LEN(F9)-FIND(".",F9)+1),'Not Req'!$D$4:$D$72,0))} -> Service Binding API | E9: =INDEX('Not Req'!$F$4:$F$72,MATCH(MID(F9,FIND(".",F9)+1,LEN(F9)-FIND(".",F9)+1),'Not Req'!$D$4:$D$72,0)) -> Business Services | F9: zbs_api_company_names_o2 0001.iwsv.xml | G9: OData interface | H9: 4 years ago | N9: zbs_c_dmocname
C10: =LEFT(F10,FIND(".",F10)-1) -> zbs_api_company_names_o2 0001 | D10: {=INDEX('Not Req'!$E$4:$E$72,MATCH(MID(F10,FIND(".",F10)+1,LEN(F10)-FIND(".",F10)+1),'Not Req'!$D$4:$D$72,0))} -> 0 | E10: =INDEX('Not Req'!$F$4:$F$72,MATCH(MID(F10,FIND(".",F10)+1,LEN(F10)-FIND(".",F10)+1),'Not Req'!$D$4:$D$72,0)) -> 0 | F10: zbs_api_company_names_o2 0001.iwmo.xml | G10: OData interface | H10: 4 years ago | N10: zbs_demo_company_names
C11: =LEFT(F11,FIND(".",F11)-1) -> zbs_api_company_names_o2 | D11: {=INDEX('Not Req'!$E$4:$E$72,MATCH(MID(F11,FIND(".",F11)+1,LEN(F11)-FIND(".",F11)+1),'Not Req'!$D$4:$D$72,0))} -> Internal (Not Req) | E11: =INDEX('Not Req'!$F$4:$F$72,MATCH(MID(F11,FIND(".",F11)+1,LEN(F11)-FIND(".",F11)+1),'Not Req'!$D$4:$D$72,0)) -> Internal (Not Req) | F11: zbs_api_company_names_o2.srvb.xml | G11: OData interface | H11: 4 years ago | N11: zbs_dmo_cname
C12: =LEFT(F12,FIND(".",F12)-1) -> zbs_c_dmocname | D12: {=INDEX('Not Req'!$E$4:$E$72,MATCH(MID(F12,FIND(".",F12)+1,LEN(F12)-FIND(".",F12)+1),'Not Req'!$D$4:$D$72,0))} -> BDEF | E12: =INDEX('Not Req'!$F$4:$F$72,MATCH(MID(F12,FIND(".",F12)+1,LEN(F12)-FIND(".",F12)+1),'Not Req'!$D$4:$D$72,0)) -> 2. CDS | F12: zbs_c_dmocname.bdef.asbdef | G12: Removed function | H12: 4 years ago | N12: zbs_i_dmocname
C13: =LEFT(F13,FIND(".",F13)-1) -> zbs_c_dmocname | D13: {=INDEX('Not Req'!$E$4:$E$72,MATCH(MID(F13,FIND(".",F13)+1,LEN(F13)-FIND(".",F13)+1),'Not Req'!$D$4:$D$72,0))} -> Description : BDEF | E13: =INDEX('Not Req'!$F$4:$F$72,MATCH(MID(F13,FIND(".",F13)+1,LEN(F13)-FIND(".",F13)+1),'Not Req'!$D$4:$D$72,0)) -> 2. CDS | F13: zbs_c_dmocname.bdef.xml | G13: OData interface | H13: 4 years ago
C14: =LEFT(F14,FIND(".",F14)-1) -> zbs_c_dmocname | D14: {=INDEX('Not Req'!$E$4:$E$72,MATCH(MID(F14,FIND(".",F14)+1,LEN(F14)-FIND(".",F14)+1),'Not Req'!$D$4:$D$72,0))} -> Data Definition | E14: =INDEX('Not Req'!$F$4:$F$72,MATCH(MID(F14,FIND(".",F14)+1,LEN(F14)-FIND(".",F14)+1),'Not Req'!$D$4:$D$72,0)) -> 2. CDS | F14: zbs_c_dmocname.ddls.asddls | G14: OData interface | H14: 4 years ago
C15: =LEFT(F15,FIND(".",F15)-1) -> zbs_c_dmocname | D15: {=INDEX('Not Req'!$E$4:$E$72,MATCH(MID(F15,FIND(".",F15)+1,LEN(F15)-FIND(".",F15)+1),'Not Req'!$D$4:$D$72,0))} -> Internal (Not Req) | E15: =INDEX('Not Req'!$F$4:$F$72,MATCH(MID(F15,FIND(".",F15)+1,LEN(F15)-FIND(".",F15)+1),'Not Req'!$D$4:$D$72,0)) -> Internal (Not Req) | F15: zbs_c_dmocname.ddls.baseinfo | G15: OData interface | H15: 4 years ago
C16: =LEFT(F16,FIND(".",F16)-1) -> zbs_c_dmocname | D16: {=INDEX('Not Req'!$E$4:$E$72,MATCH(MID(F16,FIND(".",F16)+1,LEN(F16)-FIND(".",F16)+1),'Not Req'!$D$4:$D$72,0))} -> Description : Data Definition | E16: =INDEX('Not Req'!$F$4:$F$72,MATCH(MID(F16,FIND(".",F16)+1,LEN(F16)-FIND(".",F16)+1),'Not Req'!$D$4:$D$72,0)) -> 2. CDS | F16: zbs_c_dmocname.ddls.xml | G16: OData interface | H16: 4 years ago
C17: =LEFT(F17,FIND(".",F17)-1) -> zbs_demo_company_names | D17: {=INDEX('Not Req'!$E$4:$E$72,MATCH(MID(F17,FIND(".",F17)+1,LEN(F17)-FIND(".",F17)+1),'Not Req'!$D$4:$D$72,0))} -> Service Definition | E17: =INDEX('Not Req'!$F$4:$F$72,MATCH(MID(F17,FIND(".",F17)+1,LEN(F17)-FIND(".",F17)+1),'Not Req'!$D$4:$D$72,0)) -> Business Services | F17: zbs_demo_company_names.srvd.srvdsrv | G17: OData interface | H17: 4 years ago
C18: =LEFT(F18,FIND(".",F18)-1) -> zbs_demo_company_names | D18: {=INDEX('Not Req'!$E$4:$E$72,MATCH(MID(F18,FIND(".",F18)+1,LEN(F18)-FIND(".",F18)+1),'Not Req'!$D$4:$D$72,0))} -> Internal (Not Req) | E18: =INDEX('Not Req'!$F$4:$F$72,MATCH(MID(F18,FIND(".",F18)+1,LEN(F18)-FIND(".",F18)+1),'Not Req'!$D$4:$D$72,0)) -> Internal (Not Req) | F18: zbs_demo_company_names.srvd.xml | G18: OData interface | H18: 4 years ago
C19: =LEFT(F19,FIND(".",F19)-1) -> zbs_dmo_cname | D19: {=INDEX('Not Req'!$E$4:$E$72,MATCH(MID(F19,FIND(".",F19)+1,LEN(F19)-FIND(".",F19)+1),'Not Req'!$D$4:$D$72,0))} -> Table | E19: =INDEX('Not Req'!$F$4:$F$72,MATCH(MID(F19,FIND(".",F19)+1,LEN(F19)-FIND(".",F19)+1),'Not Req'!$D$4:$D$72,0)) -> 1. Dictionary | F19: zbs_dmo_cname.tabl.xml | G19: Fixed complex type | H19: 4 years ago
C20: =LEFT(F20,FIND(".",F20)-1) -> zbs_i_dmocname | D20: {=INDEX('Not Req'!$E$4:$E$72,MATCH(MID(F20,FIND(".",F20)+1,LEN(F20)-FIND(".",F20)+1),'Not Req'!$D$4:$D$72,0))} -> BDEF | E20: =INDEX('Not Req'!$F$4:$F$72,MATCH(MID(F20,FIND(".",F20)+1,LEN(F20)-FIND(".",F20)+1),'Not Req'!$D$4:$D$72,0)) -> 2. CDS | F20: zbs_i_dmocname.bdef.asbdef | G20: Removed function | H20: 4 years ago
C21: =LEFT(F21,FIND(".",F21)-1) -> zbs_i_dmocname | D21: {=INDEX('Not Req'!$E$4:$E$72,MATCH(MID(F21,FIND(".",F21)+1,LEN(F21)-FIND(".",F21)+1),'Not Req'!$D$4:$D$72,0))} -> Description : BDEF | E21: =INDEX('Not Req'!$F$4:$F$72,MATCH(MID(F21,FIND(".",F21)+1,LEN(F21)-FIND(".",F21)+1),'Not Req'!$D$4:$D$72,0)) -> 2. CDS | F21: zbs_i_dmocname.bdef.xml | G21: OData interface | H21: 4 years ago
C22: =LEFT(F22,FIND(".",F22)-1) -> zbs_i_dmocname | D22: {=INDEX('Not Req'!$E$4:$E$72,MATCH(MID(F22,FIND(".",F22)+1,LEN(F22)-FIND(".",F22)+1),'Not Req'!$D$4:$D$72,0))} -> Data Definition | E22: =INDEX('Not Req'!$F$4:$F$72,MATCH(MID(F22,FIND(".",F22)+1,LEN(F22)-FIND(".",F22)+1),'Not Req'!$D$4:$D$72,0)) -> 2. CDS | F22: zbs_i_dmocname.ddls.asddls | G22: OData interface | H22: 4 years ago
C23: =LEFT(F23,FIND(".",F23)-1) -> zbs_i_dmocname | D23: {=INDEX('Not Req'!$E$4:$E$72,MATCH(MID(F23,FIND(".",F23)+1,LEN(F23)-FIND(".",F23)+1),'Not Req'!$D$4:$D$72,0))} -> Internal (Not Req) | E23: =INDEX('Not Req'!$F$4:$F$72,MATCH(MID(F23,FIND(".",F23)+1,LEN(F23)-FIND(".",F23)+1),'Not Req'!$D$4:$D$72,0)) -> Internal (Not Req) | F23: zbs_i_dmocname.ddls.baseinfo | G23: OData interface | H23: 4 years ago
C24: =LEFT(F24,FIND(".",F24)-1) -> zbs_i_dmocname | D24: {=INDEX('Not Req'!$E$4:$E$72,MATCH(MID(F24,FIND(".",F24)+1,LEN(F24)-FIND(".",F24)+1),'Not Req'!$D$4:$D$72,0))} -> Description : Data Definition | E24: =INDEX('Not Req'!$F$4:$F$72,MATCH(MID(F24,FIND(".",F24)+1,LEN(F24)-FIND(".",F24)+1),'Not Req'!$D$4:$D$72,0)) -> 2. CDS | F24: zbs_i_dmocname.ddls.xml | G24: OData interface | H24: 4 years ago
C25: =LEFT(F25,FIND(".",F25)-1) -> zcl_bs_demo_rebuild_intf_data | D25: {=INDEX('Not Req'!$E$4:$E$72,MATCH(MID(F25,FIND(".",F25)+1,LEN(F25)-FIND(".",F25)+1),'Not Req'!$D$4:$D$72,0))} -> Classes | E25: =INDEX('Not Req'!$F$4:$F$72,MATCH(MID(F25,FIND(".",F25)+1,LEN(F25)-FIND(".",F25)+1),'Not Req'!$D$4:$D$72,0)) -> 3. Source Code Library | F25: zcl_bs_demo_rebuild_intf_data.clas.abap | G25: OData interface | H25: 4 years ago
A26: d | B26: d | C26: =LEFT(F26,FIND(".",F26)-1) -> zcl_bs_demo_rebuild_intf_data | D26: {=INDEX('Not Req'!$E$4:$E$72,MATCH(MID(F26,FIND(".",F26)+1,LEN(F26)-FIND(".",F26)+1),'Not Req'!$D$4:$D$72,0))} -> Description : Classes | E26: =INDEX('Not Req'!$F$4:$F$72,MATCH(MID(F26,FIND(".",F26)+1,LEN(F26)-FIND(".",F26)+1),'Not Req'!$D$4:$D$72,0)) -> 3. Source Code Library | F26: zcl_bs_demo_rebuild_intf_data.clas.xml | G26: OData interface | H26: 4 years ago

Sheet Custom
B2: d | C2: Object | D2: Type | E2: Category | F2: Github Object | G2: Github Type | H2: Version
B4: 1 | C4: =LEFT(F4,FIND(".",F4)-1) -> package | D4: {=INDEX('Not Req'!$E$4:$E$72,MATCH(MID(F4,FIND(".",F4)+1,LEN(F4)-FIND(".",F4)+1),'Not Req'!$D$4:$D$72,0))} -> Description : Package | E4: =INDEX('Not Req'!$F$4:$F$72,MATCH(MID(F4,FIND(".",F4)+1,LEN(F4)-FIND(".",F4)+1),'Not Req'!$D$4:$D$72,0)) -> 0. Package | F4: package.devc.xml | G4: CDS Pattern | H4: 2 months ago | N4: {=_xlfn.UNIQUE(C4:C21)} -> package
C5: =LEFT(F5,FIND(".",F5)-1) -> zbs_r_rapcustomcompanynames | D5: {=INDEX('Not Req'!$E$4:$E$72,MATCH(MID(F5,FIND(".",F5)+1,LEN(F5)-FIND(".",F5)+1),'Not Req'!$D$4:$D$72,0))} -> BDEF | E5: =INDEX('Not Req'!$F$4:$F$72,MATCH(MID(F5,FIND(".",F5)+1,LEN(F5)-FIND(".",F5)+1),'Not Req'!$D$4:$D$72,0)) -> 2. CDS | F5: zbs_r_rapcustomcompanynames.bdef.asbdef | G5: Unmanaged (Remote) | H5: 3 years ago | N5: zbs_r_rapcustomcompanynames
C6: =LEFT(F6,FIND(".",F6)-1) -> zbs_r_rapcustomcompanynames | D6: {=INDEX('Not Req'!$E$4:$E$72,MATCH(MID(F6,FIND(".",F6)+1,LEN(F6)-FIND(".",F6)+1),'Not Req'!$D$4:$D$72,0))} -> Description : BDEF | E6: =INDEX('Not Req'!$F$4:$F$72,MATCH(MID(F6,FIND(".",F6)+1,LEN(F6)-FIND(".",F6)+1),'Not Req'!$D$4:$D$72,0)) -> 2. CDS | F6: zbs_r_rapcustomcompanynames.bdef.xml | G6: Delta commit | H6: 3 years ago | N6: zbp_bs_demo_company_names
C7: =LEFT(F7,FIND(".",F7)-1) -> zbs_r_rapcustomcompanynames | D7: {=INDEX('Not Req'!$E$4:$E$72,MATCH(MID(F7,FIND(".",F7)+1,LEN(F7)-FIND(".",F7)+1),'Not Req'!$D$4:$D$72,0))} -> Data Definition | E7: =INDEX('Not Req'!$F$4:$F$72,MATCH(MID(F7,FIND(".",F7)+1,LEN(F7)-FIND(".",F7)+1),'Not Req'!$D$4:$D$72,0)) -> 2. CDS | F7: zbs_r_rapcustomcompanynames.ddls.asddls | G7: Unmanaged (Remote) | H7: 3 years ago | N7: zcl_bs_demo_custom_company_qry
C8: =LEFT(F8,FIND(".",F8)-1) -> zbs_r_rapcustomcompanynames | D8: {=INDEX('Not Req'!$E$4:$E$72,MATCH(MID(F8,FIND(".",F8)+1,LEN(F8)-FIND(".",F8)+1),'Not Req'!$D$4:$D$72,0))} -> Description : Data Definition | E8: =INDEX('Not Req'!$F$4:$F$72,MATCH(MID(F8,FIND(".",F8)+1,LEN(F8)-FIND(".",F8)+1),'Not Req'!$D$4:$D$72,0)) -> 2. CDS | F8: zbs_r_rapcustomcompanynames.ddls.xml | G8: Unmanaged (Remote) | H8: 3 years ago | N8: zbs_demo_company_names
C9: =LEFT(F9,FIND(".",F9)-1) -> zbp_bs_demo_company_names | D9: {=INDEX('Not Req'!$E$4:$E$72,MATCH(MID(F9,FIND(".",F9)+1,LEN(F9)-FIND(".",F9)+1),'Not Req'!$D$4:$D$72,0))} -> Classes | E9: =INDEX('Not Req'!$F$4:$F$72,MATCH(MID(F9,FIND(".",F9)+1,LEN(F9)-FIND(".",F9)+1),'Not Req'!$D$4:$D$72,0)) -> 3. Source Code Library | F9: zbp_bs_demo_company_names.clas.abap | G9: Delta commit | H9: 3 years ago | N9: 8343a14d0af185665a219e7fd55368ht
C10: =LEFT(F10,FIND(".",F10)-1) -> zbp_bs_demo_company_names | D10: {=INDEX('Not Req'!$E$4:$E$72,MATCH(MID(F10,FIND(".",F10)+1,LEN(F10)-FIND(".",F10)+1),'Not Req'!$D$4:$D$72,0))} -> Classes Local | E10: =INDEX('Not Req'!$F$4:$F$72,MATCH(MID(F10,FIND(".",F10)+1,LEN(F10)-FIND(".",F10)+1),'Not Req'!$D$4:$D$72,0)) -> 3. Source Code Library | F10: zbp_bs_demo_company_names.clas.locals_imp.abap | G10: Unmanaged (Remote) | H10: 3 years ago | N10: 91f7bde389ceb5bb6efe93dccee9feht
C11: =LEFT(F11,FIND(".",F11)-1) -> zbp_bs_demo_company_names | D11: {=INDEX('Not Req'!$E$4:$E$72,MATCH(MID(F11,FIND(".",F11)+1,LEN(F11)-FIND(".",F11)+1),'Not Req'!$D$4:$D$72,0))} -> Description : Classes | E11: =INDEX('Not Req'!$F$4:$F$72,MATCH(MID(F11,FIND(".",F11)+1,LEN(F11)-FIND(".",F11)+1),'Not Req'!$D$4:$D$72,0)) -> 3. Source Code Library | F11: zbp_bs_demo_company_names.clas.xml | G11: Unmanaged (Remote) | H11: 3 years ago | N11: zbs_ui_demo_com_names_o2
C12: =LEFT(F12,FIND(".",F12)-1) -> zcl_bs_demo_custom_company_qry | D12: {=INDEX('Not Req'!$E$4:$E$72,MATCH(MID(F12,FIND(".",F12)+1,LEN(F12)-FIND(".",F12)+1),'Not Req'!$D$4:$D$72,0))} -> Classes | E12: =INDEX('Not Req'!$F$4:$F$72,MATCH(MID(F12,FIND(".",F12)+1,LEN(F12)-FIND(".",F12)+1),'Not Req'!$D$4:$D$72,0)) -> 3. Source Code Library | F12: zcl_bs_demo_custom_company_qry.clas.abap | G12: Delta commit | H12: 2 years ago | N12: zbs_ui_demo_com_names_o2_iwsg
C13: =LEFT(F13,FIND(".",F13)-1) -> zcl_bs_demo_custom_company_qry | D13: {=INDEX('Not Req'!$E$4:$E$72,MATCH(MID(F13,FIND(".",F13)+1,LEN(F13)-FIND(".",F13)+1),'Not Req'!$D$4:$D$72,0))} -> Description : Classes | E13: =INDEX('Not Req'!$F$4:$F$72,MATCH(MID(F13,FIND(".",F13)+1,LEN(F13)-FIND(".",F13)+1),'Not Req'!$D$4:$D$72,0)) -> 3. Source Code Library | F13: zcl_bs_demo_custom_company_qry.clas.xml | G13: Unmanaged (Remote) | H13: 3 years ago | N13: zbs_ui_demo_com_names_o2_iwsg_ibs
C14: =LEFT(F14,FIND(".",F14)-1) -> zbs_demo_company_names | D14: {=INDEX('Not Req'!$E$4:$E$72,MATCH(MID(F14,FIND(".",F14)+1,LEN(F14)-FIND(".",F14)+1),'Not Req'!$D$4:$D$72,0))} -> Service Definition | E14: =INDEX('Not Req'!$F$4:$F$72,MATCH(MID(F14,FIND(".",F14)+1,LEN(F14)-FIND(".",F14)+1),'Not Req'!$D$4:$D$72,0)) -> Business Services | F14: zbs_demo_company_names.srvd.srvdsrv | G14: Unmanaged (Remote) | H14: 3 years ago
C15: =LEFT(F15,FIND(".",F15)-1) -> 8343a14d0af185665a219e7fd55368ht | D15: {=INDEX('Not Req'!$E$4:$E$72,MATCH(MID(F15,FIND(".",F15)+1,LEN(F15)-FIND(".",F15)+1),'Not Req'!$D$4:$D$72,0))} -> Internal (Not Req) | E15: =INDEX('Not Req'!$F$4:$F$72,MATCH(MID(F15,FIND(".",F15)+1,LEN(F15)-FIND(".",F15)+1),'Not Req'!$D$4:$D$72,0)) -> Internal (Not Req) | F15: 8343a14d0af185665a219e7fd55368ht.sush.xml | G15: Unmanaged (Remote) | H15: 3 years ago
C16: =LEFT(F16,FIND(".",F16)-1) -> 91f7bde389ceb5bb6efe93dccee9feht | D16: {=INDEX('Not Req'!$E$4:$E$72,MATCH(MID(F16,FIND(".",F16)+1,LEN(F16)-FIND(".",F16)+1),'Not Req'!$D$4:$D$72,0))} -> Internal (Not Req) | E16: =INDEX('Not Req'!$F$4:$F$72,MATCH(MID(F16,FIND(".",F16)+1,LEN(F16)-FIND(".",F16)+1),'Not Req'!$D$4:$D$72,0)) -> Internal (Not Req) | F16: 91f7bde389ceb5bb6efe93dccee9feht.sush.xml | G16: Unmanaged (Remote) | H16: 3 years ago
C17: =LEFT(F17,FIND(".",F17)-1) -> zbs_demo_company_names | D17: {=INDEX('Not Req'!$E$4:$E$72,MATCH(MID(F17,FIND(".",F17)+1,LEN(F17)-FIND(".",F17)+1),'Not Req'!$D$4:$D$72,0))} -> Internal (Not Req) | E17: =INDEX('Not Req'!$F$4:$F$72,MATCH(MID(F17,FIND(".",F17)+1,LEN(F17)-FIND(".",F17)+1),'Not Req'!$D$4:$D$72,0)) -> Internal (Not Req) | F17: zbs_demo_company_names.srvd.xml | G17: Unmanaged (Remote) | H17: 3 years ago
C18: =LEFT(F18,FIND(".",F18)-1) -> zbs_r_rapcustomcompanynames | D18: {=INDEX('Not Req'!$E$4:$E$72,MATCH(MID(F18,FIND(".",F18)+1,LEN(F18)-FIND(".",F18)+1),'Not Req'!$D$4:$D$72,0))} -> Internal (Not Req) | E18: =INDEX('Not Req'!$F$4:$F$72,MATCH(MID(F18,FIND(".",F18)+1,LEN(F18)-FIND(".",F18)+1),'Not Req'!$D$4:$D$72,0)) -> Internal (Not Req) | F18: zbs_r_rapcustomcompanynames.ddls.baseinfo | G18: Unmanaged (Remote) | H18: 3 years ago
C19: =LEFT(F19,FIND(".",F19)-1) -> zbs_ui_demo_com_names_o2 | D19: {=INDEX('Not Req'!$E$4:$E$72,MATCH(MID(F19,FIND(".",F19)+1,LEN(F19)-FIND(".",F19)+1),'Not Req'!$D$4:$D$72,0))} -> Internal (Not Req) | E19: =INDEX('Not Req'!$F$4:$F$72,MATCH(MID(F19,FIND(".",F19)+1,LEN(F19)-FIND(".",F19)+1),'Not Req'!$D$4:$D$72,0)) -> Internal (Not Req) | F19: zbs_ui_demo_com_names_o2.srvb.xml | G19: Delta commit | H19: 2 years ago
C20: =LEFT(F20,FIND(".",F20)-1) -> zbs_ui_demo_com_names_o2_iwsg | D20: {=INDEX('Not Req'!$E$4:$E$72,MATCH(MID(F20,FIND(".",F20)+1,LEN(F20)-FIND(".",F20)+1),'Not Req'!$D$4:$D$72,0))} -> Internal (Not Req) | E20: =INDEX('Not Req'!$F$4:$F$72,MATCH(MID(F20,FIND(".",F20)+1,LEN(F20)-FIND(".",F20)+1),'Not Req'!$D$4:$D$72,0)) -> Internal (Not Req) | F20: zbs_ui_demo_com_names_o2_iwsg.sco2.xml | G20: Unmanaged (Remote) | H20: 3 years ago
A21: d | B21: d | C21: =LEFT(F21,FIND(".",F21)-1) -> zbs_ui_demo_com_names_o2_iwsg_ibs | D21: {=INDEX('Not Req'!$E$4:$E$72,MATCH(MID(F21,FIND(".",F21)+1,LEN(F21)-FIND(".",F21)+1),'Not Req'!$D$4:$D$72,0))} -> Internal (Not Req) | E21: =INDEX('Not Req'!$F$4:$F$72,MATCH(MID(F21,FIND(".",F21)+1,LEN(F21)-FIND(".",F21)+1),'Not Req'!$D$4:$D$72,0)) -> Internal (Not Req) | F21: zbs_ui_demo_com_names_o2_iwsg_ibs.sia6.xml | G21: Delta commit | H21: 2 years ago

Sheet Unmanage
B2: d | C2: Object | D2: Type | E2: Category | F2: Github Object | G2: Github Type | H2: Version
B4: 1 | C4: =LEFT(F4,FIND(".",F4)-1) -> package | D4: {=INDEX('Not Req'!$E$4:$E$72,MATCH(MID(F4,FIND(".",F4)+1,LEN(F4)-FIND(".",F4)+1),'Not Req'!$D$4:$D$72,0))} -> Description : Package | E4: =INDEX('Not Req'!$F$4:$F$72,MATCH(MID(F4,FIND(".",F4)+1,LEN(F4)-FIND(".",F4)+1),'Not Req'!$D$4:$D$72,0)) -> 0. Package | F4: package.devc.xml | G4: CDS Pattern | H4: 2 months ago | N4: {=_xlfn.UNIQUE(C4:C34)} -> package
C5: =LEFT(F5,FIND(".",F5)-1) -> zbs_dmo_un_data | D5: {=INDEX('Not Req'!$E$4:$E$72,MATCH(MID(F5,FIND(".",F5)+1,LEN(F5)-FIND(".",F5)+1),'Not Req'!$D$4:$D$72,0))} -> Table | E5: =INDEX('Not Req'!$F$4:$F$72,MATCH(MID(F5,FIND(".",F5)+1,LEN(F5)-FIND(".",F5)+1),'Not Req'!$D$4:$D$72,0)) -> 1. Dictionary | F5: zbs_dmo_un_data.tabl.xml | G5: Unmanaged (local) | H5: 3 years ago | N5: zbs_dmo_un_data
C6: =LEFT(F6,FIND(".",F6)-1) -> zbs_dmo_unmgnd | D6: {=INDEX('Not Req'!$E$4:$E$72,MATCH(MID(F6,FIND(".",F6)+1,LEN(F6)-FIND(".",F6)+1),'Not Req'!$D$4:$D$72,0))} -> Table | E6: =INDEX('Not Req'!$F$4:$F$72,MATCH(MID(F6,FIND(".",F6)+1,LEN(F6)-FIND(".",F6)+1),'Not Req'!$D$4:$D$72,0)) -> 1. Dictionary | F6: zbs_dmo_unmgnd.tabl.xml | G6: Unmanaged (local) | H6: 3 years ago | N6: zbs_dmo_unmgnd
C7: =LEFT(F7,FIND(".",F7)-1) -> zbs_c_dmounmanaged | D7: {=INDEX('Not Req'!$E$4:$E$72,MATCH(MID(F7,FIND(".",F7)+1,LEN(F7)-FIND(".",F7)+1),'Not Req'!$D$4:$D$72,0))} -> BDEF | E7: =INDEX('Not Req'!$F$4:$F$72,MATCH(MID(F7,FIND(".",F7)+1,LEN(F7)-FIND(".",F7)+1),'Not Req'!$D$4:$D$72,0)) -> 2. CDS | F7: zbs_c_dmounmanaged.bdef.asbdef | G7: Unmanaged (local) | H7: 3 years ago | N7: zbs_c_dmounmanaged
C8: =LEFT(F8,FIND(".",F8)-1) -> zbs_c_dmounmanaged | D8: {=INDEX('Not Req'!$E$4:$E$72,MATCH(MID(F8,FIND(".",F8)+1,LEN(F8)-FIND(".",F8)+1),'Not Req'!$D$4:$D$72,0))} -> Description : BDEF | E8: =INDEX('Not Req'!$F$4:$F$72,MATCH(MID(F8,FIND(".",F8)+1,LEN(F8)-FIND(".",F8)+1),'Not Req'!$D$4:$D$72,0)) -> 2. CDS | F8: zbs_c_dmounmanaged.bdef.xml | G8: Delta commit | H8: 3 years ago | N8: zbs_r_dmounmanaged
C9: =LEFT(F9,FIND(".",F9)-1) -> zbs_c_dmounmanaged | D9: {=INDEX('Not Req'!$E$4:$E$72,MATCH(MID(F9,FIND(".",F9)+1,LEN(F9)-FIND(".",F9)+1),'Not Req'!$D$4:$D$72,0))} -> Data Definition | E9: =INDEX('Not Req'!$F$4:$F$72,MATCH(MID(F9,FIND(".",F9)+1,LEN(F9)-FIND(".",F9)+1),'Not Req'!$D$4:$D$72,0)) -> 2. CDS | F9: zbs_c_dmounmanaged.ddls.asddls | G9: Unmanaged (local) | H9: 3 years ago | N9: zbp_bs_demo_unmanaged
C10: =LEFT(F10,FIND(".",F10)-1) -> zbs_c_dmounmanaged | D10: {=INDEX('Not Req'!$E$4:$E$72,MATCH(MID(F10,FIND(".",F10)+1,LEN(F10)-FIND(".",F10)+1),'Not Req'!$D$4:$D$72,0))} -> Description : Data Definition | E10: =INDEX('Not Req'!$F$4:$F$72,MATCH(MID(F10,FIND(".",F10)+1,LEN(F10)-FIND(".",F10)+1),'Not Req'!$D$4:$D$72,0)) -> 2. CDS | F10: zbs_c_dmounmanaged.ddls.xml | G10: Unmanaged (local) | H10: 3 years ago | N10: zcl_bs_demo_rap_data_handler
C11: =LEFT(F11,FIND(".",F11)-1) -> zbs_r_dmounmanaged | D11: {=INDEX('Not Req'!$E$4:$E$72,MATCH(MID(F11,FIND(".",F11)+1,LEN(F11)-FIND(".",F11)+1),'Not Req'!$D$4:$D$72,0))} -> BDEF | E11: =INDEX('Not Req'!$F$4:$F$72,MATCH(MID(F11,FIND(".",F11)+1,LEN(F11)-FIND(".",F11)+1),'Not Req'!$D$4:$D$72,0)) -> 2. CDS | F11: zbs_r_dmounmanaged.bdef.asbdef | G11: Unmanaged (local) | H11: 3 years ago | N11: zcl_bs_demo_unmanaged_data
C12: =LEFT(F12,FIND(".",F12)-1) -> zbs_r_dmounmanaged | D12: {=INDEX('Not Req'!$E$4:$E$72,MATCH(MID(F12,FIND(".",F12)+1,LEN(F12)-FIND(".",F12)+1),'Not Req'!$D$4:$D$72,0))} -> Description : BDEF | E12: =INDEX('Not Req'!$F$4:$F$72,MATCH(MID(F12,FIND(".",F12)+1,LEN(F12)-FIND(".",F12)+1),'Not Req'!$D$4:$D$72,0)) -> 2. CDS | F12: zbs_r_dmounmanaged.bdef.xml | G12: Delta commit | H12: 3 years ago | N12: zcl_bs_demo_unmanaged_query
C13: =LEFT(F13,FIND(".",F13)-1) -> zbs_r_dmounmanaged | D13: {=INDEX('Not Req'!$E$4:$E$72,MATCH(MID(F13,FIND(".",F13)+1,LEN(F13)-FIND(".",F13)+1),'Not Req'!$D$4:$D$72,0))} -> Data Definition | E13: =INDEX('Not Req'!$F$4:$F$72,MATCH(MID(F13,FIND(".",F13)+1,LEN(F13)-FIND(".",F13)+1),'Not Req'!$D$4:$D$72,0)) -> 2. CDS | F13: zbs_r_dmounmanaged.ddls.asddls | G13: Unmanaged (local) | H13: 3 years ago | N13: zif_bs_demo_rap_data_handler
C14: =LEFT(F14,FIND(".",F14)-1) -> zbs_r_dmounmanaged | D14: {=INDEX('Not Req'!$E$4:$E$72,MATCH(MID(F14,FIND(".",F14)+1,LEN(F14)-FIND(".",F14)+1),'Not Req'!$D$4:$D$72,0))} -> Description : Data Definition | E14: =INDEX('Not Req'!$F$4:$F$72,MATCH(MID(F14,FIND(".",F14)+1,LEN(F14)-FIND(".",F14)+1),'Not Req'!$D$4:$D$72,0)) -> 2. CDS | F14: zbs_r_dmounmanaged.ddls.xml | G14: Unmanaged (local) | H14: 3 years ago | N14: zbs_demo_unmanaged
C15: =LEFT(F15,FIND(".",F15)-1) -> zbp_bs_demo_unmanaged | D15: {=INDEX('Not Req'!$E$4:$E$72,MATCH(MID(F15,FIND(".",F15)+1,LEN(F15)-FIND(".",F15)+1),'Not Req'!$D$4:$D$72,0))} -> Classes | E15: =INDEX('Not Req'!$F$4:$F$72,MATCH(MID(F15,FIND(".",F15)+1,LEN(F15)-FIND(".",F15)+1),'Not Req'!$D$4:$D$72,0)) -> 3. Source Code Library | F15: zbp_bs_demo_unmanaged.clas.abap | G15: Delta commit | H15: 3 years ago | N15: 1da9f98f6e9398d184f663fb1abf78ht
C16: =LEFT(F16,FIND(".",F16)-1) -> zbp_bs_demo_unmanaged | D16: {=INDEX('Not Req'!$E$4:$E$72,MATCH(MID(F16,FIND(".",F16)+1,LEN(F16)-FIND(".",F16)+1),'Not Req'!$D$4:$D$72,0))} -> Classes Local | E16: =INDEX('Not Req'!$F$4:$F$72,MATCH(MID(F16,FIND(".",F16)+1,LEN(F16)-FIND(".",F16)+1),'Not Req'!$D$4:$D$72,0)) -> 3. Source Code Library | F16: zbp_bs_demo_unmanaged.clas.locals_imp.abap | G16: Unmanaged (local) | H16: 3 years ago | N16: eaa71198fe52a32744287311694cbbht
... C19: =LEFT(F19,FIND(".",F19)-1) -> zcl_bs_demo_rap_data_handler | D19: {=INDEX('Not Req'!$E$4:$E$72,MATCH(MID(F19,FIND(".",F19)+1,LEN(F19)-FIND(".",F19)+1),'Not Req'!$D$4:$D$72,0))} -> Description : Classes | E19: =INDEX('Not Req'!$F$4:$F$72,MATCH(MID(F19,FIND(".",F19)+1,LEN(F19)-FIND(".",F19)+1),'Not Req'!$D$4:$D$72,0)) -> 3. Source Code Library | F19: zcl_bs_demo_rap_data_handler.clas.xml | G19: Unmanaged (local) | H19: 3 years ago | N19: zbs_ui_demo_unmanaged_o2_iwsg_ibs
C20: =LEFT(F20,FIND(".",F20)-1) -> zcl_bs_demo_unmanaged_data | D20: {=INDEX('Not Req'!$E$4:$E$72,MATCH(MID(F20,FIND(".",F20)+1,LEN(F20)-FIND(".",F20)+1),'Not Req'!$D$4:$D$72,0))} -> Classes | E20: =INDEX('Not Req'!$F$4:$F$72,MATCH(MID(F20,FIND(".",F20)+1,LEN(F20)-FIND(".",F20)+1),'Not Req'!$D$4:$D$72,0)) -> 3. Source Code Library | F20: zcl_bs_demo_unmanaged_data.clas.abap | G20: Delta commit | H20: 3 years ago
C21: =LEFT(F21,FIND(".",F21)-1) -> zcl_bs_demo_unmanaged_data | D21: {=INDEX('Not Req'!$E$4:$E$72,MATCH(MID(F21,FIND(".",F21)+1,LEN(F21)-FIND(".",F21)+1),'Not Req'!$D$4:$D$72,0))} -> Description : Classes | E21: =INDEX('Not Req'!$F$4:$F$72,MATCH(MID(F21,FIND(".",F21)+1,LEN(F21)-FIND(".",F21)+1),'Not Req'!$D$4:$D$72,0)) -> 3. Source Code Library | F21: zcl_bs_demo_unmanaged_data.clas.xml | G21: Unmanaged (local) | H21: 3 years ago
C22: =LEFT(F22,FIND(".",F22)-1) -> zcl_bs_demo_unmanaged_query | D22: {=INDEX('Not Req'!$E$4:$E$72,MATCH(MID(F22,FIND(".",F22)+1,LEN(F22)-FIND(".",F22)+1),'Not Req'!$D$4:$D$72,0))} -> Classes | E22: =INDEX('Not Req'!$F$4:$F$72,MATCH(MID(F22,FIND(".",F22)+1,LEN(F22)-FIND(".",F22)+1),'Not Req'!$D$4:$D$72,0)) -> 3. Source Code Library | F22: zcl_bs_demo_unmanaged_query.clas.abap | G22: Delta commit | H22: 2 years ago
C23: =LEFT(F23,FIND(".",F23)-1) -> zcl_bs_demo_unmanaged_query | D23: {=INDEX('Not Req'!$E$4:$E$72,MATCH(MID(F23,FIND(".",F23)+1,LEN(F23)-FIND(".",F23)+1),'Not Req'!$D$4:$D$72,0))} -> Description : Classes | E23: =INDEX('Not Req'!$F$4:$F$72,MATCH(MID(F23,FIND(".",F23)+1,LEN(F23)-FIND(".",F23)+1),'Not Req'!$D$4:$D$72,0)) -> 3. Source Code Library | F23: zcl_bs_demo_unmanaged_query.clas.xml | G23: Unmanaged (local) | H23: 3 years ago
C24: =LEFT(F24,FIND(".",F24)-1) -> zif_bs_demo_rap_data_handler | D24: {=INDEX('Not Req'!$E$4:$E$72,MATCH(MID(F24,FIND(".",F24)+1,LEN(F24)-FIND(".",F24)+1),'Not Req'!$D$4:$D$72,0))} -> Interface | E24: =INDEX('Not Req'!$F$4:$F$72,MATCH(MID(F24,FIND(".",F24)+1,LEN(F24)-FIND(".",F24)+1),'Not Req'!$D$4:$D$72,0)) -> 3. Source Code Library | F24: zif_bs_demo_rap_data_handler.intf.abap | G24: Unmanaged (local) | H24: 3 years ago
A25: d | B25: d | C25: =LEFT(F25,FIND(".",F25)-1) -> zif_bs_demo_rap_data_handler | D25: {=INDEX('Not Req'!$E$4:$E$72,MATCH(MID(F25,FIND(".",F25)+1,LEN(F25)-FIND(".",F25)+1),'Not Req'!$D$4:$D$72,0))} -> Description : Interface | E25: =INDEX('Not Req'!$F$4:$F$72,MATCH(MID(F25,FIND(".",F25)+1,LEN(F25)-FIND(".",F25)+1),'Not Req'!$D$4:$D$72,0)) -> 3. Source Code Library | F25: zif_bs_demo_rap_data_handler.intf.xml | G25: Unmanaged (local) | H25: 3 years ago
C26: =LEFT(F26,FIND(".",F26)-1) -> zbs_demo_unmanaged | D26: {=INDEX('Not Req'!$E$4:$E$72,MATCH(MID(F26,FIND(".",F26)+1,LEN(F26)-FIND(".",F26)+1),'Not Req'!$D$4:$D$72,0))} -> Service Definition | E26: =INDEX('Not Req'!$F$4:$F$72,MATCH(MID(F26,FIND(".",F26)+1,LEN(F26)-FIND(".",F26)+1),'Not Req'!$D$4:$D$72,0)) -> Business Services | F26: zbs_demo_unmanaged.srvd.srvdsrv | G26: Unmanaged (local) | H26: 3 years ago
C27: =LEFT(F27,FIND(".",F27)-1) -> 1da9f98f6e9398d184f663fb1abf78ht | D27: {=INDEX('Not Req'!$E$4:$E$72,MATCH(MID(F27,FIND(".",F27)+1,LEN(F27)-FIND(".",F27)+1),'Not Req'!$D$4:$D$72,0))} -> Internal (Not Req) | E27: =INDEX('Not Req'!$F$4:$F$72,MATCH(MID(F27,FIND(".",F27)+1,LEN(F27)-FIND(".",F27)+1),'Not Req'!$D$4:$D$72,0)) -> Internal (Not Req) | F27: 1da9f98f6e9398d184f663fb1abf78ht.sush.xml | G27: Unmanaged (local) | H27: 3 years ago
A28: d | C28: =LEFT(F28,FIND(".",F28)-1) -> eaa71198fe52a32744287311694cbbht | D28: {=INDEX('Not Req'!$E$4:$E$72,MATCH(MID(F28,FIND(".",F28)+1,LEN(F28)-FIND(".",F28)+1),'Not Req'!$D$4:$D$72,0))} -> Internal (Not Req) | E28: =INDEX('Not Req'!$F$4:$F$72,MATCH(MID(F28,FIND(".",F28)+1,LEN(F28)-FIND(".",F28)+1),'Not Req'!$D$4:$D$72,0)) -> Internal (Not Req) | F28: eaa71198fe52a32744287311694cbbht.sush.xml | G28: Unmanaged (local) | H28: 3 years ago
C29: =LEFT(F29,FIND(".",F29)-1) -> zbs_c_dmounmanaged | D29: {=INDEX('Not Req'!$E$4:$E$72,MATCH(MID(F29,FIND(".",F29)+1,LEN(F29)-FIND(".",F29)+1),'Not Req'!$D$4:$D$72,0))} -> Internal (Not Req) | E29: =INDEX('Not Req'!$F$4:$F$72,MATCH(MID(F29,FIND(".",F29)+1,LEN(F29)-FIND(".",F29)+1),'Not Req'!$D$4:$D$72,0)) -> Internal (Not Req) | F29: zbs_c_dmounmanaged.ddls.baseinfo | G29: Unmanaged (local) | H29: 3 years ago
C30: =LEFT(F30,FIND(".",F30)-1) -> zbs_demo_unmanaged | D30: {=INDEX('Not Req'!$E$4:$E$72,MATCH(MID(F30,FIND(".",F30)+1,LEN(F30)-FIND(".",F30)+1),'Not Req'!$D$4:$D$72,0))} -> Internal (Not Req) | E30: =INDEX('Not Req'!$F$4:$F$72,MATCH(MID(F30,FIND(".",F30)+1,LEN(F30)-FIND(".",F30)+1),'Not Req'!$D$4:$D$72,0)) -> Internal (Not Req) | F30: zbs_demo_unmanaged.srvd.xml | G30: Unmanaged (local) | H30: 3 years ago
C31: =LEFT(F31,FIND(".",F31)-1) -> zbs_r_dmounmanaged | D31: {=INDEX('Not Req'!$E$4:$E$72,MATCH(MID(F31,FIND(".",F31)+1,LEN(F31)-FIND(".",F31)+1),'Not Req'!$D$4:$D$72,0))} -> Internal (Not Req) | E31: =INDEX('Not Req'!$F$4:$F$72,MATCH(MID(F31,FIND(".",F31)+1,LEN(F31)-FIND(".",F31)+1),'Not Req'!$D$4:$D$72,0)) -> Internal (Not Req) | F31: zbs_r_dmounmanaged.ddls.baseinfo | G31: Unmanaged (local) | H31: 3 years ago
C32: =LEFT(F32,FIND(".",F32)-1) -> zbs_ui_demo_unmanaged_o2 | D32: {=INDEX('Not Req'!$E$4:$E$72,MATCH(MID(F32,FIND(".",F32)+1,LEN(F32)-FIND(".",F32)+1),'Not Req'!$D$4:$D$72,0))} -> Internal (Not Req) | E32: =INDEX('Not Req'!$F$4:$F$72,MATCH(MID(F32,FIND(".",F32)+1,LEN(F32)-FIND(".",F32)+1),'Not Req'!$D$4:$D$72,0)) -> Internal (Not Req) | F32: zbs_ui_demo_unmanaged_o2.srvb.xml | G32: Delta commit | H32: 2 years ago
C33: =LEFT(F33,FIND(".",F33)-1) -> zbs_ui_demo_unmanaged_o2_iwsg | D33: {=INDEX('Not Req'!$E$4:$E$72,MATCH(MID(F33,FIND(".",F33)+1,LEN(F33)-FIND(".",F33)+1),'Not Req'!$D$4:$D$72,0))} -> Internal (Not Req) | E33: =INDEX('Not Req'!$F$4:$F$72,MATCH(MID(F33,FIND(".",F33)+1,LEN(F33)-FIND(".",F33)+1),'Not Req'!$D$4:$D$72,0)) -> Internal (Not Req) | F33: zbs_ui_demo_unmanaged_o2_iwsg.sco2.xml | G33: Unmanaged (local) | H33: 3 years ago
C34: =LEFT(F34,FIND(".",F34)-1) -> zbs_ui_demo_unmanaged_o2_iwsg_ibs | D34: {=INDEX('Not Req'!$E$4:$E$72,MATCH(MID(F34,FIND(".",F34)+1,LEN(F34)-FIND(".",F34)+1),'Not Req'!$D$4:$D$72,0))} -> Internal (Not Req) | E34: =INDEX('Not Req'!$F$4:$F$72,MATCH(MID(F34,FIND(".",F34)+1,LEN(F34)-FIND(".",F34)+1),'Not Req'!$D$4:$D$72,0)) -> Internal (Not Req) | F34: zbs_ui_demo_unmanaged_o2_iwsg_ibs.sia6.xml | G34: Delta commit | H34: 2 years ago

Sheet Simple
B2: d | C2: Object | D2: Type | E2: Category | F2: Github Object | G2: Github Type | H2: Version
C4: =LEFT(F4,FIND(".",F4)-1) -> package | D4: {=INDEX('Not Req'!$E$4:$E$72,MATCH(MID(F4,FIND(".",F4)+1,LEN(F4)-FIND(".",F4)+1),'Not Req'!$D$4:$D$72,0))} -> Description : Package | E4: =INDEX('Not Req'!$F$4:$F$72,MATCH(MID(F4,FIND(".",F4)+1,LEN(F4)-FIND(".",F4)+1),'Not Req'!$D$4:$D$72,0)) -> 0. Package | F4: package.devc.xml | G4: CDS Pattern | H4: 2 months ago | N4: {=_xlfn.UNIQUE(C4:C65)} -> package
A5: d | C5: =LEFT(F5,FIND(".",F5)-1) -> zbs_dmo_dpartner | D5: {=INDEX('Not Req'!$E$4:$E$72,MATCH(MID(F5,FIND(".",F5)+1,LEN(F5)-FIND(".",F5)+1),'Not Req'!$D$4:$D$72,0))} -> Table | E5: =INDEX('Not Req'!$F$4:$F$72,MATCH(MID(F5,FIND(".",F5)+1,LEN(F5)-FIND(".",F5)+1),'Not Req'!$D$4:$D$72,0)) -> 1. Dictionary | F5: zbs_dmo_dpartner.tabl.xml | G5: Delta commit | H5: 3 years ago | N5: zbs_dmo_dpartner
B6: 1 | C6: =LEFT(F6,FIND(".",F6)-1) -> zbs_c_rappartner | D6: {=INDEX('Not Req'!$E$4:$E$72,MATCH(MID(F6,FIND(".",F6)+1,LEN(F6)-FIND(".",F6)+1),'Not Req'!$D$4:$D$72,0))} -> BDEF | E6: =INDEX('Not Req'!$F$4:$F$72,MATCH(MID(F6,FIND(".",F6)+1,LEN(F6)-FIND(".",F6)+1),'Not Req'!$D$4:$D$72,0)) -> 2. CDS | F6: zbs_c_rappartner.bdef.asbdef | G6: Draft Handling | H6: 4 years ago | N6: zbs_c_rappartner
C7: =LEFT(F7,FIND(".",F7)-1) -> zbs_i_rappartner | D7: {=INDEX('Not Req'!$E$4:$E$72,MATCH(MID(F7,FIND(".",F7)+1,LEN(F7)-FIND(".",F7)+1),'Not Req'!$D$4:$D$72,0))} -> BDEF | E7: =INDEX('Not Req'!$F$4:$F$72,MATCH(MID(F7,FIND(".",F7)+1,LEN(F7)-FIND(".",F7)+1),'Not Req'!$D$4:$D$72,0)) -> 2. CDS | F7: zbs_i_rappartner.bdef.asbdef | G7: Draft part 2 | H7: 4 years ago | N7: zbs_i_rappartner
C8: =LEFT(F8,FIND(".",F8)-1) -> zbs_c_rappartner | D8: {=INDEX('Not Req'!$E$4:$E$72,MATCH(MID(F8,FIND(".",F8)+1,LEN(F8)-FIND(".",F8)+1),'Not Req'!$D$4:$D$72,0))} -> Description : BDEF | E8: =INDEX('Not Req'!$F$4:$F$72,MATCH(MID(F8,FIND(".",F8)+1,LEN(F8)-FIND(".",F8)+1),'Not Req'!$D$4:$D$72,0)) -> 2. CDS | F8: zbs_c_rappartner.bdef.xml | G8: Delta commit | H8: 3 years ago | N8: zbs_c_countryvh
C9: =LEFT(F9,FIND(".",F9)-1) -> zbs_i_rappartner | D9: {=INDEX('Not Req'!$E$4:$E$72,MATCH(MID(F9,FIND(".",F9)+1,LEN(F9)-FIND(".",F9)+1),'Not Req'!$D$4:$D$72,0))} -> Description : BDEF | E9: =INDEX('Not Req'!$F$4:$F$72,MATCH(MID(F9,FIND(".",F9)+1,LEN(F9)-FIND(".",F9)+1),'Not Req'!$D$4:$D$72,0)) -> 2. CDS | F9: zbs_i_rappartner.bdef.xml | G9: Delta commit | H9: 3 years ago | N9: zbs_i_popupentity
C10: =LEFT(F10,FIND(".",F10)-1) -> zbs_c_countryvh | D10: {=INDEX('Not Req'!$E$4:$E$72,MATCH(MID(F10,FIND(".",F10)+1,LEN(F10)-FIND(".",F10)+1),'Not Req'!$D$4:$D$72,0))} -> Data Definition | E10: =INDEX('Not Req'!$F$4:$F$72,MATCH(MID(F10,FIND(".",F10)+1,LEN(F10)-FIND(".",F10)+1),'Not Req'!$D$4:$D$72,0)) -> 2. CDS | F10: zbs_c_countryvh.ddls.asddls | G10: Search help | H10: 4 years ago | N10: zbs_i_rapcityvh
C11: =LEFT(F11,FIND(".",F11)-1) -> zbs_c_rappartner | D11: {=INDEX('Not Req'!$E$4:$E$72,MATCH(MID(F11,FIND(".",F11)+1,LEN(F11)-FIND(".",F11)+1),'Not Req'!$D$4:$D$72,0))} -> Data Definition | E11: =INDEX('Not Req'!$F$4:$F$72,MATCH(MID(F11,FIND(".",F11)+1,LEN(F11)-FIND(".",F11)+1),'Not Req'!$D$4:$D$72,0)) -> 2. CDS | F11: zbs_c_rappartner.ddls.asddls | G11: Custom Entity Value Help (Deep Dive) | H11: 2 years ago | N11: zbs_i_rapcustomentitycnames
C12: =LEFT(F12,FIND(".",F12)-1) -> zbs_i_popupentity | D12: {=INDEX('Not Req'!$E$4:$E$72,MATCH(MID(F12,FIND(".",F12)+1,LEN(F12)-FIND(".",F12)+1),'Not Req'!$D$4:$D$72,0))} -> Data Definition | E12: =INDEX('Not Req'!$F$4:$F$72,MATCH(MID(F12,FIND(".",F12)+1,LEN(F12)-FIND(".",F12)+1),'Not Req'!$D$4:$D$72,0)) -> 2. CDS | F12: zbs_i_popupentity.ddls.asddls | G12: Popup | H12: 4 years ago | N12: zbp_bs_demo_rappartner
C13: =LEFT(F13,FIND(".",F13)-1) -> zbs_i_rapcityvh | D13: {=INDEX('Not Req'!$E$4:$E$72,MATCH(MID(F13,FIND(".",F13)+1,LEN(F13)-FIND(".",F13)+1),'Not Req'!$D$4:$D$72,0))} -> Data Definition | E13: =INDEX('Not Req'!$F$4:$F$72,MATCH(MID(F13,FIND(".",F13)+1,LEN(F13)-FIND(".",F13)+1),'Not Req'!$D$4:$D$72,0)) -> 2. CDS | F13: zbs_i_rapcityvh.ddls.asddls | G13: Custom Entity Value Help (Deep Dive) | H13: 2 years ago | N13: zcl_bs_demo_action_eml
C14: =LEFT(F14,FIND(".",F14)-1) -> zbs_i_rapcustomentitycnames | D14: {=INDEX('Not Req'!$E$4:$E$72,MATCH(MID(F14,FIND(".",F14)+1,LEN(F14)-FIND(".",F14)+1),'Not Req'!$D$4:$D$72,0))} -> Data Definition | E14: =INDEX('Not Req'!$F$4:$F$72,MATCH(MID(F14,FIND(".",F14)+1,LEN(F14)-FIND(".",F14)+1),'Not Req'!$D$4:$D$72,0)) -> 2. CDS | F14: zbs_i_rapcustomentitycnames.ddls.asddls | G14: Custom entity | H14: 3 years ago | N14: zcl_bs_demo_adjust_data
C15: =LEFT(F15,FIND(".",F15)-1) -> zbs_i_rappartner | D15: {=INDEX('Not Req'!$E$4:$E$72,MATCH(MID(F15,FIND(".",F15)+1,LEN(F15)-FIND(".",F15)+1),'Not Req'!$D$4:$D$72,0))} -> Data Definition | E15: =INDEX('Not Req'!$F$4:$F$72,MATCH(MID(F15,FIND(".",F15)+1,LEN(F15)-FIND(".",F15)+1),'Not Req'!$D$4:$D$72,0)) -> 2. CDS | F15: zbs_i_rappartner.ddls.asddls | G15: Draft part 2 | H15: 4 years ago | N15: zcl_bs_demo_city_query
C16: =LEFT(F16,FIND(".",F16)-1) -> zbs_c_countryvh | D16: {=INDEX('Not Req'!$E$4:$E$72,MATCH(MID(F16,FIND(".",F16)+1,LEN(F16)-FIND(".",F16)+1),'Not Req'!$D$4:$D$72,0))} -> Description : Data Definition | E16: =INDEX('Not Req'!$F$4:$F$72,MATCH(MID(F16,FIND(".",F16)+1,LEN(F16)-FIND(".",F16)+1),'Not Req'!$D$4:$D$72,0)) -> 2. CDS | F16: zbs_c_countryvh.ddls.xml | G16: Search help | H16: 4 years ago | N16: zcl_bs_demo_cust_cname_query
C17: =LEFT(F17,FIND(".",F17)-1) -> zbs_c_rappartner | D17: {=INDEX('Not Req'!$E$4:$E$72,MATCH(MID(F17,FIND(".",F17)+1,LEN(F17)-FIND(".",F17)+1),'Not Req'!$D$4:$D$72,0))} -> Description : Data Definition | E17: =INDEX('Not Req'!$F$4:$F$72,MATCH(MID(F17,FIND(".",F17)+1,LEN(F17)-FIND(".",F17)+1),'Not Req'!$D$4:$D$72,0)) -> 2. CDS | F17: zbs_c_rappartner.ddls.xml | G17: Projection & Refactoring | H17: 4 years ago | N17: zcl_bs_demo_simple_eml
C18: =LEFT(F18,FIND(".",F18)-1) -> zbs_i_popupentity | D18: {=INDEX('Not Req'!$E$4:$E$72,MATCH(MID(F18,FIND(".",F18)+1,LEN(F18)-FIND(".",F18)+1),'Not Req'!$D$4:$D$72,0))} -> Description : Data Definition | E18: =INDEX('Not Req'!$F$4:$F$72,MATCH(MID(F18,FIND(".",F18)+1,LEN(F18)-FIND(".",F18)+1),'Not Req'!$D$4:$D$72,0)) -> 2. CDS | F18: zbs_i_popupentity.ddls.xml | G18: Popup | H18: 4 years ago | N18: zcl_bs_demo_unit_cleanup
... C34: =LEFT(F34,FIND(".",F34)-1) -> zcl_bs_demo_unit_service | D34: {=INDEX('Not Req'!$E$4:$E$72,MATCH(MID(F34,FIND(".",F34)+1,LEN(F34)-FIND(".",F34)+1),'Not Req'!$D$4:$D$72,0))} -> Classes | E34: =INDEX('Not Req'!$F$4:$F$72,MATCH(MID(F34,FIND(".",F34)+1,LEN(F34)-FIND(".",F34)+1),'Not Req'!$D$4:$D$72,0)) -> 3. Source Code Library | F34: zcl_bs_demo_unit_service.clas.abap | G34: Delta commit | H34: 2 years ago | N34: 96d1f20bc73790aea2637d1fa4b291ht
C35: =LEFT(F35,FIND(".",F35)-1) -> zbp_bs_demo_rappartner | D35: {=INDEX('Not Req'!$E$4:$E$72,MATCH(MID(F35,FIND(".",F35)+1,LEN(F35)-FIND(".",F35)+1),'Not Req'!$D$4:$D$72,0))} -> Classes Local | E35: =INDEX('Not Req'!$F$4:$F$72,MATCH(MID(F35,FIND(".",F35)+1,LEN(F35)-FIND(".",F35)+1),'Not Req'!$D$4:$D$72,0)) -> 3. Source Code Library | F35: zbp_bs_demo_rappartner.clas.locals_imp.abap | G35: Delta | H35: 2 years ago
C36: =LEFT(F36,FIND(".",F36)-1) -> zbp_bs_demo_rappartner | D36: {=INDEX('Not Req'!$E$4:$E$72,MATCH(MID(F36,FIND(".",F36)+1,LEN(F36)-FIND(".",F36)+1),'Not Req'!$D$4:$D$72,0))} -> Description : Classes | E36: =INDEX('Not Req'!$F$4:$F$72,MATCH(MID(F36,FIND(".",F36)+1,LEN(F36)-FIND(".",F36)+1),'Not Req'!$D$4:$D$72,0)) -> 3. Source Code Library | F36: zbp_bs_demo_rappartner.clas.xml | G36: Simple object | H36: 4 years ago
C37: =LEFT(F37,FIND(".",F37)-1) -> zcl_bs_demo_action_eml | D37: {=INDEX('Not Req'!$E$4:$E$72,MATCH(MID(F37,FIND(".",F37)+1,LEN(F37)-FIND(".",F37)+1),'Not Req'!$D$4:$D$72,0))} -> Description : Classes | E37: =INDEX('Not Req'!$F$4:$F$72,MATCH(MID(F37,FIND(".",F37)+1,LEN(F37)-FIND(".",F37)+1),'Not Req'!$D$4:$D$72,0)) -> 3. Source Code Library | F37: zcl_bs_demo_action_eml.clas.xml | G37: Action (Part 2) | H37: 4 years ago
C38: =LEFT(F38,FIND(".",F38)-1) -> zcl_bs_demo_adjust_data | D38: {=INDEX('Not Req'!$E$4:$E$72,MATCH(MID(F38,FIND(".",F38)+1,LEN(F38)-FIND(".",F38)+1),'Not Req'!$D$4:$D$72,0))} -> Description : Classes | E38: =INDEX('Not Req'!$F$4:$F$72,MATCH(MID(F38,FIND(".",F38)+1,LEN(F38)-FIND(".",F38)+1),'Not Req'!$D$4:$D$72,0)) -> 3. Source Code Library | F38: zcl_bs_demo_adjust_data.clas.xml | G38: Custom Entity Value Help (Deep Dive) | H38: 2 years ago
C39: =LEFT(F39,FIND(".",F39)-1) -> zcl_bs_demo_city_query | D39: {=INDEX('Not Req'!$E$4:$E$72,MATCH(MID(F39,FIND(".",F39)+1,LEN(F39)-FIND(".",F39)+1),'Not Req'!$D$4:$D$72,0))} -> Description : Classes | E39: =INDEX('Not Req'!$F$4:$F$72,MATCH(MID(F39,FIND(".",F39)+1,LEN(F39)-FIND(".",F39)+1),'Not Req'!$D$4:$D$72,0)) -> 3. Source Code Library | F39: zcl_bs_demo_city_query.clas.xml | G39: Custom Entity Value Help (Deep Dive) | H39: 2 years ago
C40: =LEFT(F40,FIND(".",F40)-1) -> zcl_bs_demo_cust_cname_query | D40: {=INDEX('Not Req'!$E$4:$E$72,MATCH(MID(F40,FIND(".",F40)+1,LEN(F40)-FIND(".",F40)+1),'Not Req'!$D$4:$D$72,0))} -> Description : Classes | E40: =INDEX('Not Req'!$F$4:$F$72,MATCH(MID(F40,FIND(".",F40)+1,LEN(F40)-FIND(".",F40)+1),'Not Req'!$D$4:$D$72,0)) -> 3. Source Code Library | F40: zcl_bs_demo_cust_cname_query.clas.xml | G40: Custom entity | H40: 3 years ago
C41: =LEFT(F41,FIND(".",F41)-1) -> zcl_bs_demo_simple_eml | D41: {=INDEX('Not Req'!$E$4:$E$72,MATCH(MID(F41,FIND(".",F41)+1,LEN(F41)-FIND(".",F41)+1),'Not Req'!$D$4:$D$72,0))} -> Description : Classes | E41: =INDEX('Not Req'!$F$4:$F$72,MATCH(MID(F41,FIND(".",F41)+1,LEN(F41)-FIND(".",F41)+1),'Not Req'!$D$4:$D$72,0)) -> 3. Source Code Library | F41: zcl_bs_demo_simple_eml.clas.xml | G41: EML | H41: 4 years ago
C42: =LEFT(F42,FIND(".",F42)-1) -> zcl_bs_demo_unit_cleanup | D42: {=INDEX('Not Req'!$E$4:$E$72,MATCH(MID(F42,FIND(".",F42)+1,LEN(F42)-FIND(".",F42)+1),'Not Req'!$D$4:$D$72,0))} -> Description : Classes | E42: =INDEX('Not Req'!$F$4:$F$72,MATCH(MID(F42,FIND(".",F42)+1,LEN(F42)-FIND(".",F42)+1),'Not Req'!$D$4:$D$72,0)) -> 3. Source Code Library | F42: zcl_bs_demo_unit_cleanup.clas.xml | G42: ABAP Unit - RAP Object | H42: 4 years ago
C43: =LEFT(F43,FIND(".",F43)-1) -> zcl_bs_demo_unit_rap | D43: {=INDEX('Not Req'!$E$4:$E$72,MATCH(MID(F43,FIND(".",F43)+1,LEN(F43)-FIND(".",F43)+1),'Not Req'!$D$4:$D$72,0))} -> Description : Classes | E43: =INDEX('Not Req'!$F$4:$F$72,MATCH(MID(F43,FIND(".",F43)+1,LEN(F43)-FIND(".",F43)+1),'Not Req'!$D$4:$D$72,0)) -> 3. Source Code Library | F43: zcl_bs_demo_unit_rap.clas.xml | G43: ABAP Unit - RAP Object | H43: 4 years ago
C44: =LEFT(F44,FIND(".",F44)-1) -> zcl_bs_demo_unit_service | D44: {=INDEX('Not Req'!$E$4:$E$72,MATCH(MID(F44,FIND(".",F44)+1,LEN(F44)-FIND(".",F44)+1),'Not Req'!$D$4:$D$72,0))} -> Description : Classes | E44: =INDEX('Not Req'!$F$4:$F$72,MATCH(MID(F44,FIND(".",F44)+1,LEN(F44)-FIND(".",F44)+1),'Not Req'!$D$4:$D$72,0)) -> 3. Source Code Library | F44: zcl_bs_demo_unit_service.clas.xml | G44: ABAP Unit - Service | H44: 4 years ago
C45: =LEFT(F45,FIND(".",F45)-1) -> zbs_simple_partner | D45: {=INDEX('Not Req'!$E$4:$E$72,MATCH(MID(F45,FIND(".",F45)+1,LEN(F45)-FIND(".",F45)+1),'Not Req'!$D$4:$D$72,0))} -> Service Definition | E45: =INDEX('Not Req'!$F$4:$F$72,MATCH(MID(F45,FIND(".",F45)+1,LEN(F45)-FIND(".",F45)+1),'Not Req'!$D$4:$D$72,0)) -> Business Services | F45: zbs_simple_partner.srvd.srvdsrv | G45: Tile Service 2 | H45: 2 months ago
C46: =LEFT(F46,FIND(".",F46)-1) -> zbs_c_countryvh | D46: {=INDEX('Not Req'!$E$4:$E$72,MATCH(MID(F46,FIND(".",F46)+1,LEN(F46)-FIND(".",F46)+1),'Not Req'!$D$4:$D$72,0))} -> Internal (Not Req) | E46: =INDEX('Not Req'!$F$4:$F$72,MATCH(MID(F46,FIND(".",F46)+1,LEN(F46)-FIND(".",F46)+1),'Not Req'!$D$4:$D$72,0)) -> Internal (Not Req) | F46: zbs_c_countryvh.ddls.baseinfo | G46: Search help | H46: 4 years ago
... C64: =LEFT(F64,FIND(".",F64)-1) -> 7773ee760dc26046c3c86bac521a4aht | D64: {=INDEX('Not Req'!$E$4:$E$72,MATCH(MID(F64,FIND(".",F64)+1,LEN(F64)-FIND(".",F64)+1),'Not Req'!$D$4:$D$72,0))} -> Internal (Not Req) | E64: =INDEX('Not Req'!$F$4:$F$72,MATCH(MID(F64,FIND(".",F64)+1,LEN(F64)-FIND(".",F64)+1),'Not Req'!$D$4:$D$72,0)) -> Internal (Not Req) | F64: 7773ee760dc26046c3c86bac521a4aht.sush.xml | G64: Delta commit | H64: 2 years ago
A65: d | C65: =LEFT(F65,FIND(".",F65)-1) -> 96d1f20bc73790aea2637d1fa4b291ht | D65: {=INDEX('Not Req'!$E$4:$E$72,MATCH(MID(F65,FIND(".",F65)+1,LEN(F65)-FIND(".",F65)+1),'Not Req'!$D$4:$D$72,0))} -> Internal (Not Req) | E65: =INDEX('Not Req'!$F$4:$F$72,MATCH(MID(F65,FIND(".",F65)+1,LEN(F65)-FIND(".",F65)+1),'Not Req'!$D$4:$D$72,0)) -> Internal (Not Req) | F65: 96d1f20bc73790aea2637d1fa4b291ht.sush.xml | G65: Delta commit | H65: 2 years ago

Sheet Not Req
D2: Type | E2: Description | F2: Cat
D4: bdef.xml | E4: Description : BDEF | F4: 2. CDS
D5: clas.xml | E5: Description : Classes | F5: 3. Source Code Library
D6: ddls.baseinfo | E6: Internal (Not Req) | F6: Internal (Not Req)
D7: ddls.xml | E7: Description : Data Definition | F7: 2. CDS
D8: sco1.xml | E8: Internal (Not Req) | F8: Internal (Not Req)
D9: sco2.xml | E9: Internal (Not Req) | F9: Internal (Not Req)
D10: sco2.xml | E10: Internal (Not Req) | F10: Internal (Not Req)
D11: sco2.xml | E11: Internal (Not Req) | F11: Internal (Not Req)
D12: sia6.xml | E12: Internal (Not Req) | F12: Internal (Not Req)
D13: srvb.xml | E13: Internal (Not Req) | F13: Internal (Not Req)
D14: srvb.xml | E14: Internal (Not Req) | F14: Internal (Not Req)
... D39: iwsv.xml | E39: Service Binding API | F39: Business Services
D40: iwmo.xml

Sheet Sheet1
F5: FIELDNAME | G5: KEYFLAG | H5: ROLLNAME | I5: ADMINFIELD | J5: NOTNULL | K5: COMPTYPE | L5: INTTYPE | M5: INTLEN | N5: DATATYPE | O5: LENG | P5: MASK | Q5: PRECFIELD | R5: DDTEXT | S5: GROUPNAME
F6: MANDT | G6: X | H6: MANDT | I6: 0 | J6: X | K6: E | L6: null | M6: null | N6: null | O6: null | P6: null | Q6: null | R6: null | S6: null
F7: PARTNERNUMBER | G7: X | H7: null | I7: 0 | J7: X | K7: null | L7: C | M7: 20 | N7: CHAR | O7: 10 | P7: CHAR | Q7: null | R7: null | S7: null
F8: DRAFTUUID | G8: X | H8: SDRAFT_UUID | I8: 0 | J8: X | K8: E | L8: null | M8: null | N8: null | O8: null | P8: null | Q8: null | R8: null | S8: null
F9: PARTNERNAME | G9: null | H9: null | I9: 0 | J9: null | K9: null | L9: C | M9: 120 | N9: CHAR | O9: 60 | P9: CHAR | Q9: null | R9: null | S9: null
F10: STREET | G10: null | H10: null | I10: 0 | J10: null | K10: null | L10: C | M10: 160 | N10: CHAR | O10: 80 | P10: CHAR | Q10: null | R10: null | S10: null
F11: CITY | G11: null | H11: null | I11: 0 | J11: null | K11: null | L11: C | M11: 120 | N11: CHAR | O11: 60 | P11: CHAR | Q11: null | R11: null | S11: null
F12: COUNTRY | G12: null | H12: LAND1 | I12: 0 | J12: null | K12: E | L12: null | M12: null | N12: null | O12: null | P12: null | Q12: null | R12: null | S12: null
F13: PAYMENTCURRENCY | G13: null | H13: null | I13: 0 | J13: null | K13: null | L13: C | M13: 10 | N13: CUKY | O13: 5 | P13: CUKY | Q13: null | R13: null | S13: null
F14: LASTCHANGEDAT | G14: null | H14: ABP_LOCINST_LASTCHANGE_TSTMPL | I14: 0 | J14: null | K14: E | L14: null | M14: null | N14: null | O14: null | P14: null | Q14: null | R14: null | S14: null
F15: LASTCHANGEDBY | G15: null | H15: ABP_LOCINST_LASTCHANGE_USER | I15: 0 | J15: null | K15: E | L15: null | M15: null | N15: null | O15: null | P15: null | Q15: null | R15: null | S15: null
F16: CREATEDAT | G16: null | H16: ABP_CREATION_TSTMPL | I16: 0 | J16: null | K16: E | L16: null | M16: null | N16: null | O16: null | P16: null | Q16: null | R16: null | S16: null
F17: CREATEDBY | G17: null | H17: ABP_CREATION_USER | I17: 0 | J17: null | K17: E | L17: null | M17: null | N17: null | O17: null | P17: null | Q17: null | R17: null | S17: null
F18: LOCALLASTCHANGEDAT | G18: null | H18: ABP_LOCINST_LASTCHANGE_TSTMPL | I18: 0 | J18: null | K18: E | L18: null | M18: null | N18: null | O18: null | P18: null | Q18: null | R18: null | S18: null
F19: .INCLUDE | G19: null | H19: null | I19: 0 | J19: null | K19: S | L19: null | M19: null | N19: null
