Workbook

Sheet zmm_t_dc_iut
C4: @EndUserText.label : 'DC details IUT Item'
C5: @AbapCatalog.enhancement.category : #NOT_EXTENSIBLE
C6: @AbapCatalog.tableCategory : #TRANSPARENT
C7: @AbapCatalog.deliveryClass : #A
C8: @AbapCatalog.dataMaintenance : #ALLOWED
C9: define table zmm_t_dc_iut {
C11: key mandt : mandt not null; | K11: =IFERROR(TRIM(MID(C11,1,FIND(":",C11)-1)),"") -> key mandt
C12: key dc_num : zdc_num not null; | K12: =IFERROR(TRIM(MID(C12,1,FIND(":",C12)-1)),"") -> key dc_num
C13: key dc_item : zdc_item not null; | K13: =IFERROR(TRIM(MID(C13,1,FIND(":",C13)-1)),"") -> key dc_item
C14: dc_type : zdc_type; | K14: =IFERROR(TRIM(MID(C14,1,FIND(":",C14)-1)),"") -> dc_type
C15: from_plant : zfrom_plant; | K15: =IFERROR(TRIM(MID(C15,1,FIND(":",C15)-1)),"") -> from_plant
C16: to_plant : zto_plant; | K16: =IFERROR(TRIM(MID(C16,1,FIND(":",C16)-1)),"") -> to_plant
C17: plant : werks_d; | K17: =IFERROR(TRIM(MID(C17,1,FIND(":",C17)-1)),"") -> plant
C18: to_vend : zvend; | K18: =IFERROR(TRIM(MID(C18,1,FIND(":",C18)-1)),"") -> to_vend
C19: matnr : matnr; | K19: =IFERROR(TRIM(MID(C19,1,FIND(":",C19)-1)),"") -> matnr
C20: mat_desc : maktx; | K20: =IFERROR(TRIM(MID(C20,1,FIND(":",C20)-1)),"") -> mat_desc
C21: vrkme : vrkme; | K21: =IFERROR(TRIM(MID(C21,1,FIND(":",C21)-1)),"") -> vrkme
C22: @Semantics.quantity.unitOfMeasure : 'vbrp.vrkme' | K22: =IFERROR(TRIM(MID(C22,1,FIND(":",C22)-1)),"") -> @Semantics.quantity.unitOfMeasure
... C69: taxval : ztax_value; | K69: =IFERROR(TRIM(MID(C69,1,FIND(":",C69)-1)),"") -> taxval
K70: =IFERROR(TRIM(MID(C70,1,FIND(":",C70)-1)),"")
C71: } | K71: =IFERROR(TRIM(MID(C71,1,FIND(":",C71)-1)),"")
C72: ------------------------------------- | K72: =IFERROR(TRIM(MID(C72,1,FIND(":",C72)-1)),"")
C73: @EndUserText.label : 'DC deatils header table IUT' | K73: =IFERROR(TRIM(MID(C73,1,FIND(":",C73)-1)),"") -> @EndUserText.label
C74: @AbapCatalog.enhancement.category : #NOT_EXTENSIBLE | K74: =IFERROR(TRIM(MID(C74,1,FIND(":",C74)-1)),"") -> @AbapCatalog.enhancement.category
C75: @AbapCatalog.tableCategory : #TRANSPARENT | K75: =IFERROR(TRIM(MID(C75,1,FIND(":",C75)-1)),"") -> @AbapCatalog.tableCategory
C76: @AbapCatalog.deliveryClass : #A | K76: =IFERROR(TRIM(MID(C76,1,FIND(":",C76)-1)),"") -> @AbapCatalog.deliveryClass
C77: @AbapCatalog.dataMaintenance : #ALLOWED | K77: =IFERROR(TRIM(MID(C77,1,FIND(":",C77)-1)),"") -> @AbapCatalog.dataMaintenance
C78: define table zmm_t_dc_iut_hd { | K78: =IFERROR(TRIM(MID(C78,1,FIND(":",C78)-1)),"")
K79: =IFERROR(TRIM(MID(C79,1,FIND(":",C79)-1)),"")
C80: key mandt : mandt not null; | K80: =IFERROR(TRIM(MID(C80,1,FIND(":",C80)-1)),"") -> key mandt
C81: key dc_num : zdc_num not null; | K81: =IFERROR(TRIM(MID(C81,1,FIND(":",C81)-1)),"") -> key dc_num
C82: to_vend : zvend; | K82: =IFERROR(TRIM(MID(C82,1,FIND(":",C82)-1)),"") -> to_vend
C83: @Semantics.amount.currencyCode : 'vbak.waerk' | K83: =IFERROR(TRIM(MID(C83,1,FIND(":",C83)-1)),"") -> @Semantics.amount.currencyCode
C84: grand_total : zgrand_tot; | K84: =IFERROR(TRIM(MID(C84,1,FIND(":",C84)-1)),"") -> grand_total
C85: @Semantics.amount.currencyCode : 'vbak.waerk' | K85: =IFERROR(TRIM(MID(C85,1,FIND(":",C85)-1)),"") -> @Semantics.amount.currencyCode
C86: total_tax : ztax_value; | K86: =IFERROR(TRIM(MID(C86,1,FIND(":",C86)-1)),"") -> total_tax
C87: @Semantics.quantity.unitOfMeasure : 'vbrp.vrkme' | K87: =IFERROR(TRIM(MID(C87,1,FIND(":",C87)-1)),"") -> @Semantics.quantity.unitOfMeasure
C88: total_qty : zbundle_qty; | K88: =IFERROR(TRIM(MID(C88,1,FIND(":",C88)-1)),"") -> total_qty
C89: @Semantics.amount.currencyCode : 'vbak.waerk' | K89: =IFERROR(TRIM(MID(C89,1,FIND(":",C89)-1)),"") -> @Semantics.amount.currencyCode
C90: taxable_amount : ztax_value; | K90: =IFERROR(TRIM(MID(C90,1,FIND(":",C90)-1)),"") -> taxable_amount
C91: tot_no_bits_qty : char10; | K91: =IFERROR(TRIM(MID(C91,1,FIND(":",C91)-1)),"") -> tot_no_bits_qty
... C106: created_at : timestamp; | K106: =IFERROR(TRIM(MID(C106,1,FIND(":",C106)-1)),"") -> created_at
K107: =IFERROR(TRIM(MID(C107,1,FIND(":",C107)-1)),"")
C108: } | K108: =IFERROR(TRIM(MID(C108,1,FIND(":",C108)-1)),"")

Sheet Sheet1
B1: LocationGstin | C1: Pass the DC number and Item to ZMM_T_DC_IUT & get FROM_GSTIN | E1: ZMM_T_DC_IUT | F1: FROM_GSTIN | G1: =MATCH(B1,ZSD_S_GLOBAL_ST!$I$9:$I$239,0) -> #N/A
B2: Purpose | C2: EWB | G2: =MATCH(B2,ZSD_S_GLOBAL_ST!$I$9:$I$239,0) -> #N/A
B3: SupplyType | C3: S | G3: =MATCH(B3,ZSD_S_GLOBAL_ST!$I$9:$I$239,0) -> #N/A
B4: DocumentType | C4: CHL | G4: =MATCH(B4,ZSD_S_GLOBAL_ST!$I$9:$I$239,0) -> #N/A
B5: TransactionType | C5: OWN | G5: =MATCH(B5,ZSD_S_GLOBAL_ST!$I$9:$I$239,0) -> #N/A
B6: DocumentNumber | C6: Pass dc number input screen | G6: =MATCH(B6,ZSD_S_GLOBAL_ST!$I$9:$I$239,0) -> #N/A
B7: DocumentDate | C7: Pass the DC number and Item to ZMM_T_DC_IUT_HD & get CREATED_AT | E7: ZMM_T_DC_IUT_HD | F7: CREATED_AT | G7: =MATCH(B7,ZSD_S_GLOBAL_ST!$I$9:$I$239,0) -> #N/A
B8: BillFromGstin | C8: Pass the DC number and Item to ZMM_T_DC_IUT & get FROM_GSTIN | E8: ZMM_T_DC_IUT | F8: FROM_GSTIN | G8: =MATCH(B8,ZSD_S_GLOBAL_ST!$I$9:$I$239,0) -> #N/A
B9: BillFromAddress1 | C9: Pass the DC number and Item to ZMM_T_DC_IUT & get FROM_ADDRESS | E9: ZMM_T_DC_IUT | F9: FROM_ADDRESS | G9: =MATCH(B9,ZSD_S_GLOBAL_ST!$I$9:$I$239,0) -> #N/A
B10: BillFromStateCode | C10: Pass the DC number and Item to ZMM_T_DC_IUT & get FROM_PLANT pass to LFA1 & get REGIO | E10: ZMM_T_DC_IUT | F10: FROM_PLANT | G10: =MATCH(B10,ZSD_S_GLOBAL_ST!$I$9:$I$239,0) -> #N/A
B11: BillFromPincode | C11: Pass the DC number and Item to ZMM_T_DC_IUT & get FROM_PLANT pass to LFA1 & get PSTLZ | E11: ZMM_T_DC_IUT | F11: FROM_PLANT | G11: =MATCH(B11,ZSD_S_GLOBAL_ST!$I$9:$I$239,0) -> #N/A
B12: BillToGstin | C12: Pass the DC number and Item to ZMM_T_DC_IUT & get TO_GSTIN | E12: ZMM_T_DC_IUT | F12: TO_GSTIN | G12: =MATCH(B12,ZSD_S_GLOBAL_ST!$I$9:$I$239,0) -> #N/A
B13: BillToTradeName | C13: Pass the DC number and Item to ZMM_T_DC_IUT & get VENDOR_NAME | E13: ZMM_T_DC_IUT | F13: VENDOR_NAME | G13: =MATCH(B13,ZSD_S_GLOBAL_ST!$I$9:$I$239,0) -> #N/A
B14: BillToAddress1 | C14: Pass the DC number and Item to ZMM_T_DC_IUT & get TO_ADDRESS | E14: ZMM_T_DC_IUT | F14: TO_ADDRESS | G14: =MATCH(B14,ZSD_S_GLOBAL_ST!$I$9:$I$239,0) -> #N/A
B15: BillToStateCode | C15: Pass the DC number and Item to ZMM_T_DC_IUT & get TO_PLANT pass to LFA1 & get REGIO | E15: ZMM_T_DC_IUT | F15: TO_PLANT | G15: =MATCH(B15,ZSD_S_GLOBAL_ST!$I$9:$I$239,0) -> #N/A
B16: BillToPincode | C16: Pass the DC number and Item to ZMM_T_DC_IUT & get TO_PLANT pass to LFA1 & get PSTLZ | E16: ZMM_T_DC_IUT | F16: TO_PLANT | G16: =MATCH(B16,ZSD_S_GLOBAL_ST!$I$9:$I$239,0) -> #N/A
B17: DocumentValue | C17: Pass the DC number to ZMM_T_DC_IUT_HD & get TAXABLE_AMOUNT | E17: ZMM_T_DC_IUT_HD | F17: TAXABLE_AMOUNT | G17: =MATCH(B17,ZSD_S_GLOBAL_ST!$I$9:$I$239,0) -> #N/A
B18: Hsn | C18: Pass the DC number and Item to ZMM_T_DC_IUT & get HSN | E18: ZMM_T_DC_IUT | F18: HSN | G18: =MATCH(B18,ZSD_S_GLOBAL_ST!$I$9:$I$239,0) -> #N/A
... B25: SgstAmount | C25: Pass the DC number and Item to ZMM_T_DC_IUT & get SGST_PERCENT | E25: ZMM_T_DC_IUT | F25: SGST_PERCENT | G25: =MATCH(B25,ZSD_S_GLOBAL_ST!$I$9:$I$239,0) -> #N/A

Sheet Sheet2

Sheet Required OBJ
E2: Availability | F2: Data Elements | K2: CDS & Tables
E3: =MATCH(F3,'Resolved Data Elem'!$D$4:$D$774,0) -> 227 | F3: zde_pos | G3: abap.char(2); | I3: Done | K3: zsd_c_condition_type | L3: Done
E4: =MATCH(F4,'Resolved Data Elem'!$D$4:$D$774,0) -> 268 | F4: zde_hsn | G4: abap.char(16); | I4: Done | K4: zsd_c_einv_uom | L4: Done
E5: =MATCH(F5,'Resolved Data Elem'!$D$4:$D$774,0) -> 269 | F5: zde_itemname | G5: abap.char(100); | I5: Done | K5: zsd_c_billtype | L5: Done
E6: =MATCH(F6,'Resolved Data Elem'!$D$4:$D$774,0) -> 270 | F6: zde_item_description | G6: abap.char(200); | I6: Done | K6: zsd_c_supply_detail | L6: Done
E7: =MATCH(F7,'Resolved Data Elem'!$D$4:$D$774,0) -> 275 | F7: zde_uqc | G7: abap.char(3); | I7: Done | K7: zsd_c_einv | L7: Done
E8: =MATCH(F8,'Resolved Data Elem'!$D$4:$D$774,0) -> 279 | F8: zde_rate11 | G8: abap.char(18); | I8: Done | K8: zsd_s_global_st | L8: Done | N8: In progress
K9: zsd_t_einv | L9: Done
E10: =MATCH(F10,'Resolved Data Elem'!$D$4:$D$774,0) -> 67 | F10: zde_transporter_id | G10: abap.char(20); | I10: Done | K10: zfi_t_doctype | L10: Done
E11: =MATCH(F11,'Resolved Data Elem'!$D$4:$D$774,0) -> 68 | F11: zde_transporter_name | G11: abap.char(100); | I11: Done
E12: =MATCH(F12,'Resolved Data Elem'!$D$4:$D$774,0) -> 69 | F12: zde_tranport_mode | G12: abap.char(10); | I12: Done
E13: =MATCH(F13,'Resolved Data Elem'!$D$4:$D$774,0) -> 70 | F13: zde_transporter_doc_num | G13: abap.char(20); | I13: Done
E14: =MATCH(F14,'Resolved Data Elem'!$D$4:$D$774,0) -> 72 | F14: zde_vehicle_number | G14: abap.char(10); | I14: Done
E15: =MATCH(F15,'Resolved Data Elem'!$D$4:$D$774,0) -> 73 | F15: zde_vehicle_type | G15: abap.char(1); | I15: Done

Sheet Resolved Data Elem
C2: First Ref Obj | D2: Data Element | E2: Type
C4: ZSD_T_EINV_LOG | D4: mandt | E4: mandt not null;
C5: ZSD_T_EINV_LOG | D5: xblnr | E5: xblnr not null;
C6: ZSD_T_EINV_LOG | D6: zde_document_date | E6: abap.dats not null;
C7: ZSD_T_EINV_LOG | D7: zde_company_code | E7: abap.char(4) not null;
C8: ZSD_T_EINV_LOG | D8: zde_fiscal_year | E8: abap.numc(4);
C9: ZSD_T_EINV_LOG | D9: zde_location_gstin | E9: abap.char(20);
C10: ZSD_T_EINV_LOG | D10: zde_billfromgstin | E10: abap.char(100);
C11: ZSD_T_EINV_LOG | D11: zde_billfromname | E11: abap.char(100);
C12: ZSD_T_EINV_LOG | D12: zde_billfromadd1 | E12: abap.char(100);
C13: ZSD_T_EINV_LOG | D13: zde_billfromadd2 | E13: abap.char(100);
C14: ZSD_T_EINV_LOG | D14: zde_billfrompincode | E14: abap.char(100);
... C279: ZSD_S_GLOBAL_ST | D279: abap.string(0) | E279: abap.string(0);
C280: ZSD_S_GLOBAL_ST | E280: 'vbrp.meins'
C281: ZSD_S_GLOBAL_ST | D281: menge_d | E281: menge_d;
C282: ZSD_S_GLOBAL_ST | D282: zde_rate11 | E282: abap.char(18);
C283: ZSD_S_GLOBAL_ST | D283: zde_cess_rate | E283: abap.char(20);
C284: ZSD_S_GLOBAL_ST | D284: zde_cess_state_cess_rate | E284: abap.char(20);
C285: ZSD_S_GLOBAL_ST | D285: zde_cess_non_advalorem_rat | E285: abap.char(20);
C286: ZSD_S_GLOBAL_ST | D286: zde_price_per_quantity | E286: abap.char(20);
C287: ZSD_S_GLOBAL_ST | D287: zde_discount_amount | E287: abap.char(20);
C288: ZSD_S_GLOBAL_ST | D288: zde_gross_amount | E288: abap.char(20);
C289: ZSD_S_GLOBAL_ST | D289: zde_other_charges | E289: abap.char(20);
C290: ZSD_S_GLOBAL_ST | D290: zde_taxable_value | E290: abap.char(20);
C291: ZSD_S_GLOBAL_ST | D291: zde_assessable_value | E291: abap.char(15);
C292: ZSD_S_GLOBAL_ST | D292: zde_pretax_value | E292: abap.char(20);
... C320: ZSD_S_GLOBAL_ST | D320: zde_custom_item9 | E320: abap.char(40);
C321: ZSD_S_GLOBAL_ST | E321: 'CUSTOM ITEM10'
C322: ZSD_S_GLOBAL_ST | D322: abap.char(200) | E322: abap.char(200);
C323: ZSD_S_GLOBAL_ST | D323: zde_invoice_no | E323: abap.char(32);
C324: ZSD_S_GLOBAL_ST | D324: abap.string(0) | E324: abap.string(0);
C325: ZSD_S_GLOBAL_ST | D325: zde_invoice_date | E325: abap.char(10);
C326: ZSD_S_GLOBAL_ST | D326: zde_acknumber | E326: abap.char(15);
C327: ZSD_S_GLOBAL_ST | D327: zde_ackdate | E327: abap.char(10);
C328: ZSD_S_GLOBAL_ST | D328: zde_assessable_success | E328: abap.char(1);
C329: ZSD_S_GLOBAL_ST | D329: zde_assessable_fail | E329: abap.char(1);
C330: ZSD_S_GLOBAL_ST | D330: zde_assessable_pending | E330: abap.char(1);
C331: ZSD_S_GLOBAL_ST | D331: zde_assessable_reprocess | E331: abap.char(1);
C332: ZSD_S_GLOBAL_ST | D332: zde_error_des | E332: abap.char(200);
C333: ZSD_S_GLOBAL_ST | D333: zde_referenceid | E333: abap.char(50);
... C341: ZSD_S_GLOBAL_ST | D341: abap.string(0) | E341: abap.string(0);

Sheet ZFI_T_DOCTYPE
A2: @EndUserText.label : 'FI Billtypes Maintenance Table'
A3: @AbapCatalog.enhancement.category : #NOT_EXTENSIBLE
A4: @AbapCatalog.tableCategory : #TRANSPARENT
A5: @AbapCatalog.deliveryClass : #A
A6: @AbapCatalog.dataMaintenance : #ALLOWED
A7: define table zfi_t_doctype {
A9: key mandt : mandt not null;
A10: key module_type : zde_module not null; | F10: char 10
A11: key blart : blart not null;
A12: doc_type : zde_invoice_subtyp; | F12: char 3
A14: }
J16: zgst_states
J17: ZSD_C_bkpf

Sheet Sheet6
C2: @EndUserText.label : 'GST E-Invoicing Status Maintenance' | K2: @EndUserText.label : 'GST States Codes' | Q2: @EndUserText.label : 'DC details IUT Item' | X2: @EndUserText.label : 'DC deatils header table IUT' | AE2: @EndUserText.label : 'ZMB1A 201 Cost Centre' | AL2: @EndUserText.label : 'E-Invoice Table to display data' | AT2: @EndUserText.label : 'Unit Order Type Master' | BA2: @AbapCatalog.viewEnhancementCategory: [#NONE] | BG2: @AbapCatalog.viewEnhancementCategory: [#NONE]
C3: @AbapCatalog.enhancement.category : #NOT_EXTENSIBLE | K3: @AbapCatalog.enhancement.category : #NOT_EXTENSIBLE | Q3: @AbapCatalog.enhancement.category : #NOT_EXTENSIBLE | X3: @AbapCatalog.enhancement.category : #NOT_EXTENSIBLE | AE3: @AbapCatalog.enhancement.category : #NOT_EXTENSIBLE | AL3: @AbapCatalog.enhancement.category : #NOT_EXTENSIBLE | AT3: @AbapCatalog.enhancement.category : #NOT_EXTENSIBLE | BA3: @AccessControl.authorizationCheck: #NOT_REQUIRED | BG3: @AccessControl.authorizationCheck: #NOT_REQUIRED
C4: @AbapCatalog.tableCategory : #TRANSPARENT | K4: @AbapCatalog.tableCategory : #TRANSPARENT | Q4: @AbapCatalog.tableCategory : #TRANSPARENT | X4: @AbapCatalog.tableCategory : #TRANSPARENT | AE4: @AbapCatalog.tableCategory : #TRANSPARENT | AL4: @AbapCatalog.tableCategory : #TRANSPARENT | AT4: @AbapCatalog.tableCategory : #TRANSPARENT | BA4: @EndUserText.label: 'View for BKPF' | BG4: @EndUserText.label: 'View for BSEG'
C5: @AbapCatalog.deliveryClass : #A | K5: @AbapCatalog.deliveryClass : #A | Q5: @AbapCatalog.deliveryClass : #A | X5: @AbapCatalog.deliveryClass : #A | AE5: @AbapCatalog.deliveryClass : #A | AL5: @AbapCatalog.deliveryClass : #A | AT5: @AbapCatalog.deliveryClass : #A | BA5: @Metadata.ignorePropagatedAnnotations: true | BG5: @Metadata.ignorePropagatedAnnotations: true
C6: @AbapCatalog.dataMaintenance : #ALLOWED | K6: @AbapCatalog.dataMaintenance : #ALLOWED | Q6: @AbapCatalog.dataMaintenance : #ALLOWED | X6: @AbapCatalog.dataMaintenance : #ALLOWED | AE6: @AbapCatalog.dataMaintenance : #ALLOWED | AL6: @AbapCatalog.dataMaintenance : #RESTRICTED | AT6: @AbapCatalog.dataMaintenance : #ALLOWED | BA6: define view entity ZSD_C_bkpf | BG6: define view entity ZSD_C_BSEG
C7: define table zeinv_status { | K7: define table zgst_states { | Q7: define table zmm_t_dc_iut { | X7: define table zmm_t_dc_iut_hd { | AE7: define table zsd_t_201costcnt { | AL7: define table zsd_t_einv { | AT7: define table zsd_t_unitotm { | BA7: as select from bkpf | BG7: as select from bseg
BA8: { | BG8: association to I_CompanyCode as _t001 on _t001.CompanyCode = $projection.Bukrs
C9: key mandt : mandt not null; | K9: key mandt : mandt not null; | Q9: key mandt : mandt not null; | X9: key mandt : mandt not null; | AE9: key mandt : mandt not null; | AL9: key mandt : mandt not null; | AT9: key mandt : mandt not null; | BA9: key bukrs as Bukrs,
C10: key inv_num : vbeln_vf not null; | K10: key region : regio not null; | Q10: key dc_num : abap.char(10) not null; | X10: key dc_num : abap.char(10) not null; | AE10: key kostl : kostl not null; | AL10: key documentnumber : xblnr not null; | AT10: key werks : werks_d not null; | BA10: key belnr as Belnr, | BG10: {
C11: key odn : xblnr not null; | K11: gst_state_code : regio; | Q11: key dc_item : abap.numc(5) not null; | X11: to_vend : abap.char(10); | AE11: key unit_id : abap.char(3) not null; | AL11: locationgstin : abap.char(15); | AT11: key unit_id : abap.char(3) not null; | BA11: key gjahr as Gjahr, | BG11: key bukrs as Bukrs,
C12: inv_date : fkdat; | K12: gst_state_desc : bezei20; | Q12: dc_type : abap.char(20); | X12: @Semantics.amount.currencyCode : 'vbak.waerk' | AE12: key unit_stxt : abap.char(15) not null; | AL12: documentdate : abap.dats not null; | AT12: key dauat : aufart not null; | BA12: blart as Blart, | BG12: key belnr as Belnr,
C13: irn : j_1ig_irn; | Q13: from_plant : abap.char(4); | X13: grand_total : abap.curr(15,2); | AL13: company_code : abap.char(4) not null; | AT13: key j_4kscat : abap.char(16) not null; | BA13: bldat as Bldat, | BG13: key gjahr as Gjahr,
C14: einv_module : abap.char(2); | K14: } | Q14: to_plant : abap.char(4); | X14: @Semantics.amount.currencyCode : 'vbak.waerk' | AE14: } | AL14: purpose : abap.char(13); | AT14: key lgort : lgort_d not null; | BA14: budat as Budat, | BG14: key buzei as Buzei,
C15: proxy_error : abap.char(1); | Q15: plant : werks_d; | X15: total_tax : abap.curr(11,2); | AL15: sapmodule : abap.char(2); | AT15: lgort_n : lgort_d; | BA15: monat as Monat, | BG15: buzid as Buzid,
C16: request_id : abap.int4; | Q16: to_vend : abap.char(10); | X16: @Semantics.quantity.unitOfMeasure : 'vbrp.vrkme' | AL16: fiscalyear : gjahr; | BA16: cpudt as Cpudt, | BG16: augdt as Augdt,
C17: message_type : bapi_mtype; | Q17: matnr : matnr; | X17: total_qty : abap.quan(13,3); | AL17: document : abap.char(12); | AT17: } | BA17: cputm as Cputm, | BG17: augcp as Augcp,
C18: message : zmsg; | Q18: mat_desc : maktx; | X18: @Semantics.amount.currencyCode : 'vbak.waerk' | AL18: branch : bupla; | BA18: aedat as Aedat, | BG18: augbl as Augbl,
C19: status_code : abap.char(10); | Q19: vrkme : vrkme; | X19: taxable_amount : abap.curr(11,2); | AL19: locationname : abap.char(50); | BA19: upddt as Upddt, | BG19: bschl as Bschl,
C20: status_message : abap.char(255); | Q20: @Semantics.quantity.unitOfMeasure : 'vbrp.vrkme' | X20: tot_no_bits_qty : char10; | AL20: returnperiod : abap.char(6); | BA20: wwert as Wwert, | BG20: koart as Koart,
C21: error_code : abap.char(10); | Q21: quantity : abap.quan(13,3); | X21: tot_qty_in_kg_pc : char10; | AL21: liabilitydischargereturnperiod : abap.char(20); | BA21: usnam as Usnam, | BG21: umskz as Umskz,
C22: error_msg : abap.char(255); | Q22: hsn : steuc; | X22: tot_bags_bin_cover : char10; | AL22: autopushorgenerate : abap.char(20); | BA22: tcode as Tcode, | BG22: umsks as Umsks,
C23: created_by : ernam; | Q23: uom : meins; | X23: waerk : waerk; | AL23: supplytype : abap.char(1); | BA23: bvorg as Bvorg, | BG23: zumsk as Zumsk,
C24: created_on : erdat; | Q24: waerk : waerk; | X24: vrkme : vrkme; | AL24: irn : abap.char(64); | BA24: xblnr as Xblnr, | BG24: shkzg as Shkzg,
C25: created_time : erzet; | Q25: @Semantics.amount.currencyCode : 'vbak.waerk' | X25: from_plant : abap.char(4); | AL25: documenttype : abap.char(3); | BA25: dbblg as Dbblg, | BG25: gsber as Gsber,
Q26: rate : abap.curr(11,2); | X26: to_plant : abap.char(4); | AL26: transactiontype : abap.char(6); | BA26: dbblg_gjahr as DbblgGjahr, | BG26: pargb as Pargb,
C27: } | Q27: @Semantics.amount.currencyCode : 'vbak.waerk' | X27: @Semantics.quantity.unitOfMeasure : 'vbrp.vrkme' | AL27: @EndUserText.label : 'DTA Transaction' | BA27: dbblg_bukrs as DbblgBukrs, | BG27: tax_country as TaxCountry,
Q28: taxable_value : abap.curr(11,2); | X28: tot_order_qty : abap.quan(13,3); | AL28: dtatransaction : abap.char(50); | BA28: stblg as Stblg, | BG28: mwskz as Mwskz,
Q29: @Semantics.amount.currencyCode : 'vbak.waerk' | X29: total_bias_weight : char10; | AL29: transactiontypedescription : abap.char(30); | BA29: stjah as Stjah, | BG29: txdat_from as TxdatFrom,
Q30: cgst_amount : abap.curr(15,2); | X30: @Semantics.quantity.unitOfMeasure : 'vbrp.vrkme' | AL30: seriescode : abap.char(15); | BA30: bktxt as Bktxt, | BG30: qsskz as Qsskz,
Q31: cgst_percent : char10; | X31: tot_bundle : abap.quan(13,3); | AL31: referencedocumentnumber : abap.char(16); | BA31: waers as Waers, | BG31: @Semantics.amount.currencyCode : 'waers'
Q32: @Semantics.amount.currencyCode : 'vbak.waerk' | X32: total_no_of_bias : char10; | AL32: referencedocumentdate : abap.char(10); | BA32: kursf as Kursf, | BG32: dmbtr as Dmbtr,
Q33: sgst_amount : abap.curr(15,2); | X33: tot_recut_bag_bins_cover : char10; | AL33: transactionmode : abap.char(20); | BA33: kzwrs as Kzwrs, | BG33: @Semantics.amount.currencyCode : 'waers'
Q34: sgst_percent : char10; | X34: created_by : ernam; | AL34: billfromgstin : abap.char(15); | BA34: kzkrs as Kzkrs, | BG34: wrbtr as Wrbtr,
Q35: @Semantics.amount.currencyCode : 'vbak.waerk' | X35: created_at : timestamp; | AL35: billfromlegalname : abap.char(50); | BA35: bstat as Bstat, | BG35: @Semantics.amount.currencyCode : 'waers'
Q36: grand_total : abap.curr(15,2); | AL36: billfromtradename : abap.char(30); | BA36: xnetb as Xnetb, | BG36: fcsl as Fcsl,
Q37: remarks : char50; | X37: } | AL37: billfrombuildingno : abap.char(60); | BA37: // frath as Frath, | BG37: rfccur as Rfccur,
Q38: to_address : char100; | AL38: billfrombuildingname : abap.char(60); | BA38: xrueb as Xrueb, | BG38: @Semantics.amount.currencyCode : 'waers'
Q39: from_address : char100; | AL39: billfromflatno : abap.char(10); | BA39: glvor as Glvor, | BG39: kzbtr as Kzbtr,
Q40: to_gstin : j_1bstains; | AL40: billfromaddress1 : abap.char(50); | BA40: grpid as Grpid, | BG40: @Semantics.amount.currencyCode : 'waers'
Q41: from_gstin : j_1bstains; | AL41: billfromaddress2 : abap.char(50); | BA41: dokid as Dokid, | BG41: pswbt as Pswbt,
Q42: igst_flag : boole_d; | AL42: billfromcity : abap.char(60); | BA42: arcid as Arcid, | BG42: pswsl as Pswsl,
Q43: @Semantics.amount.currencyCode : 'vbak.waerk' | AL43: billfromdistrict : abap.char(60); | BA43: iblar as Iblar, | BG43: @Semantics.amount.currencyCode : 'waers'
Q44: igst_amount : abap.curr(15,2); | AL44: billfromstatecode : abap.char(50); | BA44: awtyp as Awtyp, | BG44: txbhw as Txbhw,
Q45: igst_percent : char10; | AL45: billfrompincode : abap.char(6); | BA45: awkey as Awkey, | BG45: @Semantics.amount.currencyCode : 'waers'
Q46: po_number : ebeln; | AL46: billfromphone : abap.char(12); | BA46: fikrs as Fikrs, | BG46: txbfw as Txbfw,
Q47: returnable_dc : boole_d; | AL47: billfromemail : abap.char(50); | BA47: hwaer as Hwaer, | BG47: @Semantics.amount.currencyCode : 'waers'
Q48: no_bits_qty : char10; | AL48: dispatchfromgstin : abap.char(15); | BA48: hwae2 as Hwae2, | BG48: mwsts as Mwsts,
Q49: qty_in_kg_pc : char10; | AL49: dispatchfromtradename : abap.char(20); | BA49: hwae3 as Hwae3, | BG49: @Semantics.amount.currencyCode : 'waers'
... Q67: taxval : abap.curr(11,2); | AL67: billtoaddress1 : abap.char(150); | BA67: awsys as Awsys, | BG67: ktosl as Ktosl,
AL68: billtoaddress2 : abap.char(150); | BA68: txkrs as Txkrs, | BG68: @Semantics.amount.currencyCode : 'waers'
Q69: } | AL69: billtocity : abap.char(10); | BA69: ctxkrs as Ctxkrs, | BG69: qsshb as Qsshb,
AL70: billtodistrict : abap.char(10); | BA70: lotkz as Lotkz, | BG70: kursr as Kursr,
AL71: billtostatecode : abap.char(10); | BA71: xwvof as Xwvof, | BG71: bupla,
AL72: billtopincode : abap.char(10); | BA72: stgrd as Stgrd, | BG72: kunnr as kunnr,
AL73: billtophone : abap.char(10); | BA73: ppnam as Ppnam, | BG73: lifnr as lifnr,
AL74: billtoemail : abap.char(100); | BA74: ppdat as Ppdat, | BG74: segment as segment,
AL75: shiptogstin : abap.char(15); | BA75: pptme as Pptme, | BG75: vbeln,
AL76: shiptolegalname : abap.char(100); | BA76: pptcod as Pptcod, | BG76: hsn_sac,
AL77: shiptotradename : abap.char(100); | BA77: brnch as Brnch, | BG77: plc_sup,
AL78: shiptobuildingnumber : abap.char(10); | BA78: numpg as Numpg, | BG78: gst_part,
AL79: shiptobuildingname : abap.char(100); | BA79: adisc as Adisc, | BG79: matnr,
AL80: shiptoflatnumber : abap.char(10); | BA80: xref1_hd as Xref1Hd, | BG80: werks,
AL81: shiptoaddress1 : abap.char(100); | BA81: xref2_hd as Xref2Hd, | BG81: xauto,
... AL93: paymentdate : abap.char(10); | BA93: follow_on as FollowOn, | BG93: // or kunnr is not initial
AL94: paymentremarks : abap.char(200); | BA94: xreorg as Xreorg,
AL95: paymentterms : abap.char(50); | BA95: subset as Subset,
AL96: paymentinstruction : abap.char(50); | BA96: kurst as Kurst,
AL97: payeename : abap.char(100); | BA97: kursx as Kursx,
AL98: payeeaccountnumber : abap.char(18); | BA98: kur2x as Kur2x,
AL99: paymentamountdue : abap.char(18); | BA99: kur3x as Kur3x,
AL100: paymentduedate : abap.char(8); | BA100: xmca as Xmca,
AL101: ifsc : abap.char(11); | BA101: resubmission as Resubmission,
AL102: accountdetails : abap.char(50); | BA102: logsystem_sender as LogsystemSender,
AL103: credittransfer : abap.char(50); | BA103: bukrs_sender as BukrsSender,
AL104: directdebit : abap.char(50); | BA104: belnr_sender as BelnrSender,
AL105: creditdays : abap.char(10); | BA105: gjahr_sender as GjahrSender,
... AL185: statecessrate : abap.char(20); | BA185: }
AL186: cessnonadvaloremrate : abap.char(20);
AL187: priceperquantity : abap.char(20);
AL188: discountamount : abap.char(20);
AL189: grossamount : abap.char(20);
AL190: othercharges : abap.char(20);
AL191: taxablevalue : abap.char(20);
AL192: assessablevalue : abap.char(15);
AL193: pretaxvalue : abap.char(20);
AL194: igstamount : abap.char(20);
AL195: cgstamount : abap.char(20);
AL196: sgstamount : abap.char(20);
AL197: cessamount : abap.char(20);
... AL244: }

Sheet Backup
C3: before added Include
C5: METHOD get_data_for_challan. | M5: lt_unit | O5: lv_total_dmbtr
C6: TYPES: BEGIN OF ty_t001w_rto_tmp, | M6: lt_cost
C7: werks TYPE werks, | M7: lt_twlad
C8: werks1 TYPE kunnr, | M8: lt_mkpf_rto
C9: name1 TYPE name1, | M9: lt_usr21
C10: name2 TYPE name2, | M10: lt_adr6
C11: pstlz TYPE pstlz, | M11: lt_mseg_rto
C12: ort01 TYPE ort01, | M12: lt_ekpo
C13: regio TYPE regio, | M13: lt_aufk
C14: j_1bbranch TYPE j_1bbranch, | M14: lt_t001w_ekko
C15: END OF ty_t001w_rto_tmp. | M15: lt_adrc_ekko | P15: 1 | Q15: Filling Internal Tables
C16: TYPES: BEGIN OF ty_eway_bill_s, | M16: lt_mara_uqc | P16: 2 | Q16: Our Code
C17: branch TYPE char100, | M17: lt_mbew
C18: fiscal_year TYPE char100, | M18: lt_marc_hsn | P18: 3 | Q18: lt_eb_eway_bill_s_disp_rto
C19: from_gstin TYPE char100, | M19: lt_t001_plant
C20: from_name TYPE char100, | M20: lt_adrc_mseg
C21: from_address1 TYPE char100, | M21: lt_branch_plant | P21: 0 | Q21: if_rap_query_provider~select
C22: from_address2 TYPE char100,
C23: from_place TYPE char100,
C24: from_state TYPE char100,
C25: return_period TYPE char100,
C26: actual_from_state TYPE char100,
C27: actual_from_gstin TYPE char100,
C28: act_frm_oth_prty TYPE char100,
C29: from_postal_code TYPE char100,
C30: supply_type TYPE char100,
C31: sub_supply_type TYPE char100,
C32: sub_supply_description TYPE char100,
C33: document_type TYPE char100,
... C1535: ENDIF.

Sheet ZEINV_STATUS
A2: @EndUserText.label : 'GST E-Invoicing Status Maintenance'
A3: @AbapCatalog.enhancement.category : #NOT_EXTENSIBLE
A4: @AbapCatalog.tableCategory : #TRANSPARENT
A5: @AbapCatalog.deliveryClass : #A
A6: @AbapCatalog.dataMaintenance : #ALLOWED
A7: define table zeinv_status { | H7: Field | I7: Data Element
A9: key mandt : mandt not null; | H9: =TRIM(MID(A9,1,FIND(":",A9)-1)) -> key mandt | I9: =IF(ISNUMBER(SEARCH("@",A9)),"",TRIM(SUBSTITUTE(SUBSTITUTE(TRIM(MID(A9,FIND(":",A9)+1,LEN(A9))),";",""),"not null",""))) -> mandt | K9: =MATCH(I9,'Resolved Data Elem'!$D$4:$D$341,0) -> 1
A10: key inv_num : vbeln_vf not null; | H10: =TRIM(MID(A10,1,FIND(":",A10)-1)) -> key inv_num | I10: =IF(ISNUMBER(SEARCH("@",A10)),"",TRIM(SUBSTITUTE(SUBSTITUTE(TRIM(MID(A10,FIND(":",A10)+1,LEN(A10))),";",""),"not null",""))) -> vbeln_vf | K10: =MATCH(I10,'Resolved Data Elem'!$D$4:$D$341,0) -> #N/A
A11: key odn : xblnr not null; | H11: =TRIM(MID(A11,1,FIND(":",A11)-1)) -> key odn | I11: =IF(ISNUMBER(SEARCH("@",A11)),"",TRIM(SUBSTITUTE(SUBSTITUTE(TRIM(MID(A11,FIND(":",A11)+1,LEN(A11))),";",""),"not null",""))) -> xblnr | K11: =MATCH(I11,'Resolved Data Elem'!$D$4:$D$341,0) -> 2
A12: inv_date : fkdat; | H12: =TRIM(MID(A12,1,FIND(":",A12)-1)) -> inv_date | I12: =IF(ISNUMBER(SEARCH("@",A12)),"",TRIM(SUBSTITUTE(SUBSTITUTE(TRIM(MID(A12,FIND(":",A12)+1,LEN(A12))),";",""),"not null",""))) -> fkdat | K12: =MATCH(I12,'Resolved Data Elem'!$D$4:$D$341,0) -> #N/A
A13: irn : j_1ig_irn; | H13: =TRIM(MID(A13,1,FIND(":",A13)-1)) -> irn | I13: =IF(ISNUMBER(SEARCH("@",A13)),"",TRIM(SUBSTITUTE(SUBSTITUTE(TRIM(MID(A13,FIND(":",A13)+1,LEN(A13))),";",""),"not null",""))) -> j_1ig_irn | K13: =MATCH(I13,'Resolved Data Elem'!$D$4:$D$341,0) -> #N/A
A14: einv_module : zeinv_module; | H14: =TRIM(MID(A14,1,FIND(":",A14)-1)) -> einv_module | I14: =IF(ISNUMBER(SEARCH("@",A14)),"",TRIM(SUBSTITUTE(SUBSTITUTE(TRIM(MID(A14,FIND(":",A14)+1,LEN(A14))),";",""),"not null",""))) -> zeinv_module | K14: char 2
A15: proxy_error : zzproxy_error; | H15: =TRIM(MID(A15,1,FIND(":",A15)-1)) -> proxy_error | I15: =IF(ISNUMBER(SEARCH("@",A15)),"",TRIM(SUBSTITUTE(SUBSTITUTE(TRIM(MID(A15,FIND(":",A15)+1,LEN(A15))),";",""),"not null",""))) -> zzproxy_error | K15: char 1
A16: request_id : zzrequest_id; | H16: =TRIM(MID(A16,1,FIND(":",A16)-1)) -> request_id | I16: =IF(ISNUMBER(SEARCH("@",A16)),"",TRIM(SUBSTITUTE(SUBSTITUTE(TRIM(MID(A16,FIND(":",A16)+1,LEN(A16))),";",""),"not null",""))) -> zzrequest_id | K16: int 4 , 10
A17: message_type : bapi_mtype; | H17: =TRIM(MID(A17,1,FIND(":",A17)-1)) -> message_type | I17: =IF(ISNUMBER(SEARCH("@",A17)),"",TRIM(SUBSTITUTE(SUBSTITUTE(TRIM(MID(A17,FIND(":",A17)+1,LEN(A17))),";",""),"not null",""))) -> bapi_mtype | K17: =MATCH(I17,'Resolved Data Elem'!$D$4:$D$341,0) -> #N/A
A18: message : zmsg; | H18: =TRIM(MID(A18,1,FIND(":",A18)-1)) -> message | I18: =IF(ISNUMBER(SEARCH("@",A18)),"",TRIM(SUBSTITUTE(SUBSTITUTE(TRIM(MID(A18,FIND(":",A18)+1,LEN(A18))),";",""),"not null",""))) -> zmsg | K18: char 255
A19: status_code : zstatus_code; | H19: =TRIM(MID(A19,1,FIND(":",A19)-1)) -> status_code | I19: =IF(ISNUMBER(SEARCH("@",A19)),"",TRIM(SUBSTITUTE(SUBSTITUTE(TRIM(MID(A19,FIND(":",A19)+1,LEN(A19))),";",""),"not null",""))) -> zstatus_code | K19: char 10
A20: status_message : zstatus_msg; | H20: =TRIM(MID(A20,1,FIND(":",A20)-1)) -> status_message | I20: =IF(ISNUMBER(SEARCH("@",A20)),"",TRIM(SUBSTITUTE(SUBSTITUTE(TRIM(MID(A20,FIND(":",A20)+1,LEN(A20))),";",""),"not null",""))) -> zstatus_msg | K20: char 255
A21: error_code : zerror_code_bolton; | H21: =TRIM(MID(A21,1,FIND(":",A21)-1)) -> error_code | I21: =IF(ISNUMBER(SEARCH("@",A21)),"",TRIM(SUBSTITUTE(SUBSTITUTE(TRIM(MID(A21,FIND(":",A21)+1,LEN(A21))),";",""),"not null",""))) -> zerror_code_bolton | K21: char 10
A22: error_msg : zerr_msg_bolton; | H22: =TRIM(MID(A22,1,FIND(":",A22)-1)) -> error_msg | I22: =IF(ISNUMBER(SEARCH("@",A22)),"",TRIM(SUBSTITUTE(SUBSTITUTE(TRIM(MID(A22,FIND(":",A22)+1,LEN(A22))),";",""),"not null",""))) -> zerr_msg_bolton | K22: char 255
A23: created_by : ernam; | H23: =TRIM(MID(A23,1,FIND(":",A23)-1)) -> created_by | I23: =IF(ISNUMBER(SEARCH("@",A23)),"",TRIM(SUBSTITUTE(SUBSTITUTE(TRIM(MID(A23,FIND(":",A23)+1,LEN(A23))),";",""),"not null",""))) -> ernam | K23: =MATCH(I23,'Resolved Data Elem'!$D$4:$D$341,0) -> #N/A
A24: created_on : erdat; | H24: =TRIM(MID(A24,1,FIND(":",A24)-1)) -> created_on | I24: =IF(ISNUMBER(SEARCH("@",A24)),"",TRIM(SUBSTITUTE(SUBSTITUTE(TRIM(MID(A24,FIND(":",A24)+1,LEN(A24))),";",""),"not null",""))) -> erdat | K24: =MATCH(I24,'Resolved Data Elem'!$D$4:$D$341,0) -> #N/A
A25: created_time : erzet; | H25: =TRIM(MID(A25,1,FIND(":",A25)-1)) -> created_time | I25: =IF(ISNUMBER(SEARCH("@",A25)),"",TRIM(SUBSTITUTE(SUBSTITUTE(TRIM(MID(A25,FIND(":",A25)+1,LEN(A25))),";",""),"not null",""))) -> erzet | K25: =MATCH(I25,'Resolved Data Elem'!$D$4:$D$341,0) -> #N/A
A27: }

Sheet ZSD_S_GLOBAL_ST
A4: @EndUserText.label : 'Global Structure For API'
A5: @AbapCatalog.enhancement.category : #NOT_EXTENSIBLE | K5: @EndUserText.label : 'Global Structure For API'
K6: @AbapCatalog.enhancement.category : #NOT_EXTENSIBLE
A7: define structure zsd_s_global_st { | H7: Field | I7: Data Element | K7: define structure zsd_s_global_st { | P7: Field | Q7: Data Type
A9: locationgstin : zde_locationgstin; | H9: =TRIM(MID(A9,1,FIND(":",A9)-1)) -> locationgstin | I9: =IF(ISNUMBER(SEARCH("@",A9)),"",TRIM(SUBSTITUTE(SUBSTITUTE(TRIM(MID(A9,FIND(":",A9)+1,LEN(A9))),";",""),"not null",""))) -> zde_locationgstin | K9: locationgstin : abap.char(15); | P9: =TRIM(SUBSTITUTE(MID(K9,1,FIND(":",K9)-1),"key","")) -> locationgstin | Q9: =TRIM(MID(K9,FIND(":",K9)+1,LEN(K9))) -> abap.char(15);
A10: company_code : zde_company_code; | H10: =TRIM(MID(A10,1,FIND(":",A10)-1)) -> company_code | I10: =IF(ISNUMBER(SEARCH("@",A10)),"",TRIM(SUBSTITUTE(SUBSTITUTE(TRIM(MID(A10,FIND(":",A10)+1,LEN(A10))),";",""),"not null",""))) -> zde_company_code | K10: company_code : abap.char(4); | P10: =TRIM(SUBSTITUTE(MID(K10,1,FIND(":",K10)-1),"key","")) -> company_code | Q10: =TRIM(MID(K10,FIND(":",K10)+1,LEN(K10))) -> abap.char(4);
A11: documentnumber : zde_documentnumber; | H11: =TRIM(MID(A11,1,FIND(":",A11)-1)) -> documentnumber | I11: =IF(ISNUMBER(SEARCH("@",A11)),"",TRIM(SUBSTITUTE(SUBSTITUTE(TRIM(MID(A11,FIND(":",A11)+1,LEN(A11))),";",""),"not null",""))) -> zde_documentnumber | K11: documentnumber : abap.char(16); | P11: =TRIM(SUBSTITUTE(MID(K11,1,FIND(":",K11)-1),"key","")) -> documentnumber | Q11: =TRIM(MID(K11,FIND(":",K11)+1,LEN(K11))) -> abap.char(16); | AC11: =IF(ISNUMBER(SEARCH("@",H9)),A9,H9&" : "&IF(AD11="",I9,AD11)&";") -> locationgstin : abap.char(15); | AD11: ="abap.char("&AE11&")" -> abap.char(15) | AE11: 15
A12: documentdate : zde_documentdate; | H12: =TRIM(MID(A12,1,FIND(":",A12)-1)) -> documentdate | I12: =IF(ISNUMBER(SEARCH("@",A12)),"",TRIM(SUBSTITUTE(SUBSTITUTE(TRIM(MID(A12,FIND(":",A12)+1,LEN(A12))),";",""),"not null",""))) -> zde_documentdate | K12: documentdate : abap.char(10); | P12: =TRIM(SUBSTITUTE(MID(K12,1,FIND(":",K12)-1),"key","")) -> documentdate | Q12: =TRIM(MID(K12,FIND(":",K12)+1,LEN(K12))) -> abap.char(10); | AC12: =IF(ISNUMBER(SEARCH("@",H10)),A10,H10&" : "&IF(AD12="",I10,AD12)&";") -> company_code : abap.char(4); | AD12: ="abap.char("&AE12&")" -> abap.char(4) | AE12: 4
A13: purpose : zde_purpose1; | H13: =TRIM(MID(A13,1,FIND(":",A13)-1)) -> purpose | I13: =IF(ISNUMBER(SEARCH("@",A13)),"",TRIM(SUBSTITUTE(SUBSTITUTE(TRIM(MID(A13,FIND(":",A13)+1,LEN(A13))),";",""),"not null",""))) -> zde_purpose1 | K13: purpose : abap.char(13); | P13: =TRIM(SUBSTITUTE(MID(K13,1,FIND(":",K13)-1),"key","")) -> purpose | Q13: =TRIM(MID(K13,FIND(":",K13)+1,LEN(K13))) -> abap.char(13); | AC13: =IF(ISNUMBER(SEARCH("@",H11)),A11,H11&" : "&IF(AD13="",I11,AD13)&";") -> documentnumber : abap.char(16); | AD13: ="abap.char("&AE13&")" -> abap.char(16) | AE13: 16
A14: sapmodule : zde_sapmodule; | H14: =TRIM(MID(A14,1,FIND(":",A14)-1)) -> sapmodule | I14: =IF(ISNUMBER(SEARCH("@",A14)),"",TRIM(SUBSTITUTE(SUBSTITUTE(TRIM(MID(A14,FIND(":",A14)+1,LEN(A14))),";",""),"not null",""))) -> zde_sapmodule | K14: sapmodule : abap.char(2); | P14: =TRIM(SUBSTITUTE(MID(K14,1,FIND(":",K14)-1),"key","")) -> sapmodule | Q14: =TRIM(MID(K14,FIND(":",K14)+1,LEN(K14))) -> abap.char(2); | AC14: =IF(ISNUMBER(SEARCH("@",H12)),A12,H12&" : "&IF(AD14="",I12,AD14)&";") -> documentdate : abap.char(10); | AD14: ="abap.char("&AE14&")" -> abap.char(10) | AE14: 10
A15: fiscalyear : gjahr; | H15: =TRIM(MID(A15,1,FIND(":",A15)-1)) -> fiscalyear | I15: =IF(ISNUMBER(SEARCH("@",A15)),"",TRIM(SUBSTITUTE(SUBSTITUTE(TRIM(MID(A15,FIND(":",A15)+1,LEN(A15))),";",""),"not null",""))) -> gjahr | K15: fiscalyear : gjahr; | P15: =TRIM(SUBSTITUTE(MID(K15,1,FIND(":",K15)-1),"key","")) -> fiscalyear | Q15: =TRIM(MID(K15,FIND(":",K15)+1,LEN(K15))) -> gjahr; | AC15: =IF(ISNUMBER(SEARCH("@",H13)),A13,H13&" : "&IF(AD15="",I13,AD15)&";") -> purpose : abap.char(13); | AD15: ="abap.char("&AE15&")" -> abap.char(13) | AE15: 13
A16: document : zde_document; | H16: =TRIM(MID(A16,1,FIND(":",A16)-1)) -> document | I16: =IF(ISNUMBER(SEARCH("@",A16)),"",TRIM(SUBSTITUTE(SUBSTITUTE(TRIM(MID(A16,FIND(":",A16)+1,LEN(A16))),";",""),"not null",""))) -> zde_document | K16: document : abap.char(12); | P16: =TRIM(SUBSTITUTE(MID(K16,1,FIND(":",K16)-1),"key","")) -> document | Q16: =TRIM(MID(K16,FIND(":",K16)+1,LEN(K16))) -> abap.char(12); | AC16: =IF(ISNUMBER(SEARCH("@",H14)),A14,H14&" : "&IF(AD16="",I14,AD16)&";") -> sapmodule : abap.char(2); | AD16: ="abap.char("&AE16&")" -> abap.char(2) | AE16: 2
A17: branch : bupla; | H17: =TRIM(MID(A17,1,FIND(":",A17)-1)) -> branch | I17: =IF(ISNUMBER(SEARCH("@",A17)),"",TRIM(SUBSTITUTE(SUBSTITUTE(TRIM(MID(A17,FIND(":",A17)+1,LEN(A17))),";",""),"not null",""))) -> bupla | K17: branch : bupla; | P17: =TRIM(SUBSTITUTE(MID(K17,1,FIND(":",K17)-1),"key","")) -> branch | Q17: =TRIM(MID(K17,FIND(":",K17)+1,LEN(K17))) -> bupla; | AC17: =IF(ISNUMBER(SEARCH("@",H15)),A15,H15&" : "&IF(AD17="",I15,AD17)&";") -> fiscalyear : gjahr;
A18: locationname : zde_locationlegalname; | H18: =TRIM(MID(A18,1,FIND(":",A18)-1)) -> locationname | I18: =IF(ISNUMBER(SEARCH("@",A18)),"",TRIM(SUBSTITUTE(SUBSTITUTE(TRIM(MID(A18,FIND(":",A18)+1,LEN(A18))),";",""),"not null",""))) -> zde_locationlegalname | K18: locationname : abap.char(50); | P18: =TRIM(SUBSTITUTE(MID(K18,1,FIND(":",K18)-1),"key","")) -> locationname | Q18: =TRIM(MID(K18,FIND(":",K18)+1,LEN(K18))) -> abap.char(50); | AC18: =IF(ISNUMBER(SEARCH("@",H16)),A16,H16&" : "&IF(AD18="",I16,AD18)&";") -> document : abap.char(12); | AD18: ="abap.char("&AE18&")" -> abap.char(12) | AE18: 12
A19: returnperiod : zde_returnperiod; | H19: =TRIM(MID(A19,1,FIND(":",A19)-1)) -> returnperiod | I19: =IF(ISNUMBER(SEARCH("@",A19)),"",TRIM(SUBSTITUTE(SUBSTITUTE(TRIM(MID(A19,FIND(":",A19)+1,LEN(A19))),";",""),"not null",""))) -> zde_returnperiod | K19: returnperiod : abap.char(6); | P19: =TRIM(SUBSTITUTE(MID(K19,1,FIND(":",K19)-1),"key","")) -> returnperiod | Q19: =TRIM(MID(K19,FIND(":",K19)+1,LEN(K19))) -> abap.char(6); | AC19: =IF(ISNUMBER(SEARCH("@",H17)),A17,H17&" : "&IF(AD19="",I17,AD19)&";") -> branch : bupla;
A20: liabilitydischargereturnperiod : zde_lie_dis_period; | H20: =TRIM(MID(A20,1,FIND(":",A20)-1)) -> liabilitydischargereturnperiod | I20: =IF(ISNUMBER(SEARCH("@",A20)),"",TRIM(SUBSTITUTE(SUBSTITUTE(TRIM(MID(A20,FIND(":",A20)+1,LEN(A20))),";",""),"not null",""))) -> zde_lie_dis_period | K20: liabilitydischargereturnperiod : abap.char(20); | P20: =TRIM(SUBSTITUTE(MID(K20,1,FIND(":",K20)-1),"key","")) -> liabilitydischargereturnperiod | Q20: =TRIM(MID(K20,FIND(":",K20)+1,LEN(K20))) -> abap.char(20); | AC20: =IF(ISNUMBER(SEARCH("@",H18)),A18,H18&" : "&IF(AD20="",I18,AD20)&";") -> locationname : abap.char(50); | AD20: ="abap.char("&AE20&")" -> abap.char(50) | AE20: 50
A21: autopushorgenerate : zde_auto_push_period; | H21: =TRIM(MID(A21,1,FIND(":",A21)-1)) -> autopushorgenerate | I21: =IF(ISNUMBER(SEARCH("@",A21)),"",TRIM(SUBSTITUTE(SUBSTITUTE(TRIM(MID(A21,FIND(":",A21)+1,LEN(A21))),";",""),"not null",""))) -> zde_auto_push_period | K21: autopushorgenerate : abap.char(20); | P21: =TRIM(SUBSTITUTE(MID(K21,1,FIND(":",K21)-1),"key","")) -> autopushorgenerate | Q21: =TRIM(MID(K21,FIND(":",K21)+1,LEN(K21))) -> abap.char(20); | AC21: =IF(ISNUMBER(SEARCH("@",H19)),A19,H19&" : "&IF(AD21="",I19,AD21)&";") -> returnperiod : abap.char(6); | AD21: ="abap.char("&AE21&")" -> abap.char(6) | AE21: 6
A22: supplytype : zde_supplytype; | H22: =TRIM(MID(A22,1,FIND(":",A22)-1)) -> supplytype | I22: =IF(ISNUMBER(SEARCH("@",A22)),"",TRIM(SUBSTITUTE(SUBSTITUTE(TRIM(MID(A22,FIND(":",A22)+1,LEN(A22))),";",""),"not null",""))) -> zde_supplytype | K22: supplytype : abap.char(1); | P22: =TRIM(SUBSTITUTE(MID(K22,1,FIND(":",K22)-1),"key","")) -> supplytype | Q22: =TRIM(MID(K22,FIND(":",K22)+1,LEN(K22))) -> abap.char(1); | AC22: =IF(ISNUMBER(SEARCH("@",H20)),A20,H20&" : "&IF(AD22="",I20,AD22)&";") -> liabilitydischargereturnperiod : abap.char(20); | AD22: ="abap.char("&AE22&")" -> abap.char(20) | AE22: 20
A23: irn : zde_irn1; | H23: =TRIM(MID(A23,1,FIND(":",A23)-1)) -> irn | I23: =IF(ISNUMBER(SEARCH("@",A23)),"",TRIM(SUBSTITUTE(SUBSTITUTE(TRIM(MID(A23,FIND(":",A23)+1,LEN(A23))),";",""),"not null",""))) -> zde_irn1 | K23: irn : abap.char(64); | P23: =TRIM(SUBSTITUTE(MID(K23,1,FIND(":",K23)-1),"key","")) -> irn | Q23: =TRIM(MID(K23,FIND(":",K23)+1,LEN(K23))) -> abap.char(64); | AC23: =IF(ISNUMBER(SEARCH("@",H21)),A21,H21&" : "&IF(AD23="",I21,AD23)&";") -> autopushorgenerate : abap.char(20); | AD23: ="abap.char("&AE23&")" -> abap.char(20) | AE23: 20
A24: documenttype : zde_documenttype; | H24: =TRIM(MID(A24,1,FIND(":",A24)-1)) -> documenttype | I24: =IF(ISNUMBER(SEARCH("@",A24)),"",TRIM(SUBSTITUTE(SUBSTITUTE(TRIM(MID(A24,FIND(":",A24)+1,LEN(A24))),";",""),"not null",""))) -> zde_documenttype | K24: documenttype : abap.char(3); | P24: =TRIM(SUBSTITUTE(MID(K24,1,FIND(":",K24)-1),"key","")) -> documenttype | Q24: =TRIM(MID(K24,FIND(":",K24)+1,LEN(K24))) -> abap.char(3); | AC24: =IF(ISNUMBER(SEARCH("@",H22)),A22,H22&" : "&IF(AD24="",I22,AD24)&";") -> supplytype : abap.char(1); | AD24: ="abap.char("&AE24&")" -> abap.char(1) | AE24: 1
A25: transactiontype : zde_transactiontype; | H25: =TRIM(MID(A25,1,FIND(":",A25)-1)) -> transactiontype | I25: =IF(ISNUMBER(SEARCH("@",A25)),"",TRIM(SUBSTITUTE(SUBSTITUTE(TRIM(MID(A25,FIND(":",A25)+1,LEN(A25))),";",""),"not null",""))) -> zde_transactiontype | K25: transactiontype : abap.char(6); | P25: =TRIM(SUBSTITUTE(MID(K25,1,FIND(":",K25)-1),"key","")) -> transactiontype | Q25: =TRIM(MID(K25,FIND(":",K25)+1,LEN(K25))) -> abap.char(6); | AC25: =IF(ISNUMBER(SEARCH("@",H23)),A23,H23&" : "&IF(AD25="",I23,AD25)&";") -> irn : abap.char(64); | AD25: ="abap.char("&AE25&")" -> abap.char(64) | AE25: 64
A26: dtatransaction : char50; | H26: =TRIM(MID(A26,1,FIND(":",A26)-1)) -> dtatransaction | I26: =IF(ISNUMBER(SEARCH("@",A26)),"",TRIM(SUBSTITUTE(SUBSTITUTE(TRIM(MID(A26,FIND(":",A26)+1,LEN(A26))),";",""),"not null",""))) -> char50 | K26: dtatransaction : char50; | P26: =TRIM(SUBSTITUTE(MID(K26,1,FIND(":",K26)-1),"key","")) -> dtatransaction | Q26: =TRIM(MID(K26,FIND(":",K26)+1,LEN(K26))) -> char50; | AC26: =IF(ISNUMBER(SEARCH("@",H24)),A24,H24&" : "&IF(AD26="",I24,AD26)&";") -> documenttype : abap.char(3); | AD26: ="abap.char("&AE26&")" -> abap.char(3) | AE26: 3
A27: transactiontypedescription : zde_transaction_type_des; | H27: =TRIM(MID(A27,1,FIND(":",A27)-1)) -> transactiontypedescription | I27: =IF(ISNUMBER(SEARCH("@",A27)),"",TRIM(SUBSTITUTE(SUBSTITUTE(TRIM(MID(A27,FIND(":",A27)+1,LEN(A27))),";",""),"not null",""))) -> zde_transaction_type_des | K27: transactiontypedescription : abap.char(30); | P27: =TRIM(SUBSTITUTE(MID(K27,1,FIND(":",K27)-1),"key","")) -> transactiontypedescription | Q27: =TRIM(MID(K27,FIND(":",K27)+1,LEN(K27))) -> abap.char(30); | AC27: =IF(ISNUMBER(SEARCH("@",H25)),A25,H25&" : "&IF(AD27="",I25,AD27)&";") -> transactiontype : abap.char(6); | AD27: ="abap.char("&AE27&")" -> abap.char(6) | AE27: 6
A28: seriescode : zde_seriescode; | H28: =TRIM(MID(A28,1,FIND(":",A28)-1)) -> seriescode | I28: =IF(ISNUMBER(SEARCH("@",A28)),"",TRIM(SUBSTITUTE(SUBSTITUTE(TRIM(MID(A28,FIND(":",A28)+1,LEN(A28))),";",""),"not null",""))) -> zde_seriescode | K28: seriescode : abap.char(15); | P28: =TRIM(SUBSTITUTE(MID(K28,1,FIND(":",K28)-1),"key","")) -> seriescode | Q28: =TRIM(MID(K28,FIND(":",K28)+1,LEN(K28))) -> abap.char(15); | AC28: =IF(ISNUMBER(SEARCH("@",H26)),A26,H26&" : "&IF(AD28="",I26,AD28)&";") -> dtatransaction : char50;
A29: referencedocumentnumber : zde_referencedocumentnumber; | H29: =TRIM(MID(A29,1,FIND(":",A29)-1)) -> referencedocumentnumber | I29: =IF(ISNUMBER(SEARCH("@",A29)),"",TRIM(SUBSTITUTE(SUBSTITUTE(TRIM(MID(A29,FIND(":",A29)+1,LEN(A29))),";",""),"not null",""))) -> zde_referencedocumentnumber | K29: referencedocumentnumber : abap.char(16); | P29: =TRIM(SUBSTITUTE(MID(K29,1,FIND(":",K29)-1),"key","")) -> referencedocumentnumber | Q29: =TRIM(MID(K29,FIND(":",K29)+1,LEN(K29))) -> abap.char(16); | AC29: =IF(ISNUMBER(SEARCH("@",H27)),A27,H27&" : "&IF(AD29="",I27,AD29)&";") -> transactiontypedescription : abap.char(30); | AD29: ="abap.char("&AE29&")" -> abap.char(30) | AE29: 30
A30: referencedocumentdate : zde_referencedocumentdate; | H30: =TRIM(MID(A30,1,FIND(":",A30)-1)) -> referencedocumentdate | I30: =IF(ISNUMBER(SEARCH("@",A30)),"",TRIM(SUBSTITUTE(SUBSTITUTE(TRIM(MID(A30,FIND(":",A30)+1,LEN(A30))),";",""),"not null",""))) -> zde_referencedocumentdate | K30: referencedocumentdate : abap.char(10); | P30: =TRIM(SUBSTITUTE(MID(K30,1,FIND(":",K30)-1),"key","")) -> referencedocumentdate | Q30: =TRIM(MID(K30,FIND(":",K30)+1,LEN(K30))) -> abap.char(10); | AC30: =IF(ISNUMBER(SEARCH("@",H28)),A28,H28&" : "&IF(AD30="",I28,AD30)&";") -> seriescode : abap.char();); | AD30: ="abap.char("&AE30&")" -> abap.char();) | AE30: =TRIM(IF(ISNUMBER(SEARCH("char",Q30)),RIGHT(Q30,2))) -> );
A31: transactionmode : zde_transactionmode; | H31: =TRIM(MID(A31,1,FIND(":",A31)-1)) -> transactionmode | I31: =IF(ISNUMBER(SEARCH("@",A31)),"",TRIM(SUBSTITUTE(SUBSTITUTE(TRIM(MID(A31,FIND(":",A31)+1,LEN(A31))),";",""),"not null",""))) -> zde_transactionmode | K31: transactionmode : abap.char(20); | P31: =TRIM(SUBSTITUTE(MID(K31,1,FIND(":",K31)-1),"key","")) -> transactionmode | Q31: =TRIM(MID(K31,FIND(":",K31)+1,LEN(K31))) -> abap.char(20); | AC31: =IF(ISNUMBER(SEARCH("@",H29)),A29,H29&" : "&IF(AD31="",I29,AD31)&";") -> referencedocumentnumber : abap.char();); | AD31: ="abap.char("&AE31&")" -> abap.char();) | AE31: =TRIM(IF(ISNUMBER(SEARCH("char",Q31)),RIGHT(Q31,2))) -> );
A32: billfromgstin : zde_billfromgstin1; | H32: =TRIM(MID(A32,1,FIND(":",A32)-1)) -> billfromgstin | I32: =IF(ISNUMBER(SEARCH("@",A32)),"",TRIM(SUBSTITUTE(SUBSTITUTE(TRIM(MID(A32,FIND(":",A32)+1,LEN(A32))),";",""),"not null",""))) -> zde_billfromgstin1 | K32: billfromgstin : abap.char(15); | P32: =TRIM(SUBSTITUTE(MID(K32,1,FIND(":",K32)-1),"key","")) -> billfromgstin | Q32: =TRIM(MID(K32,FIND(":",K32)+1,LEN(K32))) -> abap.char(15); | AC32: =IF(ISNUMBER(SEARCH("@",H30)),A30,H30&" : "&IF(AD32="",I30,AD32)&";") -> referencedocumentdate : abap.char();); | AD32: ="abap.char("&AE32&")" -> abap.char();) | AE32: =TRIM(IF(ISNUMBER(SEARCH("char",Q32)),RIGHT(Q32,2))) -> );
A33: billfromlegalname : zde_billfromlegalname; | H33: =TRIM(MID(A33,1,FIND(":",A33)-1)) -> billfromlegalname | I33: =IF(ISNUMBER(SEARCH("@",A33)),"",TRIM(SUBSTITUTE(SUBSTITUTE(TRIM(MID(A33,FIND(":",A33)+1,LEN(A33))),";",""),"not null",""))) -> zde_billfromlegalname | K33: billfromlegalname : abap.char(50); | P33: =TRIM(SUBSTITUTE(MID(K33,1,FIND(":",K33)-1),"key","")) -> billfromlegalname | Q33: =TRIM(MID(K33,FIND(":",K33)+1,LEN(K33))) -> abap.char(50); | AC33: =IF(ISNUMBER(SEARCH("@",H31)),A31,H31&" : "&IF(AD33="",I31,AD33)&";") -> transactionmode : abap.char();); | AD33: ="abap.char("&AE33&")" -> abap.char();) | AE33: =TRIM(IF(ISNUMBER(SEARCH("char",Q33)),RIGHT(Q33,2))) -> );
A34: billfromtradename : zde_billfromtradename; | H34: =TRIM(MID(A34,1,FIND(":",A34)-1)) -> billfromtradename | I34: =IF(ISNUMBER(SEARCH("@",A34)),"",TRIM(SUBSTITUTE(SUBSTITUTE(TRIM(MID(A34,FIND(":",A34)+1,LEN(A34))),";",""),"not null",""))) -> zde_billfromtradename | K34: billfromtradename : abap.char(30); | P34: =TRIM(SUBSTITUTE(MID(K34,1,FIND(":",K34)-1),"key","")) -> billfromtradename | Q34: =TRIM(MID(K34,FIND(":",K34)+1,LEN(K34))) -> abap.char(30); | AC34: =IF(ISNUMBER(SEARCH("@",H32)),A32,H32&" : "&IF(AD34="",I32,AD34)&";") -> billfromgstin : abap.char();); | AD34: ="abap.char("&AE34&")" -> abap.char();) | AE34: =TRIM(IF(ISNUMBER(SEARCH("char",Q34)),RIGHT(Q34,2))) -> );
A35: billfrombuildingno : zde_billfrombuildingno; | H35: =TRIM(MID(A35,1,FIND(":",A35)-1)) -> billfrombuildingno | I35: =IF(ISNUMBER(SEARCH("@",A35)),"",TRIM(SUBSTITUTE(SUBSTITUTE(TRIM(MID(A35,FIND(":",A35)+1,LEN(A35))),";",""),"not null",""))) -> zde_billfrombuildingno | K35: billfrombuildingno : abap.char(60); | P35: =TRIM(SUBSTITUTE(MID(K35,1,FIND(":",K35)-1),"key","")) -> billfrombuildingno | Q35: =TRIM(MID(K35,FIND(":",K35)+1,LEN(K35))) -> abap.char(60); | AC35: =IF(ISNUMBER(SEARCH("@",H33)),A33,H33&" : "&IF(AD35="",I33,AD35)&";") -> billfromlegalname : abap.char();); | AD35: ="abap.char("&AE35&")" -> abap.char();) | AE35: =TRIM(IF(ISNUMBER(SEARCH("char",Q35)),RIGHT(Q35,2))) -> );
A36: billfrombuildingname : zde_billfrombuildingname; | H36: =TRIM(MID(A36,1,FIND(":",A36)-1)) -> billfrombuildingname | I36: =IF(ISNUMBER(SEARCH("@",A36)),"",TRIM(SUBSTITUTE(SUBSTITUTE(TRIM(MID(A36,FIND(":",A36)+1,LEN(A36))),";",""),"not null",""))) -> zde_billfrombuildingname | K36: billfrombuildingname : abap.char(60); | P36: =TRIM(SUBSTITUTE(MID(K36,1,FIND(":",K36)-1),"key","")) -> billfrombuildingname | Q36: =TRIM(MID(K36,FIND(":",K36)+1,LEN(K36))) -> abap.char(60); | AC36: =IF(ISNUMBER(SEARCH("@",H34)),A34,H34&" : "&IF(AD36="",I34,AD36)&";") -> billfromtradename : abap.char();); | AD36: ="abap.char("&AE36&")" -> abap.char();) | AE36: =TRIM(IF(ISNUMBER(SEARCH("char",Q36)),RIGHT(Q36,2))) -> );
A37: billfromflatno : zde_billfromflatno; | H37: =TRIM(MID(A37,1,FIND(":",A37)-1)) -> billfromflatno | I37: =IF(ISNUMBER(SEARCH("@",A37)),"",TRIM(SUBSTITUTE(SUBSTITUTE(TRIM(MID(A37,FIND(":",A37)+1,LEN(A37))),";",""),"not null",""))) -> zde_billfromflatno | K37: billfromflatno : abap.char(10); | P37: =TRIM(SUBSTITUTE(MID(K37,1,FIND(":",K37)-1),"key","")) -> billfromflatno | Q37: =TRIM(MID(K37,FIND(":",K37)+1,LEN(K37))) -> abap.char(10); | AC37: =IF(ISNUMBER(SEARCH("@",H35)),A35,H35&" : "&IF(AD37="",I35,AD37)&";") -> billfrombuildingno : abap.char();); | AD37: ="abap.char("&AE37&")" -> abap.char();) | AE37: =TRIM(IF(ISNUMBER(SEARCH("char",Q37)),RIGHT(Q37,2))) -> );
A38: billfromaddress1 : zde_billfromaddress1; | H38: =TRIM(MID(A38,1,FIND(":",A38)-1)) -> billfromaddress1 | I38: =IF(ISNUMBER(SEARCH("@",A38)),"",TRIM(SUBSTITUTE(SUBSTITUTE(TRIM(MID(A38,FIND(":",A38)+1,LEN(A38))),";",""),"not null",""))) -> zde_billfromaddress1 | K38: billfromaddress1 : abap.char(50); | P38: =TRIM(SUBSTITUTE(MID(K38,1,FIND(":",K38)-1),"key","")) -> billfromaddress1 | Q38: =TRIM(MID(K38,FIND(":",K38)+1,LEN(K38))) -> abap.char(50); | AC38: =IF(ISNUMBER(SEARCH("@",H36)),A36,H36&" : "&IF(AD38="",I36,AD38)&";") -> billfrombuildingname : abap.char();); | AD38: ="abap.char("&AE38&")" -> abap.char();) | AE38: =TRIM(IF(ISNUMBER(SEARCH("char",Q38)),RIGHT(Q38,2))) -> );
A39: billfromaddress2 : zde_billfromaddress2; | H39: =TRIM(MID(A39,1,FIND(":",A39)-1)) -> billfromaddress2 | I39: =IF(ISNUMBER(SEARCH("@",A39)),"",TRIM(SUBSTITUTE(SUBSTITUTE(TRIM(MID(A39,FIND(":",A39)+1,LEN(A39))),";",""),"not null",""))) -> zde_billfromaddress2 | K39: billfromaddress2 : abap.char(50); | P39: =TRIM(SUBSTITUTE(MID(K39,1,FIND(":",K39)-1),"key","")) -> billfromaddress2 | Q39: =TRIM(MID(K39,FIND(":",K39)+1,LEN(K39))) -> abap.char(50); | AC39: =IF(ISNUMBER(SEARCH("@",H37)),A37,H37&" : "&IF(AD39="",I37,AD39)&";") -> billfromflatno : abap.char();); | AD39: ="abap.char("&AE39&")" -> abap.char();) | AE39: =TRIM(IF(ISNUMBER(SEARCH("char",Q39)),RIGHT(Q39,2))) -> );
A40: billfromcity : zde_billfromcity1; | H40: =TRIM(MID(A40,1,FIND(":",A40)-1)) -> billfromcity | I40: =IF(ISNUMBER(SEARCH("@",A40)),"",TRIM(SUBSTITUTE(SUBSTITUTE(TRIM(MID(A40,FIND(":",A40)+1,LEN(A40))),";",""),"not null",""))) -> zde_billfromcity1 | K40: billfromcity : abap.char(60); | P40: =TRIM(SUBSTITUTE(MID(K40,1,FIND(":",K40)-1),"key","")) -> billfromcity | Q40: =TRIM(MID(K40,FIND(":",K40)+1,LEN(K40))) -> abap.char(60); | AC40: =IF(ISNUMBER(SEARCH("@",H38)),A38,H38&" : "&IF(AD40="",I38,AD40)&";") -> billfromaddress1 : abap.char();); | AD40: ="abap.char("&AE40&")" -> abap.char();) | AE40: =TRIM(IF(ISNUMBER(SEARCH("char",Q40)),RIGHT(Q40,2))) -> );
A41: billfromdistrict : zde_billfromdistrict; | H41: =TRIM(MID(A41,1,FIND(":",A41)-1)) -> billfromdistrict | I41: =IF(ISNUMBER(SEARCH("@",A41)),"",TRIM(SUBSTITUTE(SUBSTITUTE(TRIM(MID(A41,FIND(":",A41)+1,LEN(A41))),";",""),"not null",""))) -> zde_billfromdistrict | K41: billfromdistrict : abap.char(60); | P41: =TRIM(SUBSTITUTE(MID(K41,1,FIND(":",K41)-1),"key","")) -> billfromdistrict | Q41: =TRIM(MID(K41,FIND(":",K41)+1,LEN(K41))) -> abap.char(60); | AC41: =IF(ISNUMBER(SEARCH("@",H39)),A39,H39&" : "&IF(AD41="",I39,AD41)&";") -> billfromaddress2 : abap.char();); | AD41: ="abap.char("&AE41&")" -> abap.char();) | AE41: =TRIM(IF(ISNUMBER(SEARCH("char",Q41)),RIGHT(Q41,2))) -> );
... A52: dispatchfromadd2 : zde_dispatch_from_address2; | H52: =TRIM(MID(A52,1,FIND(":",A52)-1)) -> dispatchfromadd2 | I52: =IF(ISNUMBER(SEARCH("@",A52)),"",TRIM(SUBSTITUTE(SUBSTITUTE(TRIM(MID(A52,FIND(":",A52)+1,LEN(A52))),";",""),"not null",""))) -> zde_dispatch_from_address2 | K52: dispatchfromadd2 : abap.char(100); | P52: =TRIM(SUBSTITUTE(MID(K52,1,FIND(":",K52)-1),"key","")) -> dispatchfromadd2 | Q52: =TRIM(MID(K52,FIND(":",K52)+1,LEN(K52))) -> abap.char(100); | AC52: =IF(ISNUMBER(SEARCH("@",H50)),A50,H50&" : "&IF(AD52="",I50,AD52)&";") -> dispatchfromflatnumber : abap.char();); | AD52: ="abap.char("&AE52&")" -> abap.char();) | AE52: =TRIM(IF(ISNUMBER(SEARCH("char",Q52)),RIGHT(Q52,2))) -> );
A53: dispatchfromcity : zde_dispatch_from_city; | H53: =TRIM(MID(A53,1,FIND(":",A53)-1)) -> dispatchfromcity | I53: =IF(ISNUMBER(SEARCH("@",A53)),"",TRIM(SUBSTITUTE(SUBSTITUTE(TRIM(MID(A53,FIND(":",A53)+1,LEN(A53))),";",""),"not null",""))) -> zde_dispatch_from_city | K53: dispatchfromcity : abap.char(50); | P53: =TRIM(SUBSTITUTE(MID(K53,1,FIND(":",K53)-1),"key","")) -> dispatchfromcity | Q53: =TRIM(MID(K53,FIND(":",K53)+1,LEN(K53))) -> abap.char(50); | AC53: =IF(ISNUMBER(SEARCH("@",H51)),A51,H51&" : "&IF(AD53="",I51,AD53)&";") -> dispatchfromadd1 : abap.char(100); | AD53: ="abap.char("&AE53&")" -> abap.char(100) | AE53: 100
A54: dispatchfromdistrict : zde_dis_from_district; | H54: =TRIM(MID(A54,1,FIND(":",A54)-1)) -> dispatchfromdistrict | I54: =IF(ISNUMBER(SEARCH("@",A54)),"",TRIM(SUBSTITUTE(SUBSTITUTE(TRIM(MID(A54,FIND(":",A54)+1,LEN(A54))),";",""),"not null",""))) -> zde_dis_from_district | K54: dispatchfromdistrict : abap.char(60); | P54: =TRIM(SUBSTITUTE(MID(K54,1,FIND(":",K54)-1),"key","")) -> dispatchfromdistrict | Q54: =TRIM(MID(K54,FIND(":",K54)+1,LEN(K54))) -> abap.char(60); | AC54: =IF(ISNUMBER(SEARCH("@",H52)),A52,H52&" : "&IF(AD54="",I52,AD54)&";") -> dispatchfromadd2 : abap.char(100); | AD54: ="abap.char("&AE54&")" -> abap.char(100) | AE54: 100
A55: dispatchfromstatecode : zde_dispatch_from_state; | H55: =TRIM(MID(A55,1,FIND(":",A55)-1)) -> dispatchfromstatecode | I55: =IF(ISNUMBER(SEARCH("@",A55)),"",TRIM(SUBSTITUTE(SUBSTITUTE(TRIM(MID(A55,FIND(":",A55)+1,LEN(A55))),";",""),"not null",""))) -> zde_dispatch_from_state | K55: dispatchfromstatecode : abap.char(50); | P55: =TRIM(SUBSTITUTE(MID(K55,1,FIND(":",K55)-1),"key","")) -> dispatchfromstatecode | Q55: =TRIM(MID(K55,FIND(":",K55)+1,LEN(K55))) -> abap.char(50); | AC55: =IF(ISNUMBER(SEARCH("@",H53)),A53,H53&" : "&IF(AD55="",I53,AD55)&";") -> dispatchfromcity : abap.char();); | AD55: ="abap.char("&AE55&")" -> abap.char();) | AE55: =TRIM(IF(ISNUMBER(SEARCH("char",Q55)),RIGHT(Q55,2))) -> );
A56: dispatchfrompincode : zde_dispatch_from_pincode; | H56: =TRIM(MID(A56,1,FIND(":",A56)-1)) -> dispatchfrompincode | I56: =IF(ISNUMBER(SEARCH("@",A56)),"",TRIM(SUBSTITUTE(SUBSTITUTE(TRIM(MID(A56,FIND(":",A56)+1,LEN(A56))),";",""),"not null",""))) -> zde_dispatch_from_pincode | K56: dispatchfrompincode : abap.char(6); | P56: =TRIM(SUBSTITUTE(MID(K56,1,FIND(":",K56)-1),"key","")) -> dispatchfrompincode | Q56: =TRIM(MID(K56,FIND(":",K56)+1,LEN(K56))) -> abap.char(6); | AC56: =IF(ISNUMBER(SEARCH("@",H54)),A54,H54&" : "&IF(AD56="",I54,AD56)&";") -> dispatchfromdistrict : abap.char();); | AD56: ="abap.char("&AE56&")" -> abap.char();) | AE56: =TRIM(IF(ISNUMBER(SEARCH("char",Q56)),RIGHT(Q56,2))) -> );
A57: dispatchfromphone : zde_dis_from_phone; | H57: =TRIM(MID(A57,1,FIND(":",A57)-1)) -> dispatchfromphone | I57: =IF(ISNUMBER(SEARCH("@",A57)),"",TRIM(SUBSTITUTE(SUBSTITUTE(TRIM(MID(A57,FIND(":",A57)+1,LEN(A57))),";",""),"not null",""))) -> zde_dis_from_phone | K57: dispatchfromphone : abap.char(10); | P57: =TRIM(SUBSTITUTE(MID(K57,1,FIND(":",K57)-1),"key","")) -> dispatchfromphone | Q57: =TRIM(MID(K57,FIND(":",K57)+1,LEN(K57))) -> abap.char(10); | AC57: =IF(ISNUMBER(SEARCH("@",H55)),A55,H55&" : "&IF(AD57="",I55,AD57)&";") -> dispatchfromstatecode : abap.char();); | AD57: ="abap.char("&AE57&")" -> abap.char();) | AE57: =TRIM(IF(ISNUMBER(SEARCH("char",Q57)),RIGHT(Q57,2))) -> );
A58: dispatchfromemail : zde_dispatchfromemail; | H58: =TRIM(MID(A58,1,FIND(":",A58)-1)) -> dispatchfromemail | I58: =IF(ISNUMBER(SEARCH("@",A58)),"",TRIM(SUBSTITUTE(SUBSTITUTE(TRIM(MID(A58,FIND(":",A58)+1,LEN(A58))),";",""),"not null",""))) -> zde_dispatchfromemail | K58: dispatchfromemail : abap.char(50); | P58: =TRIM(SUBSTITUTE(MID(K58,1,FIND(":",K58)-1),"key","")) -> dispatchfromemail | Q58: =TRIM(MID(K58,FIND(":",K58)+1,LEN(K58))) -> abap.char(50); | AC58: =IF(ISNUMBER(SEARCH("@",H56)),A56,H56&" : "&IF(AD58="",I56,AD58)&";") -> dispatchfrompincode : abap.char();); | AD58: ="abap.char("&AE58&")" -> abap.char();) | AE58: =TRIM(IF(ISNUMBER(SEARCH("char",Q58)),RIGHT(Q58,2))) -> );
A59: billtogstin : zde_bill_to_gstin; | H59: =TRIM(MID(A59,1,FIND(":",A59)-1)) -> billtogstin | I59: =IF(ISNUMBER(SEARCH("@",A59)),"",TRIM(SUBSTITUTE(SUBSTITUTE(TRIM(MID(A59,FIND(":",A59)+1,LEN(A59))),";",""),"not null",""))) -> zde_bill_to_gstin | K59: billtogstin : abap.char(15); | P59: =TRIM(SUBSTITUTE(MID(K59,1,FIND(":",K59)-1),"key","")) -> billtogstin | Q59: =TRIM(MID(K59,FIND(":",K59)+1,LEN(K59))) -> abap.char(15); | AC59: =IF(ISNUMBER(SEARCH("@",H57)),A57,H57&" : "&IF(AD59="",I57,AD59)&";") -> dispatchfromphone : abap.char();); | AD59: ="abap.char("&AE59&")" -> abap.char();) | AE59: =TRIM(IF(ISNUMBER(SEARCH("char",Q59)),RIGHT(Q59,2))) -> );
A60: billtolegalname : zde_bill_to_leg_name; | H60: =TRIM(MID(A60,1,FIND(":",A60)-1)) -> billtolegalname | I60: =IF(ISNUMBER(SEARCH("@",A60)),"",TRIM(SUBSTITUTE(SUBSTITUTE(TRIM(MID(A60,FIND(":",A60)+1,LEN(A60))),";",""),"not null",""))) -> zde_bill_to_leg_name | K60: billtolegalname : abap.char(50); | P60: =TRIM(SUBSTITUTE(MID(K60,1,FIND(":",K60)-1),"key","")) -> billtolegalname | Q60: =TRIM(MID(K60,FIND(":",K60)+1,LEN(K60))) -> abap.char(50); | AC60: =IF(ISNUMBER(SEARCH("@",H58)),A58,H58&" : "&IF(AD60="",I58,AD60)&";") -> dispatchfromemail : abap.char();); | AD60: ="abap.char("&AE60&")" -> abap.char();) | AE60: =TRIM(IF(ISNUMBER(SEARCH("char",Q60)),RIGHT(Q60,2))) -> );
A61: billtotradename : zde_bill_to_trade_name; | H61: =TRIM(MID(A61,1,FIND(":",A61)-1)) -> billtotradename | I61: =IF(ISNUMBER(SEARCH("@",A61)),"",TRIM(SUBSTITUTE(SUBSTITUTE(TRIM(MID(A61,FIND(":",A61)+1,LEN(A61))),";",""),"not null",""))) -> zde_bill_to_trade_name | K61: billtotradename : abap.char(100); | P61: =TRIM(SUBSTITUTE(MID(K61,1,FIND(":",K61)-1),"key","")) -> billtotradename | Q61: =TRIM(MID(K61,FIND(":",K61)+1,LEN(K61))) -> abap.char(100); | AC61: =IF(ISNUMBER(SEARCH("@",H59)),A59,H59&" : "&IF(AD61="",I59,AD61)&";") -> billtogstin : abap.char();); | AD61: ="abap.char("&AE61&")" -> abap.char();) | AE61: =TRIM(IF(ISNUMBER(SEARCH("char",Q61)),RIGHT(Q61,2))) -> );
A62: billtobuildingnumber : zde_bill_to_building_n0; | H62: =TRIM(MID(A62,1,FIND(":",A62)-1)) -> billtobuildingnumber | I62: =IF(ISNUMBER(SEARCH("@",A62)),"",TRIM(SUBSTITUTE(SUBSTITUTE(TRIM(MID(A62,FIND(":",A62)+1,LEN(A62))),";",""),"not null",""))) -> zde_bill_to_building_n0 | K62: billtobuildingnumber : abap.char(60); | P62: =TRIM(SUBSTITUTE(MID(K62,1,FIND(":",K62)-1),"key","")) -> billtobuildingnumber | Q62: =TRIM(MID(K62,FIND(":",K62)+1,LEN(K62))) -> abap.char(60); | AC62: =IF(ISNUMBER(SEARCH("@",H60)),A60,H60&" : "&IF(AD62="",I60,AD62)&";") -> billtolegalname : abap.char();); | AD62: ="abap.char("&AE62&")" -> abap.char();) | AE62: =TRIM(IF(ISNUMBER(SEARCH("char",Q62)),RIGHT(Q62,2))) -> );
A63: billtobuildingname : zde_bill_to_building_name; | H63: =TRIM(MID(A63,1,FIND(":",A63)-1)) -> billtobuildingname | I63: =IF(ISNUMBER(SEARCH("@",A63)),"",TRIM(SUBSTITUTE(SUBSTITUTE(TRIM(MID(A63,FIND(":",A63)+1,LEN(A63))),";",""),"not null",""))) -> zde_bill_to_building_name | K63: billtobuildingname : abap.char(100); | P63: =TRIM(SUBSTITUTE(MID(K63,1,FIND(":",K63)-1),"key","")) -> billtobuildingname | Q63: =TRIM(MID(K63,FIND(":",K63)+1,LEN(K63))) -> abap.char(100); | AC63: =IF(ISNUMBER(SEARCH("@",H61)),A61,H61&" : "&IF(AD63="",I61,AD63)&";") -> billtotradename : abap.char(100); | AD63: ="abap.char("&AE63&")" -> abap.char(100) | AE63: 100
A64: billtoflatnumber : zde_bill_to_billtoflatnumb; | H64: =TRIM(MID(A64,1,FIND(":",A64)-1)) -> billtoflatnumber | I64: =IF(ISNUMBER(SEARCH("@",A64)),"",TRIM(SUBSTITUTE(SUBSTITUTE(TRIM(MID(A64,FIND(":",A64)+1,LEN(A64))),";",""),"not null",""))) -> zde_bill_to_billtoflatnumb | K64: billtoflatnumber : abap.char(15); | P64: =TRIM(SUBSTITUTE(MID(K64,1,FIND(":",K64)-1),"key","")) -> billtoflatnumber | Q64: =TRIM(MID(K64,FIND(":",K64)+1,LEN(K64))) -> abap.char(15); | AC64: =IF(ISNUMBER(SEARCH("@",H62)),A62,H62&" : "&IF(AD64="",I62,AD64)&";") -> billtobuildingnumber : abap.char();); | AD64: ="abap.char("&AE64&")" -> abap.char();) | AE64: =TRIM(IF(ISNUMBER(SEARCH("char",Q64)),RIGHT(Q64,2))) -> );
A65: billtoaddress1 : zde_bill_to_address1; | H65: =TRIM(MID(A65,1,FIND(":",A65)-1)) -> billtoaddress1 | I65: =IF(ISNUMBER(SEARCH("@",A65)),"",TRIM(SUBSTITUTE(SUBSTITUTE(TRIM(MID(A65,FIND(":",A65)+1,LEN(A65))),";",""),"not null",""))) -> zde_bill_to_address1 | K65: billtoaddress1 : abap.char(150); | P65: =TRIM(SUBSTITUTE(MID(K65,1,FIND(":",K65)-1),"key","")) -> billtoaddress1 | Q65: =TRIM(MID(K65,FIND(":",K65)+1,LEN(K65))) -> abap.char(150); | AC65: =IF(ISNUMBER(SEARCH("@",H63)),A63,H63&" : "&IF(AD65="",I63,AD65)&";") -> billtobuildingname : abap.char(100); | AD65: ="abap.char("&AE65&")" -> abap.char(100) | AE65: 100
A66: billtoaddress2 : zde_bill_to_address2; | H66: =TRIM(MID(A66,1,FIND(":",A66)-1)) -> billtoaddress2 | I66: =IF(ISNUMBER(SEARCH("@",A66)),"",TRIM(SUBSTITUTE(SUBSTITUTE(TRIM(MID(A66,FIND(":",A66)+1,LEN(A66))),";",""),"not null",""))) -> zde_bill_to_address2 | K66: billtoaddress2 : abap.char(150); | P66: =TRIM(SUBSTITUTE(MID(K66,1,FIND(":",K66)-1),"key","")) -> billtoaddress2 | Q66: =TRIM(MID(K66,FIND(":",K66)+1,LEN(K66))) -> abap.char(150); | AC66: =IF(ISNUMBER(SEARCH("@",H64)),A64,H64&" : "&IF(AD66="",I64,AD66)&";") -> billtoflatnumber : abap.char();); | AD66: ="abap.char("&AE66&")" -> abap.char();) | AE66: =TRIM(IF(ISNUMBER(SEARCH("char",Q66)),RIGHT(Q66,2))) -> );
A67: billtocity : zde_bill_to_city; | H67: =TRIM(MID(A67,1,FIND(":",A67)-1)) -> billtocity | I67: =IF(ISNUMBER(SEARCH("@",A67)),"",TRIM(SUBSTITUTE(SUBSTITUTE(TRIM(MID(A67,FIND(":",A67)+1,LEN(A67))),";",""),"not null",""))) -> zde_bill_to_city | K67: billtocity : abap.char(10); | P67: =TRIM(SUBSTITUTE(MID(K67,1,FIND(":",K67)-1),"key","")) -> billtocity | Q67: =TRIM(MID(K67,FIND(":",K67)+1,LEN(K67))) -> abap.char(10); | AC67: =IF(ISNUMBER(SEARCH("@",H65)),A65,H65&" : "&IF(AD67="",I65,AD67)&";") -> billtoaddress1 : abap.char(150); | AD67: ="abap.char("&AE67&")" -> abap.char(150) | AE67: 150
A68: billtodistrict : zde_bill_to_district; | H68: =TRIM(MID(A68,1,FIND(":",A68)-1)) -> billtodistrict | I68: =IF(ISNUMBER(SEARCH("@",A68)),"",TRIM(SUBSTITUTE(SUBSTITUTE(TRIM(MID(A68,FIND(":",A68)+1,LEN(A68))),";",""),"not null",""))) -> zde_bill_to_district | K68: billtodistrict : abap.char(10); | P68: =TRIM(SUBSTITUTE(MID(K68,1,FIND(":",K68)-1),"key","")) -> billtodistrict | Q68: =TRIM(MID(K68,FIND(":",K68)+1,LEN(K68))) -> abap.char(10); | AC68: =IF(ISNUMBER(SEARCH("@",H66)),A66,H66&" : "&IF(AD68="",I66,AD68)&";") -> billtoaddress2 : abap.char(150); | AD68: ="abap.char("&AE68&")" -> abap.char(150) | AE68: 150
A69: billtostatecode : zde_bill_to_statecode; | H69: =TRIM(MID(A69,1,FIND(":",A69)-1)) -> billtostatecode | I69: =IF(ISNUMBER(SEARCH("@",A69)),"",TRIM(SUBSTITUTE(SUBSTITUTE(TRIM(MID(A69,FIND(":",A69)+1,LEN(A69))),";",""),"not null",""))) -> zde_bill_to_statecode | K69: billtostatecode : abap.char(10); | P69: =TRIM(SUBSTITUTE(MID(K69,1,FIND(":",K69)-1),"key","")) -> billtostatecode | Q69: =TRIM(MID(K69,FIND(":",K69)+1,LEN(K69))) -> abap.char(10); | AC69: =IF(ISNUMBER(SEARCH("@",H67)),A67,H67&" : "&IF(AD69="",I67,AD69)&";") -> billtocity : abap.char();); | AD69: ="abap.char("&AE69&")" -> abap.char();) | AE69: =TRIM(IF(ISNUMBER(SEARCH("char",Q69)),RIGHT(Q69,2))) -> );
A70: billtopincode : zde_bill_to_pincode; | H70: =TRIM(MID(A70,1,FIND(":",A70)-1)) -> billtopincode | I70: =IF(ISNUMBER(SEARCH("@",A70)),"",TRIM(SUBSTITUTE(SUBSTITUTE(TRIM(MID(A70,FIND(":",A70)+1,LEN(A70))),";",""),"not null",""))) -> zde_bill_to_pincode | K70: billtopincode : abap.char(10); | P70: =TRIM(SUBSTITUTE(MID(K70,1,FIND(":",K70)-1),"key","")) -> billtopincode | Q70: =TRIM(MID(K70,FIND(":",K70)+1,LEN(K70))) -> abap.char(10); | AC70: =IF(ISNUMBER(SEARCH("@",H68)),A68,H68&" : "&IF(AD70="",I68,AD70)&";") -> billtodistrict : abap.char();); | AD70: ="abap.char("&AE70&")" -> abap.char();) | AE70: =TRIM(IF(ISNUMBER(SEARCH("char",Q70)),RIGHT(Q70,2))) -> );
A71: billtophone : zde_bill_to_phone; | H71: =TRIM(MID(A71,1,FIND(":",A71)-1)) -> billtophone | I71: =IF(ISNUMBER(SEARCH("@",A71)),"",TRIM(SUBSTITUTE(SUBSTITUTE(TRIM(MID(A71,FIND(":",A71)+1,LEN(A71))),";",""),"not null",""))) -> zde_bill_to_phone | K71: billtophone : abap.char(10); | P71: =TRIM(SUBSTITUTE(MID(K71,1,FIND(":",K71)-1),"key","")) -> billtophone | Q71: =TRIM(MID(K71,FIND(":",K71)+1,LEN(K71))) -> abap.char(10); | AC71: =IF(ISNUMBER(SEARCH("@",H69)),A69,H69&" : "&IF(AD71="",I69,AD71)&";") -> billtostatecode : abap.char();); | AD71: ="abap.char("&AE71&")" -> abap.char();) | AE71: =TRIM(IF(ISNUMBER(SEARCH("char",Q71)),RIGHT(Q71,2))) -> );
A72: billtoemail : zde_bill_to_email; | H72: =TRIM(MID(A72,1,FIND(":",A72)-1)) -> billtoemail | I72: =IF(ISNUMBER(SEARCH("@",A72)),"",TRIM(SUBSTITUTE(SUBSTITUTE(TRIM(MID(A72,FIND(":",A72)+1,LEN(A72))),";",""),"not null",""))) -> zde_bill_to_email | K72: billtoemail : abap.char(100); | P72: =TRIM(SUBSTITUTE(MID(K72,1,FIND(":",K72)-1),"key","")) -> billtoemail | Q72: =TRIM(MID(K72,FIND(":",K72)+1,LEN(K72))) -> abap.char(100); | AC72: =IF(ISNUMBER(SEARCH("@",H70)),A70,H70&" : "&IF(AD72="",I70,AD72)&";") -> billtopincode : abap.char();); | AD72: ="abap.char("&AE72&")" -> abap.char();) | AE72: =TRIM(IF(ISNUMBER(SEARCH("char",Q72)),RIGHT(Q72,2))) -> );
A73: shiptogstin : zde_ship_to_gstin; | H73: =TRIM(MID(A73,1,FIND(":",A73)-1)) -> shiptogstin | I73: =IF(ISNUMBER(SEARCH("@",A73)),"",TRIM(SUBSTITUTE(SUBSTITUTE(TRIM(MID(A73,FIND(":",A73)+1,LEN(A73))),";",""),"not null",""))) -> zde_ship_to_gstin | K73: shiptogstin : abap.char(15); | P73: =TRIM(SUBSTITUTE(MID(K73,1,FIND(":",K73)-1),"key","")) -> shiptogstin | Q73: =TRIM(MID(K73,FIND(":",K73)+1,LEN(K73))) -> abap.char(15); | AC73: =IF(ISNUMBER(SEARCH("@",H71)),A71,H71&" : "&IF(AD73="",I71,AD73)&";") -> billtophone : abap.char();); | AD73: ="abap.char("&AE73&")" -> abap.char();) | AE73: =TRIM(IF(ISNUMBER(SEARCH("char",Q73)),RIGHT(Q73,2))) -> );
A74: shiptolegalname : zde_ship_to_legal_name; | H74: =TRIM(MID(A74,1,FIND(":",A74)-1)) -> shiptolegalname | I74: =IF(ISNUMBER(SEARCH("@",A74)),"",TRIM(SUBSTITUTE(SUBSTITUTE(TRIM(MID(A74,FIND(":",A74)+1,LEN(A74))),";",""),"not null",""))) -> zde_ship_to_legal_name | K74: shiptolegalname : abap.char(100); | P74: =TRIM(SUBSTITUTE(MID(K74,1,FIND(":",K74)-1),"key","")) -> shiptolegalname | Q74: =TRIM(MID(K74,FIND(":",K74)+1,LEN(K74))) -> abap.char(100); | AC74: =IF(ISNUMBER(SEARCH("@",H72)),A72,H72&" : "&IF(AD74="",I72,AD74)&";") -> billtoemail : abap.char(100); | AD74: ="abap.char("&AE74&")" -> abap.char(100) | AE74: 100
A75: shiptotradename : zde_ship_to_trade_name; | H75: =TRIM(MID(A75,1,FIND(":",A75)-1)) -> shiptotradename | I75: =IF(ISNUMBER(SEARCH("@",A75)),"",TRIM(SUBSTITUTE(SUBSTITUTE(TRIM(MID(A75,FIND(":",A75)+1,LEN(A75))),";",""),"not null",""))) -> zde_ship_to_trade_name | K75: shiptotradename : abap.char(100); | P75: =TRIM(SUBSTITUTE(MID(K75,1,FIND(":",K75)-1),"key","")) -> shiptotradename | Q75: =TRIM(MID(K75,FIND(":",K75)+1,LEN(K75))) -> abap.char(100); | AC75: =IF(ISNUMBER(SEARCH("@",H73)),A73,H73&" : "&IF(AD75="",I73,AD75)&";") -> shiptogstin : abap.char();); | AD75: ="abap.char("&AE75&")" -> abap.char();) | AE75: =TRIM(IF(ISNUMBER(SEARCH("char",Q75)),RIGHT(Q75,2))) -> );
A76: shiptobuildingnumber : zde_ship_to_buliding_no; | H76: =TRIM(MID(A76,1,FIND(":",A76)-1)) -> shiptobuildingnumber | I76: =IF(ISNUMBER(SEARCH("@",A76)),"",TRIM(SUBSTITUTE(SUBSTITUTE(TRIM(MID(A76,FIND(":",A76)+1,LEN(A76))),";",""),"not null",""))) -> zde_ship_to_buliding_no | K76: shiptobuildingnumber : abap.char(10); | P76: =TRIM(SUBSTITUTE(MID(K76,1,FIND(":",K76)-1),"key","")) -> shiptobuildingnumber | Q76: =TRIM(MID(K76,FIND(":",K76)+1,LEN(K76))) -> abap.char(10); | AC76: =IF(ISNUMBER(SEARCH("@",H74)),A74,H74&" : "&IF(AD76="",I74,AD76)&";") -> shiptolegalname : abap.char(100); | AD76: ="abap.char("&AE76&")" -> abap.char(100) | AE76: 100
A77: shiptobuildingname : zde_ship_to_buliding_name; | H77: =TRIM(MID(A77,1,FIND(":",A77)-1)) -> shiptobuildingname | I77: =IF(ISNUMBER(SEARCH("@",A77)),"",TRIM(SUBSTITUTE(SUBSTITUTE(TRIM(MID(A77,FIND(":",A77)+1,LEN(A77))),";",""),"not null",""))) -> zde_ship_to_buliding_name | K77: shiptobuildingname : abap.char(100); | P77: =TRIM(SUBSTITUTE(MID(K77,1,FIND(":",K77)-1),"key","")) -> shiptobuildingname | Q77: =TRIM(MID(K77,FIND(":",K77)+1,LEN(K77))) -> abap.char(100); | AC77: =IF(ISNUMBER(SEARCH("@",H75)),A75,H75&" : "&IF(AD77="",I75,AD77)&";") -> shiptotradename : abap.char(100); | AD77: ="abap.char("&AE77&")" -> abap.char(100) | AE77: 100
A78: shiptoflatnumber : zde_ship_to_flat_number; | H78: =TRIM(MID(A78,1,FIND(":",A78)-1)) -> shiptoflatnumber | I78: =IF(ISNUMBER(SEARCH("@",A78)),"",TRIM(SUBSTITUTE(SUBSTITUTE(TRIM(MID(A78,FIND(":",A78)+1,LEN(A78))),";",""),"not null",""))) -> zde_ship_to_flat_number | K78: shiptoflatnumber : abap.char(10); | P78: =TRIM(SUBSTITUTE(MID(K78,1,FIND(":",K78)-1),"key","")) -> shiptoflatnumber | Q78: =TRIM(MID(K78,FIND(":",K78)+1,LEN(K78))) -> abap.char(10); | AC78: =IF(ISNUMBER(SEARCH("@",H76)),A76,H76&" : "&IF(AD78="",I76,AD78)&";") -> shiptobuildingnumber : abap.char(10); | AD78: ="abap.char("&AE78&")" -> abap.char(10) | AE78: 10
A79: shiptoaddress1 : zde_ship_to_address1; | H79: =TRIM(MID(A79,1,FIND(":",A79)-1)) -> shiptoaddress1 | I79: =IF(ISNUMBER(SEARCH("@",A79)),"",TRIM(SUBSTITUTE(SUBSTITUTE(TRIM(MID(A79,FIND(":",A79)+1,LEN(A79))),";",""),"not null",""))) -> zde_ship_to_address1 | K79: shiptoaddress1 : abap.char(100); | P79: =TRIM(SUBSTITUTE(MID(K79,1,FIND(":",K79)-1),"key","")) -> shiptoaddress1 | Q79: =TRIM(MID(K79,FIND(":",K79)+1,LEN(K79))) -> abap.char(100); | AC79: =IF(ISNUMBER(SEARCH("@",H77)),A77,H77&" : "&IF(AD79="",I77,AD79)&";") -> shiptobuildingname : abap.char(100); | AD79: ="abap.char("&AE79&")" -> abap.char(100) | AE79: 100
A80: shiptoaddress2 : zde_ship_to_address2; | H80: =TRIM(MID(A80,1,FIND(":",A80)-1)) -> shiptoaddress2 | I80: =IF(ISNUMBER(SEARCH("@",A80)),"",TRIM(SUBSTITUTE(SUBSTITUTE(TRIM(MID(A80,FIND(":",A80)+1,LEN(A80))),";",""),"not null",""))) -> zde_ship_to_address2 | K80: shiptoaddress2 : abap.char(100); | P80: =TRIM(SUBSTITUTE(MID(K80,1,FIND(":",K80)-1),"key","")) -> shiptoaddress2 | Q80: =TRIM(MID(K80,FIND(":",K80)+1,LEN(K80))) -> abap.char(100); | AC80: =IF(ISNUMBER(SEARCH("@",H78)),A78,H78&" : "&IF(AD80="",I78,AD80)&";") -> shiptoflatnumber : abap.char();); | AD80: ="abap.char("&AE80&")" -> abap.char();) | AE80: =TRIM(IF(ISNUMBER(SEARCH("char",Q80)),RIGHT(Q80,2))) -> );
A81: shiptocity : zde_ship_to_city; | H81: =TRIM(MID(A81,1,FIND(":",A81)-1)) -> shiptocity | I81: =IF(ISNUMBER(SEARCH("@",A81)),"",TRIM(SUBSTITUTE(SUBSTITUTE(TRIM(MID(A81,FIND(":",A81)+1,LEN(A81))),";",""),"not null",""))) -> zde_ship_to_city | K81: shiptocity : abap.char(50); | P81: =TRIM(SUBSTITUTE(MID(K81,1,FIND(":",K81)-1),"key","")) -> shiptocity | Q81: =TRIM(MID(K81,FIND(":",K81)+1,LEN(K81))) -> abap.char(50); | AC81: =IF(ISNUMBER(SEARCH("@",H79)),A79,H79&" : "&IF(AD81="",I79,AD81)&";") -> shiptoaddress1 : abap.char(100); | AD81: ="abap.char("&AE81&")" -> abap.char(100) | AE81: 100
A82: shiptodistrict : zde_ship_to_district; | H82: =TRIM(MID(A82,1,FIND(":",A82)-1)) -> shiptodistrict | I82: =IF(ISNUMBER(SEARCH("@",A82)),"",TRIM(SUBSTITUTE(SUBSTITUTE(TRIM(MID(A82,FIND(":",A82)+1,LEN(A82))),";",""),"not null",""))) -> zde_ship_to_district | K82: shiptodistrict : abap.char(60); | P82: =TRIM(SUBSTITUTE(MID(K82,1,FIND(":",K82)-1),"key","")) -> shiptodistrict | Q82: =TRIM(MID(K82,FIND(":",K82)+1,LEN(K82))) -> abap.char(60); | AC82: =IF(ISNUMBER(SEARCH("@",H80)),A80,H80&" : "&IF(AD82="",I80,AD82)&";") -> shiptoaddress2 : abap.char(100); | AD82: ="abap.char("&AE82&")" -> abap.char(100) | AE82: 100
A83: shiptostatecode : zde_ship_to_state; | H83: =TRIM(MID(A83,1,FIND(":",A83)-1)) -> shiptostatecode | I83: =IF(ISNUMBER(SEARCH("@",A83)),"",TRIM(SUBSTITUTE(SUBSTITUTE(TRIM(MID(A83,FIND(":",A83)+1,LEN(A83))),";",""),"not null",""))) -> zde_ship_to_state | K83: shiptostatecode : abap.char(50); | P83: =TRIM(SUBSTITUTE(MID(K83,1,FIND(":",K83)-1),"key","")) -> shiptostatecode | Q83: =TRIM(MID(K83,FIND(":",K83)+1,LEN(K83))) -> abap.char(50); | AC83: =IF(ISNUMBER(SEARCH("@",H81)),A81,H81&" : "&IF(AD83="",I81,AD83)&";") -> shiptocity : abap.char();); | AD83: ="abap.char("&AE83&")" -> abap.char();) | AE83: =TRIM(IF(ISNUMBER(SEARCH("char",Q83)),RIGHT(Q83,2))) -> );
A84: shiptopincode : zde_ship_to_pincode; | H84: =TRIM(MID(A84,1,FIND(":",A84)-1)) -> shiptopincode | I84: =IF(ISNUMBER(SEARCH("@",A84)),"",TRIM(SUBSTITUTE(SUBSTITUTE(TRIM(MID(A84,FIND(":",A84)+1,LEN(A84))),";",""),"not null",""))) -> zde_ship_to_pincode | K84: shiptopincode : abap.char(6); | P84: =TRIM(SUBSTITUTE(MID(K84,1,FIND(":",K84)-1),"key","")) -> shiptopincode | Q84: =TRIM(MID(K84,FIND(":",K84)+1,LEN(K84))) -> abap.char(6); | AC84: =IF(ISNUMBER(SEARCH("@",H82)),A82,H82&" : "&IF(AD84="",I82,AD84)&";") -> shiptodistrict : abap.char();); | AD84: ="abap.char("&AE84&")" -> abap.char();) | AE84: =TRIM(IF(ISNUMBER(SEARCH("char",Q84)),RIGHT(Q84,2))) -> );
A85: shiptophone : zde_ship_to_phone; | H85: =TRIM(MID(A85,1,FIND(":",A85)-1)) -> shiptophone | I85: =IF(ISNUMBER(SEARCH("@",A85)),"",TRIM(SUBSTITUTE(SUBSTITUTE(TRIM(MID(A85,FIND(":",A85)+1,LEN(A85))),";",""),"not null",""))) -> zde_ship_to_phone | K85: shiptophone : abap.char(10); | P85: =TRIM(SUBSTITUTE(MID(K85,1,FIND(":",K85)-1),"key","")) -> shiptophone | Q85: =TRIM(MID(K85,FIND(":",K85)+1,LEN(K85))) -> abap.char(10); | AC85: =IF(ISNUMBER(SEARCH("@",H83)),A83,H83&" : "&IF(AD85="",I83,AD85)&";") -> shiptostatecode : abap.char();); | AD85: ="abap.char("&AE85&")" -> abap.char();) | AE85: =TRIM(IF(ISNUMBER(SEARCH("char",Q85)),RIGHT(Q85,2))) -> );
A86: shiptoemail : zde_ship_to_email; | H86: =TRIM(MID(A86,1,FIND(":",A86)-1)) -> shiptoemail | I86: =IF(ISNUMBER(SEARCH("@",A86)),"",TRIM(SUBSTITUTE(SUBSTITUTE(TRIM(MID(A86,FIND(":",A86)+1,LEN(A86))),";",""),"not null",""))) -> zde_ship_to_email | K86: shiptoemail : abap.char(100); | P86: =TRIM(SUBSTITUTE(MID(K86,1,FIND(":",K86)-1),"key","")) -> shiptoemail | Q86: =TRIM(MID(K86,FIND(":",K86)+1,LEN(K86))) -> abap.char(100); | AC86: =IF(ISNUMBER(SEARCH("@",H84)),A84,H84&" : "&IF(AD86="",I84,AD86)&";") -> shiptopincode : abap.char();); | AD86: ="abap.char("&AE86&")" -> abap.char();) | AE86: =TRIM(IF(ISNUMBER(SEARCH("char",Q86)),RIGHT(Q86,2))) -> );
A87: paymenttype : zde_payment_type; | H87: =TRIM(MID(A87,1,FIND(":",A87)-1)) -> paymenttype | I87: =IF(ISNUMBER(SEARCH("@",A87)),"",TRIM(SUBSTITUTE(SUBSTITUTE(TRIM(MID(A87,FIND(":",A87)+1,LEN(A87))),";",""),"not null",""))) -> zde_payment_type | K87: paymenttype : abap.char(2); | P87: =TRIM(SUBSTITUTE(MID(K87,1,FIND(":",K87)-1),"key","")) -> paymenttype | Q87: =TRIM(MID(K87,FIND(":",K87)+1,LEN(K87))) -> abap.char(2); | AC87: =IF(ISNUMBER(SEARCH("@",H85)),A85,H85&" : "&IF(AD87="",I85,AD87)&";") -> shiptophone : abap.char();); | AD87: ="abap.char("&AE87&")" -> abap.char();) | AE87: =TRIM(IF(ISNUMBER(SEARCH("char",Q87)),RIGHT(Q87,2))) -> );
A88: paymentmode : zde_mode_of_payment; | H88: =TRIM(MID(A88,1,FIND(":",A88)-1)) -> paymentmode | I88: =IF(ISNUMBER(SEARCH("@",A88)),"",TRIM(SUBSTITUTE(SUBSTITUTE(TRIM(MID(A88,FIND(":",A88)+1,LEN(A88))),";",""),"not null",""))) -> zde_mode_of_payment | K88: paymentmode : abap.char(6); | P88: =TRIM(SUBSTITUTE(MID(K88,1,FIND(":",K88)-1),"key","")) -> paymentmode | Q88: =TRIM(MID(K88,FIND(":",K88)+1,LEN(K88))) -> abap.char(6); | AC88: =IF(ISNUMBER(SEARCH("@",H86)),A86,H86&" : "&IF(AD88="",I86,AD88)&";") -> shiptoemail : abap.char(100); | AD88: ="abap.char("&AE88&")" -> abap.char(100) | AE88: 100
A89: paymentamount : zde_payment_amount; | H89: =TRIM(MID(A89,1,FIND(":",A89)-1)) -> paymentamount | I89: =IF(ISNUMBER(SEARCH("@",A89)),"",TRIM(SUBSTITUTE(SUBSTITUTE(TRIM(MID(A89,FIND(":",A89)+1,LEN(A89))),";",""),"not null",""))) -> zde_payment_amount | K89: paymentamount : abap.char(15); | P89: =TRIM(SUBSTITUTE(MID(K89,1,FIND(":",K89)-1),"key","")) -> paymentamount | Q89: =TRIM(MID(K89,FIND(":",K89)+1,LEN(K89))) -> abap.char(15); | AC89: =IF(ISNUMBER(SEARCH("@",H87)),A87,H87&" : "&IF(AD89="",I87,AD89)&";") -> paymenttype : abap.char();); | AD89: ="abap.char("&AE89&")" -> abap.char();) | AE89: =TRIM(IF(ISNUMBER(SEARCH("char",Q89)),RIGHT(Q89,2))) -> );
A90: advancepaidamount : zde_advpaid_amount; | H90: =TRIM(MID(A90,1,FIND(":",A90)-1)) -> advancepaidamount | I90: =IF(ISNUMBER(SEARCH("@",A90)),"",TRIM(SUBSTITUTE(SUBSTITUTE(TRIM(MID(A90,FIND(":",A90)+1,LEN(A90))),";",""),"not null",""))) -> zde_advpaid_amount | K90: advancepaidamount : abap.char(50); | P90: =TRIM(SUBSTITUTE(MID(K90,1,FIND(":",K90)-1),"key","")) -> advancepaidamount | Q90: =TRIM(MID(K90,FIND(":",K90)+1,LEN(K90))) -> abap.char(50); | AC90: =IF(ISNUMBER(SEARCH("@",H88)),A88,H88&" : "&IF(AD90="",I88,AD90)&";") -> paymentmode : abap.char();); | AD90: ="abap.char("&AE90&")" -> abap.char();) | AE90: =TRIM(IF(ISNUMBER(SEARCH("char",Q90)),RIGHT(Q90,2))) -> );
A91: paymentdate : zde_payment_date; | H91: =TRIM(MID(A91,1,FIND(":",A91)-1)) -> paymentdate | I91: =IF(ISNUMBER(SEARCH("@",A91)),"",TRIM(SUBSTITUTE(SUBSTITUTE(TRIM(MID(A91,FIND(":",A91)+1,LEN(A91))),";",""),"not null",""))) -> zde_payment_date | K91: paymentdate : abap.char(10); | P91: =TRIM(SUBSTITUTE(MID(K91,1,FIND(":",K91)-1),"key","")) -> paymentdate | Q91: =TRIM(MID(K91,FIND(":",K91)+1,LEN(K91))) -> abap.char(10); | AC91: =IF(ISNUMBER(SEARCH("@",H89)),A89,H89&" : "&IF(AD91="",I89,AD91)&";") -> paymentamount : abap.char();); | AD91: ="abap.char("&AE91&")" -> abap.char();) | AE91: =TRIM(IF(ISNUMBER(SEARCH("char",Q91)),RIGHT(Q91,2))) -> );
A92: paymentremarks : zde_payment_remarks; | H92: =TRIM(MID(A92,1,FIND(":",A92)-1)) -> paymentremarks | I92: =IF(ISNUMBER(SEARCH("@",A92)),"",TRIM(SUBSTITUTE(SUBSTITUTE(TRIM(MID(A92,FIND(":",A92)+1,LEN(A92))),";",""),"not null",""))) -> zde_payment_remarks | K92: paymentremarks : abap.char(200); | P92: =TRIM(SUBSTITUTE(MID(K92,1,FIND(":",K92)-1),"key","")) -> paymentremarks | Q92: =TRIM(MID(K92,FIND(":",K92)+1,LEN(K92))) -> abap.char(200); | AC92: =IF(ISNUMBER(SEARCH("@",H90)),A90,H90&" : "&IF(AD92="",I90,AD92)&";") -> advancepaidamount : abap.char();); | AD92: ="abap.char("&AE92&")" -> abap.char();) | AE92: =TRIM(IF(ISNUMBER(SEARCH("char",Q92)),RIGHT(Q92,2))) -> );
A93: paymentterms : zde_payment_terms; | H93: =TRIM(MID(A93,1,FIND(":",A93)-1)) -> paymentterms | I93: =IF(ISNUMBER(SEARCH("@",A93)),"",TRIM(SUBSTITUTE(SUBSTITUTE(TRIM(MID(A93,FIND(":",A93)+1,LEN(A93))),";",""),"not null",""))) -> zde_payment_terms | K93: paymentterms : abap.char(50); | P93: =TRIM(SUBSTITUTE(MID(K93,1,FIND(":",K93)-1),"key","")) -> paymentterms | Q93: =TRIM(MID(K93,FIND(":",K93)+1,LEN(K93))) -> abap.char(50); | AC93: =IF(ISNUMBER(SEARCH("@",H91)),A91,H91&" : "&IF(AD93="",I91,AD93)&";") -> paymentdate : abap.char();); | AD93: ="abap.char("&AE93&")" -> abap.char();) | AE93: =TRIM(IF(ISNUMBER(SEARCH("char",Q93)),RIGHT(Q93,2))) -> );
A94: paymentinstruction : zde_payment_instruction; | H94: =TRIM(MID(A94,1,FIND(":",A94)-1)) -> paymentinstruction | I94: =IF(ISNUMBER(SEARCH("@",A94)),"",TRIM(SUBSTITUTE(SUBSTITUTE(TRIM(MID(A94,FIND(":",A94)+1,LEN(A94))),";",""),"not null",""))) -> zde_payment_instruction | K94: paymentinstruction : abap.char(50); | P94: =TRIM(SUBSTITUTE(MID(K94,1,FIND(":",K94)-1),"key","")) -> paymentinstruction | Q94: =TRIM(MID(K94,FIND(":",K94)+1,LEN(K94))) -> abap.char(50); | AC94: =IF(ISNUMBER(SEARCH("@",H92)),A92,H92&" : "&IF(AD94="",I92,AD94)&";") -> paymentremarks : abap.char(200); | AD94: ="abap.char("&AE94&")" -> abap.char(200) | AE94: 200
A95: payeename : zde_payee_name; | H95: =TRIM(MID(A95,1,FIND(":",A95)-1)) -> payeename | I95: =IF(ISNUMBER(SEARCH("@",A95)),"",TRIM(SUBSTITUTE(SUBSTITUTE(TRIM(MID(A95,FIND(":",A95)+1,LEN(A95))),";",""),"not null",""))) -> zde_payee_name | K95: payeename : abap.char(100); | P95: =TRIM(SUBSTITUTE(MID(K95,1,FIND(":",K95)-1),"key","")) -> payeename | Q95: =TRIM(MID(K95,FIND(":",K95)+1,LEN(K95))) -> abap.char(100); | AC95: =IF(ISNUMBER(SEARCH("@",H93)),A93,H93&" : "&IF(AD95="",I93,AD95)&";") -> paymentterms : abap.char();); | AD95: ="abap.char("&AE95&")" -> abap.char();) | AE95: =TRIM(IF(ISNUMBER(SEARCH("char",Q95)),RIGHT(Q95,2))) -> );
A96: payeeaccountnumber : zde_payee_account_number; | H96: =TRIM(MID(A96,1,FIND(":",A96)-1)) -> payeeaccountnumber | I96: =IF(ISNUMBER(SEARCH("@",A96)),"",TRIM(SUBSTITUTE(SUBSTITUTE(TRIM(MID(A96,FIND(":",A96)+1,LEN(A96))),";",""),"not null",""))) -> zde_payee_account_number | K96: payeeaccountnumber : abap.char(18); | P96: =TRIM(SUBSTITUTE(MID(K96,1,FIND(":",K96)-1),"key","")) -> payeeaccountnumber | Q96: =TRIM(MID(K96,FIND(":",K96)+1,LEN(K96))) -> abap.char(18); | AC96: =IF(ISNUMBER(SEARCH("@",H94)),A94,H94&" : "&IF(AD96="",I94,AD96)&";") -> paymentinstruction : abap.char();); | AD96: ="abap.char("&AE96&")" -> abap.char();) | AE96: =TRIM(IF(ISNUMBER(SEARCH("char",Q96)),RIGHT(Q96,2))) -> );
A97: paymentamountdue : zde_amount_due_for_payment; | H97: =TRIM(MID(A97,1,FIND(":",A97)-1)) -> paymentamountdue | I97: =IF(ISNUMBER(SEARCH("@",A97)),"",TRIM(SUBSTITUTE(SUBSTITUTE(TRIM(MID(A97,FIND(":",A97)+1,LEN(A97))),";",""),"not null",""))) -> zde_amount_due_for_payment | K97: paymentamountdue : abap.char(18); | P97: =TRIM(SUBSTITUTE(MID(K97,1,FIND(":",K97)-1),"key","")) -> paymentamountdue | Q97: =TRIM(MID(K97,FIND(":",K97)+1,LEN(K97))) -> abap.char(18); | AC97: =IF(ISNUMBER(SEARCH("@",H95)),A95,H95&" : "&IF(AD97="",I95,AD97)&";") -> payeename : abap.char(100); | AD97: ="abap.char("&AE97&")" -> abap.char(100) | AE97: 100
A98: paymentduedate : zde_pay_due_date; | H98: =TRIM(MID(A98,1,FIND(":",A98)-1)) -> paymentduedate | I98: =IF(ISNUMBER(SEARCH("@",A98)),"",TRIM(SUBSTITUTE(SUBSTITUTE(TRIM(MID(A98,FIND(":",A98)+1,LEN(A98))),";",""),"not null",""))) -> zde_pay_due_date | K98: paymentduedate : abap.char(8); | P98: =TRIM(SUBSTITUTE(MID(K98,1,FIND(":",K98)-1),"key","")) -> paymentduedate | Q98: =TRIM(MID(K98,FIND(":",K98)+1,LEN(K98))) -> abap.char(8); | AC98: =IF(ISNUMBER(SEARCH("@",H96)),A96,H96&" : "&IF(AD98="",I96,AD98)&";") -> payeeaccountnumber : abap.char();); | AD98: ="abap.char("&AE98&")" -> abap.char();) | AE98: =TRIM(IF(ISNUMBER(SEARCH("char",Q98)),RIGHT(Q98,2))) -> );
A99: ifsc : zde_ifsc; | H99: =TRIM(MID(A99,1,FIND(":",A99)-1)) -> ifsc | I99: =IF(ISNUMBER(SEARCH("@",A99)),"",TRIM(SUBSTITUTE(SUBSTITUTE(TRIM(MID(A99,FIND(":",A99)+1,LEN(A99))),";",""),"not null",""))) -> zde_ifsc | K99: ifsc : abap.char(11); | P99: =TRIM(SUBSTITUTE(MID(K99,1,FIND(":",K99)-1),"key","")) -> ifsc | Q99: =TRIM(MID(K99,FIND(":",K99)+1,LEN(K99))) -> abap.char(11); | AC99: =IF(ISNUMBER(SEARCH("@",H97)),A97,H97&" : "&IF(AD99="",I97,AD99)&";") -> paymentamountdue : abap.char();); | AD99: ="abap.char("&AE99&")" -> abap.char();) | AE99: =TRIM(IF(ISNUMBER(SEARCH("char",Q99)),RIGHT(Q99,2))) -> );
A100: accountdetails : zde_acc_details; | H100: =TRIM(MID(A100,1,FIND(":",A100)-1)) -> accountdetails | I100: =IF(ISNUMBER(SEARCH("@",A100)),"",TRIM(SUBSTITUTE(SUBSTITUTE(TRIM(MID(A100,FIND(":",A100)+1,LEN(A100))),";",""),"not null",""))) -> zde_acc_details | K100: accountdetails : abap.char(50); | P100: =TRIM(SUBSTITUTE(MID(K100,1,FIND(":",K100)-1),"key","")) -> accountdetails | Q100: =TRIM(MID(K100,FIND(":",K100)+1,LEN(K100))) -> abap.char(50); | AC100: =IF(ISNUMBER(SEARCH("@",H98)),A98,H98&" : "&IF(AD100="",I98,AD100)&";") -> paymentduedate : abap.char();); | AD100: ="abap.char("&AE100&")" -> abap.char();) | AE100: =TRIM(IF(ISNUMBER(SEARCH("char",Q100)),RIGHT(Q100,2))) -> );
A101: credittransfer : zde_acc_credit_transfer; | H101: =TRIM(MID(A101,1,FIND(":",A101)-1)) -> credittransfer | I101: =IF(ISNUMBER(SEARCH("@",A101)),"",TRIM(SUBSTITUTE(SUBSTITUTE(TRIM(MID(A101,FIND(":",A101)+1,LEN(A101))),";",""),"not null",""))) -> zde_acc_credit_transfer | K101: credittransfer : abap.char(50); | P101: =TRIM(SUBSTITUTE(MID(K101,1,FIND(":",K101)-1),"key","")) -> credittransfer | Q101: =TRIM(MID(K101,FIND(":",K101)+1,LEN(K101))) -> abap.char(50); | AC101: =IF(ISNUMBER(SEARCH("@",H99)),A99,H99&" : "&IF(AD101="",I99,AD101)&";") -> ifsc : abap.char();); | AD101: ="abap.char("&AE101&")" -> abap.char();) | AE101: =TRIM(IF(ISNUMBER(SEARCH("char",Q101)),RIGHT(Q101,2))) -> );
A102: directdebit : zde_direct_debit; | H102: =TRIM(MID(A102,1,FIND(":",A102)-1)) -> directdebit | I102: =IF(ISNUMBER(SEARCH("@",A102)),"",TRIM(SUBSTITUTE(SUBSTITUTE(TRIM(MID(A102,FIND(":",A102)+1,LEN(A102))),";",""),"not null",""))) -> zde_direct_debit | K102: directdebit : abap.char(50); | P102: =TRIM(SUBSTITUTE(MID(K102,1,FIND(":",K102)-1),"key","")) -> directdebit | Q102: =TRIM(MID(K102,FIND(":",K102)+1,LEN(K102))) -> abap.char(50); | AC102: =IF(ISNUMBER(SEARCH("@",H100)),A100,H100&" : "&IF(AD102="",I100,AD102)&";") -> accountdetails : abap.char();); | AD102: ="abap.char("&AE102&")" -> abap.char();) | AE102: =TRIM(IF(ISNUMBER(SEARCH("char",Q102)),RIGHT(Q102,2))) -> );
A103: creditdays : zde_acc_credit_days; | H103: =TRIM(MID(A103,1,FIND(":",A103)-1)) -> creditdays | I103: =IF(ISNUMBER(SEARCH("@",A103)),"",TRIM(SUBSTITUTE(SUBSTITUTE(TRIM(MID(A103,FIND(":",A103)+1,LEN(A103))),";",""),"not null",""))) -> zde_acc_credit_days | K103: creditdays : abap.char(10); | P103: =TRIM(SUBSTITUTE(MID(K103,1,FIND(":",K103)-1),"key","")) -> creditdays | Q103: =TRIM(MID(K103,FIND(":",K103)+1,LEN(K103))) -> abap.char(10); | AC103: =IF(ISNUMBER(SEARCH("@",H101)),A101,H101&" : "&IF(AD103="",I101,AD103)&";") -> credittransfer : abap.char();); | AD103: ="abap.char("&AE103&")" -> abap.char();) | AE103: =TRIM(IF(ISNUMBER(SEARCH("char",Q103)),RIGHT(Q103,2))) -> );
A104: creditavaileddate : zde_credit_availed_date; | H104: =TRIM(MID(A104,1,FIND(":",A104)-1)) -> creditavaileddate | I104: =IF(ISNUMBER(SEARCH("@",A104)),"",TRIM(SUBSTITUTE(SUBSTITUTE(TRIM(MID(A104,FIND(":",A104)+1,LEN(A104))),";",""),"not null",""))) -> zde_credit_availed_date | K104: creditavaileddate : abap.char(8); | P104: =TRIM(SUBSTITUTE(MID(K104,1,FIND(":",K104)-1),"key","")) -> creditavaileddate | Q104: =TRIM(MID(K104,FIND(":",K104)+1,LEN(K104))) -> abap.char(8); | AC104: =IF(ISNUMBER(SEARCH("@",H102)),A102,H102&" : "&IF(AD104="",I102,AD104)&";") -> directdebit : abap.char();); | AD104: ="abap.char("&AE104&")" -> abap.char();) | AE104: =TRIM(IF(ISNUMBER(SEARCH("char",Q104)),RIGHT(Q104,2))) -> );
A105: creditreversaldate : zde_credit_reversal_date; | H105: =TRIM(MID(A105,1,FIND(":",A105)-1)) -> creditreversaldate | I105: =IF(ISNUMBER(SEARCH("@",A105)),"",TRIM(SUBSTITUTE(SUBSTITUTE(TRIM(MID(A105,FIND(":",A105)+1,LEN(A105))),";",""),"not null",""))) -> zde_credit_reversal_date | K105: creditreversaldate : abap.char(8); | P105: =TRIM(SUBSTITUTE(MID(K105,1,FIND(":",K105)-1),"key","")) -> creditreversaldate | Q105: =TRIM(MID(K105,FIND(":",K105)+1,LEN(K105))) -> abap.char(8); | AC105: =IF(ISNUMBER(SEARCH("@",H103)),A103,H103&" : "&IF(AD105="",I103,AD105)&";") -> creditdays : abap.char();); | AD105: ="abap.char("&AE105&")" -> abap.char();) | AE105: =TRIM(IF(ISNUMBER(SEARCH("char",Q105)),RIGHT(Q105,2))) -> );
A106: additionalsupportingdocdetails : zde_add_supp_doc; | H106: =TRIM(MID(A106,1,FIND(":",A106)-1)) -> additionalsupportingdocdetails | I106: =IF(ISNUMBER(SEARCH("@",A106)),"",TRIM(SUBSTITUTE(SUBSTITUTE(TRIM(MID(A106,FIND(":",A106)+1,LEN(A106))),";",""),"not null",""))) -> zde_add_supp_doc | K106: additionalsupportingdocdetails : abap.char(50); | P106: =TRIM(SUBSTITUTE(MID(K106,1,FIND(":",K106)-1),"key","")) -> additionalsupportingdocdetails | Q106: =TRIM(MID(K106,FIND(":",K106)+1,LEN(K106))) -> abap.char(50); | AC106: =IF(ISNUMBER(SEARCH("@",H104)),A104,H104&" : "&IF(AD106="",I104,AD106)&";") -> creditavaileddate : abap.char();); | AD106: ="abap.char("&AE106&")" -> abap.char();) | AE106: =TRIM(IF(ISNUMBER(SEARCH("char",Q106)),RIGHT(Q106,2))) -> );
A107: refdocumentremarks : zde_document_remarks; | H107: =TRIM(MID(A107,1,FIND(":",A107)-1)) -> refdocumentremarks | I107: =IF(ISNUMBER(SEARCH("@",A107)),"",TRIM(SUBSTITUTE(SUBSTITUTE(TRIM(MID(A107,FIND(":",A107)+1,LEN(A107))),";",""),"not null",""))) -> zde_document_remarks | K107: refdocumentremarks : abap.char(100); | P107: =TRIM(SUBSTITUTE(MID(K107,1,FIND(":",K107)-1),"key","")) -> refdocumentremarks | Q107: =TRIM(MID(K107,FIND(":",K107)+1,LEN(K107))) -> abap.char(100); | AC107: =IF(ISNUMBER(SEARCH("@",H105)),A105,H105&" : "&IF(AD107="",I105,AD107)&";") -> creditreversaldate : abap.char();); | AD107: ="abap.char("&AE107&")" -> abap.char();) | AE107: =TRIM(IF(ISNUMBER(SEARCH("char",Q107)),RIGHT(Q107,2))) -> );
A108: documentdeliverystartdate : zde_delivery_start_date; | H108: =TRIM(MID(A108,1,FIND(":",A108)-1)) -> documentdeliverystartdate | I108: =IF(ISNUMBER(SEARCH("@",A108)),"",TRIM(SUBSTITUTE(SUBSTITUTE(TRIM(MID(A108,FIND(":",A108)+1,LEN(A108))),";",""),"not null",""))) -> zde_delivery_start_date | K108: documentdeliverystartdate : abap.char(8); | P108: =TRIM(SUBSTITUTE(MID(K108,1,FIND(":",K108)-1),"key","")) -> documentdeliverystartdate | Q108: =TRIM(MID(K108,FIND(":",K108)+1,LEN(K108))) -> abap.char(8); | AC108: =IF(ISNUMBER(SEARCH("@",H106)),A106,H106&" : "&IF(AD108="",I106,AD108)&";") -> additionalsupportingdocdetails : abap.char();); | AD108: ="abap.char("&AE108&")" -> abap.char();) | AE108: =TRIM(IF(ISNUMBER(SEARCH("char",Q108)),RIGHT(Q108,2))) -> );
A109: documentdeliveryenddate : zde_delivery_end_date; | H109: =TRIM(MID(A109,1,FIND(":",A109)-1)) -> documentdeliveryenddate | I109: =IF(ISNUMBER(SEARCH("@",A109)),"",TRIM(SUBSTITUTE(SUBSTITUTE(TRIM(MID(A109,FIND(":",A109)+1,LEN(A109))),";",""),"not null",""))) -> zde_delivery_end_date | K109: documentdeliveryenddate : abap.char(8); | P109: =TRIM(SUBSTITUTE(MID(K109,1,FIND(":",K109)-1),"key","")) -> documentdeliveryenddate | Q109: =TRIM(MID(K109,FIND(":",K109)+1,LEN(K109))) -> abap.char(8); | AC109: =IF(ISNUMBER(SEARCH("@",H107)),A107,H107&" : "&IF(AD109="",I107,AD109)&";") -> refdocumentremarks : abap.char(100); | AD109: ="abap.char("&AE109&")" -> abap.char(100) | AE109: 100
A110: receiptadvicereference : zde_receipt_advice_referen; | H110: =TRIM(MID(A110,1,FIND(":",A110)-1)) -> receiptadvicereference | I110: =IF(ISNUMBER(SEARCH("@",A110)),"",TRIM(SUBSTITUTE(SUBSTITUTE(TRIM(MID(A110,FIND(":",A110)+1,LEN(A110))),";",""),"not null",""))) -> zde_receipt_advice_referen | K110: receiptadvicereference : abap.char(20); | P110: =TRIM(SUBSTITUTE(MID(K110,1,FIND(":",K110)-1),"key","")) -> receiptadvicereference | Q110: =TRIM(MID(K110,FIND(":",K110)+1,LEN(K110))) -> abap.char(20); | AC110: =IF(ISNUMBER(SEARCH("@",H108)),A108,H108&" : "&IF(AD110="",I108,AD110)&";") -> documentdeliverystartdate : abap.char();); | AD110: ="abap.char("&AE110&")" -> abap.char();) | AE110: =TRIM(IF(ISNUMBER(SEARCH("char",Q110)),RIGHT(Q110,2))) -> );
A111: tenderlotreference : zde_tender_lot_reference; | H111: =TRIM(MID(A111,1,FIND(":",A111)-1)) -> tenderlotreference | I111: =IF(ISNUMBER(SEARCH("@",A111)),"",TRIM(SUBSTITUTE(SUBSTITUTE(TRIM(MID(A111,FIND(":",A111)+1,LEN(A111))),";",""),"not null",""))) -> zde_tender_lot_reference | K111: tenderlotreference : abap.char(20); | P111: =TRIM(SUBSTITUTE(MID(K111,1,FIND(":",K111)-1),"key","")) -> tenderlotreference | Q111: =TRIM(MID(K111,FIND(":",K111)+1,LEN(K111))) -> abap.char(20); | AC111: =IF(ISNUMBER(SEARCH("@",H109)),A109,H109&" : "&IF(AD111="",I109,AD111)&";") -> documentdeliveryenddate : abap.char();); | AD111: ="abap.char("&AE111&")" -> abap.char();) | AE111: =TRIM(IF(ISNUMBER(SEARCH("char",Q111)),RIGHT(Q111,2))) -> );
A112: contractreferencenumber : zde_contract_reference; | H112: =TRIM(MID(A112,1,FIND(":",A112)-1)) -> contractreferencenumber | I112: =IF(ISNUMBER(SEARCH("@",A112)),"",TRIM(SUBSTITUTE(SUBSTITUTE(TRIM(MID(A112,FIND(":",A112)+1,LEN(A112))),";",""),"not null",""))) -> zde_contract_reference | K112: contractreferencenumber : abap.char(20); | P112: =TRIM(SUBSTITUTE(MID(K112,1,FIND(":",K112)-1),"key","")) -> contractreferencenumber | Q112: =TRIM(MID(K112,FIND(":",K112)+1,LEN(K112))) -> abap.char(20); | AC112: =IF(ISNUMBER(SEARCH("@",H110)),A110,H110&" : "&IF(AD112="",I110,AD112)&";") -> receiptadvicereference : abap.char();); | AD112: ="abap.char("&AE112&")" -> abap.char();) | AE112: =TRIM(IF(ISNUMBER(SEARCH("char",Q112)),RIGHT(Q112,2))) -> );
A113: refprecedingdocumentdetails : zde_ref_pre_doc; | H113: =TRIM(MID(A113,1,FIND(":",A113)-1)) -> refprecedingdocumentdetails | I113: =IF(ISNUMBER(SEARCH("@",A113)),"",TRIM(SUBSTITUTE(SUBSTITUTE(TRIM(MID(A113,FIND(":",A113)+1,LEN(A113))),";",""),"not null",""))) -> zde_ref_pre_doc | K113: refprecedingdocumentdetails : abap.char(50); | P113: =TRIM(SUBSTITUTE(MID(K113,1,FIND(":",K113)-1),"key","")) -> refprecedingdocumentdetails | Q113: =TRIM(MID(K113,FIND(":",K113)+1,LEN(K113))) -> abap.char(50); | AC113: =IF(ISNUMBER(SEARCH("@",H111)),A111,H111&" : "&IF(AD113="",I111,AD113)&";") -> tenderlotreference : abap.char();); | AD113: ="abap.char("&AE113&")" -> abap.char();) | AE113: =TRIM(IF(ISNUMBER(SEARCH("char",Q113)),RIGHT(Q113,2))) -> );
A114: refcontractdetails : zde_ref_doc_details; | H114: =TRIM(MID(A114,1,FIND(":",A114)-1)) -> refcontractdetails | I114: =IF(ISNUMBER(SEARCH("@",A114)),"",TRIM(SUBSTITUTE(SUBSTITUTE(TRIM(MID(A114,FIND(":",A114)+1,LEN(A114))),";",""),"not null",""))) -> zde_ref_doc_details | K114: refcontractdetails : abap.char(50); | P114: =TRIM(SUBSTITUTE(MID(K114,1,FIND(":",K114)-1),"key","")) -> refcontractdetails | Q114: =TRIM(MID(K114,FIND(":",K114)+1,LEN(K114))) -> abap.char(50); | AC114: =IF(ISNUMBER(SEARCH("@",H112)),A112,H112&" : "&IF(AD114="",I112,AD114)&";") -> contractreferencenumber : abap.char();); | AD114: ="abap.char("&AE114&")" -> abap.char();) | AE114: =TRIM(IF(ISNUMBER(SEARCH("char",Q114)),RIGHT(Q114,2))) -> );
...

Sheet ZSD_T_EINV_LOG
A2: @EndUserText.label : 'Cygnet E-Invoice Log' | K2: @EndUserText.label : 'Cygnet E-Invoice Log'
A3: @AbapCatalog.enhancement.category : #NOT_EXTENSIBLE | K3: @AbapCatalog.enhancement.category : #NOT_EXTENSIBLE
A4: @AbapCatalog.tableCategory : #TRANSPARENT | K4: @AbapCatalog.tableCategory : #TRANSPARENT
A5: @AbapCatalog.deliveryClass : #A | K5: @AbapCatalog.deliveryClass : #A
A6: @AbapCatalog.dataMaintenance : #ALLOWED | K6: @AbapCatalog.dataMaintenance : #RESTRICTED
A7: define table zsd_t_einv_log { | H7: Field | I7: Data Element | K7: define table zsd_t_einv_log { | P7: Field | Q7: Data Type
A9: key client : mandt not null; | H9: =TRIM(MID(A9,1,FIND(":",A9)-1)) -> key client | I9: =TRIM(SUBSTITUTE(SUBSTITUTE(TRIM(MID(A9,FIND(":",A9)+1,LEN(A9))),";",""),"not null","")) -> mandt | K9: key client : mandt not null; | P9: =TRIM(SUBSTITUTE(MID(K9,1,FIND(":",K9)-1),"key","")) -> client | Q9: =TRIM(MID(K9,FIND(":",K9)+1,LEN(K9))) -> mandt not null;
A10: key document_number : xblnr not null; | H10: =TRIM(MID(A10,1,FIND(":",A10)-1)) -> key document_number | I10: =TRIM(SUBSTITUTE(SUBSTITUTE(TRIM(MID(A10,FIND(":",A10)+1,LEN(A10))),";",""),"not null","")) -> xblnr | K10: key document_number : xblnr not null; | P10: =TRIM(SUBSTITUTE(MID(K10,1,FIND(":",K10)-1),"key","")) -> document_number | Q10: =TRIM(MID(K10,FIND(":",K10)+1,LEN(K10))) -> xblnr not null;
A11: key document_date : zde_document_date not null; | H11: =TRIM(MID(A11,1,FIND(":",A11)-1)) -> key document_date | I11: =TRIM(SUBSTITUTE(SUBSTITUTE(TRIM(MID(A11,FIND(":",A11)+1,LEN(A11))),";",""),"not null","")) -> zde_document_date | K11: key document_date : abap.dats not null; | P11: =TRIM(SUBSTITUTE(MID(K11,1,FIND(":",K11)-1),"key","")) -> document_date | Q11: =TRIM(MID(K11,FIND(":",K11)+1,LEN(K11))) -> abap.dats not null;
A12: key company_code : zde_company_code not null; | H12: =TRIM(MID(A12,1,FIND(":",A12)-1)) -> key company_code | I12: =TRIM(SUBSTITUTE(SUBSTITUTE(TRIM(MID(A12,FIND(":",A12)+1,LEN(A12))),";",""),"not null","")) -> zde_company_code | K12: key company_code : abap.char(4) not null; | P12: =TRIM(SUBSTITUTE(MID(K12,1,FIND(":",K12)-1),"key","")) -> company_code | Q12: =TRIM(MID(K12,FIND(":",K12)+1,LEN(K12))) -> abap.char(4) not null;
A13: fiscal_year : zde_fiscal_year; | H13: =TRIM(MID(A13,1,FIND(":",A13)-1)) -> fiscal_year | I13: =TRIM(SUBSTITUTE(SUBSTITUTE(TRIM(MID(A13,FIND(":",A13)+1,LEN(A13))),";",""),"not null","")) -> zde_fiscal_year | K13: fiscal_year : abap.numc(4); | P13: =TRIM(SUBSTITUTE(MID(K13,1,FIND(":",K13)-1),"key","")) -> fiscal_year | Q13: =TRIM(MID(K13,FIND(":",K13)+1,LEN(K13))) -> abap.numc(4);
A14: location_gstin : zde_location_gstin; | H14: =TRIM(MID(A14,1,FIND(":",A14)-1)) -> location_gstin | I14: =TRIM(SUBSTITUTE(SUBSTITUTE(TRIM(MID(A14,FIND(":",A14)+1,LEN(A14))),";",""),"not null","")) -> zde_location_gstin | K14: location_gstin : abap.char(20); | P14: =TRIM(SUBSTITUTE(MID(K14,1,FIND(":",K14)-1),"key","")) -> location_gstin | Q14: =TRIM(MID(K14,FIND(":",K14)+1,LEN(K14))) -> abap.char(20);
A15: billfromgstin : zde_billfromgstin; | H15: =TRIM(MID(A15,1,FIND(":",A15)-1)) -> billfromgstin | I15: =TRIM(SUBSTITUTE(SUBSTITUTE(TRIM(MID(A15,FIND(":",A15)+1,LEN(A15))),";",""),"not null","")) -> zde_billfromgstin | K15: billfromgstin : abap.char(100); | P15: =TRIM(SUBSTITUTE(MID(K15,1,FIND(":",K15)-1),"key","")) -> billfromgstin | Q15: =TRIM(MID(K15,FIND(":",K15)+1,LEN(K15))) -> abap.char(100);
A16: billfromname : zde_billfromname; | H16: =TRIM(MID(A16,1,FIND(":",A16)-1)) -> billfromname | I16: =TRIM(SUBSTITUTE(SUBSTITUTE(TRIM(MID(A16,FIND(":",A16)+1,LEN(A16))),";",""),"not null","")) -> zde_billfromname | K16: billfromname : abap.char(100); | P16: =TRIM(SUBSTITUTE(MID(K16,1,FIND(":",K16)-1),"key","")) -> billfromname | Q16: =TRIM(MID(K16,FIND(":",K16)+1,LEN(K16))) -> abap.char(100);
A17: billfromadd1 : zde_billfromadd1; | H17: =TRIM(MID(A17,1,FIND(":",A17)-1)) -> billfromadd1 | I17: =TRIM(SUBSTITUTE(SUBSTITUTE(TRIM(MID(A17,FIND(":",A17)+1,LEN(A17))),";",""),"not null","")) -> zde_billfromadd1 | K17: billfromadd1 : abap.char(100); | P17: =TRIM(SUBSTITUTE(MID(K17,1,FIND(":",K17)-1),"key","")) -> billfromadd1 | Q17: =TRIM(MID(K17,FIND(":",K17)+1,LEN(K17))) -> abap.char(100);
A18: billfromadd2 : zde_billfromadd2; | H18: =TRIM(MID(A18,1,FIND(":",A18)-1)) -> billfromadd2 | I18: =TRIM(SUBSTITUTE(SUBSTITUTE(TRIM(MID(A18,FIND(":",A18)+1,LEN(A18))),";",""),"not null","")) -> zde_billfromadd2 | K18: billfromadd2 : abap.char(100); | P18: =TRIM(SUBSTITUTE(MID(K18,1,FIND(":",K18)-1),"key","")) -> billfromadd2 | Q18: =TRIM(MID(K18,FIND(":",K18)+1,LEN(K18))) -> abap.char(100);
A19: billfrompincode : zde_billfrompincode; | H19: =TRIM(MID(A19,1,FIND(":",A19)-1)) -> billfrompincode | I19: =TRIM(SUBSTITUTE(SUBSTITUTE(TRIM(MID(A19,FIND(":",A19)+1,LEN(A19))),";",""),"not null","")) -> zde_billfrompincode | K19: billfrompincode : abap.char(100); | P19: =TRIM(SUBSTITUTE(MID(K19,1,FIND(":",K19)-1),"key","")) -> billfrompincode | Q19: =TRIM(MID(K19,FIND(":",K19)+1,LEN(K19))) -> abap.char(100);
A20: billfromcity : zde_billfromcity; | H20: =TRIM(MID(A20,1,FIND(":",A20)-1)) -> billfromcity | I20: =TRIM(SUBSTITUTE(SUBSTITUTE(TRIM(MID(A20,FIND(":",A20)+1,LEN(A20))),";",""),"not null","")) -> zde_billfromcity | K20: billfromcity : abap.char(100); | P20: =TRIM(SUBSTITUTE(MID(K20,1,FIND(":",K20)-1),"key","")) -> billfromcity | Q20: =TRIM(MID(K20,FIND(":",K20)+1,LEN(K20))) -> abap.char(100);
... A103: local_last_changed_at : abp_locinst_lastchange_tstmpl; | H103: =TRIM(MID(A103,1,FIND(":",A103)-1)) -> local_last_changed_at | I103: =TRIM(SUBSTITUTE(SUBSTITUTE(TRIM(MID(A103,FIND(":",A103)+1,LEN(A103))),";",""),"not null","")) -> abp_locinst_lastchange_tstmpl | K103: local_last_changed_at : abp_locinst_lastchange_tstmpl; | P103: =TRIM(SUBSTITUTE(MID(K103,1,FIND(":",K103)-1),"key","")) -> local_last_changed_at | Q103: =TRIM(MID(K103,FIND(":",K103)+1,LEN(K103))) -> abp_locinst_lastchange_tstmpl;
A105: } | K105: }

Sheet ZSD_T_EINV
B2: @EndUserText.label : 'E-Invoice Table to display data' | I2: Field & Data Element Seprator For Mapping Data Type | L2: @EndUserText.label : 'E-Invoice Table to display data' | R2: Data Types After Corrected | V2: Extracting Data types from Already Created Data Types
B3: @AbapCatalog.enhancement.category : #NOT_EXTENSIBLE | L3: @AbapCatalog.enhancement.category : #NOT_EXTENSIBLE
B4: @AbapCatalog.tableCategory : #TRANSPARENT | L4: @AbapCatalog.tableCategory : #TRANSPARENT
B5: @AbapCatalog.deliveryClass : #A | L5: @AbapCatalog.deliveryClass : #A
B6: @AbapCatalog.dataMaintenance : #RESTRICTED | L6: @AbapCatalog.dataMaintenance : #RESTRICTED
B7: define table zsd_t_einv { | I7: Field | J7: Data Element | L7: define table zsd_t_einv { | R7: Field | S7: Data Type
B9: key mandt : mandt not null; | I9: =TRIM(MID(B9,1,FIND(":",B9)-1)) -> key mandt | J9: =TRIM(SUBSTITUTE(SUBSTITUTE(TRIM(MID(B9,FIND(":",B9)+1,LEN(B9))),";",""),"not null","")) -> mandt | L9: key mandt : mandt not null; | R9: =TRIM(SUBSTITUTE(MID(L9,1,FIND(":",L9)-1),"key","")) -> mandt | S9: =TRIM(MID(L9,FIND(":",L9)+1,LEN(L9))) -> mandt not null; | V9: =IF(OR(ISERROR(W9),W9="--"),B9,IF(ISNUMBER(SEARCH("@",I9)),B9,I9&" : "&IF(W9="",J9,W9))) -> key mandt : mandt not null; | W9: =IFERROR(INDEX('Resolved Data Elem'!$E$4:$E$1070,MATCH(J9,'Resolved Data Elem'!$D$4:$D$1070,0)),"--") -> mandt not null;
B10: key documentnumber : xblnr not null; | I10: =TRIM(MID(B10,1,FIND(":",B10)-1)) -> key documentnumber | J10: =TRIM(SUBSTITUTE(SUBSTITUTE(TRIM(MID(B10,FIND(":",B10)+1,LEN(B10))),";",""),"not null","")) -> xblnr | L10: key documentnumber : xblnr not null; | R10: =TRIM(SUBSTITUTE(MID(L10,1,FIND(":",L10)-1),"key","")) -> documentnumber | S10: =TRIM(MID(L10,FIND(":",L10)+1,LEN(L10))) -> xblnr not null; | V10: =IF(OR(ISERROR(W10),W10="--"),B10,IF(ISNUMBER(SEARCH("@",I10)),B10,I10&" : "&IF(W10="",J10,W10))) -> key documentnumber : xblnr not null; | W10: =IFERROR(INDEX('Resolved Data Elem'!$E$4:$E$1070,MATCH(J10,'Resolved Data Elem'!$D$4:$D$1070,0)),"--") -> xblnr not null;
B11: locationgstin : zde_locationgstin; | I11: =TRIM(MID(B11,1,FIND(":",B11)-1)) -> locationgstin | J11: =TRIM(SUBSTITUTE(SUBSTITUTE(TRIM(MID(B11,FIND(":",B11)+1,LEN(B11))),";",""),"not null","")) -> zde_locationgstin | L11: locationgstin : abap.char(15); | R11: =TRIM(SUBSTITUTE(MID(L11,1,FIND(":",L11)-1),"key","")) -> locationgstin | S11: =TRIM(MID(L11,FIND(":",L11)+1,LEN(L11))) -> abap.char(15); | V11: =IF(OR(ISERROR(W11),W11="--"),B11,IF(ISNUMBER(SEARCH("@",I11)),B11,I11&" : "&IF(W11="",J11,W11))) -> locationgstin : abap.char(15); | W11: =IFERROR(INDEX('Resolved Data Elem'!$E$4:$E$1070,MATCH(J11,'Resolved Data Elem'!$D$4:$D$1070,0)),"--") -> abap.char(15);
B12: documentdate : zde_document_date; | I12: =TRIM(MID(B12,1,FIND(":",B12)-1)) -> documentdate | J12: =TRIM(SUBSTITUTE(SUBSTITUTE(TRIM(MID(B12,FIND(":",B12)+1,LEN(B12))),";",""),"not null","")) -> zde_document_date | L12: documentdate : abap.dats not null; | R12: =TRIM(SUBSTITUTE(MID(L12,1,FIND(":",L12)-1),"key","")) -> documentdate | S12: =TRIM(MID(L12,FIND(":",L12)+1,LEN(L12))) -> abap.dats not null; | V12: =IF(OR(ISERROR(W12),W12="--"),B12,IF(ISNUMBER(SEARCH("@",I12)),B12,I12&" : "&IF(W12="",J12,W12))) -> documentdate : abap.dats not null; | W12: =IFERROR(INDEX('Resolved Data Elem'!$E$4:$E$1070,MATCH(J12,'Resolved Data Elem'!$D$4:$D$1070,0)),"--") -> abap.dats not null;
B13: company_code : zde_company_code; | I13: =TRIM(MID(B13,1,FIND(":",B13)-1)) -> company_code | J13: =TRIM(SUBSTITUTE(SUBSTITUTE(TRIM(MID(B13,FIND(":",B13)+1,LEN(B13))),";",""),"not null","")) -> zde_company_code | L13: company_code : abap.char(4) not null; | R13: =TRIM(SUBSTITUTE(MID(L13,1,FIND(":",L13)-1),"key","")) -> company_code | S13: =TRIM(MID(L13,FIND(":",L13)+1,LEN(L13))) -> abap.char(4) not null; | V13: =IF(OR(ISERROR(W13),W13="--"),B13,IF(ISNUMBER(SEARCH("@",I13)),B13,I13&" : "&IF(W13="",J13,W13))) -> company_code : abap.char(4) not null; | W13: =IFERROR(INDEX('Resolved Data Elem'!$E$4:$E$1070,MATCH(J13,'Resolved Data Elem'!$D$4:$D$1070,0)),"--") -> abap.char(4) not null;
B14: purpose : zde_purpose1; | I14: =TRIM(MID(B14,1,FIND(":",B14)-1)) -> purpose | J14: =TRIM(SUBSTITUTE(SUBSTITUTE(TRIM(MID(B14,FIND(":",B14)+1,LEN(B14))),";",""),"not null","")) -> zde_purpose1 | L14: purpose : abap.char(13); | R14: =TRIM(SUBSTITUTE(MID(L14,1,FIND(":",L14)-1),"key","")) -> purpose | S14: =TRIM(MID(L14,FIND(":",L14)+1,LEN(L14))) -> abap.char(13); | V14: =IF(OR(ISERROR(W14),W14="--"),B14,IF(ISNUMBER(SEARCH("@",I14)),B14,I14&" : "&IF(W14="",J14,W14))) -> purpose : abap.char(13); | W14: =IFERROR(INDEX('Resolved Data Elem'!$E$4:$E$1070,MATCH(J14,'Resolved Data Elem'!$D$4:$D$1070,0)),"--") -> abap.char(13);
B15: sapmodule : zde_sapmodule; | I15: =TRIM(MID(B15,1,FIND(":",B15)-1)) -> sapmodule | J15: =TRIM(SUBSTITUTE(SUBSTITUTE(TRIM(MID(B15,FIND(":",B15)+1,LEN(B15))),";",""),"not null","")) -> zde_sapmodule | L15: sapmodule : abap.char(2); | R15: =TRIM(SUBSTITUTE(MID(L15,1,FIND(":",L15)-1),"key","")) -> sapmodule | S15: =TRIM(MID(L15,FIND(":",L15)+1,LEN(L15))) -> abap.char(2); | V15: =IF(OR(ISERROR(W15),W15="--"),B15,IF(ISNUMBER(SEARCH("@",I15)),B15,I15&" : "&IF(W15="",J15,W15))) -> sapmodule : abap.char(2); | W15: =IFERROR(INDEX('Resolved Data Elem'!$E$4:$E$1070,MATCH(J15,'Resolved Data Elem'!$D$4:$D$1070,0)),"--") -> abap.char(2);
B16: fiscalyear : gjahr; | I16: =TRIM(MID(B16,1,FIND(":",B16)-1)) -> fiscalyear | J16: =TRIM(SUBSTITUTE(SUBSTITUTE(TRIM(MID(B16,FIND(":",B16)+1,LEN(B16))),";",""),"not null","")) -> gjahr | L16: fiscalyear : gjahr; | R16: =TRIM(SUBSTITUTE(MID(L16,1,FIND(":",L16)-1),"key","")) -> fiscalyear | S16: =TRIM(MID(L16,FIND(":",L16)+1,LEN(L16))) -> gjahr; | V16: =IF(OR(ISERROR(W16),W16="--"),B16,IF(ISNUMBER(SEARCH("@",I16)),B16,I16&" : "&IF(W16="",J16,W16))) -> fiscalyear : gjahr; | W16: =IFERROR(INDEX('Resolved Data Elem'!$E$4:$E$1070,MATCH(J16,'Resolved Data Elem'!$D$4:$D$1070,0)),"--") -> gjahr;
B17: document : zde_document; | I17: =TRIM(MID(B17,1,FIND(":",B17)-1)) -> document | J17: =TRIM(SUBSTITUTE(SUBSTITUTE(TRIM(MID(B17,FIND(":",B17)+1,LEN(B17))),";",""),"not null","")) -> zde_document | L17: document : abap.char(12); | R17: =TRIM(SUBSTITUTE(MID(L17,1,FIND(":",L17)-1),"key","")) -> document | S17: =TRIM(MID(L17,FIND(":",L17)+1,LEN(L17))) -> abap.char(12); | V17: =IF(OR(ISERROR(W17),W17="--"),B17,IF(ISNUMBER(SEARCH("@",I17)),B17,I17&" : "&IF(W17="",J17,W17))) -> document : abap.char(12); | W17: =IFERROR(INDEX('Resolved Data Elem'!$E$4:$E$1070,MATCH(J17,'Resolved Data Elem'!$D$4:$D$1070,0)),"--") -> abap.char(12);
B18: branch : bupla; | I18: =TRIM(MID(B18,1,FIND(":",B18)-1)) -> branch | J18: =TRIM(SUBSTITUTE(SUBSTITUTE(TRIM(MID(B18,FIND(":",B18)+1,LEN(B18))),";",""),"not null","")) -> bupla | L18: branch : bupla; | R18: =TRIM(SUBSTITUTE(MID(L18,1,FIND(":",L18)-1),"key","")) -> branch | S18: =TRIM(MID(L18,FIND(":",L18)+1,LEN(L18))) -> bupla; | V18: =IF(OR(ISERROR(W18),W18="--"),B18,IF(ISNUMBER(SEARCH("@",I18)),B18,I18&" : "&IF(W18="",J18,W18))) -> branch : bupla; | W18: =IFERROR(INDEX('Resolved Data Elem'!$E$4:$E$1070,MATCH(J18,'Resolved Data Elem'!$D$4:$D$1070,0)),"--") -> bupla;
B19: locationname : zde_locationlegalname; | I19: =TRIM(MID(B19,1,FIND(":",B19)-1)) -> locationname | J19: =TRIM(SUBSTITUTE(SUBSTITUTE(TRIM(MID(B19,FIND(":",B19)+1,LEN(B19))),";",""),"not null","")) -> zde_locationlegalname | L19: locationname : abap.char(50); | R19: =TRIM(SUBSTITUTE(MID(L19,1,FIND(":",L19)-1),"key","")) -> locationname | S19: =TRIM(MID(L19,FIND(":",L19)+1,LEN(L19))) -> abap.char(50); | V19: =IF(OR(ISERROR(W19),W19="--"),B19,IF(ISNUMBER(SEARCH("@",I19)),B19,I19&" : "&IF(W19="",J19,W19))) -> locationname : abap.char(50); | W19: =IFERROR(INDEX('Resolved Data Elem'!$E$4:$E$1070,MATCH(J19,'Resolved Data Elem'!$D$4:$D$1070,0)),"--") -> abap.char(50);
B20: returnperiod : zde_returnperiod; | I20: =TRIM(MID(B20,1,FIND(":",B20)-1)) -> returnperiod | J20: =TRIM(SUBSTITUTE(SUBSTITUTE(TRIM(MID(B20,FIND(":",B20)+1,LEN(B20))),";",""),"not null","")) -> zde_returnperiod | L20: returnperiod : abap.char(6); | R20: =TRIM(SUBSTITUTE(MID(L20,1,FIND(":",L20)-1),"key","")) -> returnperiod | S20: =TRIM(MID(L20,FIND(":",L20)+1,LEN(L20))) -> abap.char(6); | V20: =IF(OR(ISERROR(W20),W20="--"),B20,IF(ISNUMBER(SEARCH("@",I20)),B20,I20&" : "&IF(W20="",J20,W20))) -> returnperiod : abap.char(6); | W20: =IFERROR(INDEX('Resolved Data Elem'!$E$4:$E$1070,MATCH(J20,'Resolved Data Elem'!$D$4:$D$1070,0)),"--") -> abap.char(6);
... B242: dd_hdl_transnm : abap.int4; | I242: =TRIM(MID(B242,1,FIND(":",B242)-1)) -> dd_hdl_transnm | J242: =TRIM(SUBSTITUTE(SUBSTITUTE(TRIM(MID(B242,FIND(":",B242)+1,LEN(B242))),";",""),"not null","")) -> abap.int4 | L242: dd_hdl_transnm : abap.int4; | R242: =TRIM(SUBSTITUTE(MID(L242,1,FIND(":",L242)-1),"key","")) -> dd_hdl_transnm | S242: =TRIM(MID(L242,FIND(":",L242)+1,LEN(L242))) -> abap.int4; | V242: =IF(OR(ISERROR(W242),W242="--"),B242,IF(ISNUMBER(SEARCH("@",I242)),B242,I242&" : "&IF(W242="",J242,W242))) -> dd_hdl_transnm : abap.int4; | W242: =IFERROR(INDEX('Resolved Data Elem'!$E$4:$E$1070,MATCH(J242,'Resolved Data Elem'!$D$4:$D$1070,0)),"--") -> abap.int4;
B244: } | L244: }

Sheet ZSD_T_CONDTYPE
A2: @EndUserText.label : 'Condition Type' | K2: @EndUserText.label : 'Condition Type'
A3: @AbapCatalog.enhancement.category : #NOT_EXTENSIBLE | K3: @AbapCatalog.enhancement.category : #NOT_EXTENSIBLE
A4: @AbapCatalog.tableCategory : #TRANSPARENT | K4: @AbapCatalog.tableCategory : #TRANSPARENT
A5: @AbapCatalog.deliveryClass : #A | K5: @AbapCatalog.deliveryClass : #A
A6: @AbapCatalog.dataMaintenance : #ALLOWED | K6: @AbapCatalog.dataMaintenance : #ALLOWED
A7: define table zsd_t_condtype { | H7: Field | I7: Data Element | K7: define table zsd_t_condtype { | P7: Field | Q7: Data Type
A9: key client : mandt not null; | H9: =TRIM(MID(A9,1,FIND(":",A9)-1)) -> key client | I9: =TRIM(SUBSTITUTE(SUBSTITUTE(TRIM(MID(A9,FIND(":",A9)+1,LEN(A9))),";",""),"not null","")) -> mandt | K9: key client : mandt not null; | P9: =TRIM(SUBSTITUTE(MID(K9,1,FIND(":",K9)-1),"key","")) -> client | Q9: =TRIM(MID(K9,FIND(":",K9)+1,LEN(K9))) -> mandt not null;
A10: key condition_type : zde_condition_type not null; | H10: =TRIM(MID(A10,1,FIND(":",A10)-1)) -> key condition_type | I10: =TRIM(SUBSTITUTE(SUBSTITUTE(TRIM(MID(A10,FIND(":",A10)+1,LEN(A10))),";",""),"not null","")) -> zde_condition_type | K10: key condition_type : abap.char(10) not null; | P10: =TRIM(SUBSTITUTE(MID(K10,1,FIND(":",K10)-1),"key","")) -> condition_type | Q10: =TRIM(MID(K10,FIND(":",K10)+1,LEN(K10))) -> abap.char(10) not null;
A11: category : zde_category; | H11: =TRIM(MID(A11,1,FIND(":",A11)-1)) -> category | I11: =TRIM(SUBSTITUTE(SUBSTITUTE(TRIM(MID(A11,FIND(":",A11)+1,LEN(A11))),";",""),"not null","")) -> zde_category | K11: category : abap.char(4); | P11: =TRIM(SUBSTITUTE(MID(K11,1,FIND(":",K11)-1),"key","")) -> category | Q11: =TRIM(MID(K11,FIND(":",K11)+1,LEN(K11))) -> abap.char(4);
A13: } | K13: }

Sheet ZSD_T_EINV_UOM
A2: @EndUserText.label : 'E-invoice Unit Of Measurement' | K2: @EndUserText.label : 'E-invoice Unit Of Measurement'
A3: @AbapCatalog.enhancement.category : #NOT_EXTENSIBLE | K3: @AbapCatalog.enhancement.category : #NOT_EXTENSIBLE
A4: @AbapCatalog.tableCategory : #TRANSPARENT | K4: @AbapCatalog.tableCategory : #TRANSPARENT
A5: @AbapCatalog.deliveryClass : #A | K5: @AbapCatalog.deliveryClass : #A
A6: @AbapCatalog.dataMaintenance : #ALLOWED | K6: @AbapCatalog.dataMaintenance : #ALLOWED
A7: define table zsd_t_einv_uom { | H7: Field | I7: Data Element | K7: define table zsd_t_einv_uom { | P7: Field | Q7: Data Type
A9: key client : mandt not null; | H9: =TRIM(MID(A9,1,FIND(":",A9)-1)) -> key client | I9: =TRIM(SUBSTITUTE(SUBSTITUTE(TRIM(MID(A9,FIND(":",A9)+1,LEN(A9))),";",""),"not null","")) -> mandt | K9: key client : mandt not null; | P9: =TRIM(SUBSTITUTE(MID(K9,1,FIND(":",K9)-1),"key","")) -> client | Q9: =TRIM(MID(K9,FIND(":",K9)+1,LEN(K9))) -> mandt not null;
A10: key sap_uom : zde_sap_uom not null; | H10: =TRIM(MID(A10,1,FIND(":",A10)-1)) -> key sap_uom | I10: =TRIM(SUBSTITUTE(SUBSTITUTE(TRIM(MID(A10,FIND(":",A10)+1,LEN(A10))),";",""),"not null","")) -> zde_sap_uom | K10: key sap_uom : abap.unit(3) not null; | P10: =TRIM(SUBSTITUTE(MID(K10,1,FIND(":",K10)-1),"key","")) -> sap_uom | Q10: =TRIM(MID(K10,FIND(":",K10)+1,LEN(K10))) -> abap.unit(3) not null;
A11: gst_uom : zde_gst_uom; | H11: =TRIM(MID(A11,1,FIND(":",A11)-1)) -> gst_uom | I11: =TRIM(SUBSTITUTE(SUBSTITUTE(TRIM(MID(A11,FIND(":",A11)+1,LEN(A11))),";",""),"not null","")) -> zde_gst_uom | K11: gst_uom : abap.unit(3); | P11: =TRIM(SUBSTITUTE(MID(K11,1,FIND(":",K11)-1),"key","")) -> gst_uom | Q11: =TRIM(MID(K11,FIND(":",K11)+1,LEN(K11))) -> abap.unit(3);
A13: } | K13: }

Sheet ZSD_T_BILLTYPE
A2: @EndUserText.label : 'SD Billtypes Maintainance Table' | K2: @EndUserText.label : 'SD Billtypes Maintainance Table'
A3: @AbapCatalog.enhancement.category : #NOT_EXTENSIBLE | K3: @AbapCatalog.enhancement.category : #NOT_EXTENSIBLE
A4: @AbapCatalog.tableCategory : #TRANSPARENT | K4: @AbapCatalog.tableCategory : #TRANSPARENT
A5: @AbapCatalog.deliveryClass : #A | K5: @AbapCatalog.deliveryClass : #A
A6: @AbapCatalog.dataMaintenance : #ALLOWED | K6: @AbapCatalog.dataMaintenance : #ALLOWED
A7: define table zsd_t_billtype { | H7: Field | I7: Data Element | K7: define table zsd_t_billtype { | P7: Field | Q7: Data Type
A9: key client : mandt not null; | H9: =TRIM(MID(A9,1,FIND(":",A9)-1)) -> key client | I9: =TRIM(SUBSTITUTE(SUBSTITUTE(TRIM(MID(A9,FIND(":",A9)+1,LEN(A9))),";",""),"not null","")) -> mandt | K9: key client : mandt not null; | P9: =TRIM(SUBSTITUTE(MID(K9,1,FIND(":",K9)-1),"key","")) -> client | Q9: =TRIM(MID(K9,FIND(":",K9)+1,LEN(K9))) -> mandt not null;
A10: key fkart : fkart not null; | H10: =TRIM(MID(A10,1,FIND(":",A10)-1)) -> key fkart | I10: =TRIM(SUBSTITUTE(SUBSTITUTE(TRIM(MID(A10,FIND(":",A10)+1,LEN(A10))),";",""),"not null","")) -> fkart | K10: key fkart : fkart not null; | P10: =TRIM(SUBSTITUTE(MID(K10,1,FIND(":",K10)-1),"key","")) -> fkart | Q10: =TRIM(MID(K10,FIND(":",K10)+1,LEN(K10))) -> fkart not null;
A11: doc_type : zde_doc_type; | H11: =TRIM(MID(A11,1,FIND(":",A11)-1)) -> doc_type | I11: =TRIM(SUBSTITUTE(SUBSTITUTE(TRIM(MID(A11,FIND(":",A11)+1,LEN(A11))),";",""),"not null","")) -> zde_doc_type | K11: doc_type : abap.char(3); | P11: =TRIM(SUBSTITUTE(MID(K11,1,FIND(":",K11)-1),"key","")) -> doc_type | Q11: =TRIM(MID(K11,FIND(":",K11)+1,LEN(K11))) -> abap.char(3);
A13: } | K13: }

Sheet ZSD_T_SUPPDETAIL
A2: @EndUserText.label : 'Supplier Details' | K2: @EndUserText.label : 'Supplier Details'
A3: @AbapCatalog.enhancement.category : #NOT_EXTENSIBLE | K3: @AbapCatalog.enhancement.category : #NOT_EXTENSIBLE
A4: @AbapCatalog.tableCategory : #TRANSPARENT | K4: @AbapCatalog.tableCategory : #TRANSPARENT
A5: @AbapCatalog.deliveryClass : #A | K5: @AbapCatalog.deliveryClass : #A
A6: @AbapCatalog.dataMaintenance : #ALLOWED | K6: @AbapCatalog.dataMaintenance : #ALLOWED
A7: define table zsd_t_suppdetail { | H7: Field | I7: Data Element | K7: define table zsd_t_suppdetail { | P7: Field | Q7: Data Type
A9: key client : mandt not null; | H9: =TRIM(MID(A9,1,FIND(":",A9)-1)) -> key client | I9: =TRIM(SUBSTITUTE(SUBSTITUTE(TRIM(MID(A9,FIND(":",A9)+1,LEN(A9))),";",""),"not null","")) -> mandt | K9: key client : mandt not null; | P9: =TRIM(SUBSTITUTE(MID(K9,1,FIND(":",K9)-1),"key","")) -> client | Q9: =TRIM(MID(K9,FIND(":",K9)+1,LEN(K9))) -> mandt not null;
A10: key warehouse : zde_warehouse not null; | H10: =TRIM(MID(A10,1,FIND(":",A10)-1)) -> key warehouse | I10: =TRIM(SUBSTITUTE(SUBSTITUTE(TRIM(MID(A10,FIND(":",A10)+1,LEN(A10))),";",""),"not null","")) -> zde_warehouse | K10: key warehouse : abap.char(3) not null; | P10: =TRIM(SUBSTITUTE(MID(K10,1,FIND(":",K10)-1),"key","")) -> warehouse | Q10: =TRIM(MID(K10,FIND(":",K10)+1,LEN(K10))) -> abap.char(3) not null;
A11: key shipping_point : zde_shipping_point not null; | H11: =TRIM(MID(A11,1,FIND(":",A11)-1)) -> key shipping_point | I11: =TRIM(SUBSTITUTE(SUBSTITUTE(TRIM(MID(A11,FIND(":",A11)+1,LEN(A11))),";",""),"not null","")) -> zde_shipping_point | K11: key shipping_point : abap.char(4) not null; | P11: =TRIM(SUBSTITUTE(MID(K11,1,FIND(":",K11)-1),"key","")) -> shipping_point | Q11: =TRIM(MID(K11,FIND(":",K11)+1,LEN(K11))) -> abap.char(4) not null;
A12: address1 : zde_address1; | H12: =TRIM(MID(A12,1,FIND(":",A12)-1)) -> address1 | I12: =TRIM(SUBSTITUTE(SUBSTITUTE(TRIM(MID(A12,FIND(":",A12)+1,LEN(A12))),";",""),"not null","")) -> zde_address1 | K12: address1 : abap.char(100); | P12: =TRIM(SUBSTITUTE(MID(K12,1,FIND(":",K12)-1),"key","")) -> address1 | Q12: =TRIM(MID(K12,FIND(":",K12)+1,LEN(K12))) -> abap.char(100);
A13: address2 : zde_address2; | H13: =TRIM(MID(A13,1,FIND(":",A13)-1)) -> address2 | I13: =TRIM(SUBSTITUTE(SUBSTITUTE(TRIM(MID(A13,FIND(":",A13)+1,LEN(A13))),";",""),"not null","")) -> zde_address2 | K13: address2 : abap.char(100); | P13: =TRIM(SUBSTITUTE(MID(K13,1,FIND(":",K13)-1),"key","")) -> address2 | Q13: =TRIM(MID(K13,FIND(":",K13)+1,LEN(K13))) -> abap.char(100);
A14: place : zde_place; | H14: =TRIM(MID(A14,1,FIND(":",A14)-1)) -> place | I14: =TRIM(SUBSTITUTE(SUBSTITUTE(TRIM(MID(A14,FIND(":",A14)+1,LEN(A14))),";",""),"not null","")) -> zde_place | K14: place : abap.char(40); | P14: =TRIM(SUBSTITUTE(MID(K14,1,FIND(":",K14)-1),"key","")) -> place | Q14: =TRIM(MID(K14,FIND(":",K14)+1,LEN(K14))) -> abap.char(40);
A15: pincode : zde_pincode; | H15: =TRIM(MID(A15,1,FIND(":",A15)-1)) -> pincode | I15: =TRIM(SUBSTITUTE(SUBSTITUTE(TRIM(MID(A15,FIND(":",A15)+1,LEN(A15))),";",""),"not null","")) -> zde_pincode | K15: pincode : abap.char(10); | P15: =TRIM(SUBSTITUTE(MID(K15,1,FIND(":",K15)-1),"key","")) -> pincode | Q15: =TRIM(MID(K15,FIND(":",K15)+1,LEN(K15))) -> abap.char(10);
A17: } | K17: }
